{
  "type": "Feature",
  "properties": {
    "iso:country":"US",
    "sg:address":"3549 College Rd",
    "sg:city":"Fairbanks",
    "sg:classifiers":[
        {
            "category":"Restaurant",
            "type":"Food & Drink"
        }
    ],
    "sg:phone":"+1 907 457 2200",
    "sg:postcode":"99709",
    "sg:province":"AK",
    "sg:tags":[
        "pizza"
    ],
    "wof:name":"College Town Pizzeria",
    "wof:placetype":"venue"
},
  "geometry": {"coordinates":[-147.808346,64.856245],"type":"Point"}
}