{
  "type": "Feature",
  "properties": {
    "iso:country":"US",
    "sg:address":"794 University Ave",
    "sg:city":"Fairbanks",
    "sg:classifiers":[
        {
            "category":"Government",
            "subcategory":"Office",
            "type":"Public Place"
        }
    ],
    "sg:phone":"+1 907 451 5018",
    "sg:postcode":"99709",
    "sg:province":"AK",
    "wof:name":"Us Mineral Resources Program",
    "wof:placetype":"venue"
},
  "geometry": {"coordinates":[-147.812699,64.84909],"type":"Point"}
}