{
  "type": "Feature",
  "properties": {
    "iso:country":"US",
    "sg:address":"3829 Spenard Rd",
    "sg:city":"Anchorage",
    "sg:classifiers":[
        {
            "category":"Personal",
            "subcategory":"Beauty Salon",
            "type":"Services"
        }
    ],
    "sg:phone":"+1 907 563 6330",
    "sg:postcode":"99517",
    "sg:province":"AK",
    "wof:name":"Blue Dolphin Salon",
    "wof:placetype":"venue"
},
  "geometry": {"coordinates":[-149.918854,61.185904],"type":"Point"}
}