{
  "type": "Feature",
  "properties": {
    "iso:country":"US",
    "sg:address":"134 Lincoln St",
    "sg:city":"Sitka",
    "sg:classifiers":[
        {
            "category":"Shopping",
            "subcategory":"Gifts & Souvenirs",
            "type":"Retail Goods"
        }
    ],
    "sg:phone":"+1 907 966 2641",
    "sg:postcode":"99835",
    "sg:province":"AK",
    "sg:tags":[
        "shop"
    ],
    "wof:name":"Sovak International",
    "wof:placetype":"venue"
},
  "geometry": {"coordinates":[-135.33918,57.04967],"type":"Point"}
}