{
  "type": "Feature",
  "properties": {
    "iso:country":"US",
    "sg:address":"930 Stedman St",
    "sg:city":"Ketchikan",
    "sg:classifiers":[
        {
            "category":"Manufacturing",
            "subcategory":"Food",
            "type":"Manufacturing & Wholesale Goods"
        }
    ],
    "sg:phone":"+1 907 225 2906",
    "sg:postcode":"99901",
    "sg:province":"AK",
    "sg:tags":[
        "packer",
        "fish"
    ],
    "wof:name":"Alaska General Seafoods",
    "wof:placetype":"venue"
},
  "geometry": {"coordinates":[-131.635514,55.338642],"type":"Point"}
}