{
  "type": "Feature",
  "properties": {
    "addr:full":"331 E 87th Ave Anchorage AK 99515",
    "addr:housenumber":"331",
    "addr:postcode":"99515",
    "addr:street":"E 87Th Ave",
    "iso:country":"US",
    "sg:address":"331 E 87th Ave",
    "sg:city":"Anchorage",
    "sg:classifiers":[
        {
            "category":"Professional",
            "subcategory":"Management & Consulting",
            "type":"Services"
        }
    ],
    "sg:phone":"+1 907 522 9400",
    "sg:postcode":"99515",
    "sg:province":"AK",
    "sg:tags":[
        "consultant",
        "telecommunication"
    ],
    "wof:name":"Northern Telecommunications",
    "wof:placetype":"venue"
},
  "geometry": {"coordinates":[-149.87632400000001,61.142455],"type":"Point"}
}