{
  "type": "Feature",
  "properties": {
    "addr:full":"725 Stedman St Ketchikan AK 99901",
    "addr:housenumber":"725",
    "addr:postcode":"99901",
    "addr:street":"Stedman St",
    "iso:country":"US",
    "sg:address":"725 Stedman St",
    "sg:city":"Ketchikan",
    "sg:classifiers":[
        {
            "category":"Organizations",
            "subcategory":"Membership Organization",
            "type":"Services"
        }
    ],
    "sg:phone":"+1 907 247 4966",
    "sg:postcode":"99901",
    "sg:province":"AK",
    "sg:tags":[
        "athletic"
    ],
    "wof:name":"Ketchikan Gymnastics Club Inc",
    "wof:placetype":"venue"
},
  "geometry": {"coordinates":[-131.63113300000001,55.336523],"type":"Point"}
}