{
  "type": "Feature",
  "properties": {
    "addr:full":"2438 Chilligan Dr Anchorage AK 99517",
    "addr:housenumber":"2438",
    "addr:postcode":"99517",
    "addr:street":"Chilligan Dr",
    "iso:country":"US",
    "sg:address":"2438 Chilligan Dr",
    "sg:city":"Anchorage",
    "sg:classifiers":[
        {
            "category":"Real Estate",
            "subcategory":"Real Estate Agent",
            "type":"Services"
        }
    ],
    "sg:phone":"+1 907 243 1888",
    "sg:postcode":"99517",
    "sg:province":"AK",
    "wof:name":"Gene W Bates",
    "wof:placetype":"venue"
},
  "geometry": {"coordinates":[-149.960375,61.198424],"type":"Point"}
}