{
  "type": "Feature",
  "properties": {
    "iso:country":"US",
    "sg:address":"22750 Myrtle Dr",
    "sg:city":"Eagle River",
    "sg:classifiers":[
        {
            "category":"Shopping",
            "type":"Retail Goods"
        }
    ],
    "sg:phone":"+1 907 694 9482",
    "sg:postcode":"99577",
    "sg:province":"AK",
    "sg:tags":[
        "breast",
        "artificial"
    ],
    "wof:name":"Kay's Cameo Corner",
    "wof:placetype":"venue"
},
  "geometry": {"coordinates":[-149.45161999999999,61.303276],"type":"Point"}
}