{
  "type": "Feature",
  "properties": {
    "iso:country":"US",
    "sg:address":"8813 Boom Cir",
    "sg:city":"Anchorage",
    "sg:classifiers":[
        {
            "category":"Personal",
            "subcategory":"Beauty Salon",
            "type":"Services"
        }
    ],
    "sg:phone":"+1 907 245 7662",
    "sg:postcode":"99502",
    "sg:province":"AK",
    "wof:name":"Ooh LA LA Hair Studio",
    "wof:placetype":"venue"
},
  "geometry": {"coordinates":[-149.93569500000001,61.140569],"type":"Point"}
}