{
  "type": "Feature",
  "properties": {
    "iso:country":"US",
    "sg:address":"440 W Benson Blvd",
    "sg:city":"Anchorage",
    "sg:classifiers":[
        {
            "category":"Real Estate",
            "subcategory":"Real Estate Agent",
            "type":"Services"
        }
    ],
    "sg:phone":"+1 907 561 1145",
    "sg:postcode":"99503",
    "sg:province":"AK",
    "sg:tags":[
        "appraiser"
    ],
    "wof:name":"William A Rowe & Assoc",
    "wof:placetype":"venue"
},
  "geometry": {"coordinates":[-149.890794,61.194186],"type":"Point"}
}