{
  "type": "Feature",
  "properties": {
    "addr:full":"825 Airport Way Fairbanks AK 99701",
    "addr:housenumber":"825",
    "addr:postcode":"99701",
    "addr:street":"Airport Way",
    "iso:country":"US",
    "sg:address":"825 Airport Way",
    "sg:city":"Fairbanks",
    "sg:classifiers":[
        {
            "category":"Shopping",
            "subcategory":"Clothing, Apparel, & Fashions",
            "type":"Retail Goods"
        }
    ],
    "sg:phone":"+1 907 456 2609",
    "sg:postcode":"99701",
    "sg:province":"AK",
    "wof:name":"III Deep Fashions",
    "wof:placetype":"venue"
},
  "geometry": {"coordinates":[-147.72182000000001,64.836337],"type":"Point"}
}