{
  "type": "Feature",
  "properties": {
    "iso:country":"US",
    "sg:address":"3691 Ben Walters Ln",
    "sg:city":"Homer",
    "sg:classifiers":[
        {
            "category":"Professional",
            "subcategory":"Accounting & Tax Preparation",
            "type":"Services"
        }
    ],
    "sg:phone":"+1 907 235 6711",
    "sg:postcode":"99603",
    "sg:province":"AK",
    "sg:tags":[
        "accountant"
    ],
    "wof:name":"Buckley & Assoc PC",
    "wof:placetype":"venue"
},
  "geometry": {"coordinates":[-151.521973,59.644046],"type":"Point"}
}