{
  "type": "Feature",
  "properties": {
    "iso:country":"US",
    "sg:address":"1107 E 71st Ave",
    "sg:city":"Anchorage",
    "sg:classifiers":[
        {
            "category":"Building & Trades",
            "subcategory":"Construction",
            "type":"Services"
        }
    ],
    "sg:phone":"+1 907 563 9900",
    "sg:postcode":"99518",
    "sg:province":"AK",
    "sg:tags":[
        "general",
        "contractor"
    ],
    "wof:name":"MCN Construction Inc",
    "wof:placetype":"venue"
},
  "geometry": {"coordinates":[-149.86164299999999,61.156066],"type":"Point"}
}