{
  "type": "Feature",
  "properties": {
    "addr:full":"1701 W 33rd Ave Anchorage AK 99517",
    "addr:housenumber":"1701",
    "addr:postcode":"99517",
    "addr:street":"W 33Rd Ave",
    "iso:country":"US",
    "sg:address":"1701 W 33rd Ave",
    "sg:city":"Anchorage",
    "sg:classifiers":[
        {
            "category":"Building & Trades",
            "subcategory":"Construction",
            "type":"Services"
        }
    ],
    "sg:phone":"+1 907 276 1620",
    "sg:postcode":"99517",
    "sg:province":"AK",
    "sg:tags":[
        "contractor"
    ],
    "wof:name":"Mikes Blind Installtion & Repr",
    "wof:placetype":"venue"
},
  "geometry": {"coordinates":[-149.916832,61.190311],"type":"Point"}
}