{
  "type": "Feature",
  "properties": {
    "iso:country":"US",
    "sg:address":"8720 Cameron St",
    "sg:city":"Anchorage",
    "sg:classifiers":[
        {
            "category":"Manufacturing",
            "subcategory":"Metals",
            "type":"Manufacturing & Wholesale Goods"
        },
        {
            "category":"Manufacturing",
            "subcategory":"Building Materials",
            "type":"Manufacturing & Wholesale Goods"
        }
    ],
    "sg:phone":"+1 907 349 5599",
    "sg:postcode":"99507",
    "sg:province":"AK",
    "sg:tags":[
        "windows",
        "manufacture",
        "supply",
        "specializing"
    ],
    "sg:website":"www.northernbuildingsupplies.com",
    "wof:name":"Northern Building Supplies Inc",
    "wof:placetype":"venue"
},
  "geometry": {"coordinates":[-149.838159,61.141225],"type":"Point"}
}