{
  "type": "Feature",
  "properties": {
    "iso:country":"US",
    "sg:address":"3773 Spinach Creek Rd",
    "sg:city":"Fairbanks",
    "sg:classifiers":[
        {
            "category":"Building & Trades",
            "subcategory":"Construction",
            "type":"Services"
        }
    ],
    "sg:phone":"+1 907 455 6667",
    "sg:postcode":"99709",
    "sg:province":"AK",
    "sg:tags":[
        "general",
        "contractor"
    ],
    "wof:name":"H C Contractors Inc",
    "wof:placetype":"venue"
},
  "geometry": {"coordinates":[-148.061687,64.940162],"type":"Point"}
}