{
  "type": "Feature",
  "properties": {
    "addr:full":"2101 W 31st Ave Anchorage AK 99517",
    "addr:housenumber":"2101",
    "addr:postcode":"99517",
    "addr:street":"W 31St Ave",
    "iso:country":"US",
    "sg:address":"2101 W 31st Ave",
    "sg:city":"Anchorage",
    "sg:classifiers":[
        {
            "category":"Building & Trades",
            "subcategory":"Construction",
            "type":"Services"
        }
    ],
    "sg:phone":"+1 907 563 6867",
    "sg:postcode":"99517",
    "sg:province":"AK",
    "sg:tags":[
        "house"
    ],
    "wof:name":"Donovan Construction Inc",
    "wof:placetype":"venue"
},
  "geometry": {"coordinates":[-149.923395,61.19253],"type":"Point"}
}