{
  "type": "Feature",
  "properties": {
    "iso:country":"US",
    "sg:address":"9145 Ptarmigan St",
    "sg:city":"Bethel",
    "sg:classifiers":[
        {
            "category":"Wholesale",
            "subcategory":"Hardware",
            "type":"Manufacturing & Wholesale Goods"
        }
    ],
    "sg:phone":"+1 907 543 5308",
    "sg:postcode":"99559",
    "sg:province":"AK",
    "sg:tags":[
        "equipment",
        "heating",
        "system"
    ],
    "wof:name":"Tundra Heating",
    "wof:placetype":"venue"
},
  "geometry": {"coordinates":[-161.820628,60.805674],"type":"Point"}
}