{
  "type": "Feature",
  "properties": {
    "addr:full":"1900 Rebel Ridge Dr Anchorage AK 99504",
    "addr:housenumber":"1900",
    "addr:postcode":"99504",
    "addr:street":"Rebel Ridge Dr",
    "iso:country":"US",
    "sg:address":"1900 Rebel Ridge Dr",
    "sg:city":"Anchorage",
    "sg:classifiers":[
        {
            "category":"Shopping",
            "subcategory":"Computers & Home Electronics",
            "type":"Retail Goods"
        }
    ],
    "sg:phone":"+1 907 337 4366",
    "sg:postcode":"99504",
    "sg:province":"AK",
    "sg:tags":[
        "publishing"
    ],
    "wof:name":"Lewis Publications",
    "wof:placetype":"venue"
},
  "geometry": {"coordinates":[-149.72337300000001,61.204792],"type":"Point"}
}