{
  "type": "Feature",
  "properties": {
    "iso:country":"US",
    "sg:address":"3850 Heath St",
    "sg:city":"Homer",
    "sg:classifiers":[
        {
            "category":"Professional",
            "subcategory":"Computer Services",
            "type":"Services"
        }
    ],
    "sg:phone":"+1 907 226 3130",
    "sg:postcode":"99603",
    "sg:province":"AK",
    "sg:tags":[
        "internet"
    ],
    "wof:name":"Horizon Satellite",
    "wof:placetype":"venue"
},
  "geometry": {"coordinates":[-151.529843,59.645613],"type":"Point"}
}