{
  "type": "Feature",
  "properties": {
    "addr:full":"1400 W Dowling Rd Anchorage AK 99518",
    "addr:housenumber":"1400",
    "addr:postcode":"99518",
    "addr:street":"W Dowling Rd",
    "iso:country":"US",
    "sg:address":"1400 W Dowling Rd",
    "sg:city":"Anchorage",
    "sg:classifiers":[
        {
            "category":"Manufacturing",
            "subcategory":"Glass & Minerals",
            "type":"Manufacturing & Wholesale Goods"
        }
    ],
    "sg:phone":"+1 907 344 1423",
    "sg:postcode":"99518",
    "sg:province":"AK",
    "sg:tags":[
        "concrete",
        "block",
        "mfg"
    ],
    "wof:name":"Davis Concrete",
    "wof:placetype":"venue"
},
  "geometry": {"coordinates":[-149.905269,61.166267],"type":"Point"}
}