{
  "type": "Feature",
  "properties": {
    "addr:full":"14641 Lake Otis Pkwy Anchorage AK 99516",
    "addr:housenumber":"14641",
    "addr:postcode":"99516",
    "addr:street":"Lake Otis Pkwy",
    "iso:country":"US",
    "sg:address":"14641 Lake Otis Pkwy",
    "sg:city":"Anchorage",
    "sg:classifiers":[
        {
            "category":"Building & Trades",
            "subcategory":"Landscaping Services",
            "type":"Services"
        }
    ],
    "sg:phone":"+1 907 345 0663",
    "sg:postcode":"99516",
    "sg:province":"AK",
    "sg:tags":[
        "carpentry"
    ],
    "wof:name":"Billys Maintenance",
    "wof:placetype":"venue"
},
  "geometry": {"coordinates":[-149.83232699999999,61.088021],"type":"Point"}
}