{
  "type": "Feature",
  "properties": {
    "iso:country":"US",
    "sg:address":"20275 S Cohoe Loop Rd",
    "sg:city":"Clam Gulch",
    "sg:classifiers":[
        {
            "category":"Recreation",
            "type":"Entertainment"
        }
    ],
    "sg:phone":"+1 907 262 7807",
    "sg:postcode":"99568",
    "sg:province":"AK",
    "sg:tags":[
        "charter",
        "boat"
    ],
    "wof:name":"Early Time Charters",
    "wof:placetype":"venue"
},
  "geometry": {"coordinates":[-151.33813,60.273905],"type":"Point"}
}