{
  "type": "Feature",
  "properties": {
    "iso:country":"US",
    "sg:address":"1801 Wasilla-Fishhook Rd",
    "sg:city":"Wasilla",
    "sg:classifiers":[
        {
            "category":"Social Services",
            "subcategory":"Child Care",
            "type":"Services"
        }
    ],
    "sg:phone":"+1 907 357 8876",
    "sg:postcode":"99654",
    "sg:province":"AK",
    "wof:name":"Turning Point Child Care Ctr",
    "wof:placetype":"venue"
},
  "geometry": {"coordinates":[-149.42067299999999,61.600097],"type":"Point"}
}