{
  "type": "Feature",
  "properties": {
    "addr:full":"1121 Bridge Access Rd Kenai AK 99611",
    "addr:housenumber":"1121",
    "addr:postcode":"99611",
    "addr:street":"Bridge Access Rd",
    "iso:country":"US",
    "sg:address":"1121 Bridge Access Rd",
    "sg:city":"Kenai",
    "sg:classifiers":[
        {
            "category":"Manufacturing",
            "subcategory":"Lumber",
            "type":"Manufacturing & Wholesale Goods"
        }
    ],
    "sg:phone":"+1 907 283 0941",
    "sg:postcode":"99611",
    "sg:province":"AK",
    "sg:tags":[
        "mill"
    ],
    "wof:name":"Dave Dempster Woodworks",
    "wof:placetype":"venue"
},
  "geometry": {"coordinates":[-151.21858800000001,60.548807],"type":"Point"}
}