{
  "type": "Feature",
  "properties": {
    "iso:country":"US",
    "sg:address":"1800 Birch Cir",
    "sg:city":"Dillingham",
    "sg:classifiers":[
        {
            "category":"Travel",
            "subcategory":"Hotels & Motels",
            "type":"Entertainment"
        }
    ],
    "sg:phone":"+1 907 842 7335",
    "sg:postcode":"99576",
    "sg:province":"AK",
    "wof:name":"Beaver Creek Bed & Breakfast",
    "wof:placetype":"venue"
},
  "geometry": {"coordinates":[-158.56464,59.049873],"type":"Point"}
}