{
  "type": "Feature",
  "properties": {
    "addr:full":"1504 Fathom Dr Kenai AK 99611",
    "addr:housenumber":"1504",
    "addr:postcode":"99611",
    "addr:street":"Fathom Dr",
    "iso:country":"US",
    "sg:address":"1504 Fathom Dr",
    "sg:city":"Kenai",
    "sg:classifiers":[
        {
            "category":"Professional",
            "subcategory":"Computer Services",
            "type":"Services"
        }
    ],
    "sg:phone":"+1 907 252 8106",
    "sg:postcode":"99611",
    "sg:province":"AK",
    "sg:tags":[
        "repair"
    ],
    "wof:name":"Futuramic Computer Svc",
    "wof:placetype":"venue"
},
  "geometry": {"coordinates":[-151.28131099999999,60.558422],"type":"Point"}
}