{
  "type": "Feature",
  "properties": {
    "iso:country":"US",
    "sg:address":"2705 Mill Bay Rd",
    "sg:city":"Kodiak",
    "sg:classifiers":[
        {
            "category":"Building & Trades",
            "subcategory":"Plumbing",
            "type":"Services"
        }
    ],
    "sg:phone":"+1 907 486 1954",
    "sg:postcode":"99615",
    "sg:province":"AK",
    "sg:tags":[
        "plumbing",
        "contractor"
    ],
    "wof:name":"Tundra Plumbing",
    "wof:placetype":"venue"
},
  "geometry": {"coordinates":[-152.36295799999999,57.810926],"type":"Point"}
}