{
  "type": "Feature",
  "properties": {
    "addr:full":"7623 Duben Ave Anchorage AK 99504",
    "addr:housenumber":"7623",
    "addr:postcode":"99504",
    "addr:street":"Duben Ave",
    "iso:country":"US",
    "sg:address":"7623 Duben Ave",
    "sg:city":"Anchorage",
    "sg:classifiers":[
        {
            "category":"Professional",
            "subcategory":"Engineering",
            "type":"Services"
        }
    ],
    "sg:phone":"+1 907 338 0123",
    "sg:postcode":"99504",
    "sg:province":"AK",
    "sg:tags":[
        "engineer"
    ],
    "wof:name":"Triverus",
    "wof:placetype":"venue"
},
  "geometry": {"coordinates":[-149.74186599999999,61.220634],"type":"Point"}
}