{
  "type": "Feature",
  "properties": {
    "iso:country":"US",
    "sg:address":"1135 Muldoon Rd",
    "sg:city":"Anchorage",
    "sg:classifiers":[
        {
            "category":"Restaurant",
            "type":"Food & Drink"
        }
    ],
    "sg:menulink":"http://www.allmenus.com/ak/anchorage/159737-arbys/menu/",
    "sg:phone":"+1 907 337 5714",
    "sg:postcode":"99504",
    "sg:province":"AK",
    "sg:tags":[
        "burger",
        "american"
    ],
    "wof:name":"Arby's",
    "wof:placetype":"venue"
},
  "geometry": {"coordinates":[-149.73315600000001,61.211643],"type":"Point"}
}