{
  "type": "Feature",
  "properties": {
    "iso:country":"US",
    "sg:address":"4619 Harvard Cir",
    "sg:city":"Fairbanks",
    "sg:classifiers":[
        {
            "category":"Manufacturing",
            "subcategory":"Motor Vehicles & Parts",
            "type":"Manufacturing & Wholesale Goods"
        }
    ],
    "sg:phone":"+1 907 457 3233",
    "sg:postcode":"99709",
    "sg:province":"AK",
    "sg:tags":[
        "equipment",
        "transportation",
        "mfg"
    ],
    "wof:name":"Sledguard",
    "wof:placetype":"venue"
},
  "geometry": {"coordinates":[-147.858998,64.843372],"type":"Point"}
}