{
  "type": "Feature",
  "properties": {
    "iso:country":"US",
    "sg:address":"1207 W 36th Ave",
    "sg:city":"Anchorage",
    "sg:classifiers":[
        {
            "category":"Restaurant",
            "type":"Food & Drink"
        }
    ],
    "sg:phone":"+1 907 569 6000",
    "sg:postcode":"99503",
    "sg:province":"AK",
    "wof:name":"Milano's Pizza",
    "wof:placetype":"venue"
},
  "geometry": {"coordinates":[-149.90611100000001,61.188156],"type":"Point"}
}