{
  "type": "Feature",
  "properties": {
    "iso:country":"US",
    "sg:address":"6601 Sherwood Cir",
    "sg:city":"Anchorage",
    "sg:classifiers":[
        {
            "category":"Professional",
            "subcategory":"Art Services",
            "type":"Services"
        }
    ],
    "sg:phone":"+1 907 337 3577",
    "sg:postcode":"99504",
    "sg:province":"AK",
    "sg:tags":[
        "graphic",
        "designer"
    ],
    "wof:name":"Northern Design & Graphics",
    "wof:placetype":"venue"
},
  "geometry": {"coordinates":[-149.755009,61.202913],"type":"Point"}
}