{
  "type": "Feature",
  "properties": {
    "addr:full":"7440 Tikchik Cir Anchorage AK 99504",
    "addr:housenumber":"7440",
    "addr:postcode":"99504",
    "addr:street":"Tikchik Cir",
    "iso:country":"US",
    "sg:address":"7440 Tikchik Cir",
    "sg:city":"Anchorage",
    "sg:classifiers":[
        {
            "category":"Professional",
            "subcategory":"Business Services",
            "type":"Services"
        }
    ],
    "sg:phone":"+1 907 338 6428",
    "sg:postcode":"99504",
    "sg:province":"AK",
    "sg:tags":[
        "appraiser"
    ],
    "wof:name":"Antique & Art Appraisers",
    "wof:placetype":"venue"
},
  "geometry": {"coordinates":[-149.74229099999999,61.199143],"type":"Point"}
}