{
  "type": "Feature",
  "properties": {
    "iso:country":"US",
    "sg:address":"436 Panorama Dr",
    "sg:city":"Fairbanks",
    "sg:classifiers":[
        {
            "category":"Retail",
            "subcategory":"Repair Shop",
            "type":"Services"
        }
    ],
    "sg:phone":"+1 907 457 6986",
    "sg:postcode":"99712",
    "sg:province":"AK",
    "sg:tags":[
        "home",
        "computer",
        "audio",
        "electronic",
        "mfg"
    ],
    "wof:name":"Digital Sound Service",
    "wof:placetype":"venue"
},
  "geometry": {"coordinates":[-147.679024,64.89655500000001],"type":"Point"}
}