{
  "type": "Feature",
  "properties": {
    "addr:full":"5425 Revolutionary Way Wasilla AK 99654",
    "addr:housenumber":"5425",
    "addr:postcode":"99654",
    "addr:street":"Revolutionary Way",
    "iso:country":"US",
    "sg:address":"5425 Revolutionary Way",
    "sg:city":"Wasilla",
    "sg:classifiers":[
        {
            "category":"Professional",
            "subcategory":"Accounting & Tax Preparation",
            "type":"Services"
        }
    ],
    "sg:phone":"+1 907 376 8878",
    "sg:postcode":"99654",
    "sg:province":"AK",
    "sg:tags":[
        "bookkeeping",
        "general"
    ],
    "wof:name":"Mat-Su Bookkeeping",
    "wof:placetype":"venue"
},
  "geometry": {"coordinates":[-149.30472800000001,61.591247],"type":"Point"}
}