{
  "type": "Feature",
  "properties": {
    "iso:country":"US",
    "sg:address":"236 W 10th Ave",
    "sg:city":"Anchorage",
    "sg:classifiers":[
        {
            "category":"Health Services",
            "subcategory":"Health Practitioner",
            "type":"Services"
        }
    ],
    "sg:phone":"+1 907 222 1924",
    "sg:postcode":"99501",
    "sg:province":"AK",
    "sg:tags":[
        "occupational",
        "therapist"
    ],
    "wof:name":"Advanced Rehabilitation",
    "wof:placetype":"venue"
},
  "geometry": {"coordinates":[-149.88550599999999,61.212564],"type":"Point"}
}