{
  "type": "Feature",
  "properties": {
    "iso:country":"US",
    "sg:address":"8990 Atlin Dr",
    "sg:city":"Juneau",
    "sg:classifiers":[
        {
            "category":"Building & Trades",
            "subcategory":"Construction",
            "type":"Services"
        }
    ],
    "sg:phone":"+1 907 789 7850",
    "sg:postcode":"99801",
    "sg:province":"AK",
    "sg:tags":[
        "excavating",
        "contractor"
    ],
    "wof:name":"SJS Excavation Co",
    "wof:placetype":"venue"
},
  "geometry": {"coordinates":[-134.58072899999999,58.371674],"type":"Point"}
}