{
  "type": "Feature",
  "properties": {
    "iso:country":"US",
    "sg:address":"109 S Franklin St",
    "sg:city":"Juneau",
    "sg:classifiers":[
        {
            "category":"Organizations",
            "subcategory":"Community Association",
            "type":"Services"
        }
    ],
    "sg:phone":"+1 907 586 2420",
    "sg:postcode":"99801",
    "sg:province":"AK",
    "sg:tags":[
        "fraternal"
    ],
    "wof:name":"Elks Lodge",
    "wof:placetype":"venue"
},
  "geometry": {"coordinates":[-134.405416,58.300577],"type":"Point"}
}