{
  "type": "Feature",
  "properties": {
    "addr:full":"16932 Eagle River Rd Eagle River AK 99577",
    "addr:housenumber":"16932",
    "addr:postcode":"99577",
    "addr:street":"Eagle River Rd",
    "iso:country":"US",
    "sg:address":"16932 Eagle River Rd",
    "sg:city":"Eagle River",
    "sg:classifiers":[
        {
            "category":"Shopping",
            "subcategory":"Used Merchandise",
            "type":"Retail Goods"
        }
    ],
    "sg:phone":"+1 907 622 4004",
    "sg:postcode":"99577",
    "sg:province":"AK",
    "sg:tags":[
        "antique"
    ],
    "wof:name":"Serendipity Shop",
    "wof:placetype":"venue"
},
  "geometry": {"coordinates":[-149.56625700000001,61.310917],"type":"Point"}
}