{
  "type": "Feature",
  "properties": {
    "addr:full":"5510 Wilderness Ln Valdez AK 99686",
    "addr:housenumber":"5510",
    "addr:postcode":"99686",
    "addr:street":"Wilderness Ln",
    "iso:country":"US",
    "sg:address":"5510 Wilderness Ln",
    "sg:city":"Valdez",
    "sg:classifiers":[
        {
            "category":"Retail",
            "subcategory":"Animal Services",
            "type":"Services"
        }
    ],
    "sg:phone":"+1 907 835 4326",
    "sg:postcode":"99686",
    "sg:province":"AK",
    "sg:tags":[
        "cat",
        "dog",
        "kennel"
    ],
    "wof:name":"Happy Trails Kennels",
    "wof:placetype":"venue"
},
  "geometry": {"coordinates":[-146.00233700000001,61.059265],"type":"Point"}
}