{
  "type": "Feature",
  "properties": {
    "addr:full":"520 4th St Fairbanks AK 99701",
    "addr:housenumber":"520",
    "addr:postcode":"99701",
    "addr:street":"4Th St",
    "iso:country":"US",
    "sg:address":"520 4th St",
    "sg:city":"Fairbanks",
    "sg:classifiers":[
        {
            "category":"Shopping",
            "subcategory":"Computers & Home Electronics",
            "type":"Retail Goods"
        }
    ],
    "sg:phone":"+1 907 479 3924",
    "sg:postcode":"99701",
    "sg:province":"AK",
    "sg:tags":[
        "m",
        "related"
    ],
    "sg:website":"www.c-drive.com",
    "wof:name":"C-Drive Computers Inc",
    "wof:placetype":"venue"
},
  "geometry": {"coordinates":[-147.69561200000001,64.846672],"type":"Point"}
}