{
  "type": "Feature",
  "properties": {
    "addr:full":"1303 W 33rd Ave Anchorage AK 99503",
    "addr:housenumber":"1303",
    "addr:postcode":"99503",
    "addr:street":"W 33Rd Ave",
    "iso:country":"US",
    "sg:address":"1303 W 33rd Ave",
    "sg:city":"Anchorage",
    "sg:classifiers":[
        {
            "category":"Local Transit",
            "type":"Transportation"
        }
    ],
    "sg:phone":"+1 907 272 5466",
    "sg:postcode":"99503",
    "sg:province":"AK",
    "sg:tags":[
        "limousine"
    ],
    "wof:name":"Midnight Express Limo Svc",
    "wof:placetype":"venue"
},
  "geometry": {"coordinates":[-149.913049,61.1904],"type":"Point"}
}