{
  "type": "Feature",
  "properties": {
    "iso:country":"US",
    "sg:address":"616 Old Steese Hwy",
    "sg:city":"Fairbanks",
    "sg:classifiers":[
        {
            "category":"Recreation",
            "type":"Entertainment"
        }
    ],
    "sg:phone":"+1 907 456 6643",
    "sg:postcode":"99701",
    "sg:province":"AK",
    "sg:tags":[
        "dog",
        "sledding"
    ],
    "wof:name":"Northern Specialty",
    "wof:placetype":"venue"
},
  "geometry": {"coordinates":[-147.696572,64.850392],"type":"Point"}
}