{
  "type": "Feature",
  "properties": {
    "iso:country":"US",
    "sg:address":"205 E Dimond Blvd",
    "sg:city":"Anchorage",
    "sg:classifiers":[
        {
            "category":"Manufacturing",
            "subcategory":"Printing",
            "type":"Manufacturing & Wholesale Goods"
        }
    ],
    "sg:phone":"+1 907 522 1492",
    "sg:postcode":"99515",
    "sg:province":"AK",
    "sg:tags":[
        "magazine",
        "publish"
    ],
    "wof:name":"Alaskamen Magazine Inc",
    "wof:placetype":"venue"
},
  "geometry": {"coordinates":[-149.877252,61.144804],"type":"Point"}
}