{
  "type": "Feature",
  "properties": {
    "iso:country":"US",
    "sg:address":"855 E Loop Rd",
    "sg:city":"Anchorage",
    "sg:classifiers":[
        {
            "category":"Organizations",
            "subcategory":"Religious Organization",
            "type":"Services"
        }
    ],
    "sg:phone":"+1 907 258 9682",
    "sg:postcode":"99501",
    "sg:province":"AK",
    "sg:tags":[
        "church"
    ],
    "wof:name":"Praise Temple Way Church",
    "wof:placetype":"venue"
},
  "geometry": {"coordinates":[-149.872162,61.23115],"type":"Point"}
}