{
  "type": "Feature",
  "properties": {
    "addr:full":"44789 Sterling Hwy Soldotna AK 99669",
    "addr:housenumber":"44789",
    "addr:postcode":"99669",
    "addr:street":"Sterling Hwy",
    "iso:country":"US",
    "sg:address":"44789 Sterling Hwy",
    "sg:city":"Soldotna",
    "sg:classifiers":[
        {
            "category":"Personal",
            "subcategory":"Beauty Salon",
            "type":"Services"
        }
    ],
    "sg:phone":"+1 907 262 6456",
    "sg:postcode":"99669",
    "sg:province":"AK",
    "wof:name":"Hairstop",
    "wof:placetype":"venue"
},
  "geometry": {"coordinates":[-151.08202399999999,60.476502],"type":"Point"}
}