{
  "type": "Feature",
  "properties": {
    "addr:full":"931 Joham Cir Anchorage AK 99515",
    "addr:housenumber":"931",
    "addr:postcode":"99515",
    "addr:street":"Joham Cir",
    "iso:country":"US",
    "sg:address":"931 Joham Cir",
    "sg:city":"Anchorage",
    "sg:classifiers":[
        {
            "category":"Insurance",
            "subcategory":"Insurance Agent",
            "type":"Services"
        }
    ],
    "sg:phone":"+1 907 562 4177",
    "sg:postcode":"99515",
    "sg:province":"AK",
    "wof:name":"Springen Insurance",
    "wof:placetype":"venue"
},
  "geometry": {"coordinates":[-149.86417299999999,61.104728],"type":"Point"}
}