{
  "type": "Feature",
  "properties": {
    "addr:full":"1722 Edgecumbe Dr Sitka AK 99835",
    "addr:housenumber":"1722",
    "addr:postcode":"99835",
    "addr:street":"Edgecumbe Dr",
    "iso:country":"US",
    "sg:address":"1722 Edgecumbe Dr",
    "sg:city":"Sitka",
    "sg:classifiers":[
        {
            "category":"Farming",
            "subcategory":"Fish & Marine Products",
            "type":"Manufacturing & Wholesale Goods"
        }
    ],
    "sg:phone":"+1 907 747 3523",
    "sg:postcode":"99835",
    "sg:province":"AK",
    "sg:tags":[
        "fishing"
    ],
    "wof:name":"F V Brat",
    "wof:placetype":"venue"
},
  "geometry": {"coordinates":[-135.36125699999999,57.067959],"type":"Point"}
}