{
  "type": "Feature",
  "properties": {
    "iso:country":"US",
    "sg:address":"8107 Frank St",
    "sg:city":"Anchorage",
    "sg:classifiers":[
        {
            "category":"Building & Trades",
            "subcategory":"Construction",
            "type":"Services"
        }
    ],
    "sg:phone":"+1 907 522 6603",
    "sg:postcode":"99518",
    "sg:province":"AK",
    "sg:tags":[
        "masonry",
        "contractor"
    ],
    "wof:name":"Red Dog Masonry Inc",
    "wof:placetype":"venue"
},
  "geometry": {"coordinates":[-149.901587,61.145256],"type":"Point"}
}