{
  "type": "Feature",
  "properties": {
    "addr:full":"1090 W Dimond Blvd Anchorage AK 99515",
    "addr:housenumber":"1090",
    "addr:postcode":"99515",
    "addr:street":"W Dimond Blvd",
    "iso:country":"US",
    "sg:address":"1090 W Dimond Blvd",
    "sg:city":"Anchorage",
    "sg:classifiers":[
        {
            "category":"Retail",
            "subcategory":"Car Wash",
            "type":"Services"
        }
    ],
    "sg:phone":"+1 907 344 3444",
    "sg:postcode":"99515",
    "sg:province":"AK",
    "sg:tags":[
        "polishing",
        "washing"
    ],
    "wof:name":"Magic Wand Car Wash",
    "wof:placetype":"venue"
},
  "geometry": {"coordinates":[-149.90169499999999,61.142407],"type":"Point"}
}