{
  "type": "Feature",
  "properties": {
    "iso:country":"US",
    "sg:address":"716 W 4th Ave",
    "sg:city":"Anchorage",
    "sg:classifiers":[
        {
            "category":"Government",
            "subcategory":"Office",
            "type":"Public Place"
        }
    ],
    "sg:phone":"+1 907 443 5036",
    "sg:postcode":"99501",
    "sg:province":"AK",
    "wof:name":"Representative Richard Foster",
    "wof:placetype":"venue"
},
  "geometry": {"coordinates":[-149.897408,61.218479],"type":"Point"}
}