{
  "type": "Feature",
  "properties": {
    "iso:country":"US",
    "sg:address":"4325 E Rezanof Dr",
    "sg:city":"Kodiak",
    "sg:classifiers":[
        {
            "category":"Building & Trades",
            "subcategory":"Landscaping Services",
            "type":"Services"
        }
    ],
    "sg:phone":"+1 907 486 1045",
    "sg:postcode":"99615",
    "sg:province":"AK",
    "wof:name":"Tree Service Of Kodiak",
    "wof:placetype":"venue"
},
  "geometry": {"coordinates":[-152.355372,57.822754],"type":"Point"}
}