{
  "type": "Feature",
  "properties": {
    "iso:country":"US",
    "sg:address":"3877 University Dr",
    "sg:city":"Anchorage",
    "sg:classifiers":[
        {
            "category":"Communications",
            "subcategory":"Radio Station",
            "type":"Services"
        }
    ],
    "sg:phone":"+1 907 561 1161",
    "sg:postcode":"99508",
    "sg:province":"AK",
    "sg:tags":[
        "company",
        "broadcasting"
    ],
    "sg:website":"www.kska.org",
    "wof:name":"KSKA",
    "wof:placetype":"venue"
},
  "geometry": {"coordinates":[-149.807267,61.188428],"type":"Point"}
}