{
  "type": "Feature",
  "properties": {
    "addr:full":"4403 Spenard Rd Anchorage AK 99517",
    "addr:housenumber":"4403",
    "addr:postcode":"99517",
    "addr:street":"Spenard Rd",
    "iso:country":"US",
    "sg:address":"4403 Spenard Rd",
    "sg:city":"Anchorage",
    "sg:classifiers":[
        {
            "category":"Restaurant",
            "type":"Food & Drink"
        }
    ],
    "sg:menulink":"http://www.allmenus.com/ak/anchorage/9657-village-inn/menu/",
    "sg:phone":"+1 907 243 6009",
    "sg:postcode":"99517",
    "sg:province":"AK",
    "sg:tags":[
        "new",
        "american"
    ],
    "wof:name":"Village Inn",
    "wof:placetype":"venue"
},
  "geometry": {"coordinates":[-149.93601000000001,61.181335],"type":"Point"}
}