{
  "type": "Feature",
  "properties": {
    "addr:full":"2751 Debarr Rd Anchorage AK 99508",
    "addr:housenumber":"2751",
    "addr:postcode":"99508",
    "addr:street":"Debarr Rd",
    "iso:country":"US",
    "sg:address":"2751 Debarr Rd",
    "sg:city":"Anchorage",
    "sg:classifiers":[
        {
            "category":"Health Services",
            "subcategory":"Doctor",
            "type":"Services"
        }
    ],
    "sg:phone":"+1 907 279 5589",
    "sg:postcode":"99508",
    "sg:province":"AK",
    "sg:tags":[
        "physician",
        "surgeon"
    ],
    "wof:name":"Orthopaedic Trauma",
    "wof:placetype":"venue"
},
  "geometry": {"coordinates":[-149.82940099999999,61.209781],"type":"Point"}
}