{
  "type": "Feature",
  "properties": {
    "addr:full":"355 W Pioneer Ave Homer AK 99603",
    "addr:housenumber":"355",
    "addr:postcode":"99603",
    "addr:street":"W Pioneer Ave",
    "iso:country":"US",
    "sg:address":"355 W Pioneer Ave",
    "sg:city":"Homer",
    "sg:classifiers":[
        {
            "category":"Social Services",
            "type":"Services"
        }
    ],
    "sg:phone":"+1 907 235 4985",
    "sg:postcode":"99603",
    "sg:province":"AK",
    "sg:tags":[
        "youth",
        "organization",
        "center"
    ],
    "wof:name":"Kenai Peninsula Youth Court",
    "wof:placetype":"venue"
},
  "geometry": {"coordinates":[-151.549905,59.643385],"type":"Point"}
}