{
  "type": "Feature",
  "properties": {
    "iso:country":"US",
    "sg:address":"417 W 5th Ave",
    "sg:city":"Anchorage",
    "sg:classifiers":[
        {
            "category":"Restaurant",
            "type":"Food & Drink"
        }
    ],
    "sg:phone":"+1 907 277 6332",
    "sg:postcode":"99501",
    "sg:province":"AK",
    "sg:website":"www.clubparisrestaurant.com",
    "wof:name":"Club Paris",
    "wof:placetype":"venue"
},
  "geometry": {"coordinates":[-149.891298,61.217641],"type":"Point"}
}