{
  "type": "Feature",
  "properties": {
    "addr:full":"3711 Elliott Hwy Fairbanks AK 99712",
    "addr:housenumber":"3711",
    "addr:postcode":"99712",
    "addr:street":"Elliott Hwy",
    "iso:country":"US",
    "sg:address":"3711 Elliott Hwy",
    "sg:city":"Fairbanks",
    "sg:classifiers":[
        {
            "category":"Restaurant",
            "type":"Food & Drink"
        }
    ],
    "sg:phone":"+1 907 389 7600",
    "sg:postcode":"99712",
    "sg:province":"AK",
    "wof:name":"Hilltop Truck Stop",
    "wof:placetype":"venue"
},
  "geometry": {"coordinates":[-147.65170599999999,65.02546],"type":"Point"}
}