{
  "type": "Feature",
  "properties": {
    "addr:full":"3501 Grissom Cir Anchorage AK 99517",
    "addr:housenumber":"3501",
    "addr:postcode":"99517",
    "addr:street":"Grissom Cir",
    "iso:country":"US",
    "sg:address":"3501 Grissom Cir",
    "sg:city":"Anchorage",
    "sg:classifiers":[
        {
            "category":"Manufacturing",
            "subcategory":"Metals",
            "type":"Manufacturing & Wholesale Goods"
        }
    ],
    "sg:phone":"+1 907 764 3304",
    "sg:postcode":"99517",
    "sg:province":"AK",
    "sg:tags":[
        "steel"
    ],
    "wof:name":"Certified Mobile Welding Svc",
    "wof:placetype":"venue"
},
  "geometry": {"coordinates":[-149.948669,61.186725],"type":"Point"}
}