{
  "type": "Feature",
  "properties": {
    "iso:country":"US",
    "sg:address":"300 Barnette St",
    "sg:city":"Fairbanks",
    "sg:classifiers":[
        {
            "category":"Insurance",
            "subcategory":"Insurance Agent",
            "type":"Services"
        }
    ],
    "sg:phone":"+1 907 456 6646",
    "sg:postcode":"99701",
    "sg:province":"AK",
    "sg:website":"www.kenmurray.com",
    "wof:name":"Kenneth A Murray Insurance",
    "wof:placetype":"venue"
},
  "geometry": {"coordinates":[-147.72438,64.842782],"type":"Point"}
}