{
  "type": "Feature",
  "properties": {
    "iso:country":"US",
    "sg:address":"6613 Brayton Dr",
    "sg:city":"Anchorage",
    "sg:classifiers":[
        {
            "category":"Restaurant",
            "type":"Food & Drink"
        }
    ],
    "sg:phone":"+1 907 278 2208",
    "sg:postcode":"99507",
    "sg:province":"AK",
    "sg:tags":[
        "caterer"
    ],
    "sg:website":"www.calistacorp.com",
    "wof:name":"Chiulista Camp Svc Inc",
    "wof:placetype":"venue"
},
  "geometry": {"coordinates":[-149.855333,61.16087],"type":"Point"}
}