{
  "type": "Feature",
  "properties": {
    "iso:country":"US",
    "sg:address":"451 Sterling Hwy",
    "sg:city":"Homer",
    "sg:classifiers":[
        {
            "category":"Travel",
            "subcategory":"Hotels & Motels",
            "type":"Entertainment"
        }
    ],
    "sg:phone":"+1 907 235 7775",
    "sg:postcode":"99603",
    "sg:province":"AK",
    "sg:website":"www.oceanshoresalaska.com",
    "wof:name":"Ocean Shores Motel",
    "wof:placetype":"venue"
},
  "geometry": {"coordinates":[-151.55309800000001,59.641954],"type":"Point"}
}