{
  "type": "Feature",
  "properties": {
    "iso:country":"US",
    "sg:address":"1150 Helen Dr",
    "sg:city":"Palmer",
    "sg:classifiers":[
        {
            "category":"Organizations",
            "subcategory":"Religious Organization",
            "type":"Services"
        }
    ],
    "sg:phone":"+1 907 745 4483",
    "sg:postcode":"99645",
    "sg:province":"AK",
    "sg:tags":[
        "church"
    ],
    "sg:website":"www.firstbaptistpalmer.com",
    "wof:name":"First Baptist Church",
    "wof:placetype":"venue"
},
  "geometry": {"coordinates":[-149.16057000000001,61.590794],"type":"Point"}
}