{
  "type": "Feature",
  "properties": {
    "iso:country":"US",
    "sg:address":"150 N Willow St",
    "sg:city":"Kenai",
    "sg:classifiers":[
        {
            "category":"Building & Trades",
            "subcategory":"Construction",
            "type":"Services"
        }
    ],
    "sg:phone":"+1 907 335 5454",
    "sg:postcode":"99611",
    "sg:province":"AK",
    "sg:tags":[
        "general",
        "contractor"
    ],
    "wof:name":"Goode Construction",
    "wof:placetype":"venue"
},
  "geometry": {"coordinates":[-151.24834899999999,60.561231],"type":"Point"}
}