{
  "type": "Feature",
  "properties": {
    "iso:country":"US",
    "sg:address":"1620 Shore Dr",
    "sg:city":"Anchorage",
    "sg:classifiers":[
        {
            "category":"Health Services",
            "subcategory":"Clinic",
            "type":"Services"
        }
    ],
    "sg:phone":"+1 907 336 7439",
    "sg:postcode":"99515",
    "sg:province":"AK",
    "sg:tags":[
        "alternative",
        "care"
    ],
    "wof:name":"Whirling Rainbow",
    "wof:placetype":"venue"
},
  "geometry": {"coordinates":[-149.906229,61.108936],"type":"Point"}
}