{
  "type": "Feature",
  "properties": {
    "iso:country":"US",
    "sg:address":"1990 Phillips Field Rd",
    "sg:city":"Fairbanks",
    "sg:classifiers":[
        {
            "category":"Shopping",
            "subcategory":"Clothing, Apparel, & Fashions",
            "type":"Retail Goods"
        }
    ],
    "sg:phone":"+1 907 374 8378",
    "sg:postcode":"99701",
    "sg:province":"AK",
    "sg:tags":[
        "garment"
    ],
    "wof:name":"Maniak Collectibles",
    "wof:placetype":"venue"
},
  "geometry": {"coordinates":[-147.763939,64.84614],"type":"Point"}
}