{
  "type": "Feature",
  "properties": {
    "addr:full":"3700 de Armoun Rd Anchorage AK 99516",
    "addr:housenumber":"3700",
    "addr:postcode":"99516",
    "addr:street":"De Armoun Rd",
    "iso:country":"US",
    "sg:address":"3700 de Armoun Rd",
    "sg:city":"Anchorage",
    "sg:classifiers":[
        {
            "category":"Social Services",
            "subcategory":"Child Care",
            "type":"Services"
        }
    ],
    "sg:phone":"+1 907 345 5176",
    "sg:postcode":"99516",
    "sg:province":"AK",
    "wof:name":"Grandma's House",
    "wof:placetype":"venue"
},
  "geometry": {"coordinates":[-149.812569,61.094099],"type":"Point"}
}