{
  "type": "Feature",
  "properties": {
    "addr:full":"102 2nd St Fairbanks AK 99701",
    "addr:housenumber":"102",
    "addr:postcode":"99701",
    "addr:street":"2Nd St",
    "iso:country":"US",
    "sg:address":"102 2nd St",
    "sg:city":"Fairbanks",
    "sg:classifiers":[
        {
            "category":"Shopping",
            "subcategory":"Used Merchandise",
            "type":"Retail Goods"
        }
    ],
    "sg:phone":"+1 907 356 1458",
    "sg:postcode":"99701",
    "sg:province":"AK",
    "sg:tags":[
        "shop",
        "thrift"
    ],
    "wof:name":"Community Thrift Shop",
    "wof:placetype":"venue"
},
  "geometry": {"coordinates":[-147.706636,64.84745700000001],"type":"Point"}
}