{
  "type": "Feature",
  "properties": {
    "addr:full":"411 W 4th Ave Anchorage AK 99501",
    "addr:housenumber":"411",
    "addr:postcode":"99501",
    "addr:street":"W 4Th Ave",
    "iso:country":"US",
    "sg:address":"411 W 4th Ave",
    "sg:city":"Anchorage",
    "sg:classifiers":[
        {
            "category":"Wholesale",
            "subcategory":"Electrical",
            "type":"Manufacturing & Wholesale Goods"
        }
    ],
    "sg:phone":"+1 907 274 2695",
    "sg:postcode":"99501",
    "sg:province":"AK",
    "sg:tags":[
        "alarm",
        "burglar",
        "system"
    ],
    "wof:name":"ADT Security Svc",
    "wof:placetype":"venue"
},
  "geometry": {"coordinates":[-149.89134799999999,61.218626],"type":"Point"}
}