{
  "type": "Feature",
  "properties": {
    "iso:country":"US",
    "sg:address":"520 Saint Lazaria Cir",
    "sg:city":"Anchorage",
    "sg:classifiers":[
        {
            "category":"Travel",
            "subcategory":"Hotels & Motels",
            "type":"Entertainment"
        }
    ],
    "sg:phone":"+1 907 333 6574",
    "sg:postcode":"99508",
    "sg:province":"AK",
    "sg:tags":[
        "breakfast",
        "accommodation",
        "bed"
    ],
    "wof:name":"Lady Di's Bed & Breakfast",
    "wof:placetype":"venue"
},
  "geometry": {"coordinates":[-149.784995,61.217291],"type":"Point"}
}