{
  "type": "Feature",
  "properties": {
    "iso:country":"US",
    "sg:address":"2396 Kachemak Dr",
    "sg:city":"Homer",
    "sg:classifiers":[
        {
            "category":"Home & Garden",
            "subcategory":"Building Materials",
            "type":"Retail Goods"
        }
    ],
    "sg:phone":"+1 907 235 6791",
    "sg:postcode":"99603",
    "sg:province":"AK",
    "sg:tags":[
        "mixed",
        "concrete"
    ],
    "wof:name":"Best Transit Mix",
    "wof:placetype":"venue"
},
  "geometry": {"coordinates":[-151.474378,59.641671],"type":"Point"}
}