{
  "type": "Feature",
  "properties": {
    "addr:full":"1132 E 74th Ave Anchorage AK 99518",
    "addr:housenumber":"1132",
    "addr:postcode":"99518",
    "addr:street":"E 74Th Ave",
    "iso:country":"US",
    "sg:address":"1132 E 74th Ave",
    "sg:city":"Anchorage",
    "sg:classifiers":[
        {
            "category":"Wholesale",
            "subcategory":"Vending Machines",
            "type":"Manufacturing & Wholesale Goods"
        }
    ],
    "sg:phone":"+1 907 522 1937",
    "sg:postcode":"99518",
    "sg:province":"AK",
    "sg:website":"www.vendalaska.com",
    "wof:name":"Vend Alaska",
    "wof:placetype":"venue"
},
  "geometry": {"coordinates":[-149.860724,61.153415],"type":"Point"}
}