{
  "type": "Feature",
  "properties": {
    "iso:country":"US",
    "sg:address":"1399 Springwater Dr",
    "sg:city":"Fairbanks",
    "sg:classifiers":[
        {
            "category":"Organizations",
            "subcategory":"Religious Organization",
            "type":"Services"
        }
    ],
    "sg:phone":"+1 907 457 2644",
    "sg:postcode":"99712",
    "sg:province":"AK",
    "sg:tags":[
        "church"
    ],
    "wof:name":"American Baptist Church",
    "wof:placetype":"venue"
},
  "geometry": {"coordinates":[-147.63401099999999,64.925889],"type":"Point"}
}