{
  "type": "Feature",
  "properties": {
    "iso:country":"US",
    "sg:address":"3241 Richmond Ave",
    "sg:city":"Anchorage",
    "sg:classifiers":[
        {
            "category":"Building & Trades",
            "subcategory":"Cleaning & Sanitation",
            "type":"Services"
        }
    ],
    "sg:phone":"+1 907 338 3646",
    "sg:postcode":"99508",
    "sg:province":"AK",
    "sg:tags":[
        "janitor"
    ],
    "wof:name":"Mom & Dad's Old Fashion Cleani",
    "wof:placetype":"venue"
},
  "geometry": {"coordinates":[-149.821283,61.225137],"type":"Point"}
}