{
  "type": "Feature",
  "properties": {
    "iso:country":"US",
    "sg:address":"101 E 92nd Ave",
    "sg:city":"Anchorage",
    "sg:classifiers":[
        {
            "category":"Mining & Drilling",
            "type":"Manufacturing & Wholesale Goods"
        }
    ],
    "sg:phone":"+1 907 349 6091",
    "sg:postcode":"99515",
    "sg:province":"AK",
    "sg:tags":[
        "field",
        "oil"
    ],
    "wof:name":"Tankco Alaska Inc",
    "wof:placetype":"venue"
},
  "geometry": {"coordinates":[-149.878901,61.137508],"type":"Point"}
}