{
  "type": "Feature",
  "properties": {
    "iso:country":"US",
    "sg:address":"2302 Roosevelt Dr",
    "sg:city":"Anchorage",
    "sg:classifiers":[
        {
            "category":"Building & Trades",
            "subcategory":"Construction",
            "type":"Services"
        }
    ],
    "sg:phone":"+1 907 332 9554",
    "sg:postcode":"99517",
    "sg:province":"AK",
    "sg:tags":[
        "home",
        "improvement"
    ],
    "wof:name":"Straightline Siding",
    "wof:placetype":"venue"
},
  "geometry": {"coordinates":[-149.927796,61.181543],"type":"Point"}
}