{
  "type": "Feature",
  "properties": {
    "iso:country":"US",
    "sg:address":"425 S Franklin St",
    "sg:city":"Juneau",
    "sg:classifiers":[
        {
            "category":"Shopping",
            "subcategory":"Gifts & Souvenirs",
            "type":"Retail Goods"
        }
    ],
    "sg:phone":"+1 907 463 5595",
    "sg:postcode":"99801",
    "sg:province":"AK",
    "sg:tags":[
        "shop"
    ],
    "wof:name":"Alaska Juneau Mining Co",
    "wof:placetype":"venue"
},
  "geometry": {"coordinates":[-134.401309,58.297122],"type":"Point"}
}