{
  "type": "Feature",
  "properties": {
    "iso:country":"US",
    "sg:address":"907 E Dowling Rd",
    "sg:city":"Anchorage",
    "sg:classifiers":[
        {
            "category":"Education",
            "subcategory":"Special Training",
            "type":"Public Place"
        }
    ],
    "sg:phone":"+1 907 569 0909",
    "sg:postcode":"99518",
    "sg:province":"AK",
    "sg:tags":[
        "tutoring"
    ],
    "wof:name":"Noonnoppi Math & Language",
    "wof:placetype":"venue"
},
  "geometry": {"coordinates":[-149.86510699999999,61.166466],"type":"Point"}
}