{
  "type": "Feature",
  "properties": {
    "iso:country":"US",
    "sg:address":"1010 W 30th Ave",
    "sg:city":"Anchorage",
    "sg:classifiers":[
        {
            "category":"Travel",
            "subcategory":"Hotels & Motels",
            "type":"Entertainment"
        }
    ],
    "sg:phone":"+1 907 563 2959",
    "sg:postcode":"99503",
    "sg:province":"AK",
    "wof:name":"Eazy Inn",
    "wof:placetype":"venue"
},
  "geometry": {"coordinates":[-149.905318,61.192979],"type":"Point"}
}