{
  "type": "Feature",
  "properties": {
    "iso:country":"US",
    "sg:address":"2655 Old Glenn Hwy",
    "sg:city":"Palmer",
    "sg:classifiers":[
        {
            "category":"Travel",
            "subcategory":"Hotels & Motels",
            "type":"Entertainment"
        }
    ],
    "sg:phone":"+1 907 746 6214",
    "sg:postcode":"99645",
    "sg:province":"AK",
    "sg:tags":[
        "breakfast",
        "accommodation",
        "bed"
    ],
    "wof:name":"River Crest Manor B & B",
    "wof:placetype":"venue"
},
  "geometry": {"coordinates":[-149.034662,61.544032],"type":"Point"}
}