{
  "type": "Feature",
  "properties": {
    "addr:full":"43977 Sterling Hwy Soldotna AK 99669",
    "addr:housenumber":"43977",
    "addr:postcode":"99669",
    "addr:street":"Sterling Hwy",
    "iso:country":"US",
    "sg:address":"43977 Sterling Hwy",
    "sg:city":"Soldotna",
    "sg:classifiers":[
        {
            "category":"Social Services",
            "type":"Services"
        }
    ],
    "sg:phone":"+1 907 260 5400",
    "sg:postcode":"99669",
    "sg:province":"AK",
    "sg:tags":[
        "counseling"
    ],
    "wof:name":"Transitions",
    "wof:placetype":"venue"
},
  "geometry": {"coordinates":[-151.05604500000001,60.486633],"type":"Point"}
}