{
  "type": "Feature",
  "properties": {
    "addr:full":"4211 Arctic Blvd Anchorage AK 99503",
    "addr:housenumber":"4211",
    "addr:postcode":"99503",
    "addr:street":"Arctic Blvd",
    "iso:country":"US",
    "sg:address":"4211 Arctic Blvd",
    "sg:city":"Anchorage",
    "sg:classifiers":[
        {
            "category":"Organizations",
            "subcategory":"Community Association",
            "type":"Services"
        }
    ],
    "sg:phone":"+1 907 563 3502",
    "sg:postcode":"99503",
    "sg:province":"AK",
    "sg:tags":[
        "fraternal"
    ],
    "wof:name":"Loyal Order Of Moose",
    "wof:placetype":"venue"
},
  "geometry": {"coordinates":[-149.89787899999999,61.181388],"type":"Point"}
}