{
  "type": "Feature",
  "properties": {
    "iso:country":"US",
    "sg:address":"550 W 7th Ave",
    "sg:city":"Anchorage",
    "sg:classifiers":[
        {
            "category":"Organizations",
            "subcategory":"Professional Association",
            "type":"Services"
        }
    ],
    "sg:phone":"+1 907 272 7469",
    "sg:postcode":"99501",
    "sg:province":"AK",
    "sg:tags":[
        "attorney"
    ],
    "sg:website":"www.alaskabar.org",
    "wof:name":"Alaska Bar Assn",
    "wof:placetype":"venue"
},
  "geometry": {"coordinates":[-149.892769,61.215523],"type":"Point"}
}