{
  "type": "Feature",
  "properties": {
    "iso:country":"US",
    "sg:address":"300 Wedgewood Dr",
    "sg:city":"Fairbanks",
    "sg:classifiers":[
        {
            "category":"Real Estate",
            "subcategory":"Real Estate Operator",
            "type":"Services"
        }
    ],
    "sg:phone":"+1 907 451 0455",
    "sg:postcode":"99701",
    "sg:province":"AK",
    "sg:tags":[
        "apartment"
    ],
    "wof:name":"Willow Woods Apartments",
    "wof:placetype":"venue"
},
  "geometry": {"coordinates":[-147.718276,64.860967],"type":"Point"}
}