{
  "type": "Feature",
  "properties": {
    "iso:country":"US",
    "sg:address":"3966 Mattox Rd",
    "sg:city":"Homer",
    "sg:classifiers":[
        {
            "category":"Shopping",
            "type":"Retail Goods"
        }
    ],
    "sg:phone":"+1 907 235 6659",
    "sg:postcode":"99603",
    "sg:province":"AK",
    "sg:tags":[
        "stamp",
        "collector",
        "for"
    ],
    "wof:name":"Stamp Act",
    "wof:placetype":"venue"
},
  "geometry": {"coordinates":[-151.51091600000001,59.647365],"type":"Point"}
}