{
  "type": "Feature",
  "properties": {
    "iso:country":"US",
    "sg:address":"2508 Blueberry Rd",
    "sg:city":"Anchorage",
    "sg:classifiers":[
        {
            "category":"Education",
            "subcategory":"School",
            "type":"Public Place"
        }
    ],
    "sg:phone":"+1 907 742 4950",
    "sg:postcode":"99503",
    "sg:province":"AK",
    "wof:name":"Steller Secondary",
    "wof:placetype":"venue"
},
  "geometry": {"coordinates":[-149.891621,61.196933],"type":"Point"}
}