{
  "type": "Feature",
  "properties": {
    "iso:country":"US",
    "sg:address":"4211 Spenard Rd",
    "sg:city":"Anchorage",
    "sg:classifiers":[
        {
            "category":"Retail",
            "subcategory":"Auto Rental",
            "type":"Services"
        }
    ],
    "sg:phone":"+1 907 243 8806",
    "sg:postcode":"99517",
    "sg:province":"AK",
    "sg:tags":[
        "renting",
        "automobile"
    ],
    "wof:name":"Advantage Car & Van Rental",
    "wof:placetype":"venue"
},
  "geometry": {"coordinates":[-149.928623,61.183029],"type":"Point"}
}