{
  "type": "Feature",
  "properties": {
    "iso:country":"US",
    "sg:address":"701 E Parks Hwy",
    "sg:city":"Wasilla",
    "sg:classifiers":[
        {
            "category":"Professional",
            "subcategory":"Business Services",
            "type":"Services"
        }
    ],
    "sg:phone":"+1 907 376 3211",
    "sg:postcode":"99654",
    "sg:province":"AK",
    "sg:tags":[
        "paging",
        "answering"
    ],
    "wof:name":"Matanuska Telephone",
    "wof:placetype":"venue"
},
  "geometry": {"coordinates":[-149.43305100000001,61.581009],"type":"Point"}
}