{
  "type": "Feature",
  "properties": {
    "iso:country":"US",
    "sg:address":"1655 Okpik St",
    "sg:city":"Barrow",
    "sg:classifiers":[
        {
            "category":"Health Services",
            "subcategory":"Chiropractor",
            "type":"Services"
        }
    ],
    "sg:phone":"+1 907 852 3099",
    "sg:postcode":"99723",
    "sg:province":"AK",
    "wof:name":"Barrow Chiropractic Clinic",
    "wof:placetype":"venue"
},
  "geometry": {"coordinates":[-156.768871,71.289012],"type":"Point"}
}