{
  "type": "Feature",
  "properties": {
    "addr:full":"3437 Airport Way Fairbanks AK 99709",
    "addr:housenumber":"3437",
    "addr:postcode":"99709",
    "addr:street":"Airport Way",
    "iso:country":"US",
    "sg:address":"3437 Airport Way",
    "sg:city":"Fairbanks",
    "sg:classifiers":[
        {
            "category":"Professional",
            "subcategory":"Engineering",
            "type":"Services"
        }
    ],
    "sg:phone":"+1 907 479 7720",
    "sg:postcode":"99709",
    "sg:province":"AK",
    "sg:tags":[
        "engineer"
    ],
    "wof:name":"Shaw Environmental/Infrstrctr",
    "wof:placetype":"venue"
},
  "geometry": {"coordinates":[-147.803618,64.83671699999999],"type":"Point"}
}