{
  "type": "Feature",
  "properties": {
    "addr:full":"220 Minnie St Fairbanks AK 99701",
    "addr:housenumber":"220",
    "addr:postcode":"99701",
    "addr:street":"Minnie St",
    "iso:country":"US",
    "sg:address":"220 Minnie St",
    "sg:city":"Fairbanks",
    "sg:classifiers":[
        {
            "category":"Retail",
            "subcategory":"Repair Shop",
            "type":"Services"
        }
    ],
    "sg:phone":"+1 907 456 2593",
    "sg:postcode":"99701",
    "sg:province":"AK",
    "sg:tags":[
        "clocks",
        "parts"
    ],
    "wof:name":"Antique & Modern Clock Repairs",
    "wof:placetype":"venue"
},
  "geometry": {"coordinates":[-147.711108,64.849273],"type":"Point"}
}