{
  "type": "Feature",
  "properties": {
    "iso:country":"US",
    "sg:address":"202 S Forest Dr",
    "sg:city":"Kenai",
    "sg:classifiers":[
        {
            "category":"Real Estate",
            "subcategory":"Real Estate Operator",
            "type":"Services"
        }
    ],
    "sg:phone":"+1 907 283 2866",
    "sg:postcode":"99611",
    "sg:province":"AK",
    "sg:tags":[
        "apartment"
    ],
    "wof:name":"North Country Rentals",
    "wof:placetype":"venue"
},
  "geometry": {"coordinates":[-151.277659,60.557338],"type":"Point"}
}