{
  "type": "Feature",
  "properties": {
    "iso:country":"US",
    "sg:address":"170 N Birch Ln",
    "sg:city":"Soldotna",
    "sg:classifiers":[
        {
            "category":"Real Estate",
            "subcategory":"Real Estate Agent",
            "type":"Services"
        }
    ],
    "sg:phone":"+1 907 262 1770",
    "sg:postcode":"99669",
    "sg:province":"AK",
    "sg:website":"www.freedomrealty.com",
    "wof:name":"Freedom Realty",
    "wof:placetype":"venue"
},
  "geometry": {"coordinates":[-151.06490700000001,60.490147],"type":"Point"}
}