{
  "type": "Feature",
  "properties": {
    "addr:full":"6241 A St Anchorage AK 99518",
    "addr:housenumber":"6241",
    "addr:postcode":"99518",
    "addr:street":"A St",
    "iso:country":"US",
    "sg:address":"6241 A St",
    "sg:city":"Anchorage",
    "sg:classifiers":[
        {
            "category":"Retail",
            "subcategory":"Auto Repair",
            "type":"Services"
        }
    ],
    "sg:phone":"+1 907 562 3991",
    "sg:postcode":"99518",
    "sg:province":"AK",
    "sg:tags":[
        "body",
        "automobile",
        "painting"
    ],
    "wof:name":"Jerry's Place",
    "wof:placetype":"venue"
},
  "geometry": {"coordinates":[-149.881494,61.162832],"type":"Point"}
}