{
  "type": "Feature",
  "properties": {
    "iso:country":"US",
    "sg:address":"1310 E Dimond Blvd",
    "sg:city":"Anchorage",
    "sg:classifiers":[
        {
            "category":"Shopping",
            "subcategory":"Hobbies, Toys, & Games",
            "type":"Retail Goods"
        }
    ],
    "sg:phone":"+1 907 522 8184",
    "sg:postcode":"99515",
    "sg:province":"AK",
    "wof:name":"Over The Rainbow Toy Store",
    "wof:placetype":"venue"
},
  "geometry": {"coordinates":[-149.858816,61.144662],"type":"Point"}
}