{
  "type": "Feature",
  "properties": {
    "addr:full":"1300 W 56th Ave Anchorage AK 99518",
    "addr:housenumber":"1300",
    "addr:postcode":"99518",
    "addr:street":"W 56Th Ave",
    "iso:country":"US",
    "sg:address":"1300 W 56th Ave",
    "sg:city":"Anchorage",
    "sg:classifiers":[
        {
            "category":"Shopping",
            "subcategory":"Music",
            "type":"Retail Goods"
        }
    ],
    "sg:phone":"+1 907 561 4117",
    "sg:postcode":"99518",
    "sg:province":"AK",
    "sg:tags":[
        "video",
        "disc",
        "tape",
        "cassette"
    ],
    "wof:name":"John's Apa Video",
    "wof:placetype":"venue"
},
  "geometry": {"coordinates":[-149.91290100000001,61.170009],"type":"Point"}
}