{
  "type": "Feature",
  "properties": {
    "iso:country":"US",
    "sg:address":"4112 Blackerby St",
    "sg:city":"Juneau",
    "sg:classifiers":[
        {
            "category":"Professional",
            "subcategory":"Computer Services",
            "type":"Services"
        }
    ],
    "sg:phone":"+1 907 790 3386",
    "sg:postcode":"99801",
    "sg:province":"AK",
    "sg:tags":[
        "consultant",
        "designer",
        "datum",
        "system"
    ],
    "sg:website":"www.norcomsoftware.com",
    "wof:name":"Norcom Cobol Software",
    "wof:placetype":"venue"
},
  "geometry": {"coordinates":[-134.48570699999999,58.338031],"type":"Point"}
}