{
  "type": "Feature",
  "properties": {
    "addr:full":"101 Marine Way W Kodiak AK 99615",
    "addr:housenumber":"101",
    "addr:postcode":"99615",
    "addr:street":"Marine Way W",
    "iso:country":"US",
    "sg:address":"101 Marine Way W",
    "sg:city":"Kodiak",
    "sg:classifiers":[
        {
            "category":"Museum",
            "type":"Entertainment"
        }
    ],
    "sg:phone":"+1 907 486 5920",
    "sg:postcode":"99615",
    "sg:province":"AK",
    "wof:name":"Kodiak Historical Society",
    "wof:placetype":"venue"
},
  "geometry": {"coordinates":[-152.403325,57.787328],"type":"Point"}
}