{
  "type": "Feature",
  "properties": {
    "iso:country":"US",
    "sg:address":"195 E Bunnell Ave",
    "sg:city":"Homer",
    "sg:classifiers":[
        {
            "category":"Government",
            "subcategory":"Office",
            "type":"Public Place"
        }
    ],
    "sg:phone":"+1 907 235 8136",
    "sg:postcode":"99603",
    "sg:province":"AK",
    "wof:name":"District Recorder",
    "wof:placetype":"venue"
},
  "geometry": {"coordinates":[-151.542732,59.639667],"type":"Point"}
}