{
  "type": "Feature",
  "properties": {
    "iso:country":"US",
    "sg:address":"819 Orca St",
    "sg:city":"Anchorage",
    "sg:classifiers":[
        {
            "category":"Building & Trades",
            "subcategory":"Electrical",
            "type":"Services"
        }
    ],
    "sg:phone":"+1 907 272 4531",
    "sg:postcode":"99501",
    "sg:province":"AK",
    "sg:tags":[
        "electrical",
        "contractor"
    ],
    "sg:website":"www.cityelectricinc.com",
    "wof:name":"City Electric Inc",
    "wof:placetype":"venue"
},
  "geometry": {"coordinates":[-149.854604,61.21483],"type":"Point"}
}