{
  "type": "Feature",
  "properties": {
    "iso:country":"US",
    "sg:address":"600 E Railroad Ave",
    "sg:city":"Wasilla",
    "sg:classifiers":[
        {
            "category":"Education",
            "subcategory":"School",
            "type":"Public Place"
        }
    ],
    "sg:phone":"+1 907 373 3570",
    "sg:postcode":"99654",
    "sg:province":"AK",
    "wof:name":"Correspondence Study Program",
    "wof:placetype":"venue"
},
  "geometry": {"coordinates":[-149.433439,61.579571],"type":"Point"}
}