{
  "type": "Feature",
  "properties": {
    "iso:country":"US",
    "sg:address":"1925 E Village Loop",
    "sg:city":"Wasilla",
    "sg:classifiers":[
        {
            "category":"Building & Trades",
            "subcategory":"Construction",
            "type":"Services"
        }
    ],
    "sg:phone":"+1 907 373 8688",
    "sg:postcode":"99654",
    "sg:province":"AK",
    "sg:tags":[
        "contractor"
    ],
    "wof:name":"Arctic Mermaid Mosaics",
    "wof:placetype":"venue"
},
  "geometry": {"coordinates":[-149.40312900000001,61.607474],"type":"Point"}
}