{
  "type": "Feature",
  "properties": {
    "iso:country":"US",
    "sg:address":"3804 Spenard Rd",
    "sg:city":"Anchorage",
    "sg:classifiers":[
        {
            "category":"Retail",
            "subcategory":"Funeral Services",
            "type":"Services"
        }
    ],
    "sg:phone":"+1 907 279 3741",
    "sg:postcode":"99517",
    "sg:province":"AK",
    "sg:tags":[
        "crematory"
    ],
    "sg:website":"www.evergreenfuneral.com",
    "wof:name":"Alaska Cremation Ctr",
    "wof:placetype":"venue"
},
  "geometry": {"coordinates":[-149.915746,61.186534],"type":"Point"}
}