{
  "type": "Feature",
  "properties": {
    "iso:country":"US",
    "sg:address":"710 Orca St",
    "sg:city":"Anchorage",
    "sg:classifiers":[
        {
            "category":"Building & Trades",
            "subcategory":"Construction",
            "type":"Services"
        }
    ],
    "sg:phone":"+1 907 277 3434",
    "sg:postcode":"99501",
    "sg:province":"AK",
    "sg:tags":[
        "mfg",
        "construct",
        "install",
        "cabinet"
    ],
    "wof:name":"Indian Mountain Woodworks",
    "wof:placetype":"venue"
},
  "geometry": {"coordinates":[-149.854754,61.214653],"type":"Point"}
}