{
  "type": "Feature",
  "properties": {
    "addr:full":"601 E Pioneer Ave Homer AK 99603",
    "addr:housenumber":"601",
    "addr:postcode":"99603",
    "addr:street":"E Pioneer Ave",
    "iso:country":"US",
    "sg:address":"601 E Pioneer Ave",
    "sg:city":"Homer",
    "sg:classifiers":[
        {
            "category":"Retail",
            "subcategory":"Photofinishing",
            "type":"Services"
        }
    ],
    "sg:phone":"+1 907 235 8525",
    "sg:postcode":"99603",
    "sg:province":"AK",
    "sg:tags":[
        "photo",
        "finishing"
    ],
    "sg:website":"www.eagleeyephoto.com",
    "wof:name":"Eagle Eye Photography",
    "wof:placetype":"venue"
},
  "geometry": {"coordinates":[-151.53158199999999,59.646988],"type":"Point"}
}