{
  "type": "Feature",
  "properties": {
    "iso:country":"US",
    "sg:address":"5234 Glacier Hwy",
    "sg:city":"Juneau",
    "sg:classifiers":[
        {
            "category":"Restaurant",
            "type":"Food & Drink"
        }
    ],
    "sg:phone":"+1 907 780 6878",
    "sg:postcode":"99801",
    "sg:province":"AK",
    "sg:tags":[
        "shop",
        "coffee"
    ],
    "wof:name":"Heritage II Go-Lemon Creek",
    "wof:placetype":"venue"
},
  "geometry": {"coordinates":[-134.49121400000001,58.351955],"type":"Point"}
}