{
  "type": "Feature",
  "properties": {
    "iso:country":"US",
    "sg:address":"511 W 41st Ave",
    "sg:city":"Anchorage",
    "sg:classifiers":[
        {
            "category":"Organizations",
            "subcategory":"Non-profit Organization",
            "type":"Services"
        }
    ],
    "sg:phone":"+1 907 563 1115",
    "sg:postcode":"99503",
    "sg:province":"AK",
    "wof:name":"National Multiple Sclerosis",
    "wof:placetype":"venue"
},
  "geometry": {"coordinates":[-149.897898,61.184096],"type":"Point"}
}