{
  "type": "Feature",
  "properties": {
    "iso:country":"US",
    "sg:address":"325 Front St",
    "sg:city":"Wrangell",
    "sg:classifiers":[
        {
            "category":"Social Services",
            "type":"Services"
        }
    ],
    "sg:phone":"+1 907 874 3482",
    "sg:postcode":"99929",
    "sg:province":"AK",
    "sg:tags":[
        "organization",
        "welfare"
    ],
    "wof:name":"Tlingit & Haida Social Svc",
    "wof:placetype":"venue"
},
  "geometry": {"coordinates":[-132.382582,56.471153],"type":"Point"}
}