{
  "type": "Feature",
  "properties": {
    "iso:country":"US",
    "sg:address":"8800 Glacier Hwy",
    "sg:city":"Juneau",
    "sg:classifiers":[
        {
            "category":"Professional",
            "subcategory":"Accounting & Tax Preparation",
            "type":"Services"
        }
    ],
    "sg:phone":"+1 907 789 0899",
    "sg:postcode":"99801",
    "sg:province":"AK",
    "sg:tags":[
        "bookkeeping",
        "general"
    ],
    "wof:name":"Key Bookkeeping",
    "wof:placetype":"venue"
},
  "geometry": {"coordinates":[-134.579578,58.36306],"type":"Point"}
}