{
  "type": "Feature",
  "properties": {
    "iso:country":"US",
    "sg:address":"3565 Arctic Blvd",
    "sg:city":"Anchorage",
    "sg:classifiers":[
        {
            "category":"Shopping",
            "subcategory":"Clothing, Apparel, & Fashions",
            "type":"Retail Goods"
        }
    ],
    "sg:phone":"+1 907 562 3487",
    "sg:postcode":"99503",
    "sg:province":"AK",
    "sg:website":"www.stringbeans.net",
    "wof:name":"Threads",
    "wof:placetype":"venue"
},
  "geometry": {"coordinates":[-149.897884,61.188298],"type":"Point"}
}