{
  "type": "Feature",
  "properties": {
    "iso:country":"US",
    "sg:address":"1980 Red Berry Rd",
    "sg:city":"Fairbanks",
    "sg:phone":"+1 907 374 1082",
    "sg:postcode":"99709",
    "sg:province":"AK",
    "sg:tags":[
        "engine",
        "equipment",
        "diesel"
    ],
    "wof:name":"Diesel Engine Sales Intl",
    "wof:placetype":"venue"
},
  "geometry": {"coordinates":[-147.84863100000001,64.951267],"type":"Point"}
}