{
  "type": "Feature",
  "properties": {
    "iso:country":"US",
    "sg:address":"412 Cope St",
    "sg:city":"Kodiak",
    "sg:classifiers":[
        {
            "category":"Airline",
            "type":"Transportation"
        }
    ],
    "sg:phone":"+1 907 486 4400",
    "sg:postcode":"99615",
    "sg:province":"AK",
    "sg:tags":[
        "helicopter",
        "rental"
    ],
    "wof:name":"Maritime Helicopters",
    "wof:placetype":"venue"
},
  "geometry": {"coordinates":[-152.414273,57.788364],"type":"Point"}
}