{
  "type": "Feature",
  "properties": {
    "iso:country":"US",
    "sg:address":"7250 Dawn Dr",
    "sg:city":"Anchorage",
    "sg:classifiers":[
        {
            "category":"Banks & Credit Unions",
            "subcategory":"Investment Brokerage",
            "type":"Services"
        }
    ],
    "sg:phone":"+1 907 243 2307",
    "sg:postcode":"99502",
    "sg:province":"AK",
    "sg:tags":[
        "advisory",
        "financial",
        "remodeling"
    ],
    "wof:name":"Bob Jacobs Enterprises",
    "wof:placetype":"venue"
},
  "geometry": {"coordinates":[-149.954941,61.154734],"type":"Point"}
}