{
  "type": "Feature",
  "properties": {
    "addr:full":"1601 Trail Cir Wasilla AK 99654",
    "addr:housenumber":"1601",
    "addr:postcode":"99654",
    "addr:street":"Trail Cir",
    "iso:country":"US",
    "sg:address":"1601 Trail Cir",
    "sg:city":"Wasilla",
    "sg:classifiers":[
        {
            "category":"Building & Trades",
            "subcategory":"Landscaping Services",
            "type":"Services"
        }
    ],
    "sg:phone":"+1 907 357 0270",
    "sg:postcode":"99654",
    "sg:province":"AK",
    "sg:tags":[
        "tree"
    ],
    "wof:name":"Su Valley Landclearing",
    "wof:placetype":"venue"
},
  "geometry": {"coordinates":[-149.454387,61.598195],"type":"Point"}
}