{
  "type": "Feature",
  "properties": {
    "addr:full":"3207 Denali St Anchorage AK 99503",
    "addr:housenumber":"3207",
    "addr:postcode":"99503",
    "addr:street":"Denali St",
    "iso:country":"US",
    "sg:address":"3207 Denali St",
    "sg:city":"Anchorage",
    "sg:classifiers":[
        {
            "category":"Retail",
            "subcategory":"Auto Repair",
            "type":"Services"
        }
    ],
    "sg:phone":"+1 907 277 4253",
    "sg:postcode":"99503",
    "sg:province":"AK",
    "sg:tags":[
        "automobile",
        "diagnostic"
    ],
    "wof:name":"Hale's Technical Svc",
    "wof:placetype":"venue"
},
  "geometry": {"coordinates":[-149.876599,61.191245],"type":"Point"}
}