{
  "type": "Feature",
  "properties": {
    "iso:country":"US",
    "sg:address":"2627 Karluk St",
    "sg:city":"Anchorage",
    "sg:classifiers":[
        {
            "category":"Building & Trades",
            "subcategory":"Construction",
            "type":"Services"
        }
    ],
    "sg:phone":"+1 907 274 2210",
    "sg:postcode":"99508",
    "sg:province":"AK",
    "sg:tags":[
        "plastering",
        "contractor"
    ],
    "wof:name":"Suter Enterprises",
    "wof:placetype":"venue"
},
  "geometry": {"coordinates":[-149.86159799999999,61.196753],"type":"Point"}
}