{
  "type": "Feature",
  "properties": {
    "iso:country":"US",
    "sg:address":"1158 Lake Shore Dr",
    "sg:city":"Homer",
    "sg:classifiers":[
        {
            "category":"Building & Trades",
            "subcategory":"Equipment Rental",
            "type":"Services"
        }
    ],
    "sg:phone":"+1 907 235 8924",
    "sg:postcode":"99603",
    "sg:province":"AK",
    "sg:tags":[
        "aircraft",
        "leasing",
        "charter"
    ],
    "sg:website":"www.alaskaseaplanes.com",
    "wof:name":"Kachemak Bay Flying Svc Inc",
    "wof:placetype":"venue"
},
  "geometry": {"coordinates":[-151.51191600000001,59.639562],"type":"Point"}
}