{
  "type": "Feature",
  "properties": {
    "iso:country":"US",
    "sg:address":"1501 Huffman Rd",
    "sg:city":"Anchorage",
    "sg:classifiers":[
        {
            "category":"Retail",
            "subcategory":"Laundry & Dry Cleaning",
            "type":"Services"
        }
    ],
    "sg:phone":"+1 907 345 4631",
    "sg:postcode":"99515",
    "sg:province":"AK",
    "sg:tags":[
        "cleaners"
    ],
    "wof:name":"Alaska Cleaners",
    "wof:placetype":"venue"
},
  "geometry": {"coordinates":[-149.85268,61.108661],"type":"Point"}
}