{
  "type": "Feature",
  "properties": {
    "iso:country":"US",
    "sg:address":"3350 Commercial Dr",
    "sg:city":"Anchorage",
    "sg:classifiers":[
        {
            "category":"Social Services",
            "subcategory":"Child Care",
            "type":"Services"
        }
    ],
    "sg:phone":"+1 907 563 1966",
    "sg:postcode":"99501",
    "sg:province":"AK",
    "wof:name":"Child Care Connection Inc",
    "wof:placetype":"venue"
},
  "geometry": {"coordinates":[-149.81670800000001,61.224078],"type":"Point"}
}