{
  "type": "Feature",
  "properties": {
    "iso:country":"US",
    "sg:address":"7041 E Tree Ct",
    "sg:city":"Anchorage",
    "sg:classifiers":[
        {
            "category":"Health Services",
            "subcategory":"Chiropractor",
            "type":"Services"
        }
    ],
    "sg:phone":"+1 907 563 7700",
    "sg:postcode":"99507",
    "sg:province":"AK",
    "wof:name":"Chiropractic Health Clinic",
    "wof:placetype":"venue"
},
  "geometry": {"coordinates":[-149.750684,61.124406],"type":"Point"}
}