{
  "type": "Feature",
  "properties": {
    "iso:country":"US",
    "sg:address":"48355 Murwood Ave",
    "sg:city":"Soldotna",
    "sg:classifiers":[
        {
            "category":"Shopping",
            "type":"Retail Goods"
        }
    ],
    "sg:phone":"+1 907 262 5231",
    "sg:postcode":"99669",
    "sg:province":"AK",
    "wof:name":"Breed's Forest Products",
    "wof:placetype":"venue"
},
  "geometry": {"coordinates":[-151.186769,60.502141],"type":"Point"}
}