{
  "type": "Feature",
  "properties": {
    "addr:full":"309 James St Kenai AK 99611",
    "addr:housenumber":"309",
    "addr:postcode":"99611",
    "addr:street":"James St",
    "iso:country":"US",
    "sg:address":"309 James St",
    "sg:city":"Kenai",
    "sg:classifiers":[
        {
            "category":"Building & Trades",
            "subcategory":"Construction",
            "type":"Services"
        }
    ],
    "sg:phone":"+1 907 283 6087",
    "sg:postcode":"99611",
    "sg:province":"AK",
    "sg:tags":[
        "general",
        "contractor"
    ],
    "wof:name":"Discount Construction",
    "wof:placetype":"venue"
},
  "geometry": {"coordinates":[-151.19877099999999,60.564706],"type":"Point"}
}