{
  "type": "Feature",
  "properties": {
    "addr:full":"2209 Jordan Ave Juneau AK 99801",
    "addr:housenumber":"2209",
    "addr:postcode":"99801",
    "addr:street":"Jordan Ave",
    "iso:country":"US",
    "sg:address":"2209 Jordan Ave",
    "sg:city":"Juneau",
    "sg:classifiers":[
        {
            "category":"Professional",
            "subcategory":"Accounting & Tax Preparation",
            "type":"Services"
        }
    ],
    "sg:phone":"+1 907 789 7881",
    "sg:postcode":"99801",
    "sg:province":"AK",
    "sg:tags":[
        "accountant"
    ],
    "wof:name":"Brown & Assoc",
    "wof:placetype":"venue"
},
  "geometry": {"coordinates":[-134.578982,58.364969],"type":"Point"}
}