{
  "type": "Feature",
  "properties": {
    "addr:full":"1780 Peger Rd Fairbanks AK 99709",
    "addr:housenumber":"1780",
    "addr:postcode":"99709",
    "addr:street":"Peger Rd",
    "iso:country":"US",
    "sg:address":"1780 Peger Rd",
    "sg:city":"Fairbanks",
    "sg:classifiers":[
        {
            "category":"Restaurant",
            "type":"Food & Drink"
        }
    ],
    "sg:phone":"+1 907 457 6777",
    "sg:postcode":"99709",
    "sg:province":"AK",
    "sg:tags":[
        "shop",
        "coffee"
    ],
    "wof:name":"Forget Me Not Espresso",
    "wof:placetype":"venue"
},
  "geometry": {"coordinates":[-147.77861100000001,64.8326],"type":"Point"}
}