{
  "type": "Feature",
  "properties": {
    "iso:country":"US",
    "sg:address":"2909 Ludecker St",
    "sg:city":"Fairbanks",
    "sg:classifiers":[
        {
            "category":"Real Estate",
            "subcategory":"Real Estate Agent",
            "type":"Services"
        }
    ],
    "sg:phone":"+1 907 474 1035",
    "sg:postcode":"99709",
    "sg:province":"AK",
    "sg:tags":[
        "consultant"
    ],
    "wof:name":"Riverside Juice Bar",
    "wof:placetype":"venue"
},
  "geometry": {"coordinates":[-147.93406300000001,64.80144199999999],"type":"Point"}
}