{
  "type": "Feature",
  "properties": {
    "iso:country":"US",
    "sg:address":"11500 Daryl Ave",
    "sg:city":"Anchorage",
    "sg:classifiers":[
        {
            "category":"Real Estate",
            "subcategory":"Surveying",
            "type":"Services"
        }
    ],
    "sg:phone":"+1 907 522 6476",
    "sg:postcode":"99515",
    "sg:province":"AK",
    "sg:tags":[
        "surveyor"
    ],
    "wof:name":"Lang & Assoc Inc",
    "wof:placetype":"venue"
},
  "geometry": {"coordinates":[-149.86242899999999,61.116453],"type":"Point"}
}