{
  "type": "Feature",
  "properties": {
    "iso:country":"US",
    "sg:address":"917 Mill Bay Rd",
    "sg:city":"Kodiak",
    "sg:classifiers":[
        {
            "category":"Shopping",
            "subcategory":"Hobbies, Toys, & Games",
            "type":"Retail Goods"
        }
    ],
    "sg:phone":"+1 907 486 4900",
    "sg:postcode":"99615",
    "sg:province":"AK",
    "sg:tags":[
        "craft",
        "supply"
    ],
    "wof:name":"Castle Rock Arts & Crafts",
    "wof:placetype":"venue"
},
  "geometry": {"coordinates":[-152.394184,57.795443],"type":"Point"}
}