{
  "type": "Feature",
  "properties": {
    "addr:full":"1001 Enterprise St Wasilla AK 99654",
    "addr:housenumber":"1001",
    "addr:postcode":"99654",
    "addr:street":"Enterprise St",
    "iso:country":"US",
    "sg:address":"1001 Enterprise St",
    "sg:city":"Wasilla",
    "sg:classifiers":[
        {
            "category":"Wholesale",
            "subcategory":"Vending Machines",
            "type":"Manufacturing & Wholesale Goods"
        }
    ],
    "sg:phone":"+1 907 373 4920",
    "sg:postcode":"99654",
    "sg:province":"AK",
    "wof:name":"Tri Valley Vending",
    "wof:placetype":"venue"
},
  "geometry": {"coordinates":[-149.40511599999999,61.572585],"type":"Point"}
}