{
  "type": "Feature",
  "properties": {
    "iso:country":"US",
    "sg:address":"455 3rd Ave",
    "sg:city":"Fairbanks",
    "sg:classifiers":[
        {
            "category":"Professional",
            "subcategory":"Lawyer & Legal Services",
            "type":"Services"
        }
    ],
    "sg:phone":"+1 907 456 3383",
    "sg:postcode":"99701",
    "sg:province":"AK",
    "sg:tags":[
        "attorney"
    ],
    "wof:name":"Paul English Law Office",
    "wof:placetype":"venue"
},
  "geometry": {"coordinates":[-147.716005,64.843059],"type":"Point"}
}