{
  "type": "Feature",
  "properties": {
    "addr:full":"658 Ptarmigan St Bethel AK 99559",
    "addr:housenumber":"658",
    "addr:postcode":"99559",
    "addr:street":"Ptarmigan St",
    "iso:country":"US",
    "sg:address":"658 Ptarmigan St",
    "sg:city":"Bethel",
    "sg:classifiers":[
        {
            "category":"Shopping",
            "subcategory":"Discount & Variety Stores",
            "type":"Retail Goods"
        }
    ],
    "sg:phone":"+1 907 543 3090",
    "sg:postcode":"99559",
    "sg:province":"AK",
    "sg:tags":[
        "merchandise",
        "general"
    ],
    "wof:name":"Quick Stop",
    "wof:placetype":"venue"
},
  "geometry": {"coordinates":[-161.79969,60.805122],"type":"Point"}
}