{
  "type": "Feature",
  "properties": {
    "iso:country":"US",
    "sg:address":"201 E 54th Ave",
    "sg:city":"Anchorage",
    "sg:classifiers":[
        {
            "category":"Wholesale",
            "subcategory":"Hardware",
            "type":"Manufacturing & Wholesale Goods"
        }
    ],
    "sg:phone":"+1 907 345 3483",
    "sg:postcode":"99518",
    "sg:province":"AK",
    "sg:tags":[
        "ventilating",
        "equipment"
    ],
    "wof:name":"Heating & Ventilation Sales",
    "wof:placetype":"venue"
},
  "geometry": {"coordinates":[-149.881021,61.171669],"type":"Point"}
}