{
  "type": "Feature",
  "properties": {
    "iso:country":"US",
    "sg:address":"11701 Brayton Dr",
    "sg:city":"Anchorage",
    "sg:classifiers":[
        {
            "category":"Organizations",
            "subcategory":"Community Association",
            "type":"Services"
        }
    ],
    "sg:phone":"+1 907 276 1351",
    "sg:postcode":"99516",
    "sg:province":"AK",
    "sg:tags":[
        "fraternal"
    ],
    "wof:name":"Elks Lodge",
    "wof:placetype":"venue"
},
  "geometry": {"coordinates":[-149.85455200000001,61.114505],"type":"Point"}
}