{
  "type": "Feature",
  "properties": {
    "addr:full":"389 S Franklin St Juneau AK 99801",
    "addr:housenumber":"389",
    "addr:postcode":"99801",
    "addr:street":"S Franklin St",
    "iso:country":"US",
    "sg:address":"389 S Franklin St",
    "sg:city":"Juneau",
    "sg:classifiers":[
        {
            "category":"Shopping",
            "subcategory":"Gifts & Souvenirs",
            "type":"Retail Goods"
        }
    ],
    "sg:phone":"+1 907 586 2778",
    "sg:postcode":"99801",
    "sg:province":"AK",
    "sg:tags":[
        "shop"
    ],
    "wof:name":"Russian Shop",
    "wof:placetype":"venue"
},
  "geometry": {"coordinates":[-134.40204199999999,58.297842],"type":"Point"}
}