{
  "type": "Feature",
  "properties": {
    "iso:country":"US",
    "sg:address":"4920 Fairbanks St",
    "sg:city":"Anchorage",
    "sg:classifiers":[
        {
            "category":"Professional",
            "type":"Services"
        }
    ],
    "sg:phone":"+1 907 677 7246",
    "sg:postcode":"99503",
    "sg:province":"AK",
    "sg:tags":[
        "establishment"
    ],
    "wof:name":"Allen & Peterson",
    "wof:placetype":"venue"
},
  "geometry": {"coordinates":[-149.873022,61.174707],"type":"Point"}
}