{
  "type": "Feature",
  "properties": {
    "iso:country":"US",
    "sg:address":"7928 King St",
    "sg:city":"Anchorage",
    "sg:classifiers":[
        {
            "category":"Wholesale",
            "subcategory":"Machinery & Supplies",
            "type":"Manufacturing & Wholesale Goods"
        }
    ],
    "sg:phone":"+1 907 349 0280",
    "sg:postcode":"99518",
    "sg:province":"AK",
    "sg:tags":[
        "gage"
    ],
    "wof:name":"Paramount Supply Co",
    "wof:placetype":"venue"
},
  "geometry": {"coordinates":[-149.87793199999999,61.150952],"type":"Point"}
}