{
  "type": "Feature",
  "properties": {
    "iso:country":"US",
    "sg:address":"3155 Pioneer Ave",
    "sg:city":"Juneau",
    "sg:classifiers":[
        {
            "category":"Banks & Credit Unions",
            "subcategory":"Investment Brokerage",
            "type":"Services"
        }
    ],
    "sg:phone":"+1 907 463 1554",
    "sg:postcode":"99801",
    "sg:province":"AK",
    "sg:tags":[
        "stock",
        "bond"
    ],
    "wof:name":"Arbor Capital Management",
    "wof:placetype":"venue"
},
  "geometry": {"coordinates":[-134.431151,58.291294],"type":"Point"}
}