{
  "type": "Feature",
  "properties": {
    "iso:country":"US",
    "sg:address":"1830 Crest St",
    "sg:city":"Juneau",
    "sg:classifiers":[
        {
            "category":"Professional",
            "subcategory":"Art Services",
            "type":"Services"
        }
    ],
    "sg:phone":"+1 907 789 1366",
    "sg:postcode":"99801",
    "sg:province":"AK",
    "sg:tags":[
        "photographer"
    ],
    "wof:name":"Photographic Endeavors",
    "wof:placetype":"venue"
},
  "geometry": {"coordinates":[-134.57390799999999,58.360017],"type":"Point"}
}