{
  "type": "Feature",
  "properties": {
    "addr:full":"751 7th Ave Fairbanks AK 99701",
    "addr:housenumber":"751",
    "addr:postcode":"99701",
    "addr:street":"7Th Ave",
    "iso:country":"US",
    "sg:address":"751 7th Ave",
    "sg:city":"Fairbanks",
    "sg:classifiers":[
        {
            "category":"Professional",
            "subcategory":"Lawyer & Legal Services",
            "type":"Services"
        }
    ],
    "sg:phone":"+1 907 456 6056",
    "sg:postcode":"99701",
    "sg:province":"AK",
    "sg:tags":[
        "attorney"
    ],
    "wof:name":"Robert John Law Office",
    "wof:placetype":"venue"
},
  "geometry": {"coordinates":[-147.72918899999999,64.84092099999999],"type":"Point"}
}