{
  "type": "Feature",
  "properties": {
    "iso:country":"US",
    "sg:address":"751 7th Ave",
    "sg:city":"Fairbanks",
    "sg:classifiers":[
        {
            "category":"Professional",
            "subcategory":"Lawyer & Legal Services",
            "type":"Services"
        }
    ],
    "sg:phone":"+1 907 456 6056",
    "sg:postcode":"99701",
    "sg:province":"AK",
    "sg:tags":[
        "attorney"
    ],
    "wof:name":"Robert John Law Office",
    "wof:placetype":"venue"
},
  "geometry": {"coordinates":[-147.729189,64.840921],"type":"Point"}
}