{
  "type": "Feature",
  "properties": {
    "iso:country":"US",
    "sg:address":"221 3rd Ave",
    "sg:city":"Seward",
    "sg:classifiers":[
        {
            "category":"Social Services",
            "type":"Services"
        }
    ],
    "sg:phone":"+1 907 224 3118",
    "sg:postcode":"99664",
    "sg:province":"AK",
    "sg:tags":[
        "organization",
        "welfare"
    ],
    "wof:name":"Qutekcak Native Tribe Health",
    "wof:placetype":"venue"
},
  "geometry": {"coordinates":[-149.44217800000001,60.101368],"type":"Point"}
}