{
  "type": "Feature",
  "properties": {
    "iso:country":"US",
    "sg:address":"2110 E Northern Lights Blvd",
    "sg:city":"Anchorage",
    "sg:classifiers":[
        {
            "category":"Professional",
            "subcategory":"Accounting & Tax Preparation",
            "type":"Services"
        }
    ],
    "sg:phone":"+1 907 561 9191",
    "sg:postcode":"99508",
    "sg:province":"AK",
    "sg:tags":[
        "billing"
    ],
    "wof:name":"ABC Medical Billing Svc",
    "wof:placetype":"venue"
},
  "geometry": {"coordinates":[-149.839921,61.195304],"type":"Point"}
}