{
  "type": "Feature",
  "properties": {
    "iso:country":"US",
    "sg:address":"47 Spr View Dr",
    "sg:city":"Kenai",
    "sg:classifiers":[
        {
            "category":"Bars & Pubs",
            "type":"Food & Drink"
        }
    ],
    "sg:phone":"+1 907 283 3241",
    "sg:postcode":"99611",
    "sg:province":"AK",
    "wof:name":"Back Door Sports Bar",
    "wof:placetype":"venue"
},
  "geometry": {"coordinates":[-151.24454800000001,60.555578],"type":"Point"}
}