{
  "type": "Feature",
  "properties": {
    "addr:full":"224 Yenlo St Wasilla AK 99654",
    "addr:housenumber":"224",
    "addr:postcode":"99654",
    "addr:street":"Yenlo St",
    "iso:country":"US",
    "sg:address":"224 Yenlo St",
    "sg:city":"Wasilla",
    "sg:classifiers":[
        {
            "category":"Personal",
            "subcategory":"Tattoo Parlor",
            "type":"Services"
        }
    ],
    "sg:phone":"+1 907 376 4826",
    "sg:postcode":"99654",
    "sg:province":"AK",
    "sg:tags":[
        "tattooing"
    ],
    "wof:name":"Mat-Su Tattoo & Body Piercing",
    "wof:placetype":"venue"
},
  "geometry": {"coordinates":[-149.437343,61.581269],"type":"Point"}
}