{
  "type": "Feature",
  "properties": {
    "iso:country":"US",
    "sg:address":"264 Katlian St",
    "sg:city":"Sitka",
    "sg:classifiers":[
        {
            "category":"Wholesale",
            "subcategory":"Seafood",
            "type":"Manufacturing & Wholesale Goods"
        }
    ],
    "sg:phone":"+1 907 747 7115",
    "sg:postcode":"99835",
    "sg:province":"AK",
    "sg:website":"www.alaskaseafood.com",
    "wof:name":"Alaska Hook & Line Seafood",
    "wof:placetype":"venue"
},
  "geometry": {"coordinates":[-135.342241,57.051884],"type":"Point"}
}