{
  "type": "Feature",
  "properties": {
    "addr:full":"101 Center St Kodiak AK 99615",
    "addr:housenumber":"101",
    "addr:postcode":"99615",
    "addr:street":"Center St",
    "iso:country":"US",
    "sg:address":"101 Center St",
    "sg:city":"Kodiak",
    "sg:classifiers":[
        {
            "category":"Building & Trades",
            "subcategory":"Equipment Rental",
            "type":"Services"
        }
    ],
    "sg:phone":"+1 907 486 3662",
    "sg:postcode":"99615",
    "sg:province":"AK",
    "sg:tags":[
        "contractor"
    ],
    "wof:name":"Kodiak Rental Ctr",
    "wof:placetype":"venue"
},
  "geometry": {"coordinates":[-152.40708699999999,57.789908],"type":"Point"}
}