{
  "type": "Feature",
  "properties": {
    "iso:country":"US",
    "sg:address":"4300 Tyler Rd",
    "sg:city":"Fairbanks",
    "sg:classifiers":[
        {
            "category":"Building & Trades",
            "subcategory":"Construction",
            "type":"Services"
        }
    ],
    "sg:phone":"+1 907 474 9402",
    "sg:postcode":"99709",
    "sg:province":"AK",
    "sg:tags":[
        "roofing",
        "contractor"
    ],
    "wof:name":"Fairbanks Roofing & Repair",
    "wof:placetype":"venue"
},
  "geometry": {"coordinates":[-148.078425,64.757205],"type":"Point"}
}