{
  "type": "Feature",
  "properties": {
    "iso:country":"US",
    "sg:address":"7930 King St",
    "sg:city":"Anchorage",
    "sg:classifiers":[
        {
            "category":"Professional",
            "subcategory":"Management & Consulting",
            "type":"Services"
        }
    ],
    "sg:phone":"+1 907 562 9927",
    "sg:postcode":"99518",
    "sg:province":"AK",
    "sg:tags":[
        "consultant",
        "energy",
        "conservation"
    ],
    "wof:name":"Alaska Building Science Ntwrk",
    "wof:placetype":"venue"
},
  "geometry": {"coordinates":[-149.87793400000001,61.147926],"type":"Point"}
}