{
  "type": "Feature",
  "properties": {
    "iso:country":"US",
    "sg:address":"810 Amanita Rd",
    "sg:city":"Fairbanks",
    "sg:classifiers":[
        {
            "category":"Professional",
            "subcategory":"Business Services",
            "type":"Services"
        }
    ],
    "sg:phone":"+1 907 488 8658",
    "sg:postcode":"99712",
    "sg:province":"AK",
    "sg:tags":[
        "recording",
        "studio"
    ],
    "sg:website":"www.10thplanet.com",
    "wof:name":"10th Planet Records",
    "wof:placetype":"venue"
},
  "geometry": {"coordinates":[-147.43924799999999,64.89375],"type":"Point"}
}