{
  "type": "Feature",
  "properties": {
    "addr:full":"5331 E Parks Hwy Wasilla AK 99654",
    "addr:housenumber":"5331",
    "addr:postcode":"99654",
    "addr:street":"E Parks Hwy",
    "iso:country":"US",
    "sg:address":"5331 E Parks Hwy",
    "sg:city":"Wasilla",
    "sg:classifiers":[
        {
            "category":"Farming",
            "subcategory":"Nursery",
            "type":"Manufacturing & Wholesale Goods"
        }
    ],
    "sg:phone":"+1 907 376 5199",
    "sg:postcode":"99654",
    "sg:province":"AK",
    "sg:tags":[
        "center",
        "garden",
        "greenhouse"
    ],
    "wof:name":"Northern Lights Nursery",
    "wof:placetype":"venue"
},
  "geometry": {"coordinates":[-149.31715600000001,61.568707],"type":"Point"}
}