{
  "type": "Feature",
  "properties": {
    "iso:country":"US",
    "sg:address":"3307 Spenard Rd",
    "sg:city":"Anchorage",
    "sg:classifiers":[
        {
            "category":"Social Services",
            "subcategory":"Child Care",
            "type":"Services"
        }
    ],
    "sg:phone":"+1 907 561 5513",
    "sg:postcode":"99503",
    "sg:province":"AK",
    "wof:name":"Spenard Kiddy Drop",
    "wof:placetype":"venue"
},
  "geometry": {"coordinates":[-149.90746999999999,61.190406],"type":"Point"}
}