{
  "type": "Feature",
  "properties": {
    "addr:full":"2824 Rampart Dr Anchorage AK 99501",
    "addr:housenumber":"2824",
    "addr:postcode":"99501",
    "addr:street":"Rampart Dr",
    "iso:country":"US",
    "sg:address":"2824 Rampart Dr",
    "sg:city":"Anchorage",
    "sg:classifiers":[
        {
            "category":"Freight",
            "type":"Transportation"
        }
    ],
    "sg:phone":"+1 907 276 3535",
    "sg:postcode":"99501",
    "sg:province":"AK",
    "sg:tags":[
        "terminal",
        "line",
        "barge"
    ],
    "sg:website":"www.northlandservices.com",
    "wof:name":"Alaska Cargo Transport",
    "wof:placetype":"venue"
},
  "geometry": {"coordinates":[-149.82341500000001,61.221542],"type":"Point"}
}