{
  "type": "Feature",
  "properties": {
    "addr:full":"360 W Benson Blvd Anchorage AK 99503",
    "addr:housenumber":"360",
    "addr:postcode":"99503",
    "addr:street":"W Benson Blvd",
    "iso:country":"US",
    "sg:address":"360 W Benson Blvd",
    "sg:city":"Anchorage",
    "sg:classifiers":[
        {
            "category":"Professional",
            "subcategory":"Advertising",
            "type":"Services"
        }
    ],
    "sg:phone":"+1 907 561 2450",
    "sg:postcode":"99503",
    "sg:province":"AK",
    "wof:name":"Alaska Publishers Reps",
    "wof:placetype":"venue"
},
  "geometry": {"coordinates":[-149.88843900000001,61.194185],"type":"Point"}
}