{
  "type": "Feature",
  "properties": {
    "addr:full":"19561 Klondike Dr Chugiak AK 99567",
    "addr:housenumber":"19561",
    "addr:postcode":"99567",
    "addr:street":"Klondike Dr",
    "iso:country":"US",
    "sg:address":"19561 Klondike Dr",
    "sg:city":"Chugiak",
    "sg:classifiers":[
        {
            "category":"Shopping",
            "subcategory":"Hobbies, Toys, & Games",
            "type":"Retail Goods"
        }
    ],
    "sg:phone":"+1 907 688 9545",
    "sg:postcode":"99567",
    "sg:province":"AK",
    "sg:tags":[
        "doll"
    ],
    "wof:name":"Mc Goldrick Import Dolls",
    "wof:placetype":"venue"
},
  "geometry": {"coordinates":[-149.519689,61.381353],"type":"Point"}
}