{
  "type": "Feature",
  "properties": {
    "iso:country":"US",
    "sg:address":"2000 W Dimond Blvd",
    "sg:city":"Anchorage",
    "sg:classifiers":[
        {
            "category":"Shopping",
            "subcategory":"Department Store",
            "type":"Retail Goods"
        }
    ],
    "sg:phone":"+1 907 267 6760",
    "sg:postcode":"99515",
    "sg:province":"AK",
    "wof:name":"Fred Meyer One Stop Shopping",
    "wof:placetype":"venue"
},
  "geometry": {"coordinates":[-149.921976,61.137485],"type":"Point"}
}