{
  "type": "Feature",
  "properties": {
    "addr:full":"5716 Debarr Rd Anchorage AK 99504",
    "addr:housenumber":"5716",
    "addr:postcode":"99504",
    "addr:street":"Debarr Rd",
    "iso:country":"US",
    "sg:address":"5716 Debarr Rd",
    "sg:city":"Anchorage",
    "sg:classifiers":[
        {
            "category":"Restaurant",
            "type":"Food & Drink"
        }
    ],
    "sg:menulink":"http://www.allmenus.com/ak/anchorage/190071-mcdonalds/menu/",
    "sg:postcode":"99504",
    "sg:province":"AK",
    "sg:tags":[
        "burger",
        "american"
    ],
    "wof:name":"McDonald's",
    "wof:placetype":"venue"
},
  "geometry": {"coordinates":[-149.775229,61.209583],"type":"Point"}
}