{
  "type": "Feature",
  "properties": {
    "addr:full":"5200 Airport Industrial Rd Fairbanks AK 99709",
    "addr:housenumber":"5200",
    "addr:postcode":"99709",
    "addr:street":"Airport Industrial Rd",
    "iso:country":"US",
    "sg:address":"5200 Airport Industrial Rd",
    "sg:city":"Fairbanks",
    "sg:classifiers":[
        {
            "category":"Freight",
            "type":"Transportation"
        }
    ],
    "sg:phone":"+1 907 479 9566",
    "sg:postcode":"99709",
    "sg:province":"AK",
    "wof:name":"Midnight Sun Transportation",
    "wof:placetype":"venue"
},
  "geometry": {"coordinates":[-147.877623,64.814215],"type":"Point"}
}