{
  "type": "Feature",
  "properties": {
    "addr:full":"4705 Gambell St Anchorage AK 99503",
    "addr:housenumber":"4705",
    "addr:postcode":"99503",
    "addr:street":"Gambell St",
    "iso:country":"US",
    "sg:address":"4705 Gambell St",
    "sg:city":"Anchorage",
    "sg:classifiers":[
        {
            "category":"Professional",
            "subcategory":"Management & Consulting",
            "type":"Services"
        }
    ],
    "sg:phone":"+1 907 561 4669",
    "sg:postcode":"99503",
    "sg:province":"AK",
    "sg:tags":[
        "marketing",
        "consultant"
    ],
    "wof:name":"Thought Co",
    "wof:placetype":"venue"
},
  "geometry": {"coordinates":[-149.87079399999999,61.177962],"type":"Point"}
}