{
  "type": "Feature",
  "properties": {
    "addr:full":"150 3rd St Juneau AK 99801",
    "addr:housenumber":"150",
    "addr:postcode":"99801",
    "addr:street":"3Rd St",
    "iso:country":"US",
    "sg:address":"150 3rd St",
    "sg:city":"Juneau",
    "sg:classifiers":[
        {
            "category":"Government",
            "subcategory":"Office",
            "type":"Public Place"
        }
    ],
    "sg:phone":"+1 907 465 4700",
    "sg:postcode":"99801",
    "sg:province":"AK",
    "wof:name":"Community Regional Affrs Dept",
    "wof:placetype":"venue"
},
  "geometry": {"coordinates":[-134.40927199999999,58.301531],"type":"Point"}
}