{
  "type": "Feature",
  "properties": {
    "addr:full":"510 W Tudor Rd Anchorage AK 99503",
    "addr:housenumber":"510",
    "addr:postcode":"99503",
    "addr:street":"W Tudor Rd",
    "iso:country":"US",
    "sg:address":"510 W Tudor Rd",
    "sg:city":"Anchorage",
    "sg:classifiers":[
        {
            "category":"Shopping",
            "type":"Retail Goods"
        }
    ],
    "sg:phone":"+1 907 929 4080",
    "sg:postcode":"99503",
    "sg:province":"AK",
    "sg:tags":[
        "art",
        "gallery",
        "dealer"
    ],
    "wof:name":"Half Moon Creek Gallery",
    "wof:placetype":"venue"
},
  "geometry": {"coordinates":[-149.89236700000001,61.180734],"type":"Point"}
}