{
  "type": "Feature",
  "properties": {
    "iso:country":"US",
    "sg:address":"710 Mill Bay Rd",
    "sg:city":"Kodiak",
    "sg:classifiers":[
        {
            "category":"Government",
            "subcategory":"Office",
            "type":"Public Place"
        }
    ],
    "sg:phone":"+1 907 486 9301",
    "sg:postcode":"99615",
    "sg:province":"AK",
    "sg:tags":[
        "city"
    ],
    "wof:name":"Kodiak Island Borough Mayor",
    "wof:placetype":"venue"
},
  "geometry": {"coordinates":[-152.395174,57.794859],"type":"Point"}
}