{
  "type": "Feature",
  "properties": {
    "addr:full":"254 Roosevelt St Hoonah AK 99829",
    "addr:housenumber":"254",
    "addr:postcode":"99829",
    "addr:street":"Roosevelt St",
    "iso:country":"US",
    "sg:address":"254 Roosevelt St",
    "sg:city":"Hoonah",
    "sg:classifiers":[
        {
            "category":"Social Services",
            "type":"Services"
        }
    ],
    "sg:phone":"+1 907 945 3230",
    "sg:postcode":"99829",
    "sg:province":"AK",
    "sg:tags":[
        "organization",
        "welfare"
    ],
    "wof:name":"Youth Advocate Project",
    "wof:placetype":"venue"
},
  "geometry": {"coordinates":[-135.44356099999999,58.111834],"type":"Point"}
}