{
  "type": "Feature",
  "properties": {
    "iso:country":"US",
    "sg:address":"325 W 8th Ave",
    "sg:city":"Anchorage",
    "sg:classifiers":[
        {
            "category":"Travel",
            "subcategory":"Hotels & Motels",
            "type":"Entertainment"
        }
    ],
    "sg:phone":"+1 907 274 1000",
    "sg:postcode":"99501",
    "sg:province":"AK",
    "wof:name":"Clarion Suites",
    "wof:placetype":"venue"
},
  "geometry": {"coordinates":[-149.88894999999999,61.214685],"type":"Point"}
}