{
  "type": "Feature",
  "properties": {
    "addr:full":"2009 Radcliffe Rd Juneau AK 99801",
    "addr:housenumber":"2009",
    "addr:postcode":"99801",
    "addr:street":"Radcliffe Rd",
    "iso:country":"US",
    "sg:address":"2009 Radcliffe Rd",
    "sg:city":"Juneau",
    "sg:classifiers":[
        {
            "category":"Government",
            "subcategory":"Office",
            "type":"Public Place"
        }
    ],
    "sg:phone":"+1 907 789 9919",
    "sg:postcode":"99801",
    "sg:province":"AK",
    "sg:tags":[
        "govt",
        "city"
    ],
    "wof:name":"Juneau Waterwaste Utility Div",
    "wof:placetype":"venue"
},
  "geometry": {"coordinates":[-134.596799,58.361214],"type":"Point"}
}