{
  "type": "Feature",
  "properties": {
    "addr:full":"7721 Brentwood Dr Anchorage AK 99502",
    "addr:housenumber":"7721",
    "addr:postcode":"99502",
    "addr:street":"Brentwood Dr",
    "iso:country":"US",
    "sg:address":"7721 Brentwood Dr",
    "sg:city":"Anchorage",
    "sg:classifiers":[
        {
            "category":"Banks & Credit Unions",
            "subcategory":"Investment Brokerage",
            "type":"Services"
        }
    ],
    "sg:phone":"+1 907 677 3873",
    "sg:postcode":"99502",
    "sg:province":"AK",
    "wof:name":"Mahar Investments",
    "wof:placetype":"venue"
},
  "geometry": {"coordinates":[-149.954645,61.150878],"type":"Point"}
}