{
  "type": "Feature",
  "properties": {
    "iso:country":"US",
    "sg:address":"360 Boniface Pkwy",
    "sg:city":"Anchorage",
    "sg:classifiers":[
        {
            "category":"Retail",
            "subcategory":"Animal Services",
            "type":"Services"
        }
    ],
    "sg:phone":"+1 907 333 3132",
    "sg:postcode":"99504",
    "sg:province":"AK",
    "sg:tags":[
        "pet",
        "grooming",
        "specialty"
    ],
    "wof:name":"CS Dog Grooming",
    "wof:placetype":"venue"
},
  "geometry": {"coordinates":[-149.778472,61.2197],"type":"Point"}
}