{
  "type": "Feature",
  "properties": {
    "iso:country":"US",
    "sg:address":"230 Old Steese Hwy",
    "sg:city":"Fairbanks",
    "sg:classifiers":[
        {
            "category":"Insurance",
            "subcategory":"Insurance Agent",
            "type":"Services"
        }
    ],
    "sg:phone":"+1 907 452 4260",
    "sg:postcode":"99701",
    "sg:province":"AK",
    "wof:name":"Dave Mongold Insurance",
    "wof:placetype":"venue"
},
  "geometry": {"coordinates":[-147.705443,64.848071],"type":"Point"}
}