{
  "type": "Feature",
  "properties": {
    "iso:country":"US",
    "sg:address":"315 Main St",
    "sg:city":"Haines",
    "sg:classifiers":[
        {
            "category":"Education",
            "subcategory":"School",
            "type":"Public Place"
        }
    ],
    "sg:phone":"+1 907 766 2811",
    "sg:postcode":"99827",
    "sg:province":"AK",
    "wof:name":"Haines Elementary",
    "wof:placetype":"venue"
},
  "geometry": {"coordinates":[-135.447391,59.235251],"type":"Point"}
}