{
  "type": "Feature",
  "properties": {
    "iso:country":"US",
    "sg:address":"5584 Kenai Spur Hwy",
    "sg:city":"Kenai",
    "sg:classifiers":[
        {
            "category":"Building & Trades",
            "subcategory":"Electrical",
            "type":"Services"
        }
    ],
    "sg:phone":"+1 907 283 6469",
    "sg:postcode":"99611",
    "sg:province":"AK",
    "sg:tags":[
        "electric",
        "contractor"
    ],
    "wof:name":"Dewayne Electric",
    "wof:placetype":"venue"
},
  "geometry": {"coordinates":[-151.110456,60.557611],"type":"Point"}
}