{
  "type": "Feature",
  "properties": {
    "iso:country":"US",
    "sg:address":"2204 Cleveland Ave",
    "sg:city":"Anchorage",
    "sg:classifiers":[
        {
            "category":"Building & Trades",
            "subcategory":"Construction",
            "type":"Services"
        }
    ],
    "sg:phone":"+1 907 248 6789",
    "sg:postcode":"99517",
    "sg:province":"AK",
    "sg:tags":[
        "house",
        "speculative",
        "builder",
        "family"
    ],
    "wof:name":"Hagmeier John Co",
    "wof:placetype":"venue"
},
  "geometry": {"coordinates":[-149.924775,61.184614],"type":"Point"}
}