{
  "type": "Feature",
  "properties": {
    "iso:country":"US",
    "sg:address":"2201 Jordan Ave",
    "sg:city":"Juneau",
    "sg:classifiers":[
        {
            "category":"Professional",
            "subcategory":"Lawyer & Legal Services",
            "type":"Services"
        }
    ],
    "sg:phone":"+1 907 790 2844",
    "sg:postcode":"99801",
    "sg:province":"AK",
    "sg:tags":[
        "attorney"
    ],
    "wof:name":"Loren Domke Law Office",
    "wof:placetype":"venue"
},
  "geometry": {"coordinates":[-134.578913,58.365043],"type":"Point"}
}