{
  "type": "Feature",
  "properties": {
    "iso:country":"US",
    "sg:address":"4973 E 6th Ave",
    "sg:city":"Anchorage",
    "sg:classifiers":[
        {
            "category":"Personal",
            "subcategory":"Beauty Salon",
            "type":"Services"
        }
    ],
    "sg:phone":"+1 907 338 6211",
    "sg:postcode":"99508",
    "sg:province":"AK",
    "wof:name":"Hair By Geneva Cuts For Little",
    "wof:placetype":"venue"
},
  "geometry": {"coordinates":[-149.783988,61.216994],"type":"Point"}
}