{
  "type": "Feature",
  "properties": {
    "addr:full":"841 E Loop Rd Anchorage AK 99501",
    "addr:housenumber":"841",
    "addr:postcode":"99501",
    "addr:street":"E Loop Rd",
    "iso:country":"US",
    "sg:address":"841 E Loop Rd",
    "sg:city":"Anchorage",
    "sg:classifiers":[
        {
            "category":"Organizations",
            "subcategory":"Community Association",
            "type":"Services"
        }
    ],
    "sg:phone":"+1 907 258 7272",
    "sg:postcode":"99501",
    "sg:province":"AK",
    "sg:tags":[
        "military"
    ],
    "wof:name":"NCOA",
    "wof:placetype":"venue"
},
  "geometry": {"coordinates":[-149.87418500000001,61.230496],"type":"Point"}
}