{
  "type": "Feature",
  "properties": {
    "iso:country":"US",
    "sg:address":"1100 S Colony Way",
    "sg:city":"Palmer",
    "sg:classifiers":[
        {
            "category":"Wholesale",
            "subcategory":"Farm Supplies",
            "type":"Manufacturing & Wholesale Goods"
        }
    ],
    "sg:phone":"+1 907 745 3962",
    "sg:postcode":"99645",
    "sg:province":"AK",
    "sg:tags":[
        "animal"
    ],
    "wof:name":"Budget Feed & Farm",
    "wof:placetype":"venue"
},
  "geometry": {"coordinates":[-149.118247,61.593907],"type":"Point"}
}