{
  "type": "Feature",
  "properties": {
    "addr:full":"1840 S Bragaw St Anchorage AK 99508",
    "addr:housenumber":"1840",
    "addr:postcode":"99508",
    "addr:street":"S Bragaw St",
    "iso:country":"US",
    "sg:address":"1840 S Bragaw St",
    "sg:city":"Anchorage",
    "sg:classifiers":[
        {
            "category":"Organizations",
            "subcategory":"Community Association",
            "type":"Services"
        }
    ],
    "sg:phone":"+1 907 562 4155",
    "sg:postcode":"99508",
    "sg:province":"AK",
    "sg:tags":[
        "native"
    ],
    "sg:website":"www.chugachmiut.org",
    "wof:name":"Chugachmiut",
    "wof:placetype":"venue"
},
  "geometry": {"coordinates":[-149.808425,61.204236],"type":"Point"}
}