{
  "type": "Feature",
  "properties": {
    "iso:country":"US",
    "sg:address":"2215 Pool St",
    "sg:city":"North Pole",
    "sg:classifiers":[
        {
            "category":"Autos & Motor Vehicles",
            "subcategory":"Automobile Sales",
            "type":"Retail Goods"
        }
    ],
    "sg:phone":"+1 907 490 1118",
    "sg:postcode":"99705",
    "sg:province":"AK",
    "sg:tags":[
        "snowmobile"
    ],
    "wof:name":"Santa's Motor Sports",
    "wof:placetype":"venue"
},
  "geometry": {"coordinates":[-147.331097,64.787943],"type":"Point"}
}