{
  "type": "Feature",
  "properties": {
    "iso:country":"US",
    "sg:address":"1085 Kiogak St",
    "sg:city":"Barrow",
    "sg:classifiers":[
        {
            "category":"Utilities",
            "subcategory":"Telephone",
            "type":"Services"
        }
    ],
    "sg:phone":"+1 907 852 7100",
    "sg:postcode":"99723",
    "sg:province":"AK",
    "sg:tags":[
        "telecommunication"
    ],
    "wof:name":"Arctic Slope Telephone Assn",
    "wof:placetype":"venue"
},
  "geometry": {"coordinates":[-156.783626,71.293797],"type":"Point"}
}