{
  "type": "Feature",
  "properties": {
    "iso:country":"US",
    "sg:address":"205 Orange Leaf Cir",
    "sg:city":"Anchorage",
    "sg:classifiers":[
        {
            "category":"Travel",
            "subcategory":"Travel Agent",
            "type":"Entertainment"
        }
    ],
    "sg:phone":"+1 907 279 6667",
    "sg:postcode":"99504",
    "sg:province":"AK",
    "sg:tags":[
        "tours",
        "promoter"
    ],
    "wof:name":"Downtown Connection",
    "wof:placetype":"venue"
},
  "geometry": {"coordinates":[-149.719505,61.22233],"type":"Point"}
}