{
  "type": "Feature",
  "properties": {
    "iso:country":"US",
    "sg:address":"1364 Esro Rd",
    "sg:city":"Fairbanks",
    "sg:classifiers":[
        {
            "category":"Home & Garden",
            "subcategory":"Garden Supply",
            "type":"Retail Goods"
        }
    ],
    "sg:phone":"+1 907 488 6446",
    "sg:postcode":"99712",
    "sg:province":"AK",
    "sg:tags":[
        "nurseryman"
    ],
    "wof:name":"Clairs Cultivation",
    "wof:placetype":"venue"
},
  "geometry": {"coordinates":[-147.481755,64.919089],"type":"Point"}
}