{
  "type": "Feature",
  "properties": {
    "addr:full":"1150 Molly Rd Fairbanks AK 99709",
    "addr:housenumber":"1150",
    "addr:postcode":"99709",
    "addr:street":"Molly Rd",
    "iso:country":"US",
    "sg:address":"1150 Molly Rd",
    "sg:city":"Fairbanks",
    "sg:classifiers":[
        {
            "category":"Manufacturing",
            "subcategory":"Metals",
            "type":"Manufacturing & Wholesale Goods"
        }
    ],
    "sg:phone":"+1 907 457 5000",
    "sg:postcode":"99709",
    "sg:province":"AK",
    "sg:tags":[
        "fabrication",
        "structural"
    ],
    "wof:name":"Jons Machine Shop",
    "wof:placetype":"venue"
},
  "geometry": {"coordinates":[-147.74565000000001,64.96588],"type":"Point"}
}