{
  "type": "Feature",
  "properties": {
    "iso:country":"US",
    "sg:address":"113 Galena Dr",
    "sg:city":"Valdez",
    "sg:classifiers":[
        {
            "category":"Travel",
            "subcategory":"Hotels & Motels",
            "type":"Entertainment"
        }
    ],
    "sg:phone":"+1 907 835 2791",
    "sg:postcode":"99686",
    "sg:province":"AK",
    "wof:name":"Downtown B & B Inn",
    "wof:placetype":"venue"
},
  "geometry": {"coordinates":[-146.351428,61.127878],"type":"Point"}
}