{
  "type": "Feature",
  "properties": {
    "addr:full":"308 Portlock St Kenai AK 99611",
    "addr:housenumber":"308",
    "addr:postcode":"99611",
    "addr:street":"Portlock St",
    "iso:country":"US",
    "sg:address":"308 Portlock St",
    "sg:city":"Kenai",
    "sg:classifiers":[
        {
            "category":"Manufacturing",
            "subcategory":"Toys & Sporting Goods",
            "type":"Manufacturing & Wholesale Goods"
        }
    ],
    "sg:phone":"+1 907 283 9541",
    "sg:postcode":"99611",
    "sg:province":"AK",
    "wof:name":"Randall's Glorious Toys",
    "wof:placetype":"venue"
},
  "geometry": {"coordinates":[-151.23039399999999,60.555471],"type":"Point"}
}