{
  "type": "Feature",
  "properties": {
    "iso:country":"US",
    "sg:address":"4801 Old Seward Hwy",
    "sg:city":"Anchorage",
    "sg:classifiers":[
        {
            "category":"Bars & Pubs",
            "type":"Food & Drink"
        }
    ],
    "sg:phone":"+1 907 561 9157",
    "sg:postcode":"99503",
    "sg:province":"AK",
    "sg:tags":[
        "lounge",
        "cocktail"
    ],
    "wof:name":"Club Oasis & Oasis Liquor",
    "wof:placetype":"venue"
},
  "geometry": {"coordinates":[-149.86801399999999,61.174274],"type":"Point"}
}