{
  "type": "Feature",
  "properties": {
    "addr:full":"2000 Okpik St Barrow AK 99723",
    "addr:postcode":"99723",
    "addr:street":"St",
    "iso:country":"US",
    "sg:address":"2000 Okpik St",
    "sg:city":"Barrow",
    "sg:classifiers":[
        {
            "category":"Government",
            "subcategory":"Office",
            "type":"Public Place"
        }
    ],
    "sg:phone":"+1 907 852 0263",
    "sg:postcode":"99723",
    "sg:province":"AK",
    "wof:name":"Children's Receiving Home",
    "wof:placetype":"venue"
},
  "geometry": {"coordinates":[-156.75269,71.288667],"type":"Point"}
}