{
  "type": "Feature",
  "properties": {
    "addr:full":"3112 Airport Way Fairbanks AK 99709",
    "addr:housenumber":"3112",
    "addr:postcode":"99709",
    "addr:street":"Airport Way",
    "iso:country":"US",
    "sg:address":"3112 Airport Way",
    "sg:city":"Fairbanks",
    "sg:classifiers":[
        {
            "category":"Health Services",
            "subcategory":"Doctor",
            "type":"Services"
        }
    ],
    "sg:phone":"+1 907 452 1250",
    "sg:postcode":"99709",
    "sg:province":"AK",
    "sg:tags":[
        "dentist"
    ],
    "wof:name":"Stoltz Dental",
    "wof:placetype":"venue"
},
  "geometry": {"coordinates":[-147.795444,64.83684599999999],"type":"Point"}
}