{
  "type": "Feature",
  "properties": {
    "addr:full":"61285 E End Rd Homer AK 99603",
    "addr:housenumber":"61285",
    "addr:postcode":"99603",
    "addr:street":"E End Rd",
    "iso:country":"US",
    "sg:address":"61285 E End Rd",
    "sg:city":"Homer",
    "sg:classifiers":[
        {
            "category":"Building & Trades",
            "subcategory":"Equipment Rental",
            "type":"Services"
        }
    ],
    "sg:phone":"+1 907 235 6341",
    "sg:postcode":"99603",
    "sg:province":"AK",
    "sg:tags":[
        "contractor"
    ],
    "wof:name":"L P Tool & Equipment Rental",
    "wof:placetype":"venue"
},
  "geometry": {"coordinates":[-151.47054800000001,59.664032],"type":"Point"}
}