{
  "type": "Feature",
  "properties": {
    "iso:country":"US",
    "sg:address":"2522 Arctic Blvd",
    "sg:city":"Anchorage",
    "sg:classifiers":[
        {
            "category":"Professional",
            "subcategory":"Engineering",
            "type":"Services"
        }
    ],
    "sg:phone":"+1 907 276 0521",
    "sg:postcode":"99503",
    "sg:province":"AK",
    "sg:tags":[
        "engineer"
    ],
    "sg:website":"www.rsa-ak.com",
    "wof:name":"RSA Engineering",
    "wof:placetype":"venue"
},
  "geometry": {"coordinates":[-149.89802299999999,61.197123],"type":"Point"}
}