{
  "type": "Feature",
  "properties": {
    "addr:full":"3589 Mendenhall Loop Rd Juneau AK 99801",
    "addr:housenumber":"3589",
    "addr:postcode":"99801",
    "addr:street":"Mendenhall Loop Rd",
    "iso:country":"US",
    "sg:address":"3589 Mendenhall Loop Rd",
    "sg:city":"Juneau",
    "sg:classifiers":[
        {
            "category":"Professional",
            "subcategory":"Computer Services",
            "type":"Services"
        }
    ],
    "sg:phone":"+1 907 789 6332",
    "sg:postcode":"99801",
    "sg:province":"AK",
    "sg:tags":[
        "home",
        "consulting",
        "page",
        "dev",
        "internet"
    ],
    "wof:name":"Purrfect Design",
    "wof:placetype":"venue"
},
  "geometry": {"coordinates":[-134.57497000000001,58.385225],"type":"Point"}
}