{
  "type": "Feature",
  "properties": {
    "iso:country":"US",
    "sg:address":"48379 Golddust Dr",
    "sg:city":"Soldotna",
    "sg:classifiers":[
        {
            "category":"Organizations",
            "subcategory":"Religious Organization",
            "type":"Services"
        }
    ],
    "sg:phone":"+1 907 260 9087",
    "sg:postcode":"99669",
    "sg:province":"AK",
    "wof:name":"Helping Hands Ministry",
    "wof:placetype":"venue"
},
  "geometry": {"coordinates":[-151.163264,60.40723],"type":"Point"}
}