{
  "type": "Feature",
  "properties": {
    "iso:country":"US",
    "sg:address":"8400 Airport Blvd",
    "sg:city":"Juneau",
    "sg:classifiers":[
        {
            "category":"Wholesale",
            "subcategory":"Groceries",
            "type":"Manufacturing & Wholesale Goods"
        }
    ],
    "sg:phone":"+1 907 789 5890",
    "sg:postcode":"99801",
    "sg:province":"AK",
    "sg:tags":[
        "food",
        "product"
    ],
    "wof:name":"Juneau Wholesale",
    "wof:placetype":"venue"
},
  "geometry": {"coordinates":[-134.568881,58.359336],"type":"Point"}
}