{
  "type": "Feature",
  "properties": {
    "iso:country":"US",
    "sg:address":"4500 Mitzie Ct",
    "sg:city":"Wasilla",
    "sg:classifiers":[
        {
            "category":"Building & Trades",
            "subcategory":"Plumbing",
            "type":"Services"
        }
    ],
    "sg:phone":"+1 907 373 7892",
    "sg:postcode":"99654",
    "sg:province":"AK",
    "sg:tags":[
        "plumbing",
        "contractor"
    ],
    "wof:name":"Hard Rok Plumbing & Heating",
    "wof:placetype":"venue"
},
  "geometry": {"coordinates":[-149.337227,61.579168],"type":"Point"}
}