{
  "type": "Feature",
  "properties": {
    "iso:country":"US",
    "sg:address":"3704 Erickson Ave",
    "sg:city":"Fairbanks",
    "sg:classifiers":[
        {
            "category":"Retail",
            "subcategory":"Funeral Services",
            "type":"Services"
        }
    ],
    "sg:phone":"+1 907 451 1110",
    "sg:postcode":"99709",
    "sg:province":"AK",
    "sg:tags":[
        "director"
    ],
    "wof:name":"Fairbanks Funeral Home",
    "wof:placetype":"venue"
},
  "geometry": {"coordinates":[-147.819195,64.832869],"type":"Point"}
}