{
  "type": "Feature",
  "properties": {
    "addr:full":"9138 Arlon St Anchorage AK 99507",
    "addr:postcode":"9138;99507",
    "addr:street":"Arlon St",
    "iso:country":"US",
    "sg:address":"9138 Arlon St",
    "sg:city":"Anchorage",
    "sg:classifiers":[
        {
            "category":"Health Services",
            "subcategory":"Doctor",
            "type":"Services"
        }
    ],
    "sg:phone":"+1 907 561 7110",
    "sg:postcode":"99507",
    "sg:province":"AK",
    "sg:tags":[
        "dentist"
    ],
    "wof:name":"Robert S Matthews DDS",
    "wof:placetype":"venue"
},
  "geometry": {"coordinates":[-149.83607699999999,61.140587],"type":"Point"}
}