{
  "type": "Feature",
  "properties": {
    "addr:full":"2611 Brittany Dr Anchorage AK 99504",
    "addr:housenumber":"2611",
    "addr:postcode":"99504",
    "addr:street":"Brittany Dr",
    "iso:country":"US",
    "sg:address":"2611 Brittany Dr",
    "sg:city":"Anchorage",
    "sg:classifiers":[
        {
            "category":"Manufacturing",
            "subcategory":"Printing",
            "type":"Manufacturing & Wholesale Goods"
        }
    ],
    "sg:phone":"+1 907 333 9101",
    "sg:postcode":"99504",
    "sg:province":"AK",
    "sg:tags":[
        "print",
        "lithographic",
        "architectural",
        "engineer"
    ],
    "wof:name":"Quality Graphics",
    "wof:placetype":"venue"
},
  "geometry": {"coordinates":[-149.75358900000001,61.197452],"type":"Point"}
}