{
  "type": "Feature",
  "properties": {
    "addr:full":"8240 Hartzell Rd Anchorage AK 99507",
    "addr:housenumber":"8240",
    "addr:postcode":"99507",
    "addr:street":"Hartzell Rd",
    "iso:country":"US",
    "sg:address":"8240 Hartzell Rd",
    "sg:city":"Anchorage",
    "sg:classifiers":[
        {
            "category":"Home & Garden",
            "subcategory":"Carpets & Floor Coverings",
            "type":"Retail Goods"
        }
    ],
    "sg:phone":"+1 907 349 5223",
    "sg:postcode":"99507",
    "sg:province":"AK",
    "sg:tags":[
        "dealer",
        "rug"
    ],
    "wof:name":"Ramsey Carpet Svc",
    "wof:placetype":"venue"
},
  "geometry": {"coordinates":[-149.84916699999999,61.146293],"type":"Point"}
}