{
  "type": "Feature",
  "properties": {
    "iso:country":"US",
    "sg:address":"8240 Hartzell Rd",
    "sg:city":"Anchorage",
    "sg:classifiers":[
        {
            "category":"Home & Garden",
            "subcategory":"Carpets & Floor Coverings",
            "type":"Retail Goods"
        }
    ],
    "sg:phone":"+1 907 349 5223",
    "sg:postcode":"99507",
    "sg:province":"AK",
    "sg:tags":[
        "dealer",
        "rug"
    ],
    "wof:name":"Ramsey Carpet Svc",
    "wof:placetype":"venue"
},
  "geometry": {"coordinates":[-149.849167,61.146293],"type":"Point"}
}