{
  "type": "Feature",
  "properties": {
    "iso:country":"US",
    "sg:address":"341 W Tudor Rd",
    "sg:city":"Anchorage",
    "sg:classifiers":[
        {
            "category":"Professional",
            "subcategory":"Management & Consulting",
            "type":"Services"
        }
    ],
    "sg:phone":"+1 907 770 9600",
    "sg:postcode":"99503",
    "sg:province":"AK",
    "sg:tags":[
        "consultant",
        "medical"
    ],
    "wof:name":"Anderson Cronen Lohr Hlthcr",
    "wof:placetype":"venue"
},
  "geometry": {"coordinates":[-149.888375,61.180887],"type":"Point"}
}