{
  "type": "Feature",
  "properties": {
    "addr:full":"1657 E Dowling Rd Anchorage AK 99507",
    "addr:housenumber":"1657",
    "addr:postcode":"99507",
    "addr:street":"E Dowling Rd",
    "iso:country":"US",
    "sg:address":"1657 E Dowling Rd",
    "sg:city":"Anchorage",
    "sg:classifiers":[
        {
            "category":"Retail",
            "subcategory":"Repair Shop",
            "type":"Services"
        }
    ],
    "sg:phone":"+1 907 562 9690",
    "sg:postcode":"99507",
    "sg:province":"AK",
    "sg:tags":[
        "equipment",
        "stereo"
    ],
    "wof:name":"Aerb Auto Sound",
    "wof:placetype":"venue"
},
  "geometry": {"coordinates":[-149.852293,61.166476],"type":"Point"}
}