{
  "type": "Feature",
  "properties": {
    "iso:country":"US",
    "sg:address":"167 Warehouse Dr",
    "sg:city":"Soldotna",
    "sg:classifiers":[
        {
            "category":"Personal",
            "subcategory":"Beauty Salon",
            "type":"Services"
        }
    ],
    "sg:phone":"+1 907 262 9300",
    "sg:postcode":"99669",
    "sg:province":"AK",
    "wof:name":"Soni's Le Ritz",
    "wof:placetype":"venue"
},
  "geometry": {"coordinates":[-151.07698300000001,60.482136],"type":"Point"}
}