{
  "type": "Feature",
  "properties": {
    "addr:full":"2100 Hanson Rd Fairbanks AK 99709",
    "addr:housenumber":"2100",
    "addr:postcode":"99709",
    "addr:street":"Hanson Rd",
    "iso:country":"US",
    "sg:address":"2100 Hanson Rd",
    "sg:city":"Fairbanks",
    "sg:classifiers":[
        {
            "category":"Building & Trades",
            "subcategory":"Construction",
            "type":"Services"
        }
    ],
    "sg:phone":"+1 907 456 7361",
    "sg:postcode":"99709",
    "sg:province":"AK",
    "sg:tags":[
        "insulation",
        "heat",
        "contractor"
    ],
    "wof:name":"Vertex Insulation",
    "wof:placetype":"venue"
},
  "geometry": {"coordinates":[-147.77579,64.852193],"type":"Point"}
}