{
  "type": "Feature",
  "properties": {
    "iso:country":"US",
    "sg:address":"945 E 5th Ave",
    "sg:city":"Anchorage",
    "sg:classifiers":[
        {
            "category":"Manufacturing",
            "subcategory":"Printing",
            "type":"Manufacturing & Wholesale Goods"
        }
    ],
    "sg:phone":"+1 907 258 9455",
    "sg:postcode":"99501",
    "sg:province":"AK",
    "sg:tags":[
        "printer"
    ],
    "wof:name":"SOS Printing",
    "wof:placetype":"venue"
},
  "geometry": {"coordinates":[-149.865543,61.217637],"type":"Point"}
}