{
  "type": "Feature",
  "properties": {
    "addr:full":"5840 Gershmel Loop Palmer AK 99645",
    "addr:housenumber":"5840",
    "addr:postcode":"99645",
    "addr:street":"Gershmel Loop",
    "iso:country":"US",
    "sg:address":"5840 Gershmel Loop",
    "sg:city":"Palmer",
    "sg:classifiers":[
        {
            "category":"Farming",
            "subcategory":"Farm",
            "type":"Manufacturing & Wholesale Goods"
        }
    ],
    "sg:phone":"+1 907 376 3338",
    "sg:postcode":"99645",
    "sg:province":"AK",
    "wof:name":"Triple D Farm & Hatchery",
    "wof:placetype":"venue"
},
  "geometry": {"coordinates":[-149.30686700000001,61.563698],"type":"Point"}
}