{
  "type": "Feature",
  "properties": {
    "iso:country":"US",
    "sg:address":"925 Aurora Dr",
    "sg:city":"Fairbanks",
    "sg:classifiers":[
        {
            "category":"Building & Trades",
            "subcategory":"Construction",
            "type":"Services"
        }
    ],
    "sg:phone":"+1 907 456 5087",
    "sg:postcode":"99709",
    "sg:province":"AK",
    "wof:name":"Earth Movers Of Fairbanks Inc",
    "wof:placetype":"venue"
},
  "geometry": {"coordinates":[-147.76160300000001,64.852475],"type":"Point"}
}