{
  "type": "Feature",
  "properties": {
    "addr:full":"503 W Parks Hwy Wasilla AK 99654",
    "addr:housenumber":"503",
    "addr:postcode":"99654",
    "addr:street":"W Parks Hwy",
    "iso:country":"US",
    "sg:address":"503 W Parks Hwy",
    "sg:city":"Wasilla",
    "sg:classifiers":[
        {
            "category":"Food & Beverages",
            "subcategory":"Groceries & Convenience Stores",
            "type":"Retail Goods"
        }
    ],
    "sg:phone":"+1 907 376 5262",
    "sg:postcode":"99654",
    "sg:province":"AK",
    "sg:tags":[
        "grocer"
    ],
    "wof:name":"D & A Shop Rite",
    "wof:placetype":"venue"
},
  "geometry": {"coordinates":[-149.46267499999999,61.582178],"type":"Point"}
}