{
  "type": "Feature",
  "properties": {
    "iso:country":"US",
    "sg:address":"901 W 6th Ave",
    "sg:city":"Anchorage",
    "sg:classifiers":[
        {
            "category":"Restaurant",
            "type":"Food & Drink"
        }
    ],
    "sg:menulink":"http://www.allmenus.com/ak/anchorage/9624-platinum-jaxx/menu/",
    "sg:phone":"+1 907 278 5299",
    "sg:postcode":"99501",
    "sg:province":"AK",
    "sg:tags":[
        "american"
    ],
    "wof:name":"Platinum Jaxx",
    "wof:placetype":"venue"
},
  "geometry": {"coordinates":[-149.89973599999999,61.216579],"type":"Point"}
}