{
  "type": "Feature",
  "properties": {
    "iso:country":"US",
    "sg:address":"13830 Jarvi Dr",
    "sg:city":"Anchorage",
    "sg:classifiers":[
        {
            "category":"Shopping",
            "type":"Retail Goods"
        }
    ],
    "sg:phone":"+1 907 563 3362",
    "sg:postcode":"99515",
    "sg:province":"AK",
    "sg:tags":[
        "art",
        "gallery",
        "dealer"
    ],
    "wof:name":"Regal Studio",
    "wof:placetype":"venue"
},
  "geometry": {"coordinates":[-149.851757,61.094412],"type":"Point"}
}