{
  "type": "Feature",
  "properties": {
    "addr:full":"44 College Rd Fairbanks AK 99701",
    "addr:housenumber":"44",
    "addr:postcode":"99701",
    "addr:street":"College Rd",
    "iso:country":"US",
    "sg:address":"44 College Rd",
    "sg:city":"Fairbanks",
    "sg:classifiers":[
        {
            "category":"Restaurant",
            "type":"Food & Drink"
        }
    ],
    "sg:phone":"+1 907 452 3313",
    "sg:postcode":"99701",
    "sg:province":"AK",
    "wof:name":"Food Factory",
    "wof:placetype":"venue"
},
  "geometry": {"coordinates":[-147.70076399999999,64.84997199999999],"type":"Point"}
}