{
  "type": "Feature",
  "properties": {
    "iso:country":"US",
    "sg:address":"1100 Gambell St",
    "sg:city":"Anchorage",
    "sg:classifiers":[
        {
            "category":"Shopping",
            "subcategory":"Used Merchandise",
            "type":"Retail Goods"
        }
    ],
    "sg:phone":"+1 907 279 6328",
    "sg:postcode":"99501",
    "sg:province":"AK",
    "sg:tags":[
        "shop",
        "thrift"
    ],
    "wof:name":"Bishop's Attic",
    "wof:placetype":"venue"
},
  "geometry": {"coordinates":[-149.871028,61.210665],"type":"Point"}
}