{
  "type": "Feature",
  "properties": {
    "iso:country":"US",
    "sg:address":"35865 Sunset Park St",
    "sg:city":"Soldotna",
    "sg:classifiers":[
        {
            "category":"Wholesale",
            "subcategory":"Non-durable Goods",
            "type":"Manufacturing & Wholesale Goods"
        }
    ],
    "sg:phone":"+1 907 262 7844",
    "sg:postcode":"99669",
    "sg:province":"AK",
    "wof:name":"All Alaskan Upholstery",
    "wof:placetype":"venue"
},
  "geometry": {"coordinates":[-151.09071900000001,60.498896],"type":"Point"}
}