{
  "type": "Feature",
  "properties": {
    "addr:full":"410 Mission St Ketchikan AK 99901",
    "addr:housenumber":"410",
    "addr:postcode":"99901",
    "addr:street":"Mission St",
    "iso:country":"US",
    "sg:address":"410 Mission St",
    "sg:city":"Ketchikan",
    "sg:classifiers":[
        {
            "category":"Professional",
            "subcategory":"Lawyer & Legal Services",
            "type":"Services"
        }
    ],
    "sg:phone":"+1 907 225 4777",
    "sg:postcode":"99901",
    "sg:province":"AK",
    "sg:tags":[
        "attorney"
    ],
    "wof:name":"Zelensky Attorneys",
    "wof:placetype":"venue"
},
  "geometry": {"coordinates":[-131.64569499999999,55.341714],"type":"Point"}
}