{
  "type": "Feature",
  "properties": {
    "iso:country":"US",
    "sg:address":"320 W 6th Ave",
    "sg:city":"Anchorage",
    "sg:classifiers":[
        {
            "category":"Personal",
            "subcategory":"Beauty Salon",
            "type":"Services"
        }
    ],
    "sg:phone":"+1 907 258 1122",
    "sg:postcode":"99501",
    "sg:province":"AK",
    "sg:website":"www.allurehairdesign.com",
    "wof:name":"Allure Day Spa & Hair Design",
    "wof:placetype":"venue"
},
  "geometry": {"coordinates":[-149.88899,61.216506],"type":"Point"}
}