{
  "type": "Feature",
  "properties": {
    "addr:full":"19466 Upper Skyline Dr Eagle River AK 99577",
    "addr:housenumber":"19466",
    "addr:postcode":"99577",
    "addr:street":"Upper Skyline Dr",
    "iso:country":"US",
    "sg:address":"19466 Upper Skyline Dr",
    "sg:city":"Eagle River",
    "sg:classifiers":[
        {
            "category":"Professional",
            "subcategory":"Computer Services",
            "type":"Services"
        }
    ],
    "sg:phone":"+1 907 694 2818",
    "sg:postcode":"99577",
    "sg:province":"AK",
    "sg:tags":[
        "consultant"
    ],
    "wof:name":"E T Inc",
    "wof:placetype":"venue"
},
  "geometry": {"coordinates":[-149.518878,61.332187],"type":"Point"}
}