{
  "type": "Feature",
  "properties": {
    "addr:full":"6500 Interstate Cir Anchorage AK 99518",
    "addr:housenumber":"6500",
    "addr:postcode":"99518",
    "addr:street":"Interstate Cir",
    "iso:country":"US",
    "sg:address":"6500 Interstate Cir",
    "sg:city":"Anchorage",
    "sg:classifiers":[
        {
            "category":"Building & Trades",
            "subcategory":"Construction",
            "type":"Services"
        }
    ],
    "sg:phone":"+1 907 563 7441",
    "sg:postcode":"99518",
    "sg:province":"AK",
    "sg:tags":[
        "general",
        "contractor"
    ],
    "wof:name":"Watterson Construction Co",
    "wof:placetype":"venue"
},
  "geometry": {"coordinates":[-149.90877699999999,61.161454],"type":"Point"}
}