{
  "type": "Feature",
  "properties": {
    "addr:full":"11501 Old Glenn Hwy Eagle River AK 99577",
    "addr:housenumber":"11501",
    "addr:postcode":"99577",
    "addr:street":"Old Glenn Hwy",
    "iso:country":"US",
    "sg:address":"11501 Old Glenn Hwy",
    "sg:city":"Eagle River",
    "sg:classifiers":[
        {
            "category":"Restaurant",
            "type":"Food & Drink"
        }
    ],
    "sg:phone":"+1 907 694 9120",
    "sg:postcode":"99577",
    "sg:province":"AK",
    "wof:name":"North Slope Restaurant",
    "wof:placetype":"venue"
},
  "geometry": {"coordinates":[-149.57082299999999,61.324435],"type":"Point"}
}