{
  "type": "Feature",
  "properties": {
    "iso:country":"US",
    "sg:address":"9340 Glacier Hwy",
    "sg:city":"Juneau",
    "sg:classifiers":[
        {
            "category":"Professional",
            "subcategory":"Accounting & Tax Preparation",
            "type":"Services"
        }
    ],
    "sg:phone":"+1 907 789 3091",
    "sg:postcode":"99801",
    "sg:province":"AK",
    "sg:tags":[
        "return",
        "filing"
    ],
    "wof:name":"Hauber & James Tax Svc",
    "wof:placetype":"venue"
},
  "geometry": {"coordinates":[-134.590292,58.36632],"type":"Point"}
}