{
  "type": "Feature",
  "properties": {
    "addr:full":"990 Hermon Rd Wasilla AK 99654",
    "addr:housenumber":"990",
    "addr:postcode":"99654",
    "addr:street":"Hermon Rd",
    "iso:country":"US",
    "sg:address":"990 Hermon Rd",
    "sg:city":"Wasilla",
    "sg:classifiers":[
        {
            "category":"Restaurant",
            "type":"Food & Drink"
        }
    ],
    "sg:phone":"+1 907 373 7827",
    "sg:postcode":"99654",
    "sg:province":"AK",
    "wof:name":"Subway Sandwiches & Salads",
    "wof:placetype":"venue"
},
  "geometry": {"coordinates":[-149.39020099999999,61.573876],"type":"Point"}
}