{
  "type": "Feature",
  "properties": {
    "iso:country":"US",
    "sg:address":"321 Egan Ave",
    "sg:city":"Valdez",
    "sg:classifiers":[
        {
            "category":"Retail",
            "subcategory":"Animal Services",
            "type":"Services"
        }
    ],
    "sg:phone":"+1 907 835 2212",
    "sg:postcode":"99686",
    "sg:province":"AK",
    "sg:tags":[
        "pet",
        "grooming",
        "washing"
    ],
    "wof:name":"Pampered Pets",
    "wof:placetype":"venue"
},
  "geometry": {"coordinates":[-146.35862,61.129003],"type":"Point"}
}