{
  "type": "Feature",
  "properties": {
    "iso:country":"US",
    "sg:address":"4425 E 6th Ave",
    "sg:city":"Anchorage",
    "sg:classifiers":[
        {
            "category":"Wholesale",
            "subcategory":"Durable Goods & Equipment",
            "type":"Manufacturing & Wholesale Goods"
        }
    ],
    "sg:phone":"+1 907 333 0000",
    "sg:postcode":"99508",
    "sg:province":"AK",
    "sg:tags":[
        "representative",
        "manufacturer"
    ],
    "wof:name":"Commercial Electric",
    "wof:placetype":"venue"
},
  "geometry": {"coordinates":[-149.79830799999999,61.216997],"type":"Point"}
}