{
  "type": "Feature",
  "properties": {
    "addr:full":"122 Atsaq St Bethel AK 99559",
    "addr:housenumber":"122",
    "addr:postcode":"99559",
    "addr:street":"Atsaq St",
    "iso:country":"US",
    "sg:address":"122 Atsaq St",
    "sg:city":"Bethel",
    "sg:classifiers":[
        {
            "category":"Real Estate",
            "subcategory":"Real Estate Operator",
            "type":"Services"
        }
    ],
    "sg:phone":"+1 907 543 2228",
    "sg:postcode":"99559",
    "sg:province":"AK",
    "sg:tags":[
        "apartment"
    ],
    "wof:name":"Alaska Housing Finance Corp",
    "wof:placetype":"venue"
},
  "geometry": {"coordinates":[-161.77809600000001,60.803328],"type":"Point"}
}