{
  "type": "Feature",
  "properties": {
    "iso:country":"US",
    "sg:address":"411 S Nordic Dr",
    "sg:city":"Petersburg",
    "sg:classifiers":[
        {
            "category":"Travel",
            "subcategory":"Hotels & Motels",
            "type":"Entertainment"
        }
    ],
    "sg:phone":"+1 907 772 3459",
    "sg:postcode":"99833",
    "sg:province":"AK",
    "sg:tags":[
        "breakfast",
        "accommodation",
        "bed"
    ],
    "wof:name":"Broom Hus",
    "wof:placetype":"venue"
},
  "geometry": {"coordinates":[-132.963257,56.80777],"type":"Point"}
}