{
  "type": "Feature",
  "properties": {
    "iso:country":"US",
    "sg:address":"3513 Industrial Ave",
    "sg:city":"Fairbanks",
    "sg:classifiers":[
        {
            "category":"Restaurant",
            "type":"Food & Drink"
        }
    ],
    "sg:phone":"+1 907 456 7829",
    "sg:postcode":"99701",
    "sg:province":"AK",
    "wof:name":"Ethel's Cafe",
    "wof:placetype":"venue"
},
  "geometry": {"coordinates":[-147.75512,64.813171],"type":"Point"}
}