{
  "type": "Feature",
  "properties": {
    "addr:full":"934 Elizabeth St Fairbanks AK 99709",
    "addr:housenumber":"934",
    "addr:postcode":"99709",
    "addr:street":"Elizabeth St",
    "iso:country":"US",
    "sg:address":"934 Elizabeth St",
    "sg:city":"Fairbanks",
    "sg:classifiers":[
        {
            "category":"Freight",
            "type":"Transportation"
        }
    ],
    "sg:phone":"+1 907 452 1863",
    "sg:postcode":"99709",
    "sg:province":"AK",
    "sg:tags":[
        "mover"
    ],
    "wof:name":"World Wide Movers Inc",
    "wof:placetype":"venue"
},
  "geometry": {"coordinates":[-147.76858999999999,64.853812],"type":"Point"}
}