{
  "type": "Feature",
  "properties": {
    "addr:full":"3047 Redwood St Anchorage AK 99508",
    "addr:housenumber":"3047",
    "addr:postcode":"99508",
    "addr:street":"Redwood St",
    "iso:country":"US",
    "sg:address":"3047 Redwood St",
    "sg:city":"Anchorage",
    "sg:classifiers":[
        {
            "category":"Building & Trades",
            "subcategory":"Construction",
            "type":"Services"
        }
    ],
    "sg:phone":"+1 907 349 5442",
    "sg:postcode":"99508",
    "sg:province":"AK",
    "sg:tags":[
        "contractor"
    ],
    "wof:name":"South Central Roofing Inc",
    "wof:placetype":"venue"
},
  "geometry": {"coordinates":[-149.85784799999999,61.19231],"type":"Point"}
}