{
  "type": "Feature",
  "properties": {
    "iso:country":"US",
    "sg:address":"723 27th Ave",
    "sg:city":"Fairbanks",
    "sg:classifiers":[
        {
            "category":"Social Services",
            "type":"Services"
        }
    ],
    "sg:phone":"+1 907 452 5343",
    "sg:postcode":"99701",
    "sg:province":"AK",
    "sg:tags":[
        "organization",
        "welfare"
    ],
    "sg:website":"www.fairbanksrescuemission.org",
    "wof:name":"Fairbanks Rescue Mission",
    "wof:placetype":"venue"
},
  "geometry": {"coordinates":[-147.718069,64.822396],"type":"Point"}
}