{
  "type": "Feature",
  "properties": {
    "iso:country":"US",
    "sg:address":"1939 Commodore Dr",
    "sg:city":"Anchorage",
    "sg:classifiers":[
        {
            "category":"Building & Trades",
            "subcategory":"Construction",
            "type":"Services"
        }
    ],
    "sg:phone":"+1 907 344 1790",
    "sg:postcode":"99507",
    "sg:province":"AK",
    "sg:tags":[
        "floor",
        "laying",
        "contractor"
    ],
    "wof:name":"OFarrells Floor Covering",
    "wof:placetype":"venue"
},
  "geometry": {"coordinates":[-149.844862,61.124668],"type":"Point"}
}