{
  "type": "Feature",
  "properties": {
    "addr:full":"1939 Commodore Dr Anchorage AK 99507",
    "addr:housenumber":"1939",
    "addr:postcode":"99507",
    "addr:street":"Commodore Dr",
    "iso:country":"US",
    "sg:address":"1939 Commodore Dr",
    "sg:city":"Anchorage",
    "sg:classifiers":[
        {
            "category":"Building & Trades",
            "subcategory":"Construction",
            "type":"Services"
        }
    ],
    "sg:phone":"+1 907 344 1790",
    "sg:postcode":"99507",
    "sg:province":"AK",
    "sg:tags":[
        "floor",
        "laying",
        "contractor"
    ],
    "wof:name":"OFarrells Floor Covering",
    "wof:placetype":"venue"
},
  "geometry": {"coordinates":[-149.84486200000001,61.124668],"type":"Point"}
}