{
  "type": "Feature",
  "properties": {
    "iso:country":"US",
    "sg:address":"1624 Tongass Ave",
    "sg:city":"Ketchikan",
    "sg:classifiers":[
        {
            "category":"Building & Trades",
            "subcategory":"Plumbing",
            "type":"Services"
        }
    ],
    "sg:phone":"+1 907 225 3838",
    "sg:postcode":"99901",
    "sg:province":"AK",
    "sg:tags":[
        "plumbing",
        "contractor"
    ],
    "wof:name":"Ron's Plumbing",
    "wof:placetype":"venue"
},
  "geometry": {"coordinates":[-131.66439800000001,55.347434],"type":"Point"}
}