{
  "type": "Feature",
  "properties": {
    "iso:country":"US",
    "sg:address":"5801 Moose Meadow Lane Cir",
    "sg:city":"Anchorage",
    "sg:classifiers":[
        {
            "category":"Recreation",
            "type":"Entertainment"
        }
    ],
    "sg:phone":"+1 907 346 3745",
    "sg:postcode":"99516",
    "sg:province":"AK",
    "sg:tags":[
        "riding",
        "academy"
    ],
    "wof:name":"Eaton Equestrian Centre",
    "wof:placetype":"venue"
},
  "geometry": {"coordinates":[-149.76877,61.116748],"type":"Point"}
}