{
  "type": "Feature",
  "properties": {
    "iso:country":"US",
    "sg:address":"2604 Seward Hwy",
    "sg:city":"Anchorage",
    "sg:classifiers":[
        {
            "category":"Manufacturing",
            "subcategory":"Metals",
            "type":"Manufacturing & Wholesale Goods"
        }
    ],
    "sg:phone":"+1 907 277 0212",
    "sg:postcode":"99503",
    "sg:province":"AK",
    "sg:tags":[
        "fabricator",
        "sheet"
    ],
    "wof:name":"Western Sheet Metal & Controls",
    "wof:placetype":"venue"
},
  "geometry": {"coordinates":[-149.86809099999999,61.196176],"type":"Point"}
}