{
  "type": "Feature",
  "properties": {
    "iso:country":"US",
    "sg:address":"473 Katlian St",
    "sg:city":"Sitka",
    "sg:classifiers":[
        {
            "category":"Recreation",
            "type":"Entertainment"
        }
    ],
    "sg:phone":"+1 907 747 6110",
    "sg:postcode":"99835",
    "sg:province":"AK",
    "sg:tags":[
        "charter",
        "boat"
    ],
    "wof:name":"Aqe Fishermen's Market",
    "wof:placetype":"venue"
},
  "geometry": {"coordinates":[-135.34465,57.053104],"type":"Point"}
}