{
  "type": "Feature",
  "properties": {
    "addr:full":"11120 Chugiak Dr Eagle River AK 99577",
    "addr:housenumber":"11120",
    "addr:postcode":"99577",
    "addr:street":"Chugiak Dr",
    "iso:country":"US",
    "sg:address":"11120 Chugiak Dr",
    "sg:city":"Eagle River",
    "sg:classifiers":[
        {
            "category":"Home & Garden",
            "subcategory":"Garden Supply",
            "type":"Retail Goods"
        }
    ],
    "sg:phone":"+1 907 696 2237",
    "sg:postcode":"99577",
    "sg:province":"AK",
    "sg:tags":[
        "nurseryman"
    ],
    "wof:name":"Wilby's Greenhouse & Nursery",
    "wof:placetype":"venue"
},
  "geometry": {"coordinates":[-149.57568499999999,61.320832],"type":"Point"}
}