{
  "type": "Feature",
  "properties": {
    "iso:country":"US",
    "sg:address":"1971 Wildwood Ln",
    "sg:city":"Anchorage",
    "sg:classifiers":[
        {
            "category":"Real Estate",
            "subcategory":"Real Estate Agent",
            "type":"Services"
        }
    ],
    "sg:phone":"+1 907 258 4000",
    "sg:postcode":"99517",
    "sg:province":"AK",
    "wof:name":"Anchorage Realty",
    "wof:placetype":"venue"
},
  "geometry": {"coordinates":[-149.92272800000001,61.203282],"type":"Point"}
}