{
  "type": "Feature",
  "properties": {
    "iso:country":"US",
    "sg:address":"6901 Debarr Rd",
    "sg:city":"Anchorage",
    "sg:classifiers":[
        {
            "category":"Shopping",
            "subcategory":"Gifts & Souvenirs",
            "type":"Retail Goods"
        }
    ],
    "sg:phone":"+1 907 258 9182",
    "sg:postcode":"99504",
    "sg:province":"AK",
    "sg:tags":[
        "shop"
    ],
    "wof:name":"Far North Christian Books",
    "wof:placetype":"venue"
},
  "geometry": {"coordinates":[-149.751092,61.209796],"type":"Point"}
}