{
  "type": "Feature",
  "properties": {
    "iso:country":"US",
    "sg:address":"209 Seward St",
    "sg:city":"Juneau",
    "sg:classifiers":[
        {
            "category":"Shopping",
            "subcategory":"Clothing, Apparel, & Fashions",
            "type":"Retail Goods"
        }
    ],
    "sg:phone":"+1 907 586 6688",
    "sg:postcode":"99801",
    "sg:province":"AK",
    "sg:tags":[
        "lingerie"
    ],
    "wof:name":"Xandi's Treasure Chest",
    "wof:placetype":"venue"
},
  "geometry": {"coordinates":[-134.40805,58.301231],"type":"Point"}
}