{
  "type": "Feature",
  "properties": {
    "addr:full":"5901 Old Seward Hwy Anchorage AK 99518",
    "addr:housenumber":"5901",
    "addr:postcode":"99518",
    "addr:street":"Old Seward Hwy",
    "iso:country":"US",
    "sg:address":"5901 Old Seward Hwy",
    "sg:city":"Anchorage",
    "sg:classifiers":[
        {
            "category":"Wholesale",
            "subcategory":"Groceries",
            "type":"Manufacturing & Wholesale Goods"
        }
    ],
    "sg:phone":"+1 907 563 1836",
    "sg:postcode":"99518",
    "sg:province":"AK",
    "sg:tags":[
        "food",
        "broker"
    ],
    "wof:name":"Husky Food Products-Anchorage",
    "wof:placetype":"venue"
},
  "geometry": {"coordinates":[-149.86796699999999,61.167773],"type":"Point"}
}