{
  "type": "Feature",
  "properties": {
    "iso:country":"US",
    "sg:address":"11216 Borealis St",
    "sg:city":"Eagle River",
    "sg:classifiers":[
        {
            "category":"Building & Trades",
            "subcategory":"Construction",
            "type":"Services"
        }
    ],
    "sg:phone":"+1 907 694 5405",
    "sg:postcode":"99577",
    "sg:province":"AK",
    "sg:tags":[
        "contractor"
    ],
    "wof:name":"Northern Eagle Masonry",
    "wof:placetype":"venue"
},
  "geometry": {"coordinates":[-149.559912,61.325072],"type":"Point"}
}