{
  "type": "Feature",
  "properties": {
    "iso:country":"US",
    "sg:address":"160 Old Steese Hwy",
    "sg:city":"Fairbanks",
    "sg:classifiers":[
        {
            "category":"Sports & Exercise",
            "subcategory":"Golf",
            "type":"Entertainment"
        }
    ],
    "sg:phone":"+1 907 455 4368",
    "sg:postcode":"99701",
    "sg:province":"AK",
    "sg:tags":[
        "course"
    ],
    "wof:name":"Indoor Golf Of Fairbanks",
    "wof:placetype":"venue"
},
  "geometry": {"coordinates":[-147.70743400000001,64.847027],"type":"Point"}
}