{
  "type": "Feature",
  "properties": {
    "iso:country":"US",
    "sg:address":"3705 Arctic Blvd",
    "sg:city":"Anchorage",
    "sg:classifiers":[
        {
            "category":"Building & Trades",
            "subcategory":"Construction",
            "type":"Services"
        }
    ],
    "sg:phone":"+1 907 258 1360",
    "sg:postcode":"99503",
    "sg:province":"AK",
    "sg:tags":[
        "concrete",
        "contractor"
    ],
    "wof:name":"A Quality Concrete Svc",
    "wof:placetype":"venue"
},
  "geometry": {"coordinates":[-149.897884,61.187679],"type":"Point"}
}