{
  "type": "Feature",
  "properties": {
    "addr:full":"43843 Sterling Hwy Soldotna AK 99669",
    "addr:housenumber":"43843",
    "addr:postcode":"99669",
    "addr:street":"Sterling Hwy",
    "iso:country":"US",
    "sg:address":"43843 Sterling Hwy",
    "sg:city":"Soldotna",
    "sg:classifiers":[
        {
            "category":"Coffee & Tea",
            "type":"Food & Drink"
        }
    ],
    "sg:menulink":"http://www.allmenus.com/ak/kenai-cook-inlet/115314-starbucks-coffee/menu/",
    "sg:phone":"+1 907 262 2200",
    "sg:postcode":"99669",
    "sg:province":"AK",
    "sg:tags":[
        "american"
    ],
    "wof:name":"Starbucks Coffee",
    "wof:placetype":"venue"
},
  "geometry": {"coordinates":[-151.05609799999999,60.487229],"type":"Point"}
}