{
  "type": "Feature",
  "properties": {
    "addr:full":"16641 Eagle River Rd Eagle River AK 99577",
    "addr:housenumber":"16641",
    "addr:postcode":"99577",
    "addr:street":"Eagle River Rd",
    "iso:country":"US",
    "sg:address":"16641 Eagle River Rd",
    "sg:city":"Eagle River",
    "sg:classifiers":[
        {
            "category":"Government",
            "subcategory":"Police Station",
            "type":"Public Place"
        }
    ],
    "sg:phone":"+1 907 694 2715",
    "sg:postcode":"99577",
    "sg:province":"AK",
    "sg:tags":[
        "department"
    ],
    "wof:name":"Anchorage Police Dept Sub Div",
    "wof:placetype":"venue"
},
  "geometry": {"coordinates":[-149.57079999999999,61.315051],"type":"Point"}
}