{
  "type": "Feature",
  "properties": {
    "iso:country":"US",
    "sg:address":"6617 Arctic Blvd",
    "sg:city":"Anchorage",
    "sg:classifiers":[
        {
            "category":"Retail",
            "subcategory":"Auto Repair",
            "type":"Services"
        }
    ],
    "sg:phone":"+1 907 561 4344",
    "sg:postcode":"99518",
    "sg:province":"AK",
    "sg:tags":[
        "recreational",
        "vehicle"
    ],
    "wof:name":"Alaska Economical Rv Repair",
    "wof:placetype":"venue"
},
  "geometry": {"coordinates":[-149.89518,61.164354],"type":"Point"}
}