{
  "type": "Feature",
  "properties": {
    "iso:country":"US",
    "sg:address":"211 Clarkson Dr",
    "sg:city":"Fairbanks",
    "sg:classifiers":[
        {
            "category":"Real Estate",
            "subcategory":"Real Estate Operator",
            "type":"Services"
        }
    ],
    "sg:phone":"+1 907 452 4627",
    "sg:postcode":"99709",
    "sg:province":"AK",
    "sg:tags":[
        "apartment"
    ],
    "wof:name":"Northern Call Inc",
    "wof:placetype":"venue"
},
  "geometry": {"coordinates":[-147.873817,64.840788],"type":"Point"}
}