{
  "type": "Feature",
  "properties": {
    "iso:country":"US",
    "sg:address":"114 Lower Mill Bay Rd",
    "sg:city":"Kodiak",
    "sg:classifiers":[
        {
            "category":"Food & Beverages",
            "subcategory":"Groceries & Convenience Stores",
            "type":"Retail Goods"
        }
    ],
    "sg:phone":"+1 907 486 5305",
    "sg:postcode":"99615",
    "sg:province":"AK",
    "wof:name":"Union Tire Shop",
    "wof:placetype":"venue"
},
  "geometry": {"coordinates":[-152.401062,57.792988],"type":"Point"}
}