{
  "type": "Feature",
  "properties": {
    "addr:full":"401 W Evergreen Ave Palmer AK 99645",
    "addr:housenumber":"401",
    "addr:postcode":"99645",
    "addr:street":"W Evergreen Ave",
    "iso:country":"US",
    "sg:address":"401 W Evergreen Ave",
    "sg:city":"Palmer",
    "sg:classifiers":[
        {
            "category":"Restaurant",
            "type":"Food & Drink"
        }
    ],
    "sg:menulink":"http://www.allmenus.com/ak/matanuska-susitna/166718-burger-king/menu/",
    "sg:phone":"+1 907 746 6776",
    "sg:postcode":"99645",
    "sg:province":"AK",
    "sg:tags":[
        "burger",
        "american"
    ],
    "wof:name":"Burger King",
    "wof:placetype":"venue"
},
  "geometry": {"coordinates":[-149.12079700000001,61.599435],"type":"Point"}
}