{
  "type": "Feature",
  "properties": {
    "iso:country":"US",
    "sg:address":"48502 Tote Rd",
    "sg:city":"Soldotna",
    "sg:classifiers":[
        {
            "category":"Food & Beverages",
            "subcategory":"Specialty",
            "type":"Retail Goods"
        }
    ],
    "sg:phone":"+1 907 262 5031",
    "sg:postcode":"99669",
    "sg:province":"AK",
    "sg:tags":[
        "vitamin"
    ],
    "wof:name":"Ellen's Ray Of Light",
    "wof:placetype":"venue"
},
  "geometry": {"coordinates":[-151.168574,60.416425],"type":"Point"}
}