{
  "type": "Feature",
  "properties": {
    "addr:full":"8991 Yandukin Dr Juneau AK 99801",
    "addr:housenumber":"8991",
    "addr:postcode":"99801",
    "addr:street":"Yandukin Dr",
    "iso:country":"US",
    "sg:address":"8991 Yandukin Dr",
    "sg:city":"Juneau",
    "sg:classifiers":[
        {
            "category":"Restaurant",
            "type":"Food & Drink"
        }
    ],
    "sg:phone":"+1 907 586 8258",
    "sg:postcode":"99801",
    "sg:province":"AK",
    "wof:name":"TAKU Glacier Lodge Inc",
    "wof:placetype":"venue"
},
  "geometry": {"coordinates":[-134.57394099999999,58.358451],"type":"Point"}
}