{
  "type": "Feature",
  "properties": {
    "iso:country":"US",
    "sg:address":"8991 Yandukin Dr",
    "sg:city":"Juneau",
    "sg:classifiers":[
        {
            "category":"Restaurant",
            "type":"Food & Drink"
        }
    ],
    "sg:phone":"+1 907 586 8258",
    "sg:postcode":"99801",
    "sg:province":"AK",
    "wof:name":"TAKU Glacier Lodge Inc",
    "wof:placetype":"venue"
},
  "geometry": {"coordinates":[-134.573941,58.358451],"type":"Point"}
}