{
  "type": "Feature",
  "properties": {
    "iso:country":"US",
    "sg:address":"13041 Norak Pl",
    "sg:city":"Anchorage",
    "sg:classifiers":[
        {
            "category":"Building & Trades",
            "subcategory":"Landscaping Services",
            "type":"Services"
        }
    ],
    "sg:phone":"+1 907 345 3364",
    "sg:postcode":"99516",
    "sg:province":"AK",
    "sg:tags":[
        "landscape",
        "contractor"
    ],
    "wof:name":"Sunshine Garden Svc",
    "wof:placetype":"venue"
},
  "geometry": {"coordinates":[-149.805806,61.104474],"type":"Point"}
}