{
  "type": "Feature",
  "properties": {
    "addr:full":"13041 Norak Pl Anchorage AK 99516",
    "addr:housenumber":"13041",
    "addr:postcode":"99516",
    "addr:street":"Norak Pl",
    "iso:country":"US",
    "sg:address":"13041 Norak Pl",
    "sg:city":"Anchorage",
    "sg:classifiers":[
        {
            "category":"Building & Trades",
            "subcategory":"Landscaping Services",
            "type":"Services"
        }
    ],
    "sg:phone":"+1 907 345 3364",
    "sg:postcode":"99516",
    "sg:province":"AK",
    "sg:tags":[
        "landscape",
        "contractor"
    ],
    "wof:name":"Sunshine Garden Svc",
    "wof:placetype":"venue"
},
  "geometry": {"coordinates":[-149.80580599999999,61.104474],"type":"Point"}
}