{
  "type": "Feature",
  "properties": {
    "iso:country":"US",
    "sg:address":"874 Brown Deer Rd",
    "sg:city":"Ketchikan",
    "sg:classifiers":[
        {
            "category":"Building & Trades",
            "subcategory":"Construction",
            "type":"Services"
        }
    ],
    "sg:phone":"+1 907 225 5488",
    "sg:postcode":"99901",
    "sg:province":"AK",
    "sg:tags":[
        "custom",
        "builder",
        "material",
        "cabinet"
    ],
    "wof:name":"Woodworks Of Ketchikan",
    "wof:placetype":"venue"
},
  "geometry": {"coordinates":[-131.6445,55.350438],"type":"Point"}
}