{
  "type": "Feature",
  "properties": {
    "iso:country":"US",
    "sg:address":"1531 Gillam Way",
    "sg:city":"Fairbanks",
    "sg:classifiers":[
        {
            "category":"Professional",
            "subcategory":"Accounting & Tax Preparation",
            "type":"Services"
        }
    ],
    "sg:phone":"+1 907 452 4407",
    "sg:postcode":"99701",
    "sg:province":"AK",
    "sg:tags":[
        "accountant"
    ],
    "wof:name":"David Stephenson CPA",
    "wof:placetype":"venue"
},
  "geometry": {"coordinates":[-147.727602,64.834246],"type":"Point"}
}