{
  "type": "Feature",
  "properties": {
    "addr:full":"439 Ridgecrest Dr Bethel AK 99559",
    "addr:housenumber":"439",
    "addr:postcode":"99559",
    "addr:street":"Ridgecrest Dr",
    "iso:country":"US",
    "sg:address":"439 Ridgecrest Dr",
    "sg:city":"Bethel",
    "sg:classifiers":[
        {
            "category":"Food & Beverages",
            "subcategory":"Specialty",
            "type":"Retail Goods"
        }
    ],
    "sg:phone":"+1 907 543 4343",
    "sg:postcode":"99559",
    "sg:province":"AK",
    "sg:tags":[
        "tea",
        "coffee"
    ],
    "wof:name":"Casa Teriyaki",
    "wof:placetype":"venue"
},
  "geometry": {"coordinates":[-161.77443199999999,60.796674],"type":"Point"}
}