{
  "type": "Feature",
  "properties": {
    "addr:full":"13700 Sunset View St Anchorage AK 99515",
    "addr:housenumber":"13700",
    "addr:postcode":"99515",
    "addr:street":"Sunset View St",
    "iso:country":"US",
    "sg:address":"13700 Sunset View St",
    "sg:city":"Anchorage",
    "sg:classifiers":[
        {
            "category":"Arts & Performance",
            "subcategory":"Theater",
            "type":"Entertainment"
        }
    ],
    "sg:phone":"+1 907 868 4852",
    "sg:postcode":"99515",
    "sg:province":"AK",
    "sg:tags":[
        "dance",
        "company"
    ],
    "wof:name":"Ke Aloha Dance Co",
    "wof:placetype":"venue"
},
  "geometry": {"coordinates":[-149.844843,61.096018],"type":"Point"}
}