{
  "type": "Feature",
  "properties": {
    "addr:full":"491 W Parks Hwy Wasilla AK 99654",
    "addr:housenumber":"491",
    "addr:postcode":"99654",
    "addr:street":"W Parks Hwy",
    "iso:country":"US",
    "sg:address":"491 W Parks Hwy",
    "sg:city":"Wasilla",
    "sg:classifiers":[
        {
            "category":"Social Services",
            "type":"Services"
        }
    ],
    "sg:phone":"+1 907 376 4015",
    "sg:postcode":"99654",
    "sg:province":"AK",
    "sg:tags":[
        "organization",
        "welfare"
    ],
    "wof:name":"Alaska Family Resource Ctr",
    "wof:placetype":"venue"
},
  "geometry": {"coordinates":[-149.462863,61.582147],"type":"Point"}
}