{
  "type": "Feature",
  "properties": {
    "addr:full":"2727 Iliamna Ave Anchorage AK 99517",
    "addr:housenumber":"2727",
    "addr:postcode":"99517",
    "addr:street":"Iliamna Ave",
    "iso:country":"US",
    "sg:address":"2727 Iliamna Ave",
    "sg:city":"Anchorage",
    "sg:classifiers":[
        {
            "category":"Recreation",
            "type":"Entertainment"
        }
    ],
    "sg:phone":"+1 907 248 0426",
    "sg:postcode":"99517",
    "sg:province":"AK",
    "sg:tags":[
        "center"
    ],
    "wof:name":"American Multiplex",
    "wof:placetype":"venue"
},
  "geometry": {"coordinates":[-149.93953099999999,61.201697],"type":"Point"}
}