{
  "type": "Feature",
  "properties": {
    "iso:country":"US",
    "sg:address":"1835 Pool St",
    "sg:city":"North Pole",
    "sg:classifiers":[
        {
            "category":"Retail",
            "subcategory":"Laundry & Dry Cleaning",
            "type":"Services"
        }
    ],
    "sg:phone":"+1 907 488 1021",
    "sg:postcode":"99705",
    "sg:province":"AK",
    "sg:tags":[
        "cleaners",
        "rug",
        "carpet"
    ],
    "wof:name":"Carpet Restoration Svc",
    "wof:placetype":"venue"
},
  "geometry": {"coordinates":[-147.331099,64.78777],"type":"Point"}
}