{
  "type": "Feature",
  "properties": {
    "iso:country":"US",
    "sg:address":"10540 Wrong Way Ln",
    "sg:city":"Salcha",
    "sg:classifiers":[
        {
            "category":"Retail",
            "subcategory":"Repair Shop",
            "type":"Services"
        }
    ],
    "sg:phone":"+1 907 488 9228",
    "sg:postcode":"99714",
    "sg:province":"AK",
    "sg:tags":[
        "taxidermist"
    ],
    "wof:name":"Skip's Taxidermy",
    "wof:placetype":"venue"
},
  "geometry": {"coordinates":[-146.89074600000001,64.38698599999999],"type":"Point"}
}