{
  "type": "Feature",
  "properties": {
    "addr:full":"1129 I St Anchorage AK 99501",
    "addr:housenumber":"1129",
    "addr:postcode":"99501",
    "addr:street":"I St",
    "iso:country":"US",
    "sg:address":"1129 I St",
    "sg:city":"Anchorage",
    "sg:classifiers":[
        {
            "category":"Professional",
            "subcategory":"Computer Services",
            "type":"Services"
        }
    ],
    "sg:phone":"+1 907 277 3791",
    "sg:postcode":"99501",
    "sg:province":"AK",
    "sg:tags":[
        "scanning"
    ],
    "wof:name":"Multimedia Cottage LLC",
    "wof:placetype":"venue"
},
  "geometry": {"coordinates":[-149.899541,61.210957],"type":"Point"}
}