{
  "type": "Feature",
  "properties": {
    "iso:country":"US",
    "sg:address":"3300 Providence Dr",
    "sg:city":"Anchorage",
    "sg:classifiers":[
        {
            "category":"Health Services",
            "subcategory":"Doctor",
            "type":"Services"
        }
    ],
    "sg:phone":"+1 907 261 3162",
    "sg:postcode":"99508",
    "sg:province":"AK",
    "sg:tags":[
        "physician",
        "surgeon"
    ],
    "sg:website":"www.ourfamilydr.com",
    "wof:name":"International Travelers Clinic",
    "wof:placetype":"venue"
},
  "geometry": {"coordinates":[-149.820417,61.189751],"type":"Point"}
}