{
  "type": "Feature",
  "properties": {
    "iso:country":"US",
    "sg:address":"1901 E View Dr",
    "sg:city":"Anchorage",
    "sg:classifiers":[
        {
            "category":"Recreation",
            "type":"Entertainment"
        }
    ],
    "sg:phone":"+1 907 337 7517",
    "sg:postcode":"99504",
    "sg:province":"AK",
    "sg:tags":[
        "tours",
        "sightseeing"
    ],
    "wof:name":"Ak Snail Trails",
    "wof:placetype":"venue"
},
  "geometry": {"coordinates":[-149.720832,61.204166],"type":"Point"}
}