{
  "type": "Feature",
  "properties": {
    "iso:country":"US",
    "sg:address":"130 Carlanna Lake Rd",
    "sg:city":"Ketchikan",
    "sg:classifiers":[
        {
            "category":"Personal",
            "type":"Services"
        }
    ],
    "sg:phone":"+1 907 247 8729",
    "sg:postcode":"99901",
    "sg:province":"AK",
    "sg:tags":[
        "therapist",
        "massage"
    ],
    "wof:name":"Sound Health Massage",
    "wof:placetype":"venue"
},
  "geometry": {"coordinates":[-131.689105,55.35398],"type":"Point"}
}