{
  "type": "Feature",
  "properties": {
    "addr:full":"19179 Birchwood Loop Rd Chugiak AK 99567",
    "addr:housenumber":"19179",
    "addr:postcode":"99567",
    "addr:street":"Birchwood Loop Rd",
    "iso:country":"US",
    "sg:address":"19179 Birchwood Loop Rd",
    "sg:city":"Chugiak",
    "sg:classifiers":[
        {
            "category":"Manufacturing",
            "subcategory":"Tools & Machinery",
            "type":"Manufacturing & Wholesale Goods"
        }
    ],
    "sg:phone":"+1 907 688 2570",
    "sg:postcode":"99567",
    "sg:province":"AK",
    "sg:tags":[
        "machine",
        "shop"
    ],
    "wof:name":"Birchwood Machinery Svc",
    "wof:placetype":"venue"
},
  "geometry": {"coordinates":[-149.514433,61.393602],"type":"Point"}
}