{
  "type": "Feature",
  "properties": {
    "iso:country":"US",
    "sg:address":"729 15th Ave",
    "sg:city":"Fairbanks",
    "sg:classifiers":[
        {
            "category":"Building & Trades",
            "subcategory":"Plumbing",
            "type":"Services"
        }
    ],
    "sg:phone":"+1 907 452 4670",
    "sg:postcode":"99701",
    "sg:province":"AK",
    "sg:tags":[
        "heating",
        "contractor"
    ],
    "wof:name":"Anton Enterprises",
    "wof:placetype":"venue"
},
  "geometry": {"coordinates":[-147.719208,64.83453],"type":"Point"}
}