{
  "type": "Feature",
  "properties": {
    "iso:country":"US",
    "sg:address":"1300 N Post Rd",
    "sg:city":"Anchorage",
    "sg:classifiers":[
        {
            "category":"Wholesale",
            "subcategory":"Machinery & Supplies",
            "type":"Manufacturing & Wholesale Goods"
        }
    ],
    "sg:phone":"+1 907 258 1164",
    "sg:postcode":"99501",
    "sg:province":"AK",
    "sg:tags":[
        "contractor"
    ],
    "wof:name":"CBS Equipment",
    "wof:placetype":"venue"
},
  "geometry": {"coordinates":[-149.845477,61.226691],"type":"Point"}
}