{
  "type": "Feature",
  "properties": {
    "addr:full":"140 W Tudor Rd Anchorage AK 99503",
    "addr:housenumber":"140",
    "addr:postcode":"99503",
    "addr:street":"W Tudor Rd",
    "iso:country":"US",
    "sg:address":"140 W Tudor Rd",
    "sg:city":"Anchorage",
    "sg:classifiers":[
        {
            "category":"Travel",
            "subcategory":"Hotels & Motels",
            "type":"Entertainment"
        }
    ],
    "sg:phone":"+1 907 762 7000",
    "sg:postcode":"99503",
    "sg:province":"AK",
    "wof:name":"Homewood Suites By Hilton",
    "wof:placetype":"venue"
},
  "geometry": {"coordinates":[-149.88406900000001,61.180732],"type":"Point"}
}