{
  "type": "Feature",
  "properties": {
    "iso:country":"US",
    "sg:address":"6221 Petersburg St",
    "sg:city":"Anchorage",
    "sg:classifiers":[
        {
            "category":"Wholesale",
            "subcategory":"Seafood",
            "type":"Manufacturing & Wholesale Goods"
        }
    ],
    "sg:phone":"+1 907 563 1387",
    "sg:postcode":"99507",
    "sg:province":"AK",
    "wof:name":"Aqua Tech",
    "wof:placetype":"venue"
},
  "geometry": {"coordinates":[-149.845865,61.16425],"type":"Point"}
}