{
  "type": "Feature",
  "properties": {
    "iso:country":"US",
    "sg:address":"14065 Beach Dr",
    "sg:city":"Seward",
    "sg:classifiers":[
        {
            "category":"Travel",
            "subcategory":"Hotels & Motels",
            "type":"Entertainment"
        }
    ],
    "sg:phone":"+1 907 224 7000",
    "sg:postcode":"99664",
    "sg:province":"AK",
    "sg:tags":[
        "breakfast",
        "accommodation",
        "bed"
    ],
    "wof:name":"Beach House",
    "wof:placetype":"venue"
},
  "geometry": {"coordinates":[-149.436894,60.068444],"type":"Point"}
}