{
  "type": "Feature",
  "properties": {
    "iso:country":"US",
    "sg:address":"2530 Debarr Rd",
    "sg:city":"Anchorage",
    "sg:classifiers":[
        {
            "category":"Health Services",
            "subcategory":"Hospital",
            "type":"Services"
        }
    ],
    "sg:phone":"+1 907 258 7575",
    "sg:postcode":"99508",
    "sg:province":"AK",
    "wof:name":"North Star Behavioral Health",
    "wof:placetype":"venue"
},
  "geometry": {"coordinates":[-149.832468,61.209001],"type":"Point"}
}