{
  "type": "Feature",
  "properties": {
    "iso:country":"US",
    "sg:address":"2306 Eagle St",
    "sg:city":"Anchorage",
    "sg:classifiers":[
        {
            "category":"Manufacturing",
            "subcategory":"Building Materials",
            "type":"Manufacturing & Wholesale Goods"
        }
    ],
    "sg:phone":"+1 907 272 6658",
    "sg:postcode":"99503",
    "sg:province":"AK",
    "sg:tags":[
        "mfg",
        "wood",
        "kitchen",
        "cabinet"
    ],
    "wof:name":"York Hand Crafted",
    "wof:placetype":"venue"
},
  "geometry": {"coordinates":[-149.874737,61.199422],"type":"Point"}
}