{
  "type": "Feature",
  "properties": {
    "iso:country":"US",
    "sg:address":"111 Stedman St",
    "sg:city":"Ketchikan",
    "sg:classifiers":[
        {
            "category":"Organizations",
            "subcategory":"Professional Association",
            "type":"Services"
        }
    ],
    "sg:phone":"+1 907 225 3184",
    "sg:postcode":"99901",
    "sg:province":"AK",
    "sg:tags":[
        "chambers",
        "commerce"
    ],
    "sg:website":"www.ketchikanchamber.com",
    "wof:name":"Ketchikan Chamber Of Commerce",
    "wof:placetype":"venue"
},
  "geometry": {"coordinates":[-131.639385,55.340383],"type":"Point"}
}