{
  "type": "Feature",
  "properties": {
    "iso:country":"US",
    "sg:address":"281 Main St",
    "sg:city":"Wasilla",
    "sg:classifiers":[
        {
            "category":"Professional",
            "subcategory":"Accounting & Tax Preparation",
            "type":"Services"
        }
    ],
    "sg:phone":"+1 907 357 8291",
    "sg:postcode":"99654",
    "sg:province":"AK",
    "sg:tags":[
        "accountant"
    ],
    "wof:name":"Ron Morgan CPA",
    "wof:placetype":"venue"
},
  "geometry": {"coordinates":[-149.441411,61.582026],"type":"Point"}
}