{
  "type": "Feature",
  "properties": {
    "iso:country":"US",
    "sg:address":"402 Barnette St",
    "sg:city":"Fairbanks",
    "sg:classifiers":[
        {
            "category":"Retail",
            "subcategory":"Auto Repair",
            "type":"Services"
        }
    ],
    "sg:phone":"+1 907 479 3715",
    "sg:postcode":"99701",
    "sg:province":"AK",
    "sg:tags":[
        "repairing",
        "automobile"
    ],
    "wof:name":"Star Distributors",
    "wof:placetype":"venue"
},
  "geometry": {"coordinates":[-147.724774,64.842299],"type":"Point"}
}