{
  "type": "Feature",
  "properties": {
    "iso:country":"US",
    "sg:address":"35571 Kenai Spur Hwy",
    "sg:city":"Soldotna",
    "sg:classifiers":[
        {
            "category":"Insurance",
            "subcategory":"Insurance Agent",
            "type":"Services"
        }
    ],
    "sg:phone":"+1 907 260 6246",
    "sg:postcode":"99669",
    "sg:province":"AK",
    "wof:name":"Ribelin Lowell & Co",
    "wof:placetype":"venue"
},
  "geometry": {"coordinates":[-151.07006100000001,60.495635],"type":"Point"}
}