{
  "type": "Feature",
  "properties": {
    "iso:country":"US",
    "sg:address":"729 1st Ave",
    "sg:city":"Fairbanks",
    "sg:classifiers":[
        {
            "category":"Manufacturing",
            "subcategory":"Printing",
            "type":"Manufacturing & Wholesale Goods"
        }
    ],
    "sg:phone":"+1 907 456 7246",
    "sg:postcode":"99701",
    "sg:province":"AK",
    "sg:tags":[
        "comp",
        "commercial",
        "design",
        "typesetting"
    ],
    "wof:name":"Letter Perfect",
    "wof:placetype":"venue"
},
  "geometry": {"coordinates":[-147.725262,64.843999],"type":"Point"}
}