{
  "type": "Feature",
  "properties": {
    "iso:country":"US",
    "sg:address":"37388 Kenai Spur Hwy",
    "sg:city":"Soldotna",
    "sg:classifiers":[
        {
            "category":"Retail",
            "subcategory":"Auto Repair",
            "type":"Services"
        }
    ],
    "sg:phone":"+1 907 262 5885",
    "sg:postcode":"99669",
    "sg:province":"AK",
    "sg:tags":[
        "body",
        "automobile",
        "painting"
    ],
    "wof:name":"Kenai Auto Inc",
    "wof:placetype":"venue"
},
  "geometry": {"coordinates":[-151.08126999999999,60.521889],"type":"Point"}
}