{
  "type": "Feature",
  "properties": {
    "iso:country":"US",
    "sg:address":"3017 Clinton Dr",
    "sg:city":"Juneau",
    "sg:classifiers":[
        {
            "category":"Health Services",
            "subcategory":"Clinic",
            "type":"Services"
        }
    ],
    "sg:phone":"+1 907 790 1026",
    "sg:postcode":"99801",
    "sg:province":"AK",
    "sg:tags":[
        "information",
        "program",
        "referral"
    ],
    "sg:website":"www.fcareimbursement.com",
    "wof:name":"Fca",
    "wof:placetype":"venue"
},
  "geometry": {"coordinates":[-134.59652,58.373148],"type":"Point"}
}