{
  "type": "Feature",
  "properties": {
    "addr:full":"8225 Spring St Anchorage AK 99518",
    "addr:housenumber":"8225",
    "addr:postcode":"99518",
    "addr:street":"Spring St",
    "iso:country":"US",
    "sg:address":"8225 Spring St",
    "sg:city":"Anchorage",
    "sg:classifiers":[
        {
            "category":"Organizations",
            "subcategory":"Religious Organization",
            "type":"Services"
        }
    ],
    "sg:phone":"+1 907 336 7779",
    "sg:postcode":"99518",
    "sg:province":"AK",
    "sg:tags":[
        "church"
    ],
    "wof:name":"Victory Baptist Church",
    "wof:placetype":"venue"
},
  "geometry": {"coordinates":[-149.86195000000001,61.145502],"type":"Point"}
}