{
  "type": "Feature",
  "properties": {
    "iso:country":"US",
    "sg:address":"720 Old Steese Hwy",
    "sg:city":"Fairbanks",
    "sg:classifiers":[
        {
            "category":"Bars & Pubs",
            "type":"Food & Drink"
        }
    ],
    "sg:phone":"+1 907 456 1841",
    "sg:postcode":"99701",
    "sg:province":"AK",
    "sg:tags":[
        "lounge",
        "cocktail"
    ],
    "wof:name":"Hide Out Lounge",
    "wof:placetype":"venue"
},
  "geometry": {"coordinates":[-147.693753,64.851056],"type":"Point"}
}