{
  "type": "Feature",
  "properties": {
    "addr:full":"2601 E Tudor Rd Anchorage AK 99507",
    "addr:housenumber":"2601",
    "addr:postcode":"99507",
    "addr:street":"E Tudor Rd",
    "iso:country":"US",
    "sg:address":"2601 E Tudor Rd",
    "sg:city":"Anchorage",
    "sg:classifiers":[
        {
            "category":"Restaurant",
            "type":"Food & Drink"
        }
    ],
    "sg:menulink":"http://www.allmenus.com/ak/anchorage/190065-mcdonalds/menu/",
    "sg:postcode":"99507",
    "sg:province":"AK",
    "sg:tags":[
        "burger",
        "american"
    ],
    "wof:name":"McDonald's",
    "wof:placetype":"venue"
},
  "geometry": {"coordinates":[-149.83214699999999,61.180978],"type":"Point"}
}