{
  "type": "Feature",
  "properties": {
    "addr:full":"901 1st Ave Fairbanks AK 99701",
    "addr:housenumber":"901",
    "addr:postcode":"99701",
    "addr:street":"1St Ave",
    "iso:country":"US",
    "sg:address":"901 1st Ave",
    "sg:city":"Fairbanks",
    "sg:classifiers":[
        {
            "category":"Education",
            "subcategory":"Library",
            "type":"Public Place"
        }
    ],
    "sg:phone":"+1 907 452 5388",
    "sg:postcode":"99701",
    "sg:province":"AK",
    "wof:name":"George C Thomas Memorial Lbry",
    "wof:placetype":"venue"
},
  "geometry": {"coordinates":[-147.72897900000001,64.845303],"type":"Point"}
}