{
  "type": "Feature",
  "properties": {
    "iso:country":"US",
    "sg:address":"2441 Cinnabar Loop",
    "sg:city":"Anchorage",
    "sg:classifiers":[
        {
            "category":"Manufacturing",
            "subcategory":"Metals",
            "type":"Manufacturing & Wholesale Goods"
        }
    ],
    "sg:phone":"+1 907 349 2727",
    "sg:postcode":"99507",
    "sg:province":"AK",
    "sg:tags":[
        "fabrication",
        "structural"
    ],
    "wof:name":"ASC Building Products",
    "wof:placetype":"venue"
},
  "geometry": {"coordinates":[-149.840302,61.146861],"type":"Point"}
}