{
  "type": "Feature",
  "properties": {
    "iso:country":"US",
    "sg:address":"643 Wilcox Ave",
    "sg:city":"Fairbanks",
    "sg:classifiers":[
        {
            "category":"Wholesale",
            "subcategory":"Machinery & Supplies",
            "type":"Manufacturing & Wholesale Goods"
        }
    ],
    "sg:phone":"+1 907 479 0541",
    "sg:postcode":"99709",
    "sg:province":"AK",
    "sg:tags":[
        "salon",
        "beauty"
    ],
    "wof:name":"Alaska Beauty Barber Import",
    "wof:placetype":"venue"
},
  "geometry": {"coordinates":[-147.816807,64.847377],"type":"Point"}
}