{
  "type": "Feature",
  "properties": {
    "addr:full":"3931 W 72nd Ct Anchorage AK 99502",
    "addr:housenumber":"3931",
    "addr:postcode":"99502",
    "addr:street":"W 72Nd Ct",
    "iso:country":"US",
    "sg:address":"3931 W 72nd Ct",
    "sg:city":"Anchorage",
    "sg:classifiers":[
        {
            "category":"Building & Trades",
            "subcategory":"Cleaning & Sanitation",
            "type":"Services"
        }
    ],
    "sg:phone":"+1 907 243 7281",
    "sg:postcode":"99502",
    "sg:province":"AK",
    "sg:tags":[
        "janitor"
    ],
    "wof:name":"R T's Janitorial Svc",
    "wof:placetype":"venue"
},
  "geometry": {"coordinates":[-149.95398399999999,61.156189],"type":"Point"}
}