{
  "type": "Feature",
  "properties": {
    "iso:country":"US",
    "sg:address":"73400 Forest Dr",
    "sg:city":"Anchor Point",
    "sg:classifiers":[
        {
            "category":"Personal",
            "type":"Services"
        }
    ],
    "sg:phone":"+1 907 235 5142",
    "sg:postcode":"99556",
    "sg:province":"AK",
    "sg:tags":[
        "consultant",
        "wedding"
    ],
    "wof:name":"Bev's Northwood Design & Gifts",
    "wof:placetype":"venue"
},
  "geometry": {"coordinates":[-151.841837,59.765944],"type":"Point"}
}