{
  "type": "Feature",
  "properties": {
    "iso:country":"US",
    "sg:address":"530 Bounty Dr",
    "sg:city":"Anchorage",
    "sg:classifiers":[
        {
            "category":"Shopping",
            "type":"Retail Goods"
        }
    ],
    "sg:phone":"+1 907 345 3777",
    "sg:postcode":"99515",
    "sg:province":"AK",
    "sg:tags":[
        "miscellaneous",
        "store"
    ],
    "wof:name":"Linens & Lilacs & Lace",
    "wof:placetype":"venue"
},
  "geometry": {"coordinates":[-149.867586,61.102928],"type":"Point"}
}