{
  "type": "Feature",
  "properties": {
    "iso:country":"US",
    "sg:address":"37020 Funny River Rd",
    "sg:city":"Soldotna",
    "sg:classifiers":[
        {
            "category":"Building & Trades",
            "subcategory":"Construction",
            "type":"Services"
        }
    ],
    "sg:phone":"+1 907 260 4708",
    "sg:postcode":"99669",
    "sg:province":"AK",
    "sg:tags":[
        "contractor"
    ],
    "wof:name":"Slash E Construction",
    "wof:placetype":"venue"
},
  "geometry": {"coordinates":[-150.852042,60.502328],"type":"Point"}
}