{
  "type": "Feature",
  "properties": {
    "iso:country":"US",
    "sg:address":"705 Gaffney Rd",
    "sg:city":"Fairbanks",
    "sg:classifiers":[
        {
            "category":"Retail",
            "subcategory":"Auto Repair",
            "type":"Services"
        }
    ],
    "sg:phone":"+1 907 456 4200",
    "sg:postcode":"99701",
    "sg:province":"AK",
    "sg:tags":[
        "repairing",
        "automobile"
    ],
    "wof:name":"Totem 2 Svc",
    "wof:placetype":"venue"
},
  "geometry": {"coordinates":[-147.726007,64.837173],"type":"Point"}
}