{
  "type": "Feature",
  "properties": {
    "addr:full":"3811 University Ave S Fairbanks AK 99709",
    "addr:housenumber":"3811",
    "addr:postcode":"99709",
    "addr:street":"University Ave S",
    "iso:country":"US",
    "sg:address":"3811 University Ave S",
    "sg:city":"Fairbanks",
    "sg:classifiers":[
        {
            "category":"Government",
            "subcategory":"Office",
            "type":"Public Place"
        }
    ],
    "sg:phone":"+1 907 474 0137",
    "sg:postcode":"99709",
    "sg:province":"AK",
    "sg:tags":[
        "federal"
    ],
    "wof:name":"US Automated Flight Svc",
    "wof:placetype":"venue"
},
  "geometry": {"coordinates":[-147.852048,64.808316],"type":"Point"}
}