{
  "type": "Feature",
  "properties": {
    "addr:full":"6620 Big Salt Lake Rd Klawock AK 99925",
    "addr:housenumber":"6620",
    "addr:postcode":"99925",
    "addr:street":"Big Salt Lake Rd",
    "iso:country":"US",
    "sg:address":"6620 Big Salt Lake Rd",
    "sg:city":"Klawock",
    "sg:classifiers":[
        {
            "category":"Real Estate",
            "subcategory":"Real Estate Agent",
            "type":"Services"
        }
    ],
    "sg:phone":"+1 907 755 2216",
    "sg:postcode":"99925",
    "sg:province":"AK",
    "wof:name":"Studio Klawock",
    "wof:placetype":"venue"
},
  "geometry": {"coordinates":[-133.08291700000001,55.558077],"type":"Point"}
}