{
  "type": "Feature",
  "properties": {
    "iso:country":"US",
    "sg:address":"9525 King St",
    "sg:city":"Anchorage",
    "sg:classifiers":[
        {
            "category":"Government",
            "subcategory":"Office",
            "type":"Public Place"
        }
    ],
    "sg:phone":"+1 907 561 3939",
    "sg:postcode":"99515",
    "sg:province":"AK",
    "sg:tags":[
        "village"
    ],
    "wof:name":"Anchorrides",
    "wof:placetype":"venue"
},
  "geometry": {"coordinates":[-149.878811,61.134107],"type":"Point"}
}