{
  "type": "Feature",
  "properties": {
    "addr:full":"1000 O'Malley Rd Anchorage AK 99515",
    "addr:housenumber":"1000",
    "addr:postcode":"99515",
    "addr:street":"O'Malley Rd",
    "iso:country":"US",
    "sg:address":"1000 O'Malley Rd",
    "sg:city":"Anchorage",
    "sg:classifiers":[
        {
            "category":"Health Services",
            "subcategory":"Doctor",
            "type":"Services"
        }
    ],
    "sg:phone":"+1 907 349 0022",
    "sg:postcode":"99515",
    "sg:province":"AK",
    "sg:tags":[
        "dentist"
    ],
    "wof:name":"Excellence In Dentistry",
    "wof:placetype":"venue"
},
  "geometry": {"coordinates":[-149.77151000000001,61.207457],"type":"Point"}
}