{
  "type": "Feature",
  "properties": {
    "iso:country":"US",
    "sg:address":"6130 Nielson Way",
    "sg:city":"Anchorage",
    "sg:classifiers":[
        {
            "category":"Wholesale",
            "subcategory":"Machinery & Supplies",
            "type":"Manufacturing & Wholesale Goods"
        }
    ],
    "sg:phone":"+1 907 563 1111",
    "sg:postcode":"99518",
    "sg:province":"AK",
    "sg:tags":[
        "concrete",
        "breaking"
    ],
    "wof:name":"Cut & Core Store",
    "wof:placetype":"venue"
},
  "geometry": {"coordinates":[-149.89282900000001,61.164543],"type":"Point"}
}