{
  "type": "Feature",
  "properties": {
    "iso:country":"US",
    "sg:address":"3801 Lois Dr ",
    "sg:city":"Anchorage",
    "sg:classifiers":[
        {
            "category":"Restaurant",
            "type":"Food & Drink"
        }
    ],
    "sg:menulink":"http://www.allmenus.com/ak/anchorage/285681-kabab--curry/menu/",
    "sg:phone":"+1 907 339 9699",
    "sg:postcode":"99517",
    "sg:province":"AK",
    "sg:tags":[
        "indian",
        "asian"
    ],
    "wof:name":"Kabab & Curry",
    "wof:placetype":"venue"
},
  "geometry": {"coordinates":[-149.919025,61.185614],"type":"Point"}
}