{
  "type": "Feature",
  "properties": {
    "iso:country":"US",
    "sg:address":"258 E Fireweed Ave",
    "sg:city":"Palmer",
    "sg:classifiers":[
        {
            "category":"Government",
            "subcategory":"Court House",
            "type":"Public Place"
        }
    ],
    "sg:phone":"+1 907 745 0435",
    "sg:postcode":"99645",
    "sg:province":"AK",
    "sg:tags":[
        "state",
        "counsel"
    ],
    "wof:name":"Public Advocacy Dept",
    "wof:placetype":"venue"
},
  "geometry": {"coordinates":[-149.114335,61.597707],"type":"Point"}
}