{
  "type": "Feature",
  "properties": {
    "iso:country":"US",
    "sg:address":"5721 Rocky Mountain Ct",
    "sg:city":"Anchorage",
    "sg:classifiers":[
        {
            "category":"Personal",
            "subcategory":"Adult",
            "type":"Services"
        }
    ],
    "sg:phone":"+1 907 336 5177",
    "sg:postcode":"99504",
    "sg:province":"AK",
    "sg:tags":[
        "escort"
    ],
    "wof:name":"Journey's Svc",
    "wof:placetype":"venue"
},
  "geometry": {"coordinates":[-149.771071,61.21791],"type":"Point"}
}