{
  "type": "Feature",
  "properties": {
    "iso:country":"US",
    "sg:address":"11111 O'Malley Centre Dr",
    "sg:city":"Anchorage",
    "sg:classifiers":[
        {
            "category":"Shopping",
            "subcategory":"Bicycles & Sporting Goods",
            "type":"Retail Goods"
        }
    ],
    "sg:phone":"+1 907 868 4350",
    "sg:postcode":"99515",
    "sg:province":"AK",
    "wof:name":"Hockey Shop",
    "wof:placetype":"venue"
},
  "geometry": {"coordinates":[-149.86037099999999,61.12307],"type":"Point"}
}