{
  "type": "Feature",
  "properties": {
    "iso:country":"US",
    "sg:address":"505 Old Steese Hwy",
    "sg:city":"Fairbanks",
    "sg:classifiers":[
        {
            "category":"Personal",
            "subcategory":"Tanning Parlor",
            "type":"Services"
        }
    ],
    "sg:phone":"+1 907 452 4890",
    "sg:postcode":"99701",
    "sg:province":"AK",
    "sg:tags":[
        "salon"
    ],
    "wof:name":"Tanning Center",
    "wof:placetype":"venue"
},
  "geometry": {"coordinates":[-147.697518,64.850005],"type":"Point"}
}