{
  "type": "Feature",
  "properties": {
    "iso:country":"US",
    "sg:address":"2607 Fairbanks St",
    "sg:city":"Anchorage",
    "sg:classifiers":[
        {
            "category":"Retail",
            "subcategory":"Repair Shop",
            "type":"Services"
        }
    ],
    "sg:phone":"+1 907 272 8434",
    "sg:postcode":"99503",
    "sg:province":"AK",
    "sg:tags":[
        "appliance"
    ],
    "wof:name":"Harold's Appliance Svc Ctr",
    "wof:placetype":"venue"
},
  "geometry": {"coordinates":[-149.872423,61.1962],"type":"Point"}
}