{
  "type": "Feature",
  "properties": {
    "iso:country":"US",
    "sg:address":"423 Taurus Rd",
    "sg:city":"Fairbanks",
    "sg:classifiers":[
        {
            "category":"Professional",
            "subcategory":"Accounting & Tax Preparation",
            "type":"Services"
        }
    ],
    "sg:phone":"+1 907 457 4285",
    "sg:postcode":"99712",
    "sg:province":"AK",
    "sg:tags":[
        "bookkeeping",
        "general"
    ],
    "wof:name":"D-K Bookkeeping",
    "wof:placetype":"venue"
},
  "geometry": {"coordinates":[-147.67425800000001,64.908704],"type":"Point"}
}