{
  "type": "Feature",
  "properties": {
    "iso:country":"US",
    "sg:address":"1500 W 33rd Ave",
    "sg:city":"Anchorage",
    "sg:classifiers":[
        {
            "category":"Organizations",
            "subcategory":"Non-profit Organization",
            "type":"Services"
        }
    ],
    "sg:phone":"+1 907 561 2338",
    "sg:postcode":"99503",
    "sg:province":"AK",
    "sg:website":"www.anchoragerealtors.com",
    "wof:name":"Anchorage Board-Realtors Inc",
    "wof:placetype":"venue"
},
  "geometry": {"coordinates":[-149.91073399999999,61.190257],"type":"Point"}
}