{
  "type": "Feature",
  "properties": {
    "iso:country":"US",
    "sg:address":"2440 Seward Hwy",
    "sg:city":"Anchorage",
    "sg:classifiers":[
        {
            "category":"Shopping",
            "subcategory":"Computers & Home Electronics",
            "type":"Retail Goods"
        }
    ],
    "sg:phone":"+1 907 272 9111",
    "sg:postcode":"99503",
    "sg:province":"AK",
    "sg:tags":[
        "high",
        "fidelity",
        "stereophonic"
    ],
    "wof:name":"Pyramid Audio/Video",
    "wof:placetype":"venue"
},
  "geometry": {"coordinates":[-149.868025,61.200138],"type":"Point"}
}