{
  "type": "Feature",
  "properties": {
    "addr:full":"514 Lake St Sitka AK 99835",
    "addr:housenumber":"514",
    "addr:postcode":"99835",
    "addr:street":"Lake St",
    "iso:country":"US",
    "sg:address":"514 Lake St",
    "sg:city":"Sitka",
    "sg:classifiers":[
        {
            "category":"Social Services",
            "type":"Services"
        }
    ],
    "sg:phone":"+1 907 747 3883",
    "sg:postcode":"99835",
    "sg:province":"AK",
    "sg:tags":[
        "information",
        "planning",
        "center",
        "family"
    ],
    "wof:name":"Planned Parenthood",
    "wof:placetype":"venue"
},
  "geometry": {"coordinates":[-135.33498900000001,57.055674],"type":"Point"}
}