{
  "type": "Feature",
  "properties": {
    "iso:country":"US",
    "sg:address":"2711 Tongass Ave",
    "sg:city":"Ketchikan",
    "sg:classifiers":[
        {
            "category":"Retail",
            "subcategory":"Repair Shop",
            "type":"Services"
        }
    ],
    "sg:phone":"+1 907 225 4107",
    "sg:postcode":"99901",
    "sg:province":"AK",
    "sg:tags":[
        "lock",
        "locksmith"
    ],
    "wof:name":"Ketchikan Lock & Key Co",
    "wof:placetype":"venue"
},
  "geometry": {"coordinates":[-131.679155,55.350653],"type":"Point"}
}