{
  "type": "Feature",
  "properties": {
    "iso:country":"US",
    "sg:address":"7820 Raymar Cir",
    "sg:city":"Anchorage",
    "sg:classifiers":[
        {
            "category":"Real Estate",
            "subcategory":"Real Estate Agent",
            "type":"Services"
        }
    ],
    "sg:phone":"+1 907 277 4770",
    "sg:postcode":"99518",
    "sg:province":"AK",
    "wof:name":"Seven Star Realty",
    "wof:placetype":"venue"
},
  "geometry": {"coordinates":[-149.898703,61.149991],"type":"Point"}
}