{
  "type": "Feature",
  "properties": {
    "addr:full":"7820 Raymar Cir Anchorage AK 99518",
    "addr:housenumber":"7820",
    "addr:postcode":"99518",
    "addr:street":"Raymar Cir",
    "iso:country":"US",
    "sg:address":"7820 Raymar Cir",
    "sg:city":"Anchorage",
    "sg:classifiers":[
        {
            "category":"Real Estate",
            "subcategory":"Real Estate Agent",
            "type":"Services"
        }
    ],
    "sg:phone":"+1 907 277 4770",
    "sg:postcode":"99518",
    "sg:province":"AK",
    "wof:name":"Seven Star Realty",
    "wof:placetype":"venue"
},
  "geometry": {"coordinates":[-149.89870300000001,61.149991],"type":"Point"}
}