{
  "type": "Feature",
  "properties": {
    "addr:full":"402 Overland Ave Kenai AK 99611",
    "addr:housenumber":"402",
    "addr:postcode":"99611",
    "addr:street":"Overland Ave",
    "iso:country":"US",
    "sg:address":"402 Overland Ave",
    "sg:city":"Kenai",
    "sg:classifiers":[
        {
            "category":"Organizations",
            "subcategory":"Professional Association",
            "type":"Services"
        }
    ],
    "sg:phone":"+1 907 283 7989",
    "sg:postcode":"99611",
    "sg:province":"AK",
    "sg:tags":[
        "chambers",
        "commerce"
    ],
    "wof:name":"Kenai Chamber Of Commerce",
    "wof:placetype":"venue"
},
  "geometry": {"coordinates":[-151.263014,60.553892],"type":"Point"}
}