{
  "type": "Feature",
  "properties": {
    "iso:country":"US",
    "sg:address":"5205 Northwood Dr",
    "sg:city":"Anchorage",
    "sg:classifiers":[
        {
            "category":"Travel",
            "subcategory":"Hotels & Motels",
            "type":"Entertainment"
        }
    ],
    "sg:phone":"+1 907 245 5002",
    "sg:postcode":"99517",
    "sg:province":"AK",
    "sg:website":"www.microtelinn.com",
    "wof:name":"Microtel Inns & Suites",
    "wof:placetype":"venue"
},
  "geometry": {"coordinates":[-149.92774,61.173301],"type":"Point"}
}