{
  "type": "Feature",
  "properties": {
    "addr:full":"3201 Whispering Woods Dr Wasilla AK 99654",
    "addr:housenumber":"3201",
    "addr:postcode":"99654",
    "addr:street":"Whispering Woods Dr",
    "iso:country":"US",
    "sg:address":"3201 Whispering Woods Dr",
    "sg:city":"Wasilla",
    "sg:classifiers":[
        {
            "category":"Manufacturing",
            "subcategory":"Pottery",
            "type":"Manufacturing & Wholesale Goods"
        }
    ],
    "sg:phone":"+1 907 376 6760",
    "sg:postcode":"99654",
    "sg:province":"AK",
    "sg:website":"www.poopmoose.com",
    "wof:name":"Original Poop Moose",
    "wof:placetype":"venue"
},
  "geometry": {"coordinates":[-149.370563,61.575089],"type":"Point"}
}