{
  "type": "Feature",
  "properties": {
    "iso:country":"US",
    "sg:address":"4000 Old Seward Hwy",
    "sg:city":"Anchorage",
    "sg:classifiers":[
        {
            "category":"Shopping",
            "subcategory":"Computers & Home Electronics",
            "type":"Retail Goods"
        }
    ],
    "sg:phone":"+1 907 562 8501",
    "sg:postcode":"99503",
    "sg:province":"AK",
    "sg:tags":[
        "software"
    ],
    "sg:website":"www.amicro.biz",
    "wof:name":"Applied Microsystems Inc",
    "wof:placetype":"venue"
},
  "geometry": {"coordinates":[-149.868145,61.18307],"type":"Point"}
}