{
  "type": "Feature",
  "properties": {
    "iso:country":"US",
    "sg:address":"2101 Abbott Rd",
    "sg:city":"Anchorage",
    "sg:classifiers":[
        {
            "category":"Food & Beverages",
            "subcategory":"Bakery",
            "type":"Retail Goods"
        }
    ],
    "sg:phone":"+1 907 274 1072",
    "sg:postcode":"99507",
    "sg:province":"AK",
    "sg:tags":[
        "baker"
    ],
    "wof:name":"Flying Dutchman European Pstry",
    "wof:placetype":"venue"
},
  "geometry": {"coordinates":[-149.845606,61.138724],"type":"Point"}
}