{
  "type": "Feature",
  "properties": {
    "addr:full":"2800 Sawmill Creek Rd Sitka AK 99835",
    "addr:housenumber":"2800",
    "addr:postcode":"99835",
    "addr:street":"Sawmill Creek Rd",
    "iso:country":"US",
    "sg:address":"2800 Sawmill Creek Rd",
    "sg:city":"Sitka",
    "sg:classifiers":[
        {
            "category":"Farming",
            "subcategory":"Fish & Marine Products",
            "type":"Manufacturing & Wholesale Goods"
        }
    ],
    "sg:phone":"+1 907 747 3413",
    "sg:postcode":"99835",
    "sg:province":"AK",
    "sg:tags":[
        "commercial",
        "fishing"
    ],
    "wof:name":"Fishing Vessel Coral Lee",
    "wof:placetype":"venue"
},
  "geometry": {"coordinates":[-135.236053,57.047102],"type":"Point"}
}