{
  "type": "Feature",
  "properties": {
    "addr:full":"1438 Noble St Fairbanks AK 99701",
    "addr:housenumber":"1438",
    "addr:postcode":"99701",
    "addr:street":"Noble St",
    "iso:country":"US",
    "sg:address":"1438 Noble St",
    "sg:city":"Fairbanks",
    "sg:classifiers":[
        {
            "category":"Building & Trades",
            "subcategory":"Plumbing",
            "type":"Services"
        }
    ],
    "sg:phone":"+1 907 452 8017",
    "sg:postcode":"99701",
    "sg:province":"AK",
    "sg:tags":[
        "boiler",
        "cleaning"
    ],
    "wof:name":"Stew's Heating Svc",
    "wof:placetype":"venue"
},
  "geometry": {"coordinates":[-147.71366,64.835092],"type":"Point"}
}