{
  "type": "Feature",
  "properties": {
    "iso:country":"US",
    "sg:address":"5072 Sillary Cir",
    "sg:city":"Anchorage",
    "sg:classifiers":[
        {
            "category":"Building & Trades",
            "subcategory":"Electrical",
            "type":"Services"
        }
    ],
    "sg:phone":"+1 907 337 8969",
    "sg:postcode":"99508",
    "sg:province":"AK",
    "sg:tags":[
        "electric",
        "contractor"
    ],
    "wof:name":"Totem Enterprises",
    "wof:placetype":"venue"
},
  "geometry": {"coordinates":[-149.78737000000001,61.188458],"type":"Point"}
}