{
  "type": "Feature",
  "properties": {
    "iso:country":"US",
    "sg:address":"1113 W Fireweed Ln",
    "sg:city":"Anchorage",
    "sg:classifiers":[
        {
            "category":"Real Estate",
            "subcategory":"Real Estate Agent",
            "type":"Services"
        }
    ],
    "sg:phone":"+1 907 277 2663",
    "sg:postcode":"99503",
    "sg:province":"AK",
    "wof:name":"H J Gellert & Assoc",
    "wof:placetype":"venue"
},
  "geometry": {"coordinates":[-149.905466,61.198983],"type":"Point"}
}