{
  "type": "Feature",
  "properties": {
    "iso:country":"US",
    "sg:address":"219 E Dimond Blvd",
    "sg:city":"Anchorage",
    "sg:classifiers":[
        {
            "category":"Restaurant",
            "type":"Food & Drink"
        }
    ],
    "sg:phone":"+1 907 868 5226",
    "sg:postcode":"99515",
    "sg:province":"AK",
    "wof:name":"Thai Orchid Restaurant",
    "wof:placetype":"venue"
},
  "geometry": {"coordinates":[-149.87733499999999,61.144804],"type":"Point"}
}