{
  "type": "Feature",
  "properties": {
    "iso:country":"US",
    "sg:address":"2036 E Northern Lights Blvd",
    "sg:city":"Anchorage",
    "sg:classifiers":[
        {
            "category":"Retail",
            "subcategory":"Veterinary Services",
            "type":"Services"
        }
    ],
    "sg:phone":"+1 907 274 5623",
    "sg:postcode":"99508",
    "sg:province":"AK",
    "sg:tags":[
        "hospital",
        "animal"
    ],
    "wof:name":"College Village Animal Clinic",
    "wof:placetype":"venue"
},
  "geometry": {"coordinates":[-149.838603,61.195301],"type":"Point"}
}