{
  "type": "Feature",
  "properties": {
    "addr:full":"3901 Old Seward Hwy Anchorage AK 99503",
    "addr:housenumber":"3901",
    "addr:postcode":"99503",
    "addr:street":"Old Seward Hwy",
    "iso:country":"US",
    "sg:address":"3901 Old Seward Hwy",
    "sg:city":"Anchorage",
    "sg:classifiers":[
        {
            "category":"Restaurant",
            "type":"Food & Drink"
        }
    ],
    "sg:phone":"+1 907 561 0818",
    "sg:postcode":"99503",
    "sg:province":"AK",
    "wof:name":"New Cauldron",
    "wof:placetype":"venue"
},
  "geometry": {"coordinates":[-149.86815000000001,61.184449],"type":"Point"}
}