{
  "type": "Feature",
  "properties": {
    "iso:country":"US",
    "sg:address":"128 W 1st Ave",
    "sg:city":"Anchorage",
    "sg:classifiers":[
        {
            "category":"Manufacturing",
            "subcategory":"Food",
            "type":"Manufacturing & Wholesale Goods"
        }
    ],
    "sg:phone":"+1 907 264 0285",
    "sg:postcode":"99501",
    "sg:province":"AK",
    "sg:tags":[
        "bottler"
    ],
    "sg:website":"www.odomcorp.com",
    "wof:name":"Coca-Cola Bottling Co",
    "wof:placetype":"venue"
},
  "geometry": {"coordinates":[-149.884637,61.221426],"type":"Point"}
}