{
  "type": "Feature",
  "properties": {
    "iso:country":"US",
    "sg:address":"841 I St",
    "sg:city":"Anchorage",
    "sg:classifiers":[
        {
            "category":"Professional",
            "type":"Services"
        }
    ],
    "sg:phone":"+1 907 276 0407",
    "sg:postcode":"99501",
    "sg:province":"AK",
    "sg:tags":[
        "establishment"
    ],
    "wof:name":"Gingham House",
    "wof:placetype":"venue"
},
  "geometry": {"coordinates":[-149.89952299999999,61.214029],"type":"Point"}
}