{
  "type": "Feature",
  "properties": {
    "addr:full":"119 Seward St Juneau AK 99801",
    "addr:housenumber":"119",
    "addr:postcode":"99801",
    "addr:street":"Seward St",
    "iso:country":"US",
    "sg:address":"119 Seward St",
    "sg:city":"Juneau",
    "sg:classifiers":[
        {
            "category":"Organizations",
            "subcategory":"Community Association",
            "type":"Services"
        }
    ],
    "sg:phone":"+1 907 586 8621",
    "sg:postcode":"99801",
    "sg:province":"AK",
    "sg:tags":[
        "environmental",
        "org"
    ],
    "wof:name":"Nature Conservancy",
    "wof:placetype":"venue"
},
  "geometry": {"coordinates":[-134.40723199999999,58.300767],"type":"Point"}
}