{
  "type": "Feature",
  "properties": {
    "iso:country":"US",
    "sg:address":"1207 W 8th Ave",
    "sg:city":"Anchorage",
    "sg:classifiers":[
        {
            "category":"Professional",
            "subcategory":"Lawyer & Legal Services",
            "type":"Services"
        }
    ],
    "sg:phone":"+1 907 276 5366",
    "sg:postcode":"99501",
    "sg:province":"AK",
    "sg:tags":[
        "attorney"
    ],
    "wof:name":"Rose & Figura",
    "wof:placetype":"venue"
},
  "geometry": {"coordinates":[-149.907777,61.214695],"type":"Point"}
}