{
  "type": "Feature",
  "properties": {
    "iso:country":"US",
    "sg:address":"3003 Minnesota Dr",
    "sg:city":"Anchorage",
    "sg:classifiers":[
        {
            "category":"Health Services",
            "subcategory":"Doctor",
            "type":"Services"
        }
    ],
    "sg:phone":"+1 907 563 1123",
    "sg:postcode":"99503",
    "sg:province":"AK",
    "sg:tags":[
        "dentist"
    ],
    "wof:name":"Northland Dental Inc",
    "wof:placetype":"venue"
},
  "geometry": {"coordinates":[-149.91301200000001,61.192891],"type":"Point"}
}