{
  "type": "Feature",
  "properties": {
    "iso:country":"US",
    "sg:address":"3712 Sanders St",
    "sg:city":"Juneau",
    "sg:classifiers":[
        {
            "category":"Retail",
            "subcategory":"Repair Shop",
            "type":"Services"
        }
    ],
    "sg:phone":"+1 907 523 1916",
    "sg:postcode":"99801",
    "sg:province":"AK",
    "sg:tags":[
        "welding",
        "fabricating"
    ],
    "wof:name":"Steelhead Welding & Fabg",
    "wof:placetype":"venue"
},
  "geometry": {"coordinates":[-134.57493600000001,58.388421],"type":"Point"}
}