{
  "type": "Feature",
  "properties": {
    "addr:full":"12349 Old Glenn Hwy Eagle River AK 99577",
    "addr:housenumber":"12349",
    "addr:postcode":"99577",
    "addr:street":"Old Glenn Hwy",
    "iso:country":"US",
    "sg:address":"12349 Old Glenn Hwy",
    "sg:city":"Eagle River",
    "sg:classifiers":[
        {
            "category":"Bars & Pubs",
            "type":"Food & Drink"
        }
    ],
    "sg:phone":"+1 907 694 2372",
    "sg:postcode":"99577",
    "sg:province":"AK",
    "sg:tags":[
        "lounge",
        "cocktail"
    ],
    "wof:name":"Tips Bar",
    "wof:placetype":"venue"
},
  "geometry": {"coordinates":[-149.56559999999999,61.331941],"type":"Point"}
}