{
  "type": "Feature",
  "properties": {
    "addr:full":"501 W Potter Dr Anchorage AK 99518",
    "addr:housenumber":"501",
    "addr:postcode":"99518",
    "addr:street":"W Potter Dr",
    "iso:country":"US",
    "sg:address":"501 W Potter Dr",
    "sg:city":"Anchorage",
    "sg:classifiers":[
        {
            "category":"Wholesale",
            "subcategory":"Groceries",
            "type":"Manufacturing & Wholesale Goods"
        }
    ],
    "sg:phone":"+1 907 334 9070",
    "sg:postcode":"99518",
    "sg:province":"AK",
    "sg:tags":[
        "grocer"
    ],
    "wof:name":"Alaska Logistics",
    "wof:placetype":"venue"
},
  "geometry": {"coordinates":[-149.89604499999999,61.170994],"type":"Point"}
}