{
  "type": "Feature",
  "properties": {
    "addr:full":"1137 Huffman Rd Anchorage AK 99515",
    "addr:housenumber":"1137",
    "addr:postcode":"99515",
    "addr:street":"Huffman Rd",
    "iso:country":"US",
    "sg:address":"1137 Huffman Rd",
    "sg:city":"Anchorage",
    "sg:classifiers":[
        {
            "category":"Restaurant",
            "type":"Food & Drink"
        }
    ],
    "sg:menulink":"http://www.allmenus.com/ak/anchorage/160970-carls-jr/menu/",
    "sg:phone":"+1 907 522 7555",
    "sg:postcode":"99515",
    "sg:province":"AK",
    "sg:tags":[
        "burger",
        "american"
    ],
    "wof:name":"Carl's Jr.",
    "wof:placetype":"venue"
},
  "geometry": {"coordinates":[-149.86121199999999,61.108624],"type":"Point"}
}