{
  "type": "Feature",
  "properties": {
    "iso:country":"US",
    "sg:address":"2503 Captain Cook Dr",
    "sg:city":"Anchorage",
    "sg:classifiers":[
        {
            "category":"Professional",
            "subcategory":"Art Services",
            "type":"Services"
        }
    ],
    "sg:phone":"+1 907 243 4188",
    "sg:postcode":"99517",
    "sg:province":"AK",
    "sg:tags":[
        "photographer"
    ],
    "wof:name":"Calvin Hall Photography",
    "wof:placetype":"venue"
},
  "geometry": {"coordinates":[-149.938355,61.198332],"type":"Point"}
}