{
  "type": "Feature",
  "properties": {
    "iso:country":"US",
    "sg:address":"747 Gaffney Rd",
    "sg:city":"Fairbanks",
    "sg:classifiers":[
        {
            "category":"Autos & Motor Vehicles",
            "subcategory":"Auto Supplies",
            "type":"Retail Goods"
        }
    ],
    "sg:phone":"+1 907 479 6125",
    "sg:postcode":"99701",
    "sg:province":"AK",
    "sg:tags":[
        "automobile",
        "parts"
    ],
    "wof:name":"Performance Shop",
    "wof:placetype":"venue"
},
  "geometry": {"coordinates":[-147.724614,64.837178],"type":"Point"}
}