{
  "type": "Feature",
  "properties": {
    "iso:country":"US",
    "sg:address":"400 W Northern Lights Blvd",
    "sg:city":"Anchorage",
    "sg:classifiers":[
        {
            "category":"Health Services",
            "subcategory":"Chiropractor",
            "type":"Services"
        }
    ],
    "sg:phone":"+1 907 569 1165",
    "sg:postcode":"99503",
    "sg:province":"AK",
    "wof:name":"Bilan Chiropractic Clinic",
    "wof:placetype":"venue"
},
  "geometry": {"coordinates":[-149.890636,61.195294],"type":"Point"}
}