{
  "type": "Feature",
  "properties": {
    "iso:country":"US",
    "sg:address":"3534 International St",
    "sg:city":"Fairbanks",
    "sg:classifiers":[
        {
            "category":"Shopping",
            "subcategory":"Computers & Home Electronics",
            "type":"Retail Goods"
        }
    ],
    "sg:phone":"+1 907 452 8868",
    "sg:postcode":"99701",
    "sg:province":"AK",
    "sg:tags":[
        "equipment",
        "satellite",
        "system"
    ],
    "wof:name":"Northstar Cable Systems",
    "wof:placetype":"venue"
},
  "geometry": {"coordinates":[-147.75109699999999,64.813548],"type":"Point"}
}