{
  "type": "Feature",
  "properties": {
    "iso:country":"US",
    "sg:address":"2704 E Tudor Rd",
    "sg:city":"Anchorage",
    "sg:classifiers":[
        {
            "category":"Health Services",
            "subcategory":"Health Practitioner",
            "type":"Services"
        }
    ],
    "sg:phone":"+1 907 561 5006",
    "sg:postcode":"99507",
    "sg:province":"AK",
    "sg:tags":[
        "therapist",
        "physical"
    ],
    "wof:name":"Seethaler Physical Therapy",
    "wof:placetype":"venue"
},
  "geometry": {"coordinates":[-149.827018,61.180762],"type":"Point"}
}