{
  "type": "Feature",
  "properties": {
    "iso:country":"US",
    "sg:address":"631 W 11th St",
    "sg:city":"Juneau",
    "sg:classifiers":[
        {
            "category":"Professional",
            "subcategory":"Art Services",
            "type":"Services"
        }
    ],
    "sg:phone":"+1 907 463 2677",
    "sg:postcode":"99801",
    "sg:province":"AK",
    "sg:tags":[
        "graphic",
        "designer"
    ],
    "wof:name":"A Sign Of Design",
    "wof:placetype":"venue"
},
  "geometry": {"coordinates":[-134.42139,58.302951],"type":"Point"}
}