{
  "type": "Feature",
  "properties": {
    "iso:country":"US",
    "sg:address":"4301 Rabbit Creek Rd",
    "sg:city":"Anchorage",
    "sg:classifiers":[
        {
            "category":"Building & Trades",
            "subcategory":"Construction",
            "type":"Services"
        }
    ],
    "sg:phone":"+1 907 345 8558",
    "sg:postcode":"99516",
    "sg:province":"AK",
    "sg:tags":[
        "contractor"
    ],
    "wof:name":"Fenceman Inc Thee",
    "wof:placetype":"venue"
},
  "geometry": {"coordinates":[-149.801194,61.082952],"type":"Point"}
}