{
  "type": "Feature",
  "properties": {
    "iso:country":"US",
    "sg:address":"1564 Emma Way",
    "sg:city":"Fairbanks",
    "sg:classifiers":[
        {
            "category":"Building & Trades",
            "subcategory":"Construction",
            "type":"Services"
        }
    ],
    "sg:phone":"+1 907 479 4830",
    "sg:postcode":"99709",
    "sg:province":"AK",
    "sg:tags":[
        "general",
        "contractor"
    ],
    "wof:name":"Quality Carpentry",
    "wof:placetype":"venue"
},
  "geometry": {"coordinates":[-147.97634300000001,64.797163],"type":"Point"}
}