{
  "type": "Feature",
  "properties": {
    "iso:country":"US",
    "sg:address":"723 Gaffney Rd",
    "sg:city":"Fairbanks",
    "sg:classifiers":[
        {
            "category":"Retail",
            "subcategory":"Repair Shop",
            "type":"Services"
        }
    ],
    "sg:phone":"+1 907 452 3464",
    "sg:postcode":"99701",
    "sg:province":"AK",
    "sg:tags":[
        "television",
        "radio"
    ],
    "wof:name":"Alaska Television",
    "wof:placetype":"venue"
},
  "geometry": {"coordinates":[-147.725102,64.837175],"type":"Point"}
}