{
  "type": "Feature",
  "properties": {
    "addr:full":"7250 Shorewood Dr Palmer AK 99654",
    "addr:housenumber":"7250",
    "addr:postcode":"99654",
    "addr:street":"Shorewood Dr",
    "iso:country":"US",
    "sg:address":"7250 Shorewood Dr",
    "sg:city":"Palmer",
    "sg:classifiers":[
        {
            "category":"Professional",
            "subcategory":"Advertising",
            "type":"Services"
        }
    ],
    "sg:phone":"+1 907 746 0403",
    "sg:postcode":"99654",
    "sg:province":"AK",
    "sg:tags":[
        "distribution"
    ],
    "wof:name":"Amway Distributors",
    "wof:placetype":"venue"
},
  "geometry": {"coordinates":[-149.270015,61.626169],"type":"Point"}
}