{
  "type": "Feature",
  "properties": {
    "iso:country":"US",
    "sg:address":"11000 Cange St",
    "sg:city":"Anchorage",
    "sg:classifiers":[
        {
            "category":"Wholesale",
            "subcategory":"Durable Goods & Equipment",
            "type":"Manufacturing & Wholesale Goods"
        }
    ],
    "sg:phone":"+1 907 344 2900",
    "sg:postcode":"99516",
    "sg:province":"AK",
    "sg:tags":[
        "representative",
        "manufacturer"
    ],
    "wof:name":"Health For Life",
    "wof:placetype":"venue"
},
  "geometry": {"coordinates":[-149.819216,61.121278],"type":"Point"}
}