{
  "type": "Feature",
  "properties": {
    "addr:full":"207 E Northern Lights Blvd Anchorage AK 99503",
    "addr:housenumber":"207",
    "addr:postcode":"99503",
    "addr:street":"E Northern Lights Blvd",
    "iso:country":"US",
    "sg:address":"207 E Northern Lights Blvd",
    "sg:city":"Anchorage",
    "sg:classifiers":[
        {
            "category":"Health Services",
            "subcategory":"Optometrist",
            "type":"Services"
        }
    ],
    "sg:phone":"+1 907 272 9800",
    "sg:postcode":"99503",
    "sg:province":"AK",
    "wof:name":"Accurate Vision Clinic",
    "wof:placetype":"venue"
},
  "geometry": {"coordinates":[-149.878792,61.195363],"type":"Point"}
}