{
  "type": "Feature",
  "properties": {
    "addr:full":"41810 E Hill Rd Homer AK 99603",
    "addr:housenumber":"41810",
    "addr:postcode":"99603",
    "addr:street":"E Hill Rd",
    "iso:country":"US",
    "sg:address":"41810 E Hill Rd",
    "sg:city":"Homer",
    "sg:classifiers":[
        {
            "category":"Building & Trades",
            "subcategory":"Construction",
            "type":"Services"
        }
    ],
    "sg:phone":"+1 907 235 4137",
    "sg:postcode":"99603",
    "sg:province":"AK",
    "sg:tags":[
        "house"
    ],
    "wof:name":"Big Mountain Builders Inc",
    "wof:placetype":"venue"
},
  "geometry": {"coordinates":[-151.514993,59.667655],"type":"Point"}
}