{
  "type": "Feature",
  "properties": {
    "iso:country":"US",
    "sg:address":"2014 N Post Rd",
    "sg:city":"Anchorage",
    "sg:classifiers":[
        {
            "category":"Retail",
            "subcategory":"Auto Repair",
            "type":"Services"
        }
    ],
    "sg:phone":"+1 907 277 4970",
    "sg:postcode":"99501",
    "sg:province":"AK",
    "sg:tags":[
        "truck"
    ],
    "wof:name":"Commercial Truck Svc",
    "wof:placetype":"venue"
},
  "geometry": {"coordinates":[-149.84168,61.227554],"type":"Point"}
}