{
  "type": "Feature",
  "properties": {
    "iso:country":"US",
    "sg:address":"3615 Braddock St",
    "sg:city":"Fairbanks",
    "sg:classifiers":[
        {
            "category":"Freight",
            "type":"Transportation"
        }
    ],
    "sg:phone":"+1 907 456 4285",
    "sg:postcode":"99701",
    "sg:province":"AK",
    "sg:tags":[
        "trucking"
    ],
    "wof:name":"ASRC Transport",
    "wof:placetype":"venue"
},
  "geometry": {"coordinates":[-147.70203599999999,64.809695],"type":"Point"}
}