{
  "type": "Feature",
  "properties": {
    "iso:country":"US",
    "sg:address":"5131 Mayflower Ln",
    "sg:city":"Wasilla",
    "sg:classifiers":[
        {
            "category":"Shopping",
            "type":"Retail Goods"
        }
    ],
    "sg:phone":"+1 907 373 7627",
    "sg:postcode":"99654",
    "sg:province":"AK",
    "sg:tags":[
        "pet",
        "food",
        "supply"
    ],
    "wof:name":"Soapy Dog",
    "wof:placetype":"venue"
},
  "geometry": {"coordinates":[-149.322992,61.585201],"type":"Point"}
}