{
  "type": "Feature",
  "properties": {
    "iso:country":"US",
    "sg:address":"115 E 3rd Ave",
    "sg:city":"Anchorage",
    "sg:classifiers":[
        {
            "category":"Restaurant",
            "type":"Food & Drink"
        }
    ],
    "sg:phone":"+1 907 334 8408",
    "sg:postcode":"99501",
    "sg:province":"AK",
    "wof:name":"Yukon Yacht Club",
    "wof:placetype":"venue"
},
  "geometry": {"coordinates":[-149.883129,61.21961],"type":"Point"}
}