{
  "type": "Feature",
  "properties": {
    "iso:country":"US",
    "sg:address":"1007 Shannon Dr",
    "sg:city":"Fairbanks",
    "sg:classifiers":[
        {
            "category":"Building & Trades",
            "subcategory":"Plumbing",
            "type":"Services"
        }
    ],
    "sg:phone":"+1 907 456 5147",
    "sg:postcode":"99701",
    "sg:province":"AK",
    "sg:tags":[
        "plumbing",
        "heating"
    ],
    "wof:name":"Progressive Plumbing & Heating",
    "wof:placetype":"venue"
},
  "geometry": {"coordinates":[-147.66933800000001,64.85169999999999],"type":"Point"}
}