{
  "type": "Feature",
  "properties": {
    "iso:country":"US",
    "sg:address":"555 E Northern Lights Blvd",
    "sg:city":"Anchorage",
    "sg:classifiers":[
        {
            "category":"Personal",
            "subcategory":"Beauty Salon",
            "type":"Services"
        }
    ],
    "sg:phone":"+1 907 277 4989",
    "sg:postcode":"99503",
    "sg:province":"AK",
    "wof:name":"Mimo Hair Salon",
    "wof:placetype":"venue"
},
  "geometry": {"coordinates":[-149.87329199999999,61.195359],"type":"Point"}
}