{
  "type": "Feature",
  "properties": {
    "iso:country":"US",
    "sg:address":"1350 Seward Meridian Rd",
    "sg:city":"Wasilla",
    "sg:classifiers":[
        {
            "category":"Health Services",
            "subcategory":"Optometrist",
            "type":"Services"
        }
    ],
    "sg:phone":"+1 907 376 0837",
    "sg:postcode":"99654",
    "sg:province":"AK",
    "wof:name":"Wal-Mart",
    "wof:placetype":"venue"
},
  "geometry": {"coordinates":[-149.35994700000001,61.5683],"type":"Point"}
}