{
  "type": "Feature",
  "properties": {
    "iso:country":"US",
    "sg:address":"8035 Lloyd Dr",
    "sg:city":"Anchorage",
    "sg:classifiers":[
        {
            "category":"Organizations",
            "subcategory":"Religious Organization",
            "type":"Services"
        }
    ],
    "sg:phone":"+1 907 346 2604",
    "sg:postcode":"99502",
    "sg:province":"AK",
    "sg:tags":[
        "church"
    ],
    "wof:name":"Southside Church Of God",
    "wof:placetype":"venue"
},
  "geometry": {"coordinates":[-149.93874400000001,61.147729],"type":"Point"}
}