{
  "type": "Feature",
  "properties": {
    "addr:full":"246 N Binkley St Soldotna AK 99669",
    "addr:housenumber":"246",
    "addr:postcode":"99669",
    "addr:street":"N Binkley St",
    "iso:country":"US",
    "sg:address":"246 N Binkley St",
    "sg:city":"Soldotna",
    "sg:classifiers":[
        {
            "category":"Health Services",
            "subcategory":"Doctor",
            "type":"Services"
        }
    ],
    "sg:phone":"+1 907 262 6393",
    "sg:postcode":"99669",
    "sg:province":"AK",
    "sg:tags":[
        "dentist"
    ],
    "wof:name":"Binkley Street Dental Clinic",
    "wof:placetype":"venue"
},
  "geometry": {"coordinates":[-151.07223400000001,60.493321],"type":"Point"}
}