{
  "type": "Feature",
  "properties": {
    "iso:country":"US",
    "sg:address":"1021 Sandy Beach Rd",
    "sg:city":"Petersburg",
    "sg:classifiers":[
        {
            "category":"Shopping",
            "type":"Retail Goods"
        }
    ],
    "sg:phone":"+1 907 772 2266",
    "sg:postcode":"99833",
    "sg:province":"AK",
    "sg:tags":[
        "pet",
        "shop"
    ],
    "wof:name":"Place Of All Good Things",
    "wof:placetype":"venue"
},
  "geometry": {"coordinates":[-132.92054099999999,56.805597],"type":"Point"}
}