{
  "type": "Feature",
  "properties": {
    "addr:full":"613 Cedar St Cordova AK 99574",
    "addr:housenumber":"613",
    "addr:postcode":"99574",
    "addr:street":"Cedar St",
    "iso:country":"US",
    "sg:address":"613 Cedar St",
    "sg:city":"Cordova",
    "sg:classifiers":[
        {
            "category":"Home & Garden",
            "subcategory":"Building Materials",
            "type":"Retail Goods"
        }
    ],
    "sg:phone":"+1 907 424 4530",
    "sg:postcode":"99574",
    "sg:province":"AK",
    "sg:tags":[
        "glass",
        "window",
        "plate"
    ],
    "wof:name":"Cordova Glass Shop",
    "wof:placetype":"venue"
},
  "geometry": {"coordinates":[-145.74184399999999,60.54349],"type":"Point"}
}