{
  "type": "Feature",
  "properties": {
    "iso:country":"US",
    "sg:address":"6317 Nielson Way",
    "sg:city":"Anchorage",
    "sg:classifiers":[
        {
            "category":"Wholesale",
            "subcategory":"Chemicals & Plastics",
            "type":"Manufacturing & Wholesale Goods"
        }
    ],
    "sg:phone":"+1 907 562 2933",
    "sg:postcode":"99518",
    "sg:province":"AK",
    "wof:name":"Garness Industrial Inc",
    "wof:placetype":"venue"
},
  "geometry": {"coordinates":[-149.894065,61.165042],"type":"Point"}
}