{
  "type": "Feature",
  "properties": {
    "iso:country":"US",
    "sg:address":"809 S Chugach St",
    "sg:city":"Palmer",
    "sg:classifiers":[
        {
            "category":"Health Services",
            "subcategory":"Health Practitioner",
            "type":"Services"
        }
    ],
    "sg:phone":"+1 907 746 4373",
    "sg:postcode":"99645",
    "sg:province":"AK",
    "sg:tags":[
        "therapist",
        "physical"
    ],
    "wof:name":"Excel Physical Therapy",
    "wof:placetype":"venue"
},
  "geometry": {"coordinates":[-149.110602,61.597033],"type":"Point"}
}