{
  "type": "Feature",
  "properties": {
    "addr:full":"5701 Silverado Way Anchorage AK 99518",
    "addr:housenumber":"5701",
    "addr:postcode":"99518",
    "addr:street":"Silverado Way",
    "iso:country":"US",
    "sg:address":"5701 Silverado Way",
    "sg:city":"Anchorage",
    "sg:classifiers":[
        {
            "category":"Manufacturing",
            "subcategory":"Printing",
            "type":"Manufacturing & Wholesale Goods"
        }
    ],
    "sg:phone":"+1 907 562 6554",
    "sg:postcode":"99518",
    "sg:province":"AK",
    "sg:tags":[
        "printer",
        "lithographic",
        "offset"
    ],
    "wof:name":"Northern Printing Co Inc",
    "wof:placetype":"venue"
},
  "geometry": {"coordinates":[-149.88853800000001,61.168471],"type":"Point"}
}