{
  "type": "Feature",
  "properties": {
    "iso:country":"US",
    "sg:address":"4741 Silver Spring Cir",
    "sg:city":"Anchorage",
    "sg:classifiers":[
        {
            "category":"Professional",
            "type":"Services"
        }
    ],
    "sg:phone":"+1 907 346 2468",
    "sg:postcode":"99507",
    "sg:province":"AK",
    "wof:name":"Turnings By Bill Bowers",
    "wof:placetype":"venue"
},
  "geometry": {"coordinates":[-149.792484,61.131748],"type":"Point"}
}