{
  "type": "Feature",
  "properties": {
    "iso:country":"US",
    "sg:address":"4040 Mountain View Dr",
    "sg:city":"Anchorage",
    "sg:classifiers":[
        {
            "category":"Food & Beverages",
            "subcategory":"Groceries & Convenience Stores",
            "type":"Retail Goods"
        }
    ],
    "sg:phone":"+1 907 279 0121",
    "sg:postcode":"99508",
    "sg:province":"AK",
    "sg:tags":[
        "grocer"
    ],
    "wof:name":"New Asian Market",
    "wof:placetype":"venue"
},
  "geometry": {"coordinates":[-149.80513099999999,61.223875],"type":"Point"}
}