{
  "type": "Feature",
  "properties": {
    "addr:full":"3439 E Tudor Rd Anchorage AK 99507",
    "addr:housenumber":"3439",
    "addr:postcode":"99507",
    "addr:street":"E Tudor Rd",
    "iso:country":"US",
    "sg:address":"3439 E Tudor Rd",
    "sg:city":"Anchorage",
    "sg:classifiers":[
        {
            "category":"Shopping",
            "subcategory":"Music",
            "type":"Retail Goods"
        }
    ],
    "sg:phone":"+1 907 569 2801",
    "sg:postcode":"99507",
    "sg:province":"AK",
    "sg:tags":[
        "video",
        "disc",
        "tape",
        "cassette"
    ],
    "wof:name":"Movie Zone",
    "wof:placetype":"venue"
},
  "geometry": {"coordinates":[-149.817115,61.18091],"type":"Point"}
}