{
  "type": "Feature",
  "properties": {
    "addr:full":"2040 S Cushman St Fairbanks AK 99701",
    "addr:housenumber":"2040",
    "addr:postcode":"99701",
    "addr:street":"S Cushman St",
    "iso:country":"US",
    "sg:address":"2040 S Cushman St",
    "sg:city":"Fairbanks",
    "sg:classifiers":[
        {
            "category":"Shopping",
            "subcategory":"Clothing, Apparel, & Fashions",
            "type":"Retail Goods"
        }
    ],
    "sg:phone":"+1 907 452 5750",
    "sg:postcode":"99701",
    "sg:province":"AK",
    "sg:tags":[
        "alteration"
    ],
    "wof:name":"S & S Sewing",
    "wof:placetype":"venue"
},
  "geometry": {"coordinates":[-147.71475799999999,64.828963],"type":"Point"}
}