{
  "type": "Feature",
  "properties": {
    "iso:country":"US",
    "sg:address":"600 Barrow St",
    "sg:city":"Anchorage",
    "sg:classifiers":[
        {
            "category":"Social Services",
            "subcategory":"Job Training",
            "type":"Services"
        }
    ],
    "sg:phone":"+1 907 258 3498",
    "sg:postcode":"99501",
    "sg:province":"AK",
    "sg:tags":[
        "disabled",
        "employment"
    ],
    "sg:website":"www.jobready-ak.com",
    "wof:name":"Job Ready",
    "wof:placetype":"venue"
},
  "geometry": {"coordinates":[-149.881225,61.215592],"type":"Point"}
}