{
  "type": "Feature",
  "properties": {
    "iso:country":"US",
    "sg:address":"1503 Joliet Dr",
    "sg:city":"Fairbanks",
    "sg:classifiers":[
        {
            "category":"Travel",
            "subcategory":"Hotels & Motels",
            "type":"Entertainment"
        }
    ],
    "sg:phone":"+1 907 474 9022",
    "sg:postcode":"99709",
    "sg:province":"AK",
    "sg:tags":[
        "breakfast",
        "accommodation",
        "bed"
    ],
    "wof:name":"Mountain View Bed & Breakfast",
    "wof:placetype":"venue"
},
  "geometry": {"coordinates":[-147.788638,64.8903],"type":"Point"}
}