{
  "type": "Feature",
  "properties": {
    "addr:full":"617 27th Ave Fairbanks AK 99701",
    "addr:housenumber":"617",
    "addr:postcode":"99701",
    "addr:street":"27Th Ave",
    "iso:country":"US",
    "sg:address":"617 27th Ave",
    "sg:city":"Fairbanks",
    "sg:classifiers":[
        {
            "category":"Restaurant",
            "type":"Food & Drink"
        }
    ],
    "sg:phone":"+1 907 452 3827",
    "sg:postcode":"99701",
    "sg:province":"AK",
    "wof:name":"Mom's Kitchen",
    "wof:placetype":"venue"
},
  "geometry": {"coordinates":[-147.715597,64.822399],"type":"Point"}
}