{
  "type": "Feature",
  "properties": {
    "addr:full":"2627 C St Anchorage AK 99503",
    "addr:housenumber":"2627",
    "addr:postcode":"99503",
    "addr:street":"C St",
    "iso:country":"US",
    "sg:address":"2627 C St",
    "sg:city":"Anchorage",
    "sg:classifiers":[
        {
            "category":"Building & Trades",
            "subcategory":"Construction",
            "type":"Services"
        }
    ],
    "sg:phone":"+1 907 276 1454",
    "sg:postcode":"99503",
    "sg:province":"AK",
    "sg:tags":[
        "general",
        "contractor"
    ],
    "wof:name":"ANDREWS Group",
    "wof:placetype":"venue"
},
  "geometry": {"coordinates":[-149.88661400000001,61.197005],"type":"Point"}
}