{
  "type": "Feature",
  "properties": {
    "iso:country":"US",
    "sg:address":"411 W Tudor Rd",
    "sg:city":"Anchorage",
    "sg:classifiers":[
        {
            "category":"Retail",
            "subcategory":"Auto Repair",
            "type":"Services"
        }
    ],
    "sg:phone":"+1 907 562 2077",
    "sg:postcode":"99503",
    "sg:province":"AK",
    "sg:tags":[
        "repairing",
        "automobile"
    ],
    "wof:name":"Euro-Car Svc",
    "wof:placetype":"venue"
},
  "geometry": {"coordinates":[-149.894116,61.180886],"type":"Point"}
}