{
  "type": "Feature",
  "properties": {
    "iso:country":"US",
    "sg:address":"1749 Ship Ave",
    "sg:city":"Anchorage",
    "sg:classifiers":[
        {
            "category":"Building & Trades",
            "subcategory":"Construction",
            "type":"Services"
        }
    ],
    "sg:phone":"+1 907 274 5454",
    "sg:postcode":"99501",
    "sg:province":"AK",
    "sg:tags":[
        "general",
        "contractor"
    ],
    "wof:name":"Amigo",
    "wof:placetype":"venue"
},
  "geometry": {"coordinates":[-149.84759,61.223529],"type":"Point"}
}