{
  "type": "Feature",
  "properties": {
    "addr:full":"660 3rd Ave Bethel AK 99559",
    "addr:housenumber":"660",
    "addr:postcode":"99559",
    "addr:street":"3Rd Ave",
    "iso:country":"US",
    "sg:address":"660 3rd Ave",
    "sg:city":"Bethel",
    "sg:classifiers":[
        {
            "category":"Personal",
            "subcategory":"Barber",
            "type":"Services"
        }
    ],
    "sg:phone":"+1 907 543 5666",
    "sg:postcode":"99559",
    "sg:province":"AK",
    "sg:tags":[
        "school"
    ],
    "wof:name":"Stan's Barber Shop",
    "wof:placetype":"venue"
},
  "geometry": {"coordinates":[-161.755976,60.795078],"type":"Point"}
}