{
  "type": "Feature",
  "properties": {
    "addr:full":"806 S Colony Way Palmer AK 99645",
    "addr:housenumber":"806",
    "addr:postcode":"99645",
    "addr:street":"S Colony Way",
    "iso:country":"US",
    "sg:address":"806 S Colony Way",
    "sg:city":"Palmer",
    "sg:classifiers":[
        {
            "category":"Manufacturing",
            "subcategory":"Motor Vehicles & Parts",
            "type":"Manufacturing & Wholesale Goods"
        }
    ],
    "sg:phone":"+1 907 746 2454",
    "sg:postcode":"99645",
    "sg:province":"AK",
    "sg:tags":[
        "screen",
        "printing",
        "printed",
        "t"
    ],
    "wof:name":"Brandywine Designs",
    "wof:placetype":"venue"
},
  "geometry": {"coordinates":[-149.11505,61.598451],"type":"Point"}
}