{
  "type": "Feature",
  "properties": {
    "addr:full":"501 Willow St Bethel AK 99559",
    "addr:housenumber":"501",
    "addr:postcode":"99559",
    "addr:street":"Willow St",
    "iso:country":"US",
    "sg:address":"501 Willow St",
    "sg:city":"Bethel",
    "sg:classifiers":[
        {
            "category":"Retail",
            "subcategory":"Veterinary Services",
            "type":"Services"
        }
    ],
    "sg:phone":"+1 907 543 2823",
    "sg:postcode":"99559",
    "sg:province":"AK",
    "sg:tags":[
        "veterinarian"
    ],
    "wof:name":"Bering Sea Animal Clinic",
    "wof:placetype":"venue"
},
  "geometry": {"coordinates":[-161.76912999999999,60.796528],"type":"Point"}
}