{
  "type": "Feature",
  "properties": {
    "iso:country":"US",
    "sg:address":"3601 C St",
    "sg:city":"Anchorage",
    "sg:classifiers":[
        {
            "category":"Professional",
            "type":"Services"
        }
    ],
    "sg:phone":"+1 907 272 1232",
    "sg:postcode":"99503",
    "sg:province":"AK",
    "sg:tags":[
        "geophysicist"
    ],
    "sg:website":"www.petroak.com",
    "wof:name":"Petrotechnical Resources Of Ak",
    "wof:placetype":"venue"
},
  "geometry": {"coordinates":[-149.886592,61.187549],"type":"Point"}
}