{
  "type": "Feature",
  "properties": {
    "addr:full":"127 E Potter Dr Anchorage AK 99518",
    "addr:housenumber":"127",
    "addr:postcode":"99518",
    "addr:street":"E Potter Dr",
    "iso:country":"US",
    "sg:address":"127 E Potter Dr",
    "sg:city":"Anchorage",
    "sg:classifiers":[
        {
            "category":"Farming",
            "subcategory":"Farm",
            "type":"Manufacturing & Wholesale Goods"
        }
    ],
    "sg:phone":"+1 907 563 7849",
    "sg:postcode":"99518",
    "sg:province":"AK",
    "sg:tags":[
        "crop",
        "general"
    ],
    "wof:name":"Flyway Farm LLC",
    "wof:placetype":"venue"
},
  "geometry": {"coordinates":[-149.88087200000001,61.167151],"type":"Point"}
}