{
  "type": "Feature",
  "properties": {
    "iso:country":"US",
    "sg:address":"3952 Julep St",
    "sg:city":"Juneau",
    "sg:classifiers":[
        {
            "category":"Retail",
            "subcategory":"Laundry & Dry Cleaning",
            "type":"Services"
        }
    ],
    "sg:phone":"+1 907 790 2140",
    "sg:postcode":"99801",
    "sg:province":"AK",
    "sg:tags":[
        "cleaners",
        "rug",
        "carpet"
    ],
    "wof:name":"Superior Services Of Juneau",
    "wof:placetype":"venue"
},
  "geometry": {"coordinates":[-134.580341,58.390542],"type":"Point"}
}