{
  "type": "Feature",
  "properties": {
    "addr:full":"1016 W 6th Ave Anchorage AK 99501",
    "addr:housenumber":"1016",
    "addr:postcode":"99501",
    "addr:street":"W 6Th Ave",
    "iso:country":"US",
    "sg:address":"1016 W 6th Ave",
    "sg:city":"Anchorage",
    "sg:classifiers":[
        {
            "category":"Government",
            "subcategory":"Office",
            "type":"Public Place"
        }
    ],
    "sg:phone":"+1 907 277 1496",
    "sg:postcode":"99501",
    "sg:province":"AK",
    "wof:name":"Permanent Fund Div",
    "wof:placetype":"venue"
},
  "geometry": {"coordinates":[-149.90357900000001,61.216506],"type":"Point"}
}