{
  "type": "Feature",
  "properties": {
    "addr:full":"2700 E Broadview Ave Wasilla AK 99654",
    "addr:housenumber":"2700",
    "addr:postcode":"99654",
    "addr:street":"E Broadview Ave",
    "iso:country":"US",
    "sg:address":"2700 E Broadview Ave",
    "sg:city":"Wasilla",
    "sg:classifiers":[
        {
            "category":"Organizations",
            "subcategory":"Religious Organization",
            "type":"Services"
        }
    ],
    "sg:phone":"+1 907 373 3615",
    "sg:postcode":"99654",
    "sg:province":"AK",
    "sg:tags":[
        "church"
    ],
    "wof:name":"Pioneer Christian Fellowship",
    "wof:placetype":"venue"
},
  "geometry": {"coordinates":[-149.383343,61.570465],"type":"Point"}
}