{
  "type": "Feature",
  "properties": {
    "iso:country":"US",
    "sg:address":"4105 E Turnagain Blvd",
    "sg:city":"Anchorage",
    "sg:classifiers":[
        {
            "category":"Professional",
            "type":"Services"
        }
    ],
    "sg:phone":"+1 907 245 2328",
    "sg:postcode":"99517",
    "sg:province":"AK",
    "sg:tags":[
        "arranger",
        "music",
        "composer"
    ],
    "sg:website":"www.frozenmusic.com",
    "wof:name":"Frozen Music Productions",
    "wof:placetype":"venue"
},
  "geometry": {"coordinates":[-149.935292,61.182279],"type":"Point"}
}