{
  "type": "Feature",
  "properties": {
    "addr:full":"12720 Tanada Loop Anchorage AK 99515",
    "addr:housenumber":"12720",
    "addr:postcode":"99515",
    "addr:street":"Tanada Loop",
    "iso:country":"US",
    "sg:address":"12720 Tanada Loop",
    "sg:city":"Anchorage",
    "sg:classifiers":[
        {
            "category":"Shopping",
            "type":"Retail Goods"
        }
    ],
    "sg:phone":"+1 907 338 6435",
    "sg:postcode":"99515",
    "sg:province":"AK",
    "sg:tags":[
        "cosmetic",
        "perfume"
    ],
    "wof:name":"Mary Kay Cosmetics",
    "wof:placetype":"venue"
},
  "geometry": {"coordinates":[-149.85134400000001,61.107197],"type":"Point"}
}