{
  "type": "Feature",
  "properties": {
    "addr:full":"514 W Dimond Blvd Anchorage AK 99515",
    "addr:housenumber":"514",
    "addr:postcode":"99515",
    "addr:street":"W Dimond Blvd",
    "iso:country":"US",
    "sg:address":"514 W Dimond Blvd",
    "sg:city":"Anchorage",
    "sg:classifiers":[
        {
            "category":"Organizations",
            "subcategory":"Religious Organization",
            "type":"Services"
        }
    ],
    "sg:phone":"+1 907 344 3113",
    "sg:postcode":"99515",
    "sg:province":"AK",
    "sg:tags":[
        "church"
    ],
    "wof:name":"Bethel Missionary Baptist Chr",
    "wof:placetype":"venue"
},
  "geometry": {"coordinates":[-149.88937000000001,61.144766],"type":"Point"}
}