{
  "type": "Feature",
  "properties": {
    "iso:country":"US",
    "sg:address":"4010 Romanzof Cir",
    "sg:city":"Anchorage",
    "sg:classifiers":[
        {
            "category":"Real Estate",
            "subcategory":"Real Estate Agent",
            "type":"Services"
        }
    ],
    "sg:phone":"+1 907 336 1963",
    "sg:postcode":"99517",
    "sg:province":"AK",
    "sg:tags":[
        "buyer",
        "broker"
    ],
    "wof:name":"New Horizons Assn Management",
    "wof:placetype":"venue"
},
  "geometry": {"coordinates":[-149.96069199999999,61.194644],"type":"Point"}
}