{
  "type": "Feature",
  "properties": {
    "addr:full":"329 F St Anchorage AK 99501",
    "addr:housenumber":"329",
    "addr:postcode":"99501",
    "addr:street":"F St",
    "iso:country":"US",
    "sg:address":"329 F St",
    "sg:city":"Anchorage",
    "sg:classifiers":[
        {
            "category":"Professional",
            "subcategory":"Business Services",
            "type":"Services"
        }
    ],
    "sg:phone":"+1 907 646 9000",
    "sg:postcode":"99501",
    "sg:province":"AK",
    "sg:tags":[
        "convention",
        "meeting",
        "facility"
    ],
    "wof:name":"Coordinators Inc",
    "wof:placetype":"venue"
},
  "geometry": {"coordinates":[-149.89341400000001,61.218833],"type":"Point"}
}