{
  "type": "Feature",
  "properties": {
    "addr:full":"5705 Hideaway Cir Wasilla AK 99654",
    "addr:housenumber":"5705",
    "addr:postcode":"99654",
    "addr:street":"Hideaway Cir",
    "iso:country":"US",
    "sg:address":"5705 Hideaway Cir",
    "sg:city":"Wasilla",
    "sg:classifiers":[
        {
            "category":"Retail",
            "subcategory":"Repair Shop",
            "type":"Services"
        }
    ],
    "sg:phone":"+1 907 376 1607",
    "sg:postcode":"99654",
    "sg:province":"AK",
    "sg:tags":[
        "taxidermist"
    ],
    "wof:name":"Foster's Taxidermy",
    "wof:placetype":"venue"
},
  "geometry": {"coordinates":[-149.305307,61.578836],"type":"Point"}
}