{
  "type": "Feature",
  "properties": {
    "iso:country":"US",
    "sg:address":"9719 Trappers Ln",
    "sg:city":"Juneau",
    "sg:classifiers":[
        {
            "category":"Travel",
            "subcategory":"Hotels & Motels",
            "type":"Entertainment"
        }
    ],
    "sg:phone":"+1 907 789 2647",
    "sg:postcode":"99801",
    "sg:province":"AK",
    "sg:tags":[
        "breakfast",
        "accommodation",
        "bed"
    ],
    "wof:name":"Mountain View B & B",
    "wof:placetype":"venue"
},
  "geometry": {"coordinates":[-134.594534,58.407176],"type":"Point"}
}