{
  "type": "Feature",
  "properties": {
    "iso:country":"US",
    "sg:address":"745 8th Ave",
    "sg:city":"Fairbanks",
    "sg:classifiers":[
        {
            "category":"Professional",
            "subcategory":"Lawyer & Legal Services",
            "type":"Services"
        }
    ],
    "sg:phone":"+1 907 456 6632",
    "sg:postcode":"99701",
    "sg:province":"AK",
    "sg:tags":[
        "attorney"
    ],
    "wof:name":"Gail Ballou Law Office",
    "wof:placetype":"venue"
},
  "geometry": {"coordinates":[-147.727875,64.840422],"type":"Point"}
}