{
  "type": "Feature",
  "properties": {
    "iso:country":"US",
    "sg:address":"209 E Dimond Blvd",
    "sg:city":"Anchorage",
    "sg:classifiers":[
        {
            "category":"Restaurant",
            "type":"Food & Drink"
        }
    ],
    "sg:phone":"+1 907 344 1669",
    "sg:postcode":"99515",
    "sg:province":"AK",
    "wof:name":"King's Burger",
    "wof:placetype":"venue"
},
  "geometry": {"coordinates":[-149.87727599999999,61.144804],"type":"Point"}
}