{
  "type": "Feature",
  "properties": {
    "iso:country":"US",
    "sg:address":"3900 C St",
    "sg:city":"Anchorage",
    "sg:classifiers":[
        {
            "category":"Manufacturing",
            "subcategory":"Petroleum Products",
            "type":"Manufacturing & Wholesale Goods"
        }
    ],
    "sg:phone":"+1 907 339 6638",
    "sg:postcode":"99503",
    "sg:province":"AK",
    "sg:tags":[
        "refining"
    ],
    "wof:name":"Petro Star Refining LLC",
    "wof:placetype":"venue"
},
  "geometry": {"coordinates":[-149.886575,61.18447],"type":"Point"}
}