{
  "type": "Feature",
  "properties": {
    "iso:country":"US",
    "sg:address":"59 College Rd",
    "sg:city":"Fairbanks",
    "sg:classifiers":[
        {
            "category":"Restaurant",
            "type":"Food & Drink"
        }
    ],
    "sg:menulink":"http://www.allmenus.com/ak/fairbanks-north-star/63955-dominos-pizza/menu/",
    "sg:phone":"+1 907 451 8201",
    "sg:postcode":"99701",
    "sg:province":"AK",
    "sg:tags":[
        "american",
        "wing",
        "pizza"
    ],
    "wof:name":"Domino's Pizza",
    "wof:placetype":"venue"
},
  "geometry": {"coordinates":[-147.70898,64.851929],"type":"Point"}
}