{
  "type": "Feature",
  "properties": {
    "addr:full":"11651 Hillside Dr Anchorage AK 99507",
    "addr:housenumber":"11651",
    "addr:postcode":"99507",
    "addr:street":"Hillside Dr",
    "iso:country":"US",
    "sg:address":"11651 Hillside Dr",
    "sg:city":"Anchorage",
    "sg:classifiers":[
        {
            "category":"Travel",
            "subcategory":"Hotels & Motels",
            "type":"Entertainment"
        }
    ],
    "sg:phone":"+1 907 336 2312",
    "sg:postcode":"99507",
    "sg:province":"AK",
    "sg:tags":[
        "breakfast",
        "accommodation",
        "bed"
    ],
    "wof:name":"Highland Glen Lodge",
    "wof:placetype":"venue"
},
  "geometry": {"coordinates":[-149.74443099999999,61.115342],"type":"Point"}
}