{
  "type": "Feature",
  "properties": {
    "addr:full":"500 E Railroad Ave Wasilla AK 99654",
    "addr:housenumber":"500",
    "addr:postcode":"99654",
    "addr:street":"E Railroad Ave",
    "iso:country":"US",
    "sg:address":"500 E Railroad Ave",
    "sg:city":"Wasilla",
    "sg:classifiers":[
        {
            "category":"Restaurant",
            "type":"Food & Drink"
        }
    ],
    "sg:phone":"+1 907 376 4919",
    "sg:postcode":"99654",
    "sg:province":"AK",
    "wof:name":"Peking Chinese Restaurant",
    "wof:placetype":"venue"
},
  "geometry": {"coordinates":[-149.43827300000001,61.580229],"type":"Point"}
}