{
  "type": "Feature",
  "properties": {
    "iso:country":"US",
    "sg:address":"1010 Deere St",
    "sg:city":"Fairbanks",
    "sg:classifiers":[
        {
            "category":"Manufacturing",
            "subcategory":"Metals",
            "type":"Manufacturing & Wholesale Goods"
        }
    ],
    "sg:phone":"+1 907 479 2174",
    "sg:postcode":"99709",
    "sg:province":"AK",
    "sg:tags":[
        "coating"
    ],
    "wof:name":"Urethane Contractor Supply",
    "wof:placetype":"venue"
},
  "geometry": {"coordinates":[-147.77877100000001,64.854095],"type":"Point"}
}