{
  "type": "Feature",
  "properties": {
    "iso:country":"US",
    "sg:address":"112 Wooded Glen Ct",
    "sg:city":"Kenai",
    "sg:classifiers":[
        {
            "category":"Real Estate",
            "subcategory":"Real Estate Agent",
            "type":"Services"
        }
    ],
    "sg:phone":"+1 907 283 9378",
    "sg:postcode":"99611",
    "sg:province":"AK",
    "wof:name":"Saylor Rehm Co",
    "wof:placetype":"venue"
},
  "geometry": {"coordinates":[-151.208845,60.558443],"type":"Point"}
}