{
  "type": "Feature",
  "properties": {
    "iso:country":"US",
    "sg:address":"201 E Tudor Rd",
    "sg:city":"Anchorage",
    "sg:classifiers":[
        {
            "category":"Shopping",
            "subcategory":"Stationery & Office Supplies",
            "type":"Retail Goods"
        }
    ],
    "sg:phone":"+1 907 562 3993",
    "sg:postcode":"99503",
    "sg:province":"AK",
    "sg:website":"www.officedepot.com",
    "wof:name":"Office Depot",
    "wof:placetype":"venue"
},
  "geometry": {"coordinates":[-149.87947199999999,61.180879],"type":"Point"}
}