{
  "type": "Feature",
  "properties": {
    "iso:country":"US",
    "sg:address":"236 Lincoln St",
    "sg:city":"Sitka",
    "sg:classifiers":[
        {
            "category":"Shopping",
            "subcategory":"Music",
            "type":"Retail Goods"
        }
    ],
    "sg:phone":"+1 907 747 7190",
    "sg:postcode":"99835",
    "sg:province":"AK",
    "sg:tags":[
        "video",
        "disc",
        "tape",
        "cassette"
    ],
    "wof:name":"Videl Video",
    "wof:placetype":"venue"
},
  "geometry": {"coordinates":[-135.33614600000001,57.050681],"type":"Point"}
}