{
  "type": "Feature",
  "properties": {
    "iso:country":"US",
    "sg:address":"1801 Mc Kinley Ave",
    "sg:city":"Anchorage",
    "sg:classifiers":[
        {
            "category":"Recreation",
            "type":"Entertainment"
        }
    ],
    "sg:phone":"+1 907 563 8240",
    "sg:postcode":"99517",
    "sg:province":"AK",
    "sg:tags":[
        "guide"
    ],
    "wof:name":"Alaska Big Game",
    "wof:placetype":"venue"
},
  "geometry": {"coordinates":[-149.91707099999999,61.184785],"type":"Point"}
}