{
  "type": "Feature",
  "properties": {
    "iso:country":"US",
    "sg:address":"8400 Raintree Cir",
    "sg:city":"Anchorage",
    "sg:classifiers":[
        {
            "category":"Personal",
            "type":"Services"
        }
    ],
    "sg:phone":"+1 907 522 7663",
    "sg:postcode":"99507",
    "sg:province":"AK",
    "sg:tags":[
        "control",
        "weight"
    ],
    "wof:name":"Herablife Distributor",
    "wof:placetype":"venue"
},
  "geometry": {"coordinates":[-149.814593,61.143367],"type":"Point"}
}