{
  "type": "Feature",
  "properties": {
    "addr:full":"3100 Channel Dr Juneau AK 99801",
    "addr:housenumber":"3100",
    "addr:postcode":"99801",
    "addr:street":"Channel Dr",
    "iso:country":"US",
    "sg:address":"3100 Channel Dr",
    "sg:city":"Juneau",
    "sg:classifiers":[
        {
            "category":"Social Services",
            "type":"Services"
        }
    ],
    "sg:phone":"+1 907 790 4357",
    "sg:postcode":"99801",
    "sg:province":"AK",
    "sg:tags":[
        "counselor",
        "marriage",
        "family"
    ],
    "wof:name":"Intergral Practice LLC",
    "wof:placetype":"venue"
},
  "geometry": {"coordinates":[-134.46911,58.327688],"type":"Point"}
}