{
  "type": "Feature",
  "properties": {
    "addr:full":"201 Barrow St Anchorage AK 99501",
    "addr:housenumber":"201",
    "addr:postcode":"99501",
    "addr:street":"Barrow St",
    "iso:country":"US",
    "sg:address":"201 Barrow St",
    "sg:city":"Anchorage",
    "sg:classifiers":[
        {
            "category":"Social Services",
            "type":"Services"
        }
    ],
    "sg:phone":"+1 907 278 5437",
    "sg:postcode":"99501",
    "sg:province":"AK",
    "sg:tags":[
        "organization",
        "welfare"
    ],
    "wof:name":"Native Village Of Eklutna's",
    "wof:placetype":"venue"
},
  "geometry": {"coordinates":[-149.88122999999999,61.219531],"type":"Point"}
}