{
  "type": "Feature",
  "properties": {
    "iso:country":"US",
    "sg:address":"232 4th Ave",
    "sg:city":"Seward",
    "sg:classifiers":[
        {
            "category":"Shopping",
            "subcategory":"Jewelry",
            "type":"Retail Goods"
        }
    ],
    "sg:phone":"+1 907 224 8800",
    "sg:postcode":"99664",
    "sg:province":"AK",
    "sg:tags":[
        "jeweler"
    ],
    "wof:name":"Juneau Gold Nugget & Diamond",
    "wof:placetype":"venue"
},
  "geometry": {"coordinates":[-149.440435,60.101593],"type":"Point"}
}