{
  "type": "Feature",
  "properties": {
    "iso:country":"US",
    "sg:address":"1840 S Bragaw St",
    "sg:city":"Anchorage",
    "sg:classifiers":[
        {
            "category":"Education",
            "subcategory":"School",
            "type":"Public Place"
        }
    ],
    "sg:phone":"+1 907 561 2229",
    "sg:postcode":"99508",
    "sg:province":"AK",
    "sg:tags":[
        "academic",
        "special"
    ],
    "sg:website":"www.educate.com",
    "wof:name":"Sylvan Learning Ctr",
    "wof:placetype":"venue"
},
  "geometry": {"coordinates":[-149.808425,61.204236],"type":"Point"}
}