{
  "type": "Feature",
  "properties": {
    "iso:country":"US",
    "sg:address":"7611 Bethany Cir",
    "sg:city":"Anchorage",
    "sg:classifiers":[
        {
            "category":"Utilities",
            "subcategory":"Refuse",
            "type":"Services"
        }
    ],
    "sg:phone":"+1 907 344 1718",
    "sg:postcode":"99507",
    "sg:province":"AK",
    "sg:tags":[
        "equipment",
        "recycling",
        "system"
    ],
    "wof:name":"Can-O-Worms",
    "wof:placetype":"venue"
},
  "geometry": {"coordinates":[-149.81422900000001,61.151508],"type":"Point"}
}