{
  "type": "Feature",
  "properties": {
    "iso:country":"US",
    "sg:address":"1001 Northway Dr",
    "sg:city":"Anchorage",
    "sg:classifiers":[
        {
            "category":"Manufacturing",
            "subcategory":"Printing",
            "type":"Manufacturing & Wholesale Goods"
        }
    ],
    "sg:phone":"+1 907 563 2800",
    "sg:postcode":"99508",
    "sg:province":"AK",
    "sg:tags":[
        "newspaper",
        "commercial"
    ],
    "wof:name":"Pennysaver Publications",
    "wof:placetype":"venue"
},
  "geometry": {"coordinates":[-149.81220200000001,61.212234],"type":"Point"}
}