{
  "type": "Feature",
  "properties": {
    "addr:full":"1901 Hilling Ave Fairbanks AK 99709",
    "addr:housenumber":"1901",
    "addr:postcode":"99709",
    "addr:street":"Hilling Ave",
    "iso:country":"US",
    "sg:address":"1901 Hilling Ave",
    "sg:city":"Fairbanks",
    "sg:classifiers":[
        {
            "category":"Professional",
            "subcategory":"Engineering",
            "type":"Services"
        }
    ],
    "sg:phone":"+1 907 456 7403",
    "sg:postcode":"99709",
    "sg:province":"AK",
    "sg:tags":[
        "engineer"
    ],
    "wof:name":"Robert H Tilly Consulting Engs",
    "wof:placetype":"venue"
},
  "geometry": {"coordinates":[-147.765289,64.861227],"type":"Point"}
}