{
  "type": "Feature",
  "properties": {
    "iso:country":"US",
    "sg:address":"2828 W Dimond Blvd",
    "sg:city":"Anchorage",
    "sg:classifiers":[
        {
            "category":"Bars & Pubs",
            "type":"Food & Drink"
        }
    ],
    "sg:phone":"+1 907 243 2163",
    "sg:postcode":"99502",
    "sg:province":"AK",
    "sg:website":"www.lord-kane.com",
    "wof:name":"Hideaway Club",
    "wof:placetype":"venue"
},
  "geometry": {"coordinates":[-149.92971,61.137409],"type":"Point"}
}