{
  "type": "Feature",
  "properties": {
    "addr:full":"2917 Jackson Rd Juneau AK 99801",
    "addr:housenumber":"2917",
    "addr:postcode":"99801",
    "addr:street":"Jackson Rd",
    "iso:country":"US",
    "sg:address":"2917 Jackson Rd",
    "sg:city":"Juneau",
    "sg:classifiers":[
        {
            "category":"Travel",
            "subcategory":"Hotels & Motels",
            "type":"Entertainment"
        }
    ],
    "sg:phone":"+1 907 586 3036",
    "sg:postcode":"99801",
    "sg:province":"AK",
    "sg:tags":[
        "breakfast",
        "accommodation",
        "bed"
    ],
    "wof:name":"Aurora View Inn On The Mtn",
    "wof:placetype":"venue"
},
  "geometry": {"coordinates":[-134.42784800000001,58.287043],"type":"Point"}
}