{
  "type": "Feature",
  "properties": {
    "iso:country":"US",
    "sg:address":"341 W Tudor Rd",
    "sg:city":"Anchorage",
    "sg:classifiers":[
        {
            "category":"Professional",
            "subcategory":"Computer Services",
            "type":"Services"
        }
    ],
    "sg:phone":"+1 907 441 8472",
    "sg:postcode":"99503",
    "sg:province":"AK",
    "wof:name":"E Docs Alaska Inc",
    "wof:placetype":"venue"
},
  "geometry": {"coordinates":[-149.888375,61.180887],"type":"Point"}
}