{
  "type": "Feature",
  "properties": {
    "addr:full":"2906 Boniface Pkwy Anchorage AK 99504",
    "addr:housenumber":"2906",
    "addr:postcode":"99504",
    "addr:street":"Boniface Pkwy",
    "iso:country":"US",
    "sg:address":"2906 Boniface Pkwy",
    "sg:city":"Anchorage",
    "sg:classifiers":[
        {
            "category":"Health Services",
            "subcategory":"Doctor",
            "type":"Services"
        }
    ],
    "sg:phone":"+1 907 333 0696",
    "sg:postcode":"99504",
    "sg:province":"AK",
    "sg:tags":[
        "dentist"
    ],
    "wof:name":"Alaska Denture Ctr",
    "wof:placetype":"venue"
},
  "geometry": {"coordinates":[-149.778446,61.194374],"type":"Point"}
}