{
  "type": "Feature",
  "properties": {
    "addr:full":"915 2nd Ave Fairbanks AK 99701",
    "addr:housenumber":"915",
    "addr:postcode":"99701",
    "addr:street":"2Nd Ave",
    "iso:country":"US",
    "sg:address":"915 2nd Ave",
    "sg:city":"Fairbanks",
    "sg:classifiers":[
        {
            "category":"Organizations",
            "subcategory":"Religious Organization",
            "type":"Services"
        }
    ],
    "sg:phone":"+1 907 452 2956",
    "sg:postcode":"99701",
    "sg:province":"AK",
    "sg:tags":[
        "church"
    ],
    "sg:website":"www.fairbanksfirst.org",
    "wof:name":"First United Methodist Church",
    "wof:placetype":"venue"
},
  "geometry": {"coordinates":[-147.72986499999999,64.844763],"type":"Point"}
}