{
  "type": "Feature",
  "properties": {
    "addr:full":"4000 W 50th Ave Anchorage AK 99502",
    "addr:housenumber":"4000",
    "addr:postcode":"99502",
    "addr:street":"W 50Th Ave",
    "iso:country":"US",
    "sg:address":"4000 W 50th Ave",
    "sg:city":"Anchorage",
    "sg:classifiers":[
        {
            "category":"Government",
            "subcategory":"Office",
            "type":"Public Place"
        }
    ],
    "sg:phone":"+1 907 271 2243",
    "sg:postcode":"99502",
    "sg:province":"AK",
    "wof:name":"US Civil Aviation Security",
    "wof:placetype":"venue"
},
  "geometry": {"coordinates":[-149.95749699999999,61.175637],"type":"Point"}
}