{
  "type": "Feature",
  "properties": {
    "iso:country":"US",
    "sg:address":"448 Eagle Ridge Rd",
    "sg:city":"Fairbanks",
    "sg:classifiers":[
        {
            "category":"Recreation",
            "type":"Entertainment"
        }
    ],
    "sg:phone":"+1 907 457 3096",
    "sg:postcode":"99712",
    "sg:province":"AK",
    "sg:tags":[
        "stable"
    ],
    "wof:name":"Eagle Ridge Stables",
    "wof:placetype":"venue"
},
  "geometry": {"coordinates":[-147.67434299999999,64.913937],"type":"Point"}
}