{
  "type": "Feature",
  "properties": {
    "addr:full":"2560 S Cushman St Fairbanks AK 99701",
    "addr:housenumber":"2560",
    "addr:postcode":"99701",
    "addr:street":"S Cushman St",
    "iso:country":"US",
    "sg:address":"2560 S Cushman St",
    "sg:city":"Fairbanks",
    "sg:classifiers":[
        {
            "category":"Retail",
            "subcategory":"Auto Repair",
            "type":"Services"
        }
    ],
    "sg:phone":"+1 907 452 4796",
    "sg:postcode":"99701",
    "sg:province":"AK",
    "sg:tags":[
        "repairing",
        "automobile",
        "radiator"
    ],
    "wof:name":"Fairbanks Radiator & Muffler",
    "wof:placetype":"venue"
},
  "geometry": {"coordinates":[-147.712547,64.82373200000001],"type":"Point"}
}