{
  "type": "Feature",
  "properties": {
    "iso:country":"US",
    "sg:address":"12531 Turks Turn St",
    "sg:city":"Anchorage",
    "sg:classifiers":[
        {
            "category":"Travel",
            "subcategory":"Hotels & Motels",
            "type":"Entertainment"
        }
    ],
    "sg:phone":"+1 907 345 4279",
    "sg:postcode":"99516",
    "sg:province":"AK",
    "sg:tags":[
        "breakfast",
        "accommodation",
        "bed"
    ],
    "wof:name":"All The Comforts Of Home",
    "wof:placetype":"venue"
},
  "geometry": {"coordinates":[-149.736976,61.106389],"type":"Point"}
}