{
  "type": "Feature",
  "properties": {
    "addr:full":"3551 Postmark Dr Anchorage AK 99502",
    "addr:housenumber":"3551",
    "addr:postcode":"99502",
    "addr:street":"Postmark Dr",
    "iso:country":"US",
    "sg:address":"3551 Postmark Dr",
    "sg:city":"Anchorage",
    "sg:classifiers":[
        {
            "category":"Building & Trades",
            "subcategory":"Construction",
            "type":"Services"
        }
    ],
    "sg:phone":"+1 907 884 1478",
    "sg:postcode":"99502",
    "sg:province":"AK",
    "sg:tags":[
        "marking",
        "maintenance",
        "parking"
    ],
    "wof:name":"AAA Asphalt Maintenance",
    "wof:placetype":"venue"
},
  "geometry": {"coordinates":[-149.990273,61.190288],"type":"Point"}
}