{
  "type": "Feature",
  "properties": {
    "addr:full":"600 Daron Dr Palmer AK 99645",
    "addr:housenumber":"600",
    "addr:postcode":"99645",
    "addr:street":"Daron Dr",
    "iso:country":"US",
    "sg:address":"600 Daron Dr",
    "sg:city":"Palmer",
    "sg:classifiers":[
        {
            "category":"Restaurant",
            "type":"Food & Drink"
        }
    ],
    "sg:menulink":"http://www.allmenus.com/ak/matanuska-susitna/190088-mcdonalds/menu/",
    "sg:postcode":"99645",
    "sg:province":"AK",
    "sg:tags":[
        "burger",
        "american"
    ],
    "wof:name":"McDonald's",
    "wof:placetype":"venue"
},
  "geometry": {"coordinates":[-149.12841299999999,61.597208],"type":"Point"}
}