{
  "type": "Feature",
  "properties": {
    "iso:country":"US",
    "sg:address":"5 Clark-Wolverine Rd",
    "sg:city":"Palmer",
    "sg:classifiers":[
        {
            "category":"Farming",
            "subcategory":"Nursery",
            "type":"Manufacturing & Wholesale Goods"
        }
    ],
    "sg:phone":"+1 907 745 1070",
    "sg:postcode":"99645",
    "sg:province":"AK",
    "sg:tags":[
        "ornamental"
    ],
    "wof:name":"Northern Frits Grnhuses U-Pick",
    "wof:placetype":"venue"
},
  "geometry": {"coordinates":[-149.047986,61.613865],"type":"Point"}
}