{
  "type": "Feature",
  "properties": {
    "iso:country":"US",
    "sg:address":"1216 Madsen Ave",
    "sg:city":"Kodiak",
    "sg:classifiers":[
        {
            "category":"Real Estate",
            "subcategory":"Real Estate Agent",
            "type":"Services"
        }
    ],
    "sg:phone":"+1 907 486 3305",
    "sg:postcode":"99615",
    "sg:province":"AK",
    "wof:name":"For Sale By Owner",
    "wof:placetype":"venue"
},
  "geometry": {"coordinates":[-152.39393100000001,57.798436],"type":"Point"}
}