{
  "type": "Feature",
  "properties": {
    "iso:country":"US",
    "sg:address":"1107 W 7th Ave",
    "sg:city":"Anchorage",
    "sg:classifiers":[
        {
            "category":"Professional",
            "subcategory":"Lawyer & Legal Services",
            "type":"Services"
        }
    ],
    "sg:phone":"+1 907 278 4584",
    "sg:postcode":"99501",
    "sg:province":"AK",
    "sg:tags":[
        "attorney"
    ],
    "wof:name":"Tom F Janidlo Law Offices",
    "wof:placetype":"venue"
},
  "geometry": {"coordinates":[-149.905739,61.215687],"type":"Point"}
}