{
  "type": "Feature",
  "properties": {
    "iso:country":"US",
    "sg:address":"1569 Garden St",
    "sg:city":"Anchorage",
    "sg:classifiers":[
        {
            "category":"Building & Trades",
            "subcategory":"Construction",
            "type":"Services"
        }
    ],
    "sg:phone":"+1 907 646 4002",
    "sg:postcode":"99508",
    "sg:province":"AK",
    "sg:tags":[
        "concrete",
        "restoration",
        "cleaning",
        "repair"
    ],
    "wof:name":"Uretek Alaska Inc",
    "wof:placetype":"venue"
},
  "geometry": {"coordinates":[-149.825093,61.207357],"type":"Point"}
}