{
  "type": "Feature",
  "properties": {
    "iso:country":"US",
    "sg:address":"1023 Ermine St",
    "sg:city":"Anchorage",
    "sg:classifiers":[
        {
            "category":"Organizations",
            "subcategory":"Religious Organization",
            "type":"Services"
        }
    ],
    "sg:phone":"+1 907 333 1943",
    "sg:postcode":"99504",
    "sg:province":"AK",
    "sg:tags":[
        "church"
    ],
    "wof:name":"North Anchorage Church Of God",
    "wof:placetype":"venue"
},
  "geometry": {"coordinates":[-149.75040000000001,61.212037],"type":"Point"}
}