{
  "type": "Feature",
  "properties": {
    "iso:country":"US",
    "sg:address":"245 W 5th Ave",
    "sg:city":"Anchorage",
    "sg:classifiers":[
        {
            "category":"Travel",
            "subcategory":"Travel Agent",
            "type":"Entertainment"
        }
    ],
    "sg:phone":"+1 907 277 3580",
    "sg:postcode":"99501",
    "sg:province":"AK",
    "sg:tags":[
        "tours",
        "promoter"
    ],
    "wof:name":"Alaska's Finest Tours & Cruise",
    "wof:placetype":"venue"
},
  "geometry": {"coordinates":[-149.886692,61.217641],"type":"Point"}
}