{
  "type": "Feature",
  "properties": {
    "addr:full":"10224 W Frontage Rd Eagle River AK 99577",
    "addr:housenumber":"10224",
    "addr:postcode":"99577",
    "addr:street":"W Frontage Rd",
    "iso:country":"US",
    "sg:address":"10224 W Frontage Rd",
    "sg:city":"Eagle River",
    "sg:classifiers":[
        {
            "category":"Building & Trades",
            "subcategory":"Construction",
            "type":"Services"
        }
    ],
    "sg:phone":"+1 907 694 4047",
    "sg:postcode":"99577",
    "sg:province":"AK",
    "sg:tags":[
        "contractor"
    ],
    "wof:name":"Lindall Cedar Homes",
    "wof:placetype":"venue"
},
  "geometry": {"coordinates":[-149.577744,61.312505],"type":"Point"}
}