{
  "type": "Feature",
  "properties": {
    "addr:full":"4519 Enstrom Cir Anchorage AK 99502",
    "addr:housenumber":"4519",
    "addr:postcode":"99502",
    "addr:street":"Enstrom Cir",
    "iso:country":"US",
    "sg:address":"4519 Enstrom Cir",
    "sg:city":"Anchorage",
    "sg:classifiers":[
        {
            "category":"Recreation",
            "type":"Entertainment"
        }
    ],
    "sg:phone":"+1 907 248 5983",
    "sg:postcode":"99502",
    "sg:province":"AK",
    "sg:tags":[
        "guide"
    ],
    "wof:name":"R & R Guide Svc",
    "wof:placetype":"venue"
},
  "geometry": {"coordinates":[-149.970867,61.179518],"type":"Point"}
}