{
  "type": "Feature",
  "properties": {
    "iso:country":"US",
    "sg:address":"8630 Witherspoon Cir",
    "sg:city":"Anchorage",
    "sg:classifiers":[
        {
            "category":"Building & Trades",
            "subcategory":"Construction",
            "type":"Services"
        }
    ],
    "sg:phone":"+1 907 338 3098",
    "sg:postcode":"99504",
    "sg:province":"AK",
    "sg:tags":[
        "house"
    ],
    "wof:name":"Just ME",
    "wof:placetype":"venue"
},
  "geometry": {"coordinates":[-149.71951,61.185806],"type":"Point"}
}