{
  "type": "Feature",
  "properties": {
    "iso:country":"US",
    "sg:address":"2259 S Tongass Hwy",
    "sg:city":"Ketchikan",
    "sg:classifiers":[
        {
            "category":"Travel",
            "subcategory":"Hotels & Motels",
            "type":"Entertainment"
        }
    ],
    "sg:phone":"+1 907 225 3449",
    "sg:postcode":"99901",
    "sg:province":"AK",
    "sg:tags":[
        "breakfast",
        "accommodation",
        "bed"
    ],
    "wof:name":"Oyster Avenue Bed & Breakfast",
    "wof:placetype":"venue"
},
  "geometry": {"coordinates":[-131.607178,55.323285],"type":"Point"}
}