{
  "type": "Feature",
  "properties": {
    "iso:country":"US",
    "sg:address":"1485 30th Ave",
    "sg:city":"Fairbanks",
    "sg:classifiers":[
        {
            "category":"Social Services",
            "type":"Services"
        }
    ],
    "sg:phone":"+1 907 456 7029",
    "sg:postcode":"99701",
    "sg:province":"AK",
    "sg:tags":[
        "youth",
        "organization",
        "center"
    ],
    "wof:name":"Young Life",
    "wof:placetype":"venue"
},
  "geometry": {"coordinates":[-147.73817099999999,64.820025],"type":"Point"}
}