{
  "type": "Feature",
  "properties": {
    "iso:country":"US",
    "sg:address":"733 W 4th Ave",
    "sg:city":"Anchorage",
    "sg:classifiers":[
        {
            "category":"Professional",
            "subcategory":"Lawyer & Legal Services",
            "type":"Services"
        }
    ],
    "sg:phone":"+1 907 277 7677",
    "sg:postcode":"99501",
    "sg:province":"AK",
    "sg:tags":[
        "attorney"
    ],
    "wof:name":"Patrick G Ross",
    "wof:placetype":"venue"
},
  "geometry": {"coordinates":[-149.89703900000001,61.218629],"type":"Point"}
}