{
  "type": "Feature",
  "properties": {
    "iso:country":"US",
    "sg:address":"211 4th Ave",
    "sg:city":"Bethel",
    "sg:classifiers":[
        {
            "category":"Building & Trades",
            "subcategory":"Plumbing",
            "type":"Services"
        }
    ],
    "sg:phone":"+1 907 543 3443",
    "sg:postcode":"99559",
    "sg:province":"AK",
    "sg:tags":[
        "plumbing",
        "contractor"
    ],
    "wof:name":"Fix It Plumbing & Rentals",
    "wof:placetype":"venue"
},
  "geometry": {"coordinates":[-161.7625,60.796036],"type":"Point"}
}