{
  "type": "Feature",
  "properties": {
    "iso:country":"US",
    "sg:address":"3300 Arctic Blvd",
    "sg:city":"Anchorage",
    "sg:classifiers":[
        {
            "category":"Professional",
            "subcategory":"Art Services",
            "type":"Services"
        }
    ],
    "sg:phone":"+1 907 562 8229",
    "sg:postcode":"99503",
    "sg:province":"AK",
    "sg:tags":[
        "graphic",
        "designer"
    ],
    "wof:name":"Slama Design",
    "wof:placetype":"venue"
},
  "geometry": {"coordinates":[-149.898031,61.191053],"type":"Point"}
}