{
  "type": "Feature",
  "properties": {
    "iso:country":"US",
    "sg:address":"343 W Benson Blvd",
    "sg:city":"Anchorage",
    "sg:classifiers":[
        {
            "category":"Health Services",
            "subcategory":"Chiropractor",
            "type":"Services"
        }
    ],
    "sg:phone":"+1 907 562 6181",
    "sg:postcode":"99503",
    "sg:province":"AK",
    "wof:name":"Anchor Chiropractic Healing",
    "wof:placetype":"venue"
},
  "geometry": {"coordinates":[-149.888984,61.194261],"type":"Point"}
}