{
  "type": "Feature",
  "properties": {
    "addr:full":"9000 Lake Otis Pkwy Anchorage AK 99507",
    "addr:housenumber":"9000",
    "addr:postcode":"99507",
    "addr:street":"Lake Otis Pkwy",
    "iso:country":"US",
    "sg:address":"9000 Lake Otis Pkwy",
    "sg:city":"Anchorage",
    "sg:classifiers":[
        {
            "category":"Restaurant",
            "type":"Food & Drink"
        }
    ],
    "sg:menulink":"http://www.allmenus.com/ak/anchorage/109665-subway/menu/",
    "sg:phone":"+1 907 349 7827",
    "sg:postcode":"99507",
    "sg:province":"AK",
    "sg:tags":[
        "american",
        "sandwich"
    ],
    "wof:name":"Subway",
    "wof:placetype":"venue"
},
  "geometry": {"coordinates":[-149.83441500000001,61.139216],"type":"Point"}
}