{
  "type": "Feature",
  "properties": {
    "addr:full":"420 M St Anchorage AK 99501",
    "addr:housenumber":"420",
    "addr:postcode":"99501",
    "addr:street":"M St",
    "iso:country":"US",
    "sg:address":"420 M St",
    "sg:city":"Anchorage",
    "sg:classifiers":[
        {
            "category":"Museum",
            "type":"Entertainment"
        }
    ],
    "sg:phone":"+1 907 274 2336",
    "sg:postcode":"99501",
    "sg:province":"AK",
    "wof:name":"Oscar Anderson House Museum",
    "wof:placetype":"venue"
},
  "geometry": {"coordinates":[-149.90583000000001,61.218127],"type":"Point"}
}