{
  "type": "Feature",
  "properties": {
    "iso:country":"US",
    "sg:address":"222 Front St",
    "sg:city":"Fairbanks",
    "sg:classifiers":[
        {
            "category":"Health Services",
            "subcategory":"Health Practitioner",
            "type":"Services"
        }
    ],
    "sg:phone":"+1 907 451 7100",
    "sg:postcode":"99701",
    "sg:province":"AK",
    "sg:tags":[
        "physician"
    ],
    "sg:website":"www.holisticmedicalclinic.us",
    "wof:name":"Holistic Medical Clinic",
    "wof:placetype":"venue"
},
  "geometry": {"coordinates":[-147.707036,64.846536],"type":"Point"}
}