{
  "type": "Feature",
  "properties": {
    "iso:country":"US",
    "sg:address":"258 4th Ave",
    "sg:city":"Kotzebue",
    "sg:classifiers":[
        {
            "category":"Government",
            "subcategory":"Jail",
            "type":"Public Place"
        }
    ],
    "sg:phone":"+1 907 442 3353",
    "sg:postcode":"99752",
    "sg:province":"AK",
    "sg:tags":[
        "govt",
        "city",
        "institution"
    ],
    "wof:name":"Kotzebue City Jail",
    "wof:placetype":"venue"
},
  "geometry": {"coordinates":[-162.596891,66.894195],"type":"Point"}
}