{
  "type": "Feature",
  "properties": {
    "iso:country":"US",
    "sg:address":"16946 Eagle River Rd",
    "sg:city":"Eagle River",
    "sg:classifiers":[
        {
            "category":"Shopping",
            "type":"Retail Goods"
        }
    ],
    "sg:phone":"+1 907 694 2980",
    "sg:postcode":"99577",
    "sg:province":"AK",
    "sg:tags":[
        "pet",
        "food",
        "supply"
    ],
    "wof:name":"Valley Seed & Feed",
    "wof:placetype":"venue"
},
  "geometry": {"coordinates":[-149.56669099999999,61.311011],"type":"Point"}
}