{
  "type": "Feature",
  "properties": {
    "iso:country":"US",
    "sg:address":"118 Lincoln St",
    "sg:city":"Sitka",
    "sg:classifiers":[
        {
            "category":"Travel",
            "subcategory":"Hotels & Motels",
            "type":"Entertainment"
        }
    ],
    "sg:phone":"+1 907 747 3288",
    "sg:postcode":"99835",
    "sg:province":"AK",
    "wof:name":"Sitka Hotel",
    "wof:placetype":"venue"
},
  "geometry": {"coordinates":[-135.33927299999999,57.049282],"type":"Point"}
}