{
  "type": "Feature",
  "properties": {
    "addr:full":"8505 Old Dairy Rd Juneau AK 99801",
    "addr:housenumber":"8505",
    "addr:postcode":"99801",
    "addr:street":"Old Dairy Rd",
    "iso:country":"US",
    "sg:address":"8505 Old Dairy Rd",
    "sg:city":"Juneau",
    "sg:classifiers":[
        {
            "category":"Health Services",
            "subcategory":"Doctor",
            "type":"Services"
        }
    ],
    "sg:phone":"+1 907 790 4111",
    "sg:postcode":"99801",
    "sg:province":"AK",
    "sg:tags":[
        "physician",
        "surgeon"
    ],
    "wof:name":"Juneau Urgent Care & Family",
    "wof:placetype":"venue"
},
  "geometry": {"coordinates":[-134.57313300000001,58.362628],"type":"Point"}
}