{
  "type": "Feature",
  "properties": {
    "iso:country":"US",
    "sg:address":"1200 S Century Cir",
    "sg:city":"Wasilla",
    "sg:classifiers":[
        {
            "category":"Real Estate",
            "subcategory":"Real Estate Operator",
            "type":"Services"
        }
    ],
    "sg:phone":"+1 907 373 0590",
    "sg:postcode":"99654",
    "sg:province":"AK",
    "sg:tags":[
        "apartment"
    ],
    "wof:name":"Chinook Apartments",
    "wof:placetype":"venue"
},
  "geometry": {"coordinates":[-149.44935100000001,61.569841],"type":"Point"}
}