{
  "type": "Feature",
  "properties": {
    "iso:country":"US",
    "sg:address":"12300 Old Glenn Hwy",
    "sg:city":"Eagle River",
    "sg:classifiers":[
        {
            "category":"Bars & Pubs",
            "type":"Food & Drink"
        }
    ],
    "sg:phone":"+1 907 696 2489",
    "sg:postcode":"99577",
    "sg:province":"AK",
    "wof:name":"River City",
    "wof:placetype":"venue"
},
  "geometry": {"coordinates":[-149.566158,61.33144],"type":"Point"}
}