{
  "type": "Feature",
  "properties": {
    "iso:country":"US",
    "sg:address":"5820 E Tudor Rd",
    "sg:city":"Anchorage",
    "sg:classifiers":[
        {
            "category":"Government",
            "subcategory":"Office",
            "type":"Public Place"
        }
    ],
    "sg:phone":"+1 907 333 2411",
    "sg:postcode":"99507",
    "sg:province":"AK",
    "wof:name":"DOT-Pf M & O",
    "wof:placetype":"venue"
},
  "geometry": {"coordinates":[-149.77127899999999,61.18068],"type":"Point"}
}