{
  "type": "Feature",
  "properties": {
    "addr:full":"5437 E Northern Lights Blvd Anchorage AK 99508",
    "addr:housenumber":"5437",
    "addr:postcode":"99508",
    "addr:street":"E Northern Lights Blvd",
    "iso:country":"US",
    "sg:address":"5437 E Northern Lights Blvd",
    "sg:city":"Anchorage",
    "sg:classifiers":[
        {
            "category":"Restaurant",
            "type":"Food & Drink"
        }
    ],
    "sg:phone":"+1 907 338 5034",
    "sg:postcode":"99508",
    "sg:province":"AK",
    "sg:tags":[
        "shop",
        "coffee"
    ],
    "wof:name":"Espresso Expressions",
    "wof:placetype":"venue"
},
  "geometry": {"coordinates":[-149.77903900000001,61.195322],"type":"Point"}
}