{
  "type": "Feature",
  "properties": {
    "iso:country":"US",
    "sg:address":"11985 Glacier Hwy",
    "sg:city":"Juneau",
    "sg:classifiers":[
        {
            "category":"Travel",
            "subcategory":"Hotels & Motels",
            "type":"Entertainment"
        }
    ],
    "sg:phone":"+1 907 789 7473",
    "sg:postcode":"99801",
    "sg:province":"AK",
    "sg:tags":[
        "breakfast",
        "accommodation",
        "bed"
    ],
    "wof:name":"Alexis Suites & Ocean Spa",
    "wof:placetype":"venue"
},
  "geometry": {"coordinates":[-134.649797,58.387446],"type":"Point"}
}