{
  "type": "Feature",
  "properties": {
    "iso:country":"US",
    "sg:address":"212 Carlanna Lake Rd",
    "sg:city":"Ketchikan",
    "sg:classifiers":[
        {
            "category":"Health Services",
            "subcategory":"Doctor",
            "type":"Services"
        }
    ],
    "sg:phone":"+1 907 225 4104",
    "sg:postcode":"99901",
    "sg:province":"AK",
    "sg:tags":[
        "physician",
        "surgeon"
    ],
    "wof:name":"Wilson Medical Clinic",
    "wof:placetype":"venue"
},
  "geometry": {"coordinates":[-131.688838,55.354215],"type":"Point"}
}