{
  "type": "Feature",
  "properties": {
    "iso:country":"US",
    "sg:address":"1003 Aspen St",
    "sg:city":"Fairbanks",
    "sg:classifiers":[
        {
            "category":"Freight",
            "type":"Transportation"
        }
    ],
    "sg:phone":"+1 907 456 2496",
    "sg:postcode":"99709",
    "sg:province":"AK",
    "sg:tags":[
        "trucking"
    ],
    "wof:name":"Airland Transport",
    "wof:placetype":"venue"
},
  "geometry": {"coordinates":[-147.773008,64.855295],"type":"Point"}
}