{
  "type": "Feature",
  "properties": {
    "iso:country":"US",
    "sg:address":"940 S Chugach St",
    "sg:city":"Palmer",
    "sg:classifiers":[
        {
            "category":"Building & Trades",
            "subcategory":"Plumbing",
            "type":"Services"
        }
    ],
    "sg:phone":"+1 907 745 3780",
    "sg:postcode":"99645",
    "sg:province":"AK",
    "sg:tags":[
        "plumbing",
        "contractor"
    ],
    "wof:name":"Mac's Plumbing & Heating Inc",
    "wof:placetype":"venue"
},
  "geometry": {"coordinates":[-149.110728,61.595318],"type":"Point"}
}