{
  "type": "Feature",
  "properties": {
    "iso:country":"US",
    "sg:address":"1104 E 5th Ave",
    "sg:city":"Anchorage",
    "sg:classifiers":[
        {
            "category":"Travel",
            "subcategory":"Hotels & Motels",
            "type":"Entertainment"
        }
    ],
    "sg:phone":"+1 907 274 1655",
    "sg:postcode":"99501",
    "sg:province":"AK",
    "wof:name":"Rodeway Inn",
    "wof:placetype":"venue"
},
  "geometry": {"coordinates":[-149.858801,61.217483],"type":"Point"}
}