{
  "type": "Feature",
  "properties": {
    "iso:country":"US",
    "sg:address":"3601 C St",
    "sg:city":"Anchorage",
    "sg:classifiers":[
        {
            "category":"Government",
            "subcategory":"Office",
            "type":"Public Place"
        }
    ],
    "sg:phone":"+1 907 269 3790",
    "sg:postcode":"99503",
    "sg:province":"AK",
    "sg:tags":[
        "state",
        "resource"
    ],
    "wof:name":"Health & Social Svc Dept",
    "wof:placetype":"venue"
},
  "geometry": {"coordinates":[-149.886592,61.187549],"type":"Point"}
}