{
  "type": "Feature",
  "properties": {
    "iso:country":"US",
    "sg:address":"10361 Nigh Rd",
    "sg:city":"Anchorage",
    "sg:classifiers":[
        {
            "category":"Wholesale",
            "subcategory":"Non-durable Goods",
            "type":"Manufacturing & Wholesale Goods"
        }
    ],
    "sg:phone":"+1 907 349 4409",
    "sg:postcode":"99515",
    "sg:province":"AK",
    "wof:name":"Triangle Marketing",
    "wof:placetype":"venue"
},
  "geometry": {"coordinates":[-149.868112,61.128461],"type":"Point"}
}