{
  "type": "Feature",
  "properties": {
    "iso:country":"US",
    "sg:address":"1382 6th Ave",
    "sg:city":"Fairbanks",
    "sg:classifiers":[
        {
            "category":"Travel",
            "subcategory":"Hotels & Motels",
            "type":"Entertainment"
        }
    ],
    "sg:phone":"+1 907 451 9931",
    "sg:postcode":"99701",
    "sg:province":"AK",
    "sg:tags":[
        "breakfast",
        "accommodation",
        "bed"
    ],
    "wof:name":"Arctic Slumber B & B",
    "wof:placetype":"venue"
},
  "geometry": {"coordinates":[-147.74087299999999,64.844179],"type":"Point"}
}