{
  "type": "Feature",
  "properties": {
    "addr:full":"315 Seward St Sitka AK 99835",
    "addr:housenumber":"315",
    "addr:postcode":"99835",
    "addr:street":"Seward St",
    "iso:country":"US",
    "sg:address":"315 Seward St",
    "sg:city":"Sitka",
    "sg:classifiers":[
        {
            "category":"Building & Trades",
            "subcategory":"Construction",
            "type":"Services"
        }
    ],
    "sg:phone":"+1 907 747 6274",
    "sg:postcode":"99835",
    "sg:province":"AK",
    "sg:tags":[
        "general",
        "contractor"
    ],
    "wof:name":"Tisher Construction",
    "wof:placetype":"venue"
},
  "geometry": {"coordinates":[-135.33570900000001,57.050974],"type":"Point"}
}