{
  "type": "Feature",
  "properties": {
    "addr:full":"2225 Jordan Ave Juneau AK 99801",
    "addr:housenumber":"2225",
    "addr:postcode":"99801",
    "addr:street":"Jordan Ave",
    "iso:country":"US",
    "sg:address":"2225 Jordan Ave",
    "sg:city":"Juneau",
    "sg:classifiers":[
        {
            "category":"Organizations",
            "subcategory":"Professional Association",
            "type":"Services"
        }
    ],
    "sg:phone":"+1 907 789 4980",
    "sg:postcode":"99801",
    "sg:province":"AK",
    "wof:name":"Bartlett Hospital Foundation",
    "wof:placetype":"venue"
},
  "geometry": {"coordinates":[-134.57907,58.364821],"type":"Point"}
}