{
  "type": "Feature",
  "properties": {
    "iso:country":"US",
    "sg:address":"1016 Water St",
    "sg:city":"Ketchikan",
    "sg:classifiers":[
        {
            "category":"Social Services",
            "subcategory":"Adult Care",
            "type":"Services"
        }
    ],
    "sg:phone":"+1 907 225 9777",
    "sg:postcode":"99901",
    "sg:province":"AK",
    "sg:tags":[
        "organization",
        "senior",
        "citizen"
    ],
    "wof:name":"Ketchikan Senior Care",
    "wof:placetype":"venue"
},
  "geometry": {"coordinates":[-131.65505899999999,55.344974],"type":"Point"}
}