{
  "type": "Feature",
  "properties": {
    "iso:country":"US",
    "sg:address":"40494 Waterman Rd",
    "sg:city":"Homer",
    "sg:classifiers":[
        {
            "category":"Building & Trades",
            "subcategory":"Cleaning & Sanitation",
            "type":"Services"
        }
    ],
    "sg:phone":"+1 907 235 4174",
    "sg:postcode":"99603",
    "sg:province":"AK",
    "sg:tags":[
        "window"
    ],
    "wof:name":"Clear View Window Washing",
    "wof:placetype":"venue"
},
  "geometry": {"coordinates":[-151.406829,59.690188],"type":"Point"}
}