{
  "type": "Feature",
  "properties": {
    "iso:country":"US",
    "sg:address":"3380 C St",
    "sg:city":"Anchorage",
    "sg:classifiers":[
        {
            "category":"Banks & Credit Unions",
            "subcategory":"Investment Brokerage",
            "type":"Services"
        }
    ],
    "sg:phone":"+1 907 561 3275",
    "sg:postcode":"99503",
    "sg:province":"AK",
    "sg:tags":[
        "stock",
        "bond"
    ],
    "sg:website":"www.edwardjones.com",
    "wof:name":"Edward Jones Co",
    "wof:placetype":"venue"
},
  "geometry": {"coordinates":[-149.88668200000001,61.190505],"type":"Point"}
}