{
  "type": "Feature",
  "properties": {
    "addr:full":"13331 Old Glenn Hwy Eagle River AK 99577",
    "addr:housenumber":"13331",
    "addr:postcode":"99577",
    "addr:street":"Old Glenn Hwy",
    "iso:country":"US",
    "sg:address":"13331 Old Glenn Hwy",
    "sg:city":"Eagle River",
    "sg:classifiers":[
        {
            "category":"Restaurant",
            "type":"Food & Drink"
        }
    ],
    "sg:menulink":"http://www.allmenus.com/ak/anchorage/78130-papa-murphys/menu/",
    "sg:phone":"+1 907 694 7272",
    "sg:postcode":"99577",
    "sg:province":"AK",
    "sg:tags":[
        "american",
        "pizza"
    ],
    "wof:name":"Papa Murphy's",
    "wof:placetype":"venue"
},
  "geometry": {"coordinates":[-149.55823799999999,61.342135],"type":"Point"}
}