{
  "type": "Feature",
  "properties": {
    "iso:country":"US",
    "sg:address":"720 Bennett Rd",
    "sg:city":"Fairbanks",
    "sg:classifiers":[
        {
            "category":"Recreation",
            "type":"Entertainment"
        }
    ],
    "sg:phone":"+1 907 457 7902",
    "sg:postcode":"99712",
    "sg:province":"AK",
    "sg:tags":[
        "animal",
        "stable"
    ],
    "wof:name":"Wynfromere Farms Inc",
    "wof:placetype":"venue"
},
  "geometry": {"coordinates":[-147.565822,64.896314],"type":"Point"}
}