{
  "type": "Feature",
  "properties": {
    "iso:country":"US",
    "sg:address":"1415 Bannister Dr",
    "sg:city":"Anchorage",
    "sg:classifiers":[
        {
            "category":"Professional",
            "subcategory":"Business Services",
            "type":"Services"
        }
    ],
    "sg:phone":"+1 907 276 2087",
    "sg:postcode":"99508",
    "sg:province":"AK",
    "sg:tags":[
        "convention",
        "meeting",
        "facility"
    ],
    "wof:name":"Event Specialists Inc",
    "wof:placetype":"venue"
},
  "geometry": {"coordinates":[-149.854559,61.199524],"type":"Point"}
}