{
  "type": "Feature",
  "properties": {
    "addr:full":"619 E 5th Ave Anchorage AK 99501",
    "addr:housenumber":"619",
    "addr:postcode":"99501",
    "addr:street":"E 5Th Ave",
    "iso:country":"US",
    "sg:address":"619 E 5th Ave",
    "sg:city":"Anchorage",
    "sg:classifiers":[
        {
            "category":"Manufacturing",
            "subcategory":"Tools & Machinery",
            "type":"Manufacturing & Wholesale Goods"
        }
    ],
    "sg:phone":"+1 907 274 4995",
    "sg:postcode":"99501",
    "sg:province":"AK",
    "sg:tags":[
        "machine",
        "copying",
        "supply"
    ],
    "sg:website":"www.ops-copiers.com",
    "wof:name":"Alaska Econo Copy",
    "wof:placetype":"venue"
},
  "geometry": {"coordinates":[-149.87119300000001,61.217638],"type":"Point"}
}