{
  "type": "Feature",
  "properties": {
    "iso:country":"US",
    "sg:address":"11600 Wagner St",
    "sg:city":"Anchorage",
    "sg:classifiers":[
        {
            "category":"Farming",
            "subcategory":"Livestock Farm",
            "type":"Manufacturing & Wholesale Goods"
        }
    ],
    "sg:phone":"+1 907 345 3043",
    "sg:postcode":"99516",
    "sg:province":"AK",
    "sg:tags":[
        "animal",
        "general"
    ],
    "sg:website":"www.alaskabedandbreakfast.net",
    "wof:name":"Summit Ridge Ranch",
    "wof:placetype":"venue"
},
  "geometry": {"coordinates":[-149.82282000000001,61.112242],"type":"Point"}
}