{
  "type": "Feature",
  "properties": {
    "addr:full":"920 W Dimond Blvd Anchorage AK 99515",
    "addr:housenumber":"920",
    "addr:postcode":"99515",
    "addr:street":"W Dimond Blvd",
    "iso:country":"US",
    "sg:address":"920 W Dimond Blvd",
    "sg:city":"Anchorage",
    "sg:classifiers":[
        {
            "category":"Social Services",
            "type":"Services"
        }
    ],
    "sg:phone":"+1 907 349 0077",
    "sg:postcode":"99515",
    "sg:province":"AK",
    "sg:tags":[
        "counseling"
    ],
    "wof:name":"Alaska Pacific Rim Counseling",
    "wof:placetype":"venue"
},
  "geometry": {"coordinates":[-149.90476699999999,61.141165],"type":"Point"}
}