{
  "type": "Feature",
  "properties": {
    "iso:country":"US",
    "sg:address":"43420 Kalifornsky Beach Rd",
    "sg:city":"Soldotna",
    "sg:classifiers":[
        {
            "category":"Manufacturing",
            "subcategory":"Signs",
            "type":"Manufacturing & Wholesale Goods"
        },
        {
            "category":"Professional",
            "subcategory":"Business Services",
            "type":"Services"
        }
    ],
    "sg:phone":"+1 907 262 4294",
    "sg:postcode":"99669",
    "sg:province":"AK",
    "sg:tags":[
        "shop",
        "lettering",
        "painting"
    ],
    "wof:name":"G F Sherman Signs",
    "wof:placetype":"venue"
},
  "geometry": {"coordinates":[-151.1584,60.493163],"type":"Point"}
}