{
  "type": "Feature",
  "properties": {
    "addr:full":"5700 Old Seward Hwy Anchorage AK 99518",
    "addr:housenumber":"5700",
    "addr:postcode":"99518",
    "addr:street":"Old Seward Hwy",
    "iso:country":"US",
    "sg:address":"5700 Old Seward Hwy",
    "sg:city":"Anchorage",
    "sg:classifiers":[
        {
            "category":"Professional",
            "subcategory":"Management & Consulting",
            "type":"Services"
        }
    ],
    "sg:phone":"+1 907 562 0462",
    "sg:postcode":"99518",
    "sg:province":"AK",
    "sg:tags":[
        "consultant",
        "business"
    ],
    "wof:name":"IMA",
    "wof:placetype":"venue"
},
  "geometry": {"coordinates":[-149.86805100000001,61.168648],"type":"Point"}
}