{
  "type": "Feature",
  "properties": {
    "addr:full":"1113 W 12th Ave Anchorage AK 99501",
    "addr:housenumber":"1113",
    "addr:postcode":"99501",
    "addr:street":"W 12Th Ave",
    "iso:country":"US",
    "sg:address":"1113 W 12th Ave",
    "sg:city":"Anchorage",
    "sg:classifiers":[
        {
            "category":"Communications",
            "subcategory":"Film & Video Production",
            "type":"Services"
        }
    ],
    "sg:phone":"+1 907 277 2583",
    "sg:postcode":"99501",
    "sg:province":"AK",
    "sg:tags":[
        "taping"
    ],
    "sg:website":"www.blueberryproductions.com",
    "wof:name":"Blueberry Productions Inc",
    "wof:placetype":"venue"
},
  "geometry": {"coordinates":[-149.90427299999999,61.210748],"type":"Point"}
}