{
  "type": "Feature",
  "properties": {
    "iso:country":"US",
    "sg:address":"609 Etolin St",
    "sg:city":"Sitka",
    "sg:classifiers":[
        {
            "category":"Manufacturing",
            "subcategory":"Tools & Machinery",
            "type":"Manufacturing & Wholesale Goods"
        }
    ],
    "sg:phone":"+1 907 747 8520",
    "sg:postcode":"99835",
    "sg:province":"AK",
    "sg:tags":[
        "marine",
        "refrigeration",
        "air"
    ],
    "wof:name":"PHR Plowing & Sanding",
    "wof:placetype":"venue"
},
  "geometry": {"coordinates":[-135.33022099999999,57.05226],"type":"Point"}
}