{
  "type": "Feature",
  "properties": {
    "iso:country":"US",
    "sg:address":"340 Fairway Cir",
    "sg:city":"Soldotna",
    "sg:classifiers":[
        {
            "category":"Shopping",
            "subcategory":"Bicycles & Sporting Goods",
            "type":"Retail Goods"
        }
    ],
    "sg:phone":"+1 907 262 7492",
    "sg:postcode":"99669",
    "sg:province":"AK",
    "sg:tags":[
        "equipment",
        "golf",
        "supply"
    ],
    "wof:name":"Golf Shop",
    "wof:placetype":"venue"
},
  "geometry": {"coordinates":[-151.00864799999999,60.497438],"type":"Point"}
}