{
  "type": "Feature",
  "properties": {
    "addr:full":"4627 Old Seward Hwy Anchorage AK 99503",
    "addr:housenumber":"4627",
    "addr:postcode":"99503",
    "addr:street":"Old Seward Hwy",
    "iso:country":"US",
    "sg:address":"4627 Old Seward Hwy",
    "sg:city":"Anchorage",
    "sg:classifiers":[
        {
            "category":"Retail",
            "subcategory":"Car Wash",
            "type":"Services"
        }
    ],
    "sg:phone":"+1 907 561 2012",
    "sg:postcode":"99503",
    "sg:province":"AK",
    "sg:tags":[
        "automobile",
        "detail",
        "clean"
    ],
    "wof:name":"Finer Detail",
    "wof:placetype":"venue"
},
  "geometry": {"coordinates":[-149.86812499999999,61.179217],"type":"Point"}
}