{
  "type": "Feature",
  "properties": {
    "iso:country":"US",
    "sg:address":"550 W 21st Ave",
    "sg:city":"Anchorage",
    "sg:classifiers":[
        {
            "category":"Health Services",
            "subcategory":"Clinic",
            "type":"Services"
        }
    ],
    "sg:phone":"+1 907 350 1077",
    "sg:postcode":"99503",
    "sg:province":"AK",
    "sg:tags":[
        "home"
    ],
    "wof:name":"Family Home Medical Care",
    "wof:placetype":"venue"
},
  "geometry": {"coordinates":[-149.89327800000001,61.201462],"type":"Point"}
}