{
  "type": "Feature",
  "properties": {
    "iso:country":"US",
    "sg:address":"3535 College Rd",
    "sg:city":"Fairbanks",
    "sg:classifiers":[
        {
            "category":"Restaurant",
            "type":"Food & Drink"
        }
    ],
    "sg:menulink":"http://www.allmenus.com/ak/fairbanks-north-star/239609-wok-n-roll/menu/",
    "sg:phone":"+1 907 455 4848",
    "sg:postcode":"99709",
    "sg:province":"AK",
    "sg:tags":[
        "asian",
        "chinese"
    ],
    "wof:name":"Wok 'n Roll",
    "wof:placetype":"venue"
},
  "geometry": {"coordinates":[-147.808931,64.85624799999999],"type":"Point"}
}