{
  "type": "Feature",
  "properties": {
    "addr:full":"1574 Wintergreen St Anchorage AK 99508",
    "addr:housenumber":"1574",
    "addr:postcode":"99508",
    "addr:street":"Wintergreen St",
    "iso:country":"US",
    "sg:address":"1574 Wintergreen St",
    "sg:city":"Anchorage",
    "sg:classifiers":[
        {
            "category":"Building & Trades",
            "subcategory":"Construction",
            "type":"Services"
        }
    ],
    "sg:phone":"+1 907 223 1577",
    "sg:postcode":"99508",
    "sg:province":"AK",
    "sg:tags":[
        "carpentry",
        "contractor"
    ],
    "wof:name":"Paragon Cstm Crpntry Cnstr LLC",
    "wof:placetype":"venue"
},
  "geometry": {"coordinates":[-149.81607500000001,61.207464],"type":"Point"}
}