{
  "type": "Feature",
  "properties": {
    "iso:country":"US",
    "sg:address":"1050 W Dimond Blvd",
    "sg:city":"Anchorage",
    "sg:classifiers":[
        {
            "category":"Farming",
            "subcategory":"Nursery",
            "type":"Manufacturing & Wholesale Goods"
        }
    ],
    "sg:phone":"+1 907 349 2552",
    "sg:postcode":"99515",
    "sg:province":"AK",
    "sg:tags":[
        "grown",
        "shrubbery",
        "cover",
        "greenhouse",
        "under",
        "growing",
        "stock"
    ],
    "wof:name":"Dimond Greenhouses Inc",
    "wof:placetype":"venue"
},
  "geometry": {"coordinates":[-149.90222399999999,61.142099],"type":"Point"}
}