{
  "type": "Feature",
  "properties": {
    "iso:country":"US",
    "sg:address":"9151 Glacier Hwy",
    "sg:city":"Juneau",
    "sg:classifiers":[
        {
            "category":"Autos & Motor Vehicles",
            "subcategory":"Auto Supplies",
            "type":"Retail Goods"
        }
    ],
    "sg:phone":"+1 907 789 9210",
    "sg:postcode":"99801",
    "sg:province":"AK",
    "sg:tags":[
        "automobile",
        "parts"
    ],
    "wof:name":"Valley Auto Parts Alaska",
    "wof:placetype":"venue"
},
  "geometry": {"coordinates":[-134.582966,58.362808],"type":"Point"}
}