{
  "type": "Feature",
  "properties": {
    "iso:country":"US",
    "sg:address":"1070 Arctic Cir",
    "sg:city":"Juneau",
    "sg:classifiers":[
        {
            "category":"Real Estate",
            "subcategory":"Surveying",
            "type":"Services"
        }
    ],
    "sg:phone":"+1 907 789 0590",
    "sg:postcode":"99801",
    "sg:province":"AK",
    "sg:tags":[
        "surveyor"
    ],
    "wof:name":"J W Bean Pro Surveyors",
    "wof:placetype":"venue"
},
  "geometry": {"coordinates":[-134.592788,58.411869],"type":"Point"}
}