{
  "type": "Feature",
  "properties": {
    "addr:full":"1245 Tongass Ave Ketchikan AK 99901",
    "addr:housenumber":"1245",
    "addr:postcode":"99901",
    "addr:street":"Tongass Ave",
    "iso:country":"US",
    "sg:address":"1245 Tongass Ave",
    "sg:city":"Ketchikan",
    "sg:classifiers":[
        {
            "category":"Organizations",
            "subcategory":"Community Association",
            "type":"Services"
        }
    ],
    "sg:phone":"+1 907 225 4520",
    "sg:postcode":"99901",
    "sg:province":"AK",
    "sg:tags":[
        "fraternal"
    ],
    "wof:name":"Loyal Order Of Moose",
    "wof:placetype":"venue"
},
  "geometry": {"coordinates":[-131.65714,55.345097],"type":"Point"}
}