{
  "type": "Feature",
  "properties": {
    "addr:full":"35440 Kenai Spur Hwy Soldotna AK 99669",
    "addr:postcode":"35440;99669",
    "addr:street":"Kenai Spur Hwy",
    "iso:country":"US",
    "sg:address":"35440 Kenai Spur Hwy",
    "sg:city":"Soldotna",
    "sg:classifiers":[
        {
            "category":"Professional",
            "subcategory":"Business Services",
            "type":"Services"
        }
    ],
    "sg:phone":"+1 907 262 6100",
    "sg:postcode":"99669",
    "sg:province":"AK",
    "sg:tags":[
        "auctioneer"
    ],
    "wof:name":"Blakeley's Auction Co",
    "wof:placetype":"venue"
},
  "geometry": {"coordinates":[-151.06779299999999,60.493683],"type":"Point"}
}