{
  "type": "Feature",
  "properties": {
    "addr:full":"1533 Lacey St Fairbanks AK 99701",
    "addr:housenumber":"1533",
    "addr:postcode":"99701",
    "addr:street":"Lacey St",
    "iso:country":"US",
    "sg:address":"1533 Lacey St",
    "sg:city":"Fairbanks",
    "sg:classifiers":[
        {
            "category":"Travel",
            "subcategory":"Hotels & Motels",
            "type":"Entertainment"
        }
    ],
    "sg:phone":"+1 907 452 4826",
    "sg:postcode":"99701",
    "sg:province":"AK",
    "wof:name":"Best Value Inn",
    "wof:placetype":"venue"
},
  "geometry": {"coordinates":[-147.71534299999999,64.833316],"type":"Point"}
}