{
  "type": "Feature",
  "properties": {
    "iso:country":"US",
    "sg:address":"1000 E 76th Ave",
    "sg:city":"Anchorage",
    "sg:classifiers":[
        {
            "category":"Manufacturing",
            "subcategory":"Food",
            "type":"Manufacturing & Wholesale Goods"
        }
    ],
    "sg:phone":"+1 907 349 1878",
    "sg:postcode":"99518",
    "sg:province":"AK",
    "sg:tags":[
        "water",
        "treat",
        "bottle"
    ],
    "wof:name":"Valaska Watcher",
    "wof:placetype":"venue"
},
  "geometry": {"coordinates":[-149.86203599999999,61.151959],"type":"Point"}
}