{
  "type": "Feature",
  "properties": {
    "iso:country":"US",
    "sg:address":"201 Old Steese Hwy",
    "sg:city":"Fairbanks",
    "sg:classifiers":[
        {
            "category":"Real Estate",
            "subcategory":"Real Estate Agent",
            "type":"Services"
        }
    ],
    "sg:phone":"+1 907 374 9132",
    "sg:postcode":"99701",
    "sg:province":"AK",
    "wof:name":"Wallace Wallace & Wakefield",
    "wof:placetype":"venue"
},
  "geometry": {"coordinates":[-147.704993,64.848236],"type":"Point"}
}