{
  "type": "Feature",
  "properties": {
    "iso:country":"US",
    "sg:address":"2750 E Palmer-Wasilla Hwy",
    "sg:city":"Wasilla",
    "sg:classifiers":[
        {
            "category":"Wholesale",
            "subcategory":"Vending Machines",
            "type":"Manufacturing & Wholesale Goods"
        }
    ],
    "sg:phone":"+1 907 376 6999",
    "sg:postcode":"99654",
    "sg:province":"AK",
    "wof:name":"JFI Amusements",
    "wof:placetype":"venue"
},
  "geometry": {"coordinates":[-149.38426200000001,61.585001],"type":"Point"}
}