{
  "type": "Feature",
  "properties": {
    "iso:country":"US",
    "sg:address":"508 Marine Way W",
    "sg:city":"Kodiak",
    "sg:classifiers":[
        {
            "category":"Retail",
            "subcategory":"Auto Rental",
            "type":"Services"
        }
    ],
    "sg:phone":"+1 907 486 8550",
    "sg:postcode":"99615",
    "sg:province":"AK",
    "sg:tags":[
        "renting",
        "automobile"
    ],
    "wof:name":"Budget Rent A Car",
    "wof:placetype":"venue"
},
  "geometry": {"coordinates":[-152.40792200000001,57.788266],"type":"Point"}
}