{
  "type": "Feature",
  "properties": {
    "addr:full":"109 Cranberry Rd Ketchikan AK 99901",
    "addr:housenumber":"109",
    "addr:postcode":"99901",
    "addr:street":"Cranberry Rd",
    "iso:country":"US",
    "sg:address":"109 Cranberry Rd",
    "sg:city":"Ketchikan",
    "sg:classifiers":[
        {
            "category":"Shopping",
            "subcategory":"Hobbies, Toys, & Games",
            "type":"Retail Goods"
        }
    ],
    "sg:phone":"+1 907 247 2627",
    "sg:postcode":"99901",
    "sg:province":"AK",
    "sg:tags":[
        "craft"
    ],
    "wof:name":"Hild's Craft",
    "wof:placetype":"venue"
},
  "geometry": {"coordinates":[-131.81768199999999,55.448695],"type":"Point"}
}