{
  "type": "Feature",
  "properties": {
    "iso:country":"US",
    "sg:address":"6225 Alaway Ave",
    "sg:city":"Juneau",
    "sg:classifiers":[
        {
            "category":"Building & Trades",
            "subcategory":"Construction",
            "type":"Services"
        }
    ],
    "sg:phone":"+1 907 780 6161",
    "sg:postcode":"99801",
    "sg:province":"AK",
    "sg:tags":[
        "general",
        "contractor"
    ],
    "wof:name":"Duran Construction Co",
    "wof:placetype":"venue"
},
  "geometry": {"coordinates":[-134.50729699999999,58.356217],"type":"Point"}
}