{
  "type": "Feature",
  "properties": {
    "addr:full":"1011 4th Ave Seward AK 99664",
    "addr:housenumber":"1011",
    "addr:postcode":"99664",
    "addr:street":"4Th Ave",
    "iso:country":"US",
    "sg:address":"1011 4th Ave",
    "sg:city":"Seward",
    "sg:classifiers":[
        {
            "category":"Real Estate",
            "subcategory":"Real Estate Operator",
            "type":"Services"
        }
    ],
    "sg:phone":"+1 907 224 5767",
    "sg:postcode":"99664",
    "sg:province":"AK",
    "sg:tags":[
        "apartment"
    ],
    "wof:name":"Bayside Apartments",
    "wof:placetype":"venue"
},
  "geometry": {"coordinates":[-149.44054800000001,60.113179],"type":"Point"}
}