{
  "type": "Feature",
  "properties": {
    "iso:country":"US",
    "sg:address":"2358 Mendenhall Loop Rd",
    "sg:city":"Juneau",
    "sg:classifiers":[
        {
            "category":"Travel",
            "subcategory":"Hotels & Motels",
            "type":"Entertainment"
        }
    ],
    "sg:phone":"+1 907 789 5566",
    "sg:postcode":"99801",
    "sg:province":"AK",
    "sg:tags":[
        "breakfast",
        "accommodation",
        "bed"
    ],
    "wof:name":"Best Western Inn",
    "wof:placetype":"venue"
},
  "geometry": {"coordinates":[-134.58898500000001,58.367339],"type":"Point"}
}