{
  "type": "Feature",
  "properties": {
    "iso:country":"US",
    "sg:address":"374 Lovers Ln",
    "sg:city":"Soldotna",
    "sg:classifiers":[
        {
            "category":"Recreation",
            "type":"Entertainment"
        }
    ],
    "sg:phone":"+1 907 262 9880",
    "sg:postcode":"99669",
    "sg:province":"AK",
    "sg:tags":[
        "skating",
        "rink"
    ],
    "wof:name":"Alaska's Great Skate",
    "wof:placetype":"venue"
},
  "geometry": {"coordinates":[-151.075858,60.479113],"type":"Point"}
}