{
  "type": "Feature",
  "properties": {
    "iso:country":"US",
    "sg:address":"110 Cushman St",
    "sg:city":"Fairbanks",
    "sg:classifiers":[
        {
            "category":"Insurance",
            "subcategory":"Insurance Agent",
            "type":"Services"
        }
    ],
    "sg:phone":"+1 907 452 4400",
    "sg:postcode":"99701",
    "sg:province":"AK",
    "wof:name":"New York Life Insurance Co",
    "wof:placetype":"venue"
},
  "geometry": {"coordinates":[-147.721496,64.84377000000001],"type":"Point"}
}