{
  "type": "Feature",
  "properties": {
    "iso:country":"US",
    "sg:address":"4831 Eagle St",
    "sg:city":"Anchorage",
    "sg:classifiers":[
        {
            "category":"Utilities",
            "subcategory":"Electric",
            "type":"Services"
        }
    ],
    "sg:phone":"+1 907 561 1818",
    "sg:postcode":"99503",
    "sg:province":"AK",
    "sg:tags":[
        "company"
    ],
    "sg:website":"www.avec.org",
    "wof:name":"Alaska Village Electric Co-Op",
    "wof:placetype":"venue"
},
  "geometry": {"coordinates":[-149.875507,61.17592],"type":"Point"}
}