{
  "type": "Feature",
  "properties": {
    "iso:country":"US",
    "sg:address":"4240 Old Seward Hwy",
    "sg:city":"Anchorage",
    "sg:classifiers":[
        {
            "category":"Professional",
            "subcategory":"Computer Services",
            "type":"Services"
        }
    ],
    "sg:phone":"+1 907 272 7697",
    "sg:postcode":"99503",
    "sg:province":"AK",
    "sg:tags":[
        "repair"
    ],
    "sg:website":"www.akmacstore.com",
    "wof:name":"Alaska Mac Store",
    "wof:placetype":"venue"
},
  "geometry": {"coordinates":[-149.86822900000001,61.181164],"type":"Point"}
}