{
  "type": "Feature",
  "properties": {
    "iso:country":"US",
    "sg:address":"59415 E End Rd",
    "sg:city":"Homer",
    "sg:classifiers":[
        {
            "category":"Retail",
            "subcategory":"Repair Shop",
            "type":"Services"
        }
    ],
    "sg:phone":"+1 907 235 4241",
    "sg:postcode":"99603",
    "sg:province":"AK",
    "sg:tags":[
        "bicycle"
    ],
    "wof:name":"Wheelsmith",
    "wof:placetype":"venue"
},
  "geometry": {"coordinates":[-151.423945,59.675605],"type":"Point"}
}