{
  "type": "Feature",
  "properties": {
    "iso:country":"US",
    "sg:address":"6480 Kenai Spur Hwy",
    "sg:city":"Kenai",
    "sg:classifiers":[
        {
            "category":"Wholesale",
            "subcategory":"Metals & Minerals",
            "type":"Manufacturing & Wholesale Goods"
        }
    ],
    "sg:phone":"+1 907 283 7136",
    "sg:postcode":"99611",
    "sg:province":"AK",
    "sg:tags":[
        "steel",
        "warehouse"
    ],
    "wof:name":"Morgan Steel Inc",
    "wof:placetype":"venue"
},
  "geometry": {"coordinates":[-151.13717,60.566976],"type":"Point"}
}