{
  "type": "Feature",
  "properties": {
    "iso:country":"US",
    "sg:address":"2504 Birch St",
    "sg:city":"Seward",
    "sg:classifiers":[
        {
            "category":"Marine",
            "type":"Transportation"
        }
    ],
    "sg:phone":"+1 907 224 5245",
    "sg:postcode":"99664",
    "sg:province":"AK",
    "sg:tags":[
        "surveyor"
    ],
    "wof:name":"Marine Mechanical",
    "wof:placetype":"venue"
},
  "geometry": {"coordinates":[-149.43495200000001,60.139389],"type":"Point"}
}