{
  "type": "Feature",
  "properties": {
    "iso:country":"US",
    "sg:address":"6150 A St",
    "sg:city":"Anchorage",
    "sg:classifiers":[
        {
            "category":"Building & Trades",
            "subcategory":"Construction",
            "type":"Services"
        }
    ],
    "sg:phone":"+1 907 562 2240",
    "sg:postcode":"99518",
    "sg:province":"AK",
    "sg:tags":[
        "concrete",
        "contractor"
    ],
    "wof:name":"Diggins Concrete",
    "wof:placetype":"venue"
},
  "geometry": {"coordinates":[-149.881661,61.166245],"type":"Point"}
}