{
  "type": "Feature",
  "properties": {
    "iso:country":"US",
    "sg:address":"411 Harris St",
    "sg:city":"Juneau",
    "sg:classifiers":[
        {
            "category":"Professional",
            "subcategory":"Lawyer & Legal Services",
            "type":"Services"
        }
    ],
    "sg:phone":"+1 907 586 8200",
    "sg:postcode":"99801",
    "sg:province":"AK",
    "sg:tags":[
        "attorney"
    ],
    "wof:name":"Kirsten Swanson",
    "wof:placetype":"venue"
},
  "geometry": {"coordinates":[-134.406443,58.303118],"type":"Point"}
}