{
  "type": "Feature",
  "properties": {
    "iso:country":"US",
    "sg:address":"5422 Shaune Dr",
    "sg:city":"Juneau",
    "sg:classifiers":[
        {
            "category":"Retail",
            "subcategory":"Laundry & Dry Cleaning",
            "type":"Services"
        }
    ],
    "sg:phone":"+1 907 789 3200",
    "sg:postcode":"99801",
    "sg:province":"AK",
    "sg:tags":[
        "cleaners",
        "rug",
        "carpet"
    ],
    "wof:name":"J & J-Jet Steam",
    "wof:placetype":"venue"
},
  "geometry": {"coordinates":[-134.48701299999999,58.35665],"type":"Point"}
}