{
  "type": "Feature",
  "properties": {
    "addr:full":"3800 Lake Otis Pkwy Anchorage AK 99508",
    "addr:housenumber":"3800",
    "addr:postcode":"99508",
    "addr:street":"Lake Otis Pkwy",
    "iso:country":"US",
    "sg:address":"3800 Lake Otis Pkwy",
    "sg:city":"Anchorage",
    "sg:classifiers":[
        {
            "category":"Health Services",
            "subcategory":"Chiropractor",
            "type":"Services"
        }
    ],
    "sg:phone":"+1 907 562 2345",
    "sg:postcode":"99508",
    "sg:province":"AK",
    "wof:name":"Alaska Chiropractic Ctr Inc",
    "wof:placetype":"venue"
},
  "geometry": {"coordinates":[-149.838212,61.184447],"type":"Point"}
}