{
  "type": "Feature",
  "properties": {
    "iso:country":"US",
    "sg:address":"1679 23rd Ave",
    "sg:city":"Fairbanks",
    "sg:classifiers":[
        {
            "category":"Organizations",
            "subcategory":"Religious Organization",
            "type":"Services"
        }
    ],
    "sg:phone":"+1 907 456 4585",
    "sg:postcode":"99701",
    "sg:province":"AK",
    "sg:tags":[
        "church"
    ],
    "wof:name":"Corinthian Baptist Church",
    "wof:placetype":"venue"
},
  "geometry": {"coordinates":[-147.74233899999999,64.826108],"type":"Point"}
}