{
  "type": "Feature",
  "properties": {
    "iso:country":"US",
    "sg:address":"605 W Willoughby Ave",
    "sg:city":"Juneau",
    "sg:classifiers":[
        {
            "category":"Shopping",
            "subcategory":"Music",
            "type":"Retail Goods"
        }
    ],
    "sg:phone":"+1 907 586 1718",
    "sg:postcode":"99801",
    "sg:province":"AK",
    "sg:tags":[
        "video",
        "disc",
        "tape",
        "cassette"
    ],
    "wof:name":"Downtown Video",
    "wof:placetype":"venue"
},
  "geometry": {"coordinates":[-134.41791000000001,58.3006],"type":"Point"}
}