{
  "type": "Feature",
  "properties": {
    "iso:country":"US",
    "sg:address":"510 L St",
    "sg:city":"Anchorage",
    "sg:classifiers":[
        {
            "category":"Government",
            "subcategory":"Office",
            "type":"Public Place"
        }
    ],
    "sg:phone":"+1 907 271 3735",
    "sg:postcode":"99501",
    "sg:province":"AK",
    "wof:name":"Senator Lisa Murkowski",
    "wof:placetype":"venue"
},
  "geometry": {"coordinates":[-149.903818,61.216682],"type":"Point"}
}