{
  "type": "Feature",
  "properties": {
    "iso:country":"US",
    "sg:address":"352 Front St",
    "sg:city":"Ketchikan",
    "sg:classifiers":[
        {
            "category":"Government",
            "subcategory":"Police Station",
            "type":"Public Place"
        }
    ],
    "sg:phone":"+1 907 225 8088",
    "sg:postcode":"99901",
    "sg:province":"AK",
    "sg:tags":[
        "state"
    ],
    "wof:name":"Senator Robin Taylor",
    "wof:placetype":"venue"
},
  "geometry": {"coordinates":[-131.646514,55.340934],"type":"Point"}
}