{
  "type": "Feature",
  "properties": {
    "iso:country":"US",
    "sg:address":"6841 Joseph St",
    "sg:city":"Anchorage",
    "sg:classifiers":[
        {
            "category":"Real Estate",
            "subcategory":"Real Estate Agent",
            "type":"Services"
        }
    ],
    "sg:phone":"+1 907 336 1300",
    "sg:postcode":"99518",
    "sg:province":"AK",
    "sg:tags":[
        "inspection"
    ],
    "wof:name":"Arctic Property Inspection",
    "wof:placetype":"venue"
},
  "geometry": {"coordinates":[-149.900981,61.157682],"type":"Point"}
}