{
  "type": "Feature",
  "properties": {
    "iso:country":"US",
    "sg:address":"403 S Alaska St",
    "sg:city":"Palmer",
    "sg:classifiers":[
        {
            "category":"Social Services",
            "type":"Services"
        }
    ],
    "sg:phone":"+1 907 745 6098",
    "sg:postcode":"99645",
    "sg:province":"AK",
    "sg:tags":[
        "organization",
        "welfare"
    ],
    "wof:name":"Child Care Assistance Program",
    "wof:placetype":"venue"
},
  "geometry": {"coordinates":[-149.11446,61.602385],"type":"Point"}
}