{
  "type": "Feature",
  "properties": {
    "iso:country":"US",
    "sg:address":"3601 Arkansas Dr",
    "sg:city":"Anchorage",
    "sg:classifiers":[
        {
            "category":"Professional",
            "subcategory":"Art Services",
            "type":"Services"
        }
    ],
    "sg:phone":"+1 907 563 5005",
    "sg:postcode":"99517",
    "sg:province":"AK",
    "sg:tags":[
        "graphic",
        "designer"
    ],
    "wof:name":"Nedland Design & Illustrations",
    "wof:placetype":"venue"
},
  "geometry": {"coordinates":[-149.92993100000001,61.186578],"type":"Point"}
}