{
  "type": "Feature",
  "properties": {
    "iso:country":"US",
    "sg:address":"1027 Evergreen St",
    "sg:city":"Fairbanks",
    "sg:classifiers":[
        {
            "category":"Organizations",
            "subcategory":"Non-profit Organization",
            "type":"Services"
        }
    ],
    "sg:phone":"+1 907 451 8164",
    "sg:postcode":"99709",
    "sg:province":"AK",
    "sg:tags":[
        "information",
        "alcoholism",
        "treatment"
    ],
    "wof:name":"Women & Children Ctr",
    "wof:placetype":"venue"
},
  "geometry": {"coordinates":[-147.754459,64.854466],"type":"Point"}
}