{
  "type": "Feature",
  "properties": {
    "iso:country":"US",
    "sg:address":"1949 Kittiwake Dr",
    "sg:city":"Fairbanks",
    "sg:classifiers":[
        {
            "category":"Mining & Drilling",
            "type":"Manufacturing & Wholesale Goods"
        }
    ],
    "sg:phone":"+1 907 479 8153",
    "sg:postcode":"99709",
    "sg:province":"AK",
    "sg:tags":[
        "field"
    ],
    "wof:name":"Larry Hinzman",
    "wof:placetype":"venue"
},
  "geometry": {"coordinates":[-147.834925,64.884125],"type":"Point"}
}