{
  "type": "Feature",
  "properties": {
    "iso:country":"US",
    "sg:address":"173 W Pioneer Ave",
    "sg:city":"Homer",
    "sg:classifiers":[
        {
            "category":"Shopping",
            "subcategory":"Gifts & Souvenirs",
            "type":"Retail Goods"
        }
    ],
    "sg:phone":"+1 907 235 0766",
    "sg:postcode":"99603",
    "sg:province":"AK",
    "sg:tags":[
        "shop"
    ],
    "wof:name":"North Wind Home Collection",
    "wof:placetype":"venue"
},
  "geometry": {"coordinates":[-151.546165,59.645004],"type":"Point"}
}