{
  "type": "Feature",
  "properties": {
    "addr:full":"312 Marine Way W Kodiak AK 99615",
    "addr:housenumber":"312",
    "addr:postcode":"99615",
    "addr:street":"Marine Way W",
    "iso:country":"US",
    "sg:address":"312 Marine Way W",
    "sg:city":"Kodiak",
    "sg:classifiers":[
        {
            "category":"Organizations",
            "subcategory":"Professional Association",
            "type":"Services"
        }
    ],
    "sg:phone":"+1 907 486 4449",
    "sg:postcode":"99615",
    "sg:province":"AK",
    "sg:tags":[
        "corporation",
        "native"
    ],
    "wof:name":"Kodiak Tribal Council",
    "wof:placetype":"venue"
},
  "geometry": {"coordinates":[-152.406755,57.787455],"type":"Point"}
}