{
  "type": "Feature",
  "properties": {
    "addr:full":"1561 E Parks Hwy Wasilla AK 99654",
    "addr:housenumber":"1561",
    "addr:postcode":"99654",
    "addr:street":"E Parks Hwy",
    "iso:country":"US",
    "sg:address":"1561 E Parks Hwy",
    "sg:city":"Wasilla",
    "sg:classifiers":[
        {
            "category":"Restaurant",
            "type":"Food & Drink"
        }
    ],
    "sg:menulink":"http://www.allmenus.com/ak/matanuska-susitna/78131-papa-murphys/menu/",
    "sg:phone":"+1 907 376 3696",
    "sg:postcode":"99654",
    "sg:province":"AK",
    "sg:tags":[
        "american",
        "pizza"
    ],
    "wof:name":"Papa Murphy's",
    "wof:placetype":"venue"
},
  "geometry": {"coordinates":[-149.412474,61.577774],"type":"Point"}
}