{
  "type": "Feature",
  "properties": {
    "addr:full":"100 Lincoln St Sitka AK 99835",
    "addr:housenumber":"100",
    "addr:postcode":"99835",
    "addr:street":"Lincoln St",
    "iso:country":"US",
    "sg:address":"100 Lincoln St",
    "sg:city":"Sitka",
    "sg:classifiers":[
        {
            "category":"Government",
            "subcategory":"Office",
            "type":"Public Place"
        }
    ],
    "sg:phone":"+1 907 747 1816",
    "sg:postcode":"99835",
    "sg:province":"AK",
    "sg:tags":[
        "village"
    ],
    "wof:name":"Human Resources Director",
    "wof:placetype":"venue"
},
  "geometry": {"coordinates":[-135.339786,57.048783],"type":"Point"}
}