{
  "type": "Feature",
  "properties": {
    "addr:full":"509 9th Ave Fairbanks AK 99701",
    "addr:housenumber":"509",
    "addr:postcode":"99701",
    "addr:street":"9Th Ave",
    "iso:country":"US",
    "sg:address":"509 9th Ave",
    "sg:city":"Fairbanks",
    "sg:classifiers":[
        {
            "category":"Social Services",
            "type":"Services"
        }
    ],
    "sg:phone":"+1 907 452 4259",
    "sg:postcode":"99701",
    "sg:province":"AK",
    "sg:tags":[
        "organization",
        "welfare"
    ],
    "wof:name":"Companions Inc",
    "wof:placetype":"venue"
},
  "geometry": {"coordinates":[-147.719346,64.839472],"type":"Point"}
}