{
  "type": "Feature",
  "properties": {
    "iso:country":"US",
    "sg:address":"606 Bentley Dr",
    "sg:city":"Fairbanks",
    "sg:classifiers":[
        {
            "category":"Retail",
            "subcategory":"Portrait Studio",
            "type":"Services"
        }
    ],
    "sg:phone":"+1 907 452 3116",
    "sg:postcode":"99701",
    "sg:province":"AK",
    "sg:tags":[
        "photographer"
    ],
    "wof:name":"Nelson's Photography",
    "wof:placetype":"venue"
},
  "geometry": {"coordinates":[-147.696967,64.836893],"type":"Point"}
}