{
  "type": "Feature",
  "properties": {
    "iso:country":"US",
    "sg:address":"1200 Wilshire Ave",
    "sg:city":"Anchorage",
    "sg:classifiers":[
        {
            "category":"Personal",
            "subcategory":"Beauty Salon",
            "type":"Services"
        }
    ],
    "sg:phone":"+1 907 277 5511",
    "sg:postcode":"99503",
    "sg:province":"AK",
    "sg:tags":[
        "manicuring"
    ],
    "wof:name":"Lana's Perfect TEN",
    "wof:placetype":"venue"
},
  "geometry": {"coordinates":[-149.90634900000001,61.18752],"type":"Point"}
}