{
  "type": "Feature",
  "properties": {
    "iso:country":"US",
    "sg:address":"814 W 2nd Ave",
    "sg:city":"Anchorage",
    "sg:classifiers":[
        {
            "category":"Professional",
            "subcategory":"Lawyer & Legal Services",
            "type":"Services"
        }
    ],
    "sg:phone":"+1 907 279 8260",
    "sg:postcode":"99501",
    "sg:province":"AK",
    "sg:tags":[
        "attorney"
    ],
    "wof:name":"Dan S Bair",
    "wof:placetype":"venue"
},
  "geometry": {"coordinates":[-149.901501,61.220423],"type":"Point"}
}