{
  "type": "Feature",
  "properties": {
    "iso:country":"US",
    "sg:address":"174 W Arctic Ave",
    "sg:city":"Palmer",
    "sg:classifiers":[
        {
            "category":"Autos & Motor Vehicles",
            "subcategory":"Fuel & Gas Station",
            "type":"Retail Goods"
        }
    ],
    "sg:phone":"+1 907 746 3550",
    "sg:postcode":"99645",
    "sg:province":"AK",
    "sg:tags":[
        "oil"
    ],
    "wof:name":"Palmer Tesoro",
    "wof:placetype":"venue"
},
  "geometry": {"coordinates":[-149.116426,61.606588],"type":"Point"}
}