{
  "type": "Feature",
  "properties": {
    "iso:country":"US",
    "sg:address":"169 W Riverview Ave",
    "sg:city":"Soldotna",
    "sg:classifiers":[
        {
            "category":"Social Services",
            "subcategory":"Child Care",
            "type":"Services"
        }
    ],
    "sg:phone":"+1 907 262 6807",
    "sg:postcode":"99669",
    "sg:province":"AK",
    "wof:name":"Cano Kids & Co Child Care",
    "wof:placetype":"venue"
},
  "geometry": {"coordinates":[-151.077213,60.484061],"type":"Point"}
}