{
  "type": "Feature",
  "properties": {
    "addr:full":"123 S Seward St Juneau AK 99801",
    "addr:housenumber":"123",
    "addr:postcode":"99801",
    "addr:street":"S Seward St",
    "iso:country":"US",
    "sg:address":"123 S Seward St",
    "sg:city":"Juneau",
    "sg:classifiers":[
        {
            "category":"Professional",
            "subcategory":"Printing & Photocopies",
            "type":"Services"
        }
    ],
    "sg:phone":"+1 907 586 9696",
    "sg:postcode":"99801",
    "sg:province":"AK",
    "sg:tags":[
        "photocopying",
        "bindery",
        "full"
    ],
    "sg:website":"www.capitalcopy.com",
    "wof:name":"Capital Copy LTD",
    "wof:placetype":"venue"
},
  "geometry": {"coordinates":[-134.407205,58.300622],"type":"Point"}
}