{
  "type": "Feature",
  "properties": {
    "iso:country":"US",
    "sg:address":"2513 Davis Rd",
    "sg:city":"Fairbanks",
    "sg:classifiers":[
        {
            "category":"Retail",
            "subcategory":"Repair Shop",
            "type":"Services"
        }
    ],
    "sg:phone":"+1 907 474 0259",
    "sg:postcode":"99709",
    "sg:province":"AK",
    "sg:tags":[
        "upholsterer"
    ],
    "wof:name":"Jodie's Upholstery",
    "wof:placetype":"venue"
},
  "geometry": {"coordinates":[-147.781499,64.827313],"type":"Point"}
}