{
  "type": "Feature",
  "properties": {
    "iso:country":"US",
    "sg:address":"901 S Nordic Dr",
    "sg:city":"Petersburg",
    "sg:classifiers":[
        {
            "category":"Manufacturing",
            "subcategory":"Tools & Machinery",
            "type":"Manufacturing & Wholesale Goods"
        }
    ],
    "sg:phone":"+1 907 772 4251",
    "sg:postcode":"99833",
    "sg:province":"AK",
    "sg:tags":[
        "industry"
    ],
    "wof:name":"Petro Marine Svc",
    "wof:placetype":"venue"
},
  "geometry": {"coordinates":[-132.97175899999999,56.807676],"type":"Point"}
}