{
  "type": "Feature",
  "properties": {
    "addr:full":"2900 Barbara St Anchorage AK 99517",
    "addr:housenumber":"2900",
    "addr:postcode":"99517",
    "addr:street":"Barbara St",
    "iso:country":"US",
    "sg:address":"2900 Barbara St",
    "sg:city":"Anchorage",
    "sg:classifiers":[
        {
            "category":"Building & Trades",
            "subcategory":"Construction",
            "type":"Services"
        }
    ],
    "sg:phone":"+1 907 677 8635",
    "sg:postcode":"99517",
    "sg:province":"AK",
    "sg:tags":[
        "handyman"
    ],
    "wof:name":"AAA Affordable",
    "wof:placetype":"venue"
},
  "geometry": {"coordinates":[-149.93172300000001,61.193401],"type":"Point"}
}