{
  "type": "Feature",
  "properties": {
    "iso:country":"US",
    "sg:address":"17205 Eagle River Rd",
    "sg:city":"Eagle River",
    "sg:classifiers":[
        {
            "category":"Retail",
            "subcategory":"Repair Shop",
            "type":"Services"
        }
    ],
    "sg:phone":"+1 907 694 1700",
    "sg:postcode":"99577",
    "sg:province":"AK",
    "sg:tags":[
        "appliance"
    ],
    "wof:name":"Eagle Appliance Svc Ctr",
    "wof:placetype":"venue"
},
  "geometry": {"coordinates":[-149.560493,61.310612],"type":"Point"}
}