{
  "type": "Feature",
  "properties": {
    "iso:country":"US",
    "sg:address":"4400 Mac Alister Dr",
    "sg:city":"Anchorage",
    "sg:classifiers":[
        {
            "category":"Travel",
            "subcategory":"Campground",
            "type":"Entertainment"
        }
    ],
    "sg:phone":"+1 907 892 7413",
    "sg:postcode":"99502",
    "sg:province":"AK",
    "sg:tags":[
        "camp"
    ],
    "wof:name":"PC Enterprises",
    "wof:placetype":"venue"
},
  "geometry": {"coordinates":[-149.96206100000001,61.136084],"type":"Point"}
}