{
  "type": "Feature",
  "properties": {
    "addr:full":"508 W 2nd Ave Anchorage AK 99501",
    "addr:housenumber":"508",
    "addr:postcode":"99501",
    "addr:street":"W 2Nd Ave",
    "iso:country":"US",
    "sg:address":"508 W 2nd Ave",
    "sg:city":"Anchorage",
    "sg:classifiers":[
        {
            "category":"Professional",
            "subcategory":"Lawyer & Legal Services",
            "type":"Services"
        }
    ],
    "sg:phone":"+1 907 278 8533",
    "sg:postcode":"99501",
    "sg:province":"AK",
    "sg:tags":[
        "attorney"
    ],
    "wof:name":"Tindall Bennett & Shoup",
    "wof:placetype":"venue"
},
  "geometry": {"coordinates":[-149.891513,61.220454],"type":"Point"}
}