{
  "type": "Feature",
  "properties": {
    "iso:country":"US",
    "sg:address":"3275 Montclaire Ct",
    "sg:city":"Anchorage",
    "sg:classifiers":[
        {
            "category":"Professional",
            "subcategory":"Computer Services",
            "type":"Services"
        }
    ],
    "sg:phone":"+1 907 274 0042",
    "sg:postcode":"99503",
    "sg:province":"AK",
    "sg:tags":[
        "internet"
    ],
    "wof:name":"Alaska Directory Of Products",
    "wof:placetype":"venue"
},
  "geometry": {"coordinates":[-149.894903,61.190795],"type":"Point"}
}