{
  "type": "Feature",
  "properties": {
    "addr:full":"805 Airport Way Fairbanks AK 99701",
    "addr:housenumber":"805",
    "addr:postcode":"99701",
    "addr:street":"Airport Way",
    "iso:country":"US",
    "sg:address":"805 Airport Way",
    "sg:city":"Fairbanks",
    "sg:classifiers":[
        {
            "category":"Building & Trades",
            "subcategory":"Cleaning & Sanitation",
            "type":"Services"
        }
    ],
    "sg:phone":"+1 907 456 8901",
    "sg:postcode":"99701",
    "sg:province":"AK",
    "sg:tags":[
        "janitor"
    ],
    "sg:website":"www.fra-alaska.net",
    "wof:name":"Fairbanks Resource Agency",
    "wof:placetype":"venue"
},
  "geometry": {"coordinates":[-147.72142700000001,64.83632299999999],"type":"Point"}
}