{
  "type": "Feature",
  "properties": {
    "iso:country":"US",
    "sg:address":"4411 Spenard Rd",
    "sg:city":"Anchorage",
    "sg:classifiers":[
        {
            "category":"Travel",
            "subcategory":"Hotels & Motels",
            "type":"Entertainment"
        }
    ],
    "sg:phone":"+1 907 248 8848",
    "sg:postcode":"99517",
    "sg:province":"AK",
    "sg:website":"www.staysmart.com",
    "wof:name":"Holiday Inn Express Anchorage",
    "wof:placetype":"venue"
},
  "geometry": {"coordinates":[-149.93662,61.181178],"type":"Point"}
}