{
  "type": "Feature",
  "properties": {
    "addr:full":"5550 Camelot Dr Anchorage AK 99504",
    "addr:housenumber":"5550",
    "addr:postcode":"99504",
    "addr:street":"Camelot Dr",
    "iso:country":"US",
    "sg:address":"5550 Camelot Dr",
    "sg:city":"Anchorage",
    "sg:classifiers":[
        {
            "category":"Retail",
            "subcategory":"Auto Repair",
            "type":"Services"
        }
    ],
    "sg:phone":"+1 907 337 8222",
    "sg:postcode":"99504",
    "sg:province":"AK",
    "sg:tags":[
        "body",
        "automobile",
        "painting"
    ],
    "wof:name":"Alaska Custom Refinishing",
    "wof:placetype":"venue"
},
  "geometry": {"coordinates":[-149.774933,61.220474],"type":"Point"}
}