{
  "type": "Feature",
  "properties": {
    "iso:country":"US",
    "sg:address":"568 Hilltop Ave",
    "sg:city":"Fairbanks",
    "sg:classifiers":[
        {
            "category":"Health Services",
            "subcategory":"Doctor",
            "type":"Services"
        }
    ],
    "sg:phone":"+1 907 479 6540",
    "sg:postcode":"99709",
    "sg:province":"AK",
    "sg:tags":[
        "physician",
        "surgeon"
    ],
    "wof:name":"Fairbanks Anesthesia",
    "wof:placetype":"venue"
},
  "geometry": {"coordinates":[-147.798874,64.884079],"type":"Point"}
}