{
  "type": "Feature",
  "properties": {
    "iso:country":"US",
    "sg:address":"1301 W Parks Hwy",
    "sg:city":"Wasilla",
    "sg:classifiers":[
        {
            "category":"Personal",
            "subcategory":"Beauty Salon",
            "type":"Services"
        }
    ],
    "sg:phone":"+1 907 357 4247",
    "sg:postcode":"99654",
    "sg:province":"AK",
    "wof:name":"Hair Effects",
    "wof:placetype":"venue"
},
  "geometry": {"coordinates":[-149.49411000000001,61.5794],"type":"Point"}
}