{
  "type": "Feature",
  "properties": {
    "iso:country":"US",
    "sg:address":"3901 Patricia Ln",
    "sg:city":"Anchorage",
    "sg:classifiers":[
        {
            "category":"Health Services",
            "subcategory":"Health Practitioner",
            "type":"Services"
        }
    ],
    "sg:phone":"+1 907 337 1696",
    "sg:postcode":"99504",
    "sg:province":"AK",
    "sg:tags":[
        "nutritionist"
    ],
    "wof:name":"AJP Nutrition & Weight Loss",
    "wof:placetype":"venue"
},
  "geometry": {"coordinates":[-149.742625,61.185237],"type":"Point"}
}