{
  "type": "Feature",
  "properties": {
    "iso:country":"US",
    "sg:address":"620 Fideler Rd",
    "sg:city":"Fairbanks",
    "sg:classifiers":[
        {
            "category":"Farming",
            "subcategory":"Nursery",
            "type":"Manufacturing & Wholesale Goods"
        }
    ],
    "sg:phone":"+1 907 457 5268",
    "sg:postcode":"99712",
    "sg:province":"AK",
    "sg:tags":[
        "greenhouse"
    ],
    "wof:name":"Plant Kingdom",
    "wof:placetype":"venue"
},
  "geometry": {"coordinates":[-147.69480899999999,64.892292],"type":"Point"}
}