{
  "type": "Feature",
  "properties": {
    "iso:country":"US",
    "sg:address":"6620 Crooked Tree Dr",
    "sg:city":"Anchorage",
    "sg:classifiers":[
        {
            "category":"Professional",
            "subcategory":"Research",
            "type":"Services"
        }
    ],
    "sg:phone":"+1 907 349 8719",
    "sg:postcode":"99507",
    "sg:province":"AK",
    "sg:tags":[
        "environmental",
        "ecological"
    ],
    "sg:website":"www.wardcon.com",
    "wof:name":"Ward Consulting",
    "wof:placetype":"venue"
},
  "geometry": {"coordinates":[-149.7587,61.128958],"type":"Point"}
}