{
  "type": "Feature",
  "properties": {
    "iso:country":"US",
    "sg:address":"3002 Spenard Rd",
    "sg:city":"Anchorage",
    "sg:classifiers":[
        {
            "category":"Retail",
            "subcategory":"Auto Repair",
            "type":"Services"
        }
    ],
    "sg:phone":"+1 907 274 4888",
    "sg:postcode":"99503",
    "sg:province":"AK",
    "sg:tags":[
        "repairing",
        "automobile"
    ],
    "wof:name":"Senior Automotive",
    "wof:placetype":"venue"
},
  "geometry": {"coordinates":[-149.90543099999999,61.193054],"type":"Point"}
}