{
  "type": "Feature",
  "properties": {
    "iso:country":"US",
    "sg:address":"3621 W 79th Ave",
    "sg:city":"Anchorage",
    "sg:classifiers":[
        {
            "category":"Travel",
            "subcategory":"Hotels & Motels",
            "type":"Entertainment"
        }
    ],
    "sg:phone":"+1 907 243 8631",
    "sg:postcode":"99502",
    "sg:province":"AK",
    "sg:tags":[
        "breakfast",
        "accommodation",
        "bed"
    ],
    "wof:name":"Berry Patch Bed & Breakfast",
    "wof:placetype":"venue"
},
  "geometry": {"coordinates":[-149.950035,61.149293],"type":"Point"}
}