{
  "type": "Feature",
  "properties": {
    "iso:country":"US",
    "sg:address":"3419 Jerde Cir",
    "sg:city":"Anchorage",
    "sg:classifiers":[
        {
            "category":"Building & Trades",
            "subcategory":"Plumbing",
            "type":"Services"
        }
    ],
    "sg:phone":"+1 907 337 2444",
    "sg:postcode":"99504",
    "sg:province":"AK",
    "sg:tags":[
        "contractor"
    ],
    "wof:name":"South Central Plumbing & Htg",
    "wof:placetype":"venue"
},
  "geometry": {"coordinates":[-149.76434,61.189443],"type":"Point"}
}