{
  "type": "Feature",
  "properties": {
    "addr:full":"542 4th Ave Fairbanks AK 99701",
    "addr:housenumber":"542",
    "addr:postcode":"99701",
    "addr:street":"4Th Ave",
    "iso:country":"US",
    "sg:address":"542 4th Ave",
    "sg:city":"Fairbanks",
    "sg:classifiers":[
        {
            "category":"Professional",
            "subcategory":"Lawyer & Legal Services",
            "type":"Services"
        }
    ],
    "sg:phone":"+1 907 451 0926",
    "sg:postcode":"99701",
    "sg:province":"AK",
    "sg:tags":[
        "attorney"
    ],
    "wof:name":"Greg Berger",
    "wof:placetype":"venue"
},
  "geometry": {"coordinates":[-147.719585,64.842422],"type":"Point"}
}