{
  "type": "Feature",
  "properties": {
    "addr:full":"1930 E Northern Lights Blvd Anchorage AK 99508",
    "addr:housenumber":"1930",
    "addr:postcode":"99508",
    "addr:street":"E Northern Lights Blvd",
    "iso:country":"US",
    "sg:address":"1930 E Northern Lights Blvd",
    "sg:city":"Anchorage",
    "sg:classifiers":[
        {
            "category":"Organizations",
            "subcategory":"Non-profit Organization",
            "type":"Services"
        }
    ],
    "sg:phone":"+1 907 274 4344",
    "sg:postcode":"99508",
    "sg:province":"AK",
    "wof:name":"Al Aska Shriners",
    "wof:placetype":"venue"
},
  "geometry": {"coordinates":[-149.84453300000001,61.195314],"type":"Point"}
}