{
  "type": "Feature",
  "properties": {
    "iso:country":"US",
    "sg:address":"777 Juneau St",
    "sg:city":"Anchorage",
    "sg:classifiers":[
        {
            "category":"Banks & Credit Unions",
            "subcategory":"Bank",
            "type":"Services"
        }
    ],
    "sg:phone":"+1 907 276 2455",
    "sg:postcode":"99501",
    "sg:province":"AK",
    "wof:name":"TWS Svc Of Alaska Inc",
    "wof:placetype":"venue"
},
  "geometry": {"coordinates":[-149.86480800000001,61.215367],"type":"Point"}
}