{
  "type": "Feature",
  "properties": {
    "addr:full":"125 Main St E Dillingham AK 99576",
    "addr:housenumber":"125",
    "addr:postcode":"99576",
    "addr:street":"Main St E Dillingham",
    "iso:country":"US",
    "sg:address":"125 Main St E",
    "sg:city":"Dillingham",
    "sg:classifiers":[
        {
            "category":"Government",
            "subcategory":"Office",
            "type":"Public Place"
        }
    ],
    "sg:phone":"+1 907 842 5981",
    "sg:postcode":"99576",
    "sg:province":"AK",
    "sg:tags":[
        "state",
        "program",
        "health"
    ],
    "wof:name":"Health Ctr",
    "wof:placetype":"venue"
},
  "geometry": {"coordinates":[-158.46202500000001,59.039905],"type":"Point"}
}