{
  "type": "Feature",
  "properties": {
    "iso:country":"US",
    "sg:address":"159 Front St",
    "sg:city":"Nome",
    "sg:classifiers":[
        {
            "category":"Government",
            "subcategory":"Office",
            "type":"Public Place"
        }
    ],
    "sg:phone":"+1 907 443 5282",
    "sg:postcode":"99762",
    "sg:province":"AK",
    "sg:tags":[
        "state",
        "security"
    ],
    "wof:name":"National Guard",
    "wof:placetype":"venue"
},
  "geometry": {"coordinates":[-165.40966399999999,64.497922],"type":"Point"}
}