{
  "type": "Feature",
  "properties": {
    "iso:country":"US",
    "sg:address":"11621 Old Seward Hwy",
    "sg:city":"Anchorage",
    "sg:classifiers":[
        {
            "category":"Retail",
            "subcategory":"Funeral Services",
            "type":"Services"
        }
    ],
    "sg:phone":"+1 907 344 1497",
    "sg:postcode":"99515",
    "sg:province":"AK",
    "sg:tags":[
        "director"
    ],
    "wof:name":"Kehl's Forest Lawn Memorial",
    "wof:placetype":"venue"
},
  "geometry": {"coordinates":[-149.86379299999999,61.114228],"type":"Point"}
}