{
  "type": "Feature",
  "properties": {
    "iso:country":"US",
    "sg:address":"18749 Old Glenn Hwy",
    "sg:city":"Chugiak",
    "sg:classifiers":[
        {
            "category":"Building & Trades",
            "subcategory":"Construction",
            "type":"Services"
        }
    ],
    "sg:phone":"+1 907 688 7623",
    "sg:postcode":"99567",
    "sg:province":"AK",
    "sg:tags":[
        "fence",
        "contractor"
    ],
    "wof:name":"Roadrunner Fence Co",
    "wof:placetype":"venue"
},
  "geometry": {"coordinates":[-149.46389199999999,61.394549],"type":"Point"}
}