{
  "type": "Feature",
  "properties": {
    "iso:country":"US",
    "sg:address":"1000 Lakeview Ter",
    "sg:city":"Fairbanks",
    "sg:classifiers":[
        {
            "category":"Real Estate",
            "subcategory":"Real Estate Operator",
            "type":"Services"
        }
    ],
    "sg:phone":"+1 907 452 2553",
    "sg:postcode":"99701",
    "sg:province":"AK",
    "sg:tags":[
        "mobile",
        "home",
        "community"
    ],
    "wof:name":"Lakeview Terrace",
    "wof:placetype":"venue"
},
  "geometry": {"coordinates":[-147.688889,64.806438],"type":"Point"}
}