{
  "type": "Feature",
  "properties": {
    "addr:full":"450 Whittier St Juneau AK 99801",
    "addr:housenumber":"450",
    "addr:postcode":"99801",
    "addr:street":"Whittier St",
    "iso:country":"US",
    "sg:address":"450 Whittier St",
    "sg:city":"Juneau",
    "sg:classifiers":[
        {
            "category":"Government",
            "subcategory":"Fire Station",
            "type":"Public Place"
        }
    ],
    "sg:phone":"+1 907 465 4331",
    "sg:postcode":"99801",
    "sg:province":"AK",
    "sg:tags":[
        "state",
        "protection"
    ],
    "wof:name":"Fire Prevention",
    "wof:placetype":"venue"
},
  "geometry": {"coordinates":[-134.414571,58.300801],"type":"Point"}
}