{
  "type": "Feature",
  "properties": {
    "addr:full":"270 W Pioneer Ave Homer AK 99603",
    "addr:housenumber":"270",
    "addr:postcode":"99603",
    "addr:street":"W Pioneer Ave",
    "iso:country":"US",
    "sg:address":"270 W Pioneer Ave",
    "sg:city":"Homer",
    "sg:classifiers":[
        {
            "category":"Government",
            "subcategory":"Office",
            "type":"Public Place"
        }
    ],
    "sg:phone":"+1 907 235 7791",
    "sg:postcode":"99603",
    "sg:province":"AK",
    "sg:tags":[
        "state",
        "inspection"
    ],
    "wof:name":"Labor Dept",
    "wof:placetype":"venue"
},
  "geometry": {"coordinates":[-151.549654,59.64372],"type":"Point"}
}