{
  "type": "Feature",
  "properties": {
    "iso:country":"US",
    "sg:address":"418 3rd St",
    "sg:city":"Fairbanks",
    "sg:classifiers":[
        {
            "category":"Professional",
            "subcategory":"Advertising",
            "type":"Services"
        }
    ],
    "sg:phone":"+1 907 456 7348",
    "sg:postcode":"99701",
    "sg:province":"AK",
    "sg:tags":[
        "mailing",
        "shipping"
    ],
    "sg:website":"www.fedexkinkos.com",
    "wof:name":"Fed Ex",
    "wof:placetype":"venue"
},
  "geometry": {"coordinates":[-147.69817599999999,64.846107],"type":"Point"}
}