{
  "type": "Feature",
  "properties": {
    "iso:country":"US",
    "sg:address":"340 Centaur Ave",
    "sg:city":"Wasilla",
    "sg:classifiers":[
        {
            "category":"Manufacturing",
            "subcategory":"Metals",
            "type":"Manufacturing & Wholesale Goods"
        },
        {
            "category":"Building & Trades",
            "subcategory":"Plumbing",
            "type":"Services"
        }
    ],
    "sg:phone":"+1 907 376 0474",
    "sg:postcode":"99654",
    "sg:province":"AK",
    "sg:tags":[
        "mfg",
        "metalwork",
        "sheet",
        "heating",
        "contractor"
    ],
    "wof:name":"AA-1 Sheet Metal Fabrication",
    "wof:placetype":"venue"
},
  "geometry": {"coordinates":[-149.444014,61.575549],"type":"Point"}
}