{
  "type": "Feature",
  "properties": {
    "iso:country":"US",
    "sg:address":"1665 Howling Dog Trl",
    "sg:city":"Fairbanks",
    "sg:classifiers":[
        {
            "category":"Wholesale",
            "subcategory":"Sporting Goods",
            "type":"Manufacturing & Wholesale Goods"
        }
    ],
    "sg:phone":"+1 907 452 8108",
    "sg:postcode":"99709",
    "sg:province":"AK",
    "wof:name":"V F Grace Inc",
    "wof:placetype":"venue"
},
  "geometry": {"coordinates":[-147.926812,64.934745],"type":"Point"}
}