{
  "type": "Feature",
  "properties": {
    "addr:full":"851 E Parks Hwy Wasilla AK 99654",
    "addr:housenumber":"851",
    "addr:postcode":"99654",
    "addr:street":"E Parks Hwy",
    "iso:country":"US",
    "sg:address":"851 E Parks Hwy",
    "sg:city":"Wasilla",
    "sg:classifiers":[
        {
            "category":"Restaurant",
            "type":"Food & Drink"
        }
    ],
    "sg:phone":"+1 907 373 6600",
    "sg:postcode":"99654",
    "sg:province":"AK",
    "wof:name":"Pizza Hut",
    "wof:placetype":"venue"
},
  "geometry": {"coordinates":[-149.429247,61.580645],"type":"Point"}
}