{
  "type": "Feature",
  "properties": {
    "iso:country":"US",
    "sg:address":"9343 Rivercourt Way",
    "sg:city":"Juneau",
    "sg:classifiers":[
        {
            "category":"Personal",
            "type":"Services"
        }
    ],
    "sg:phone":"+1 907 790 2337",
    "sg:postcode":"99803",
    "sg:province":"AK",
    "sg:tags":[
        "therapist",
        "massage"
    ],
    "wof:name":"Traci K Gilmour",
    "wof:placetype":"venue"
},
  "geometry": {"coordinates":[-134.588221,58.380785],"type":"Point"}
}