{
  "type": "Feature",
  "properties": {
    "iso:country":"US",
    "sg:address":"1201 Hay St",
    "sg:city":"Wasilla",
    "sg:classifiers":[
        {
            "category":"Autos & Motor Vehicles",
            "subcategory":"Automobile Sales",
            "type":"Retail Goods"
        }
    ],
    "sg:phone":"+1 907 279 4462",
    "sg:postcode":"99654",
    "sg:province":"AK",
    "sg:tags":[
        "car",
        "dealer"
    ],
    "wof:name":"Alaska Sales & Svc Inc-Valley",
    "wof:placetype":"venue"
},
  "geometry": {"coordinates":[-149.329699,61.570577],"type":"Point"}
}