{
  "type": "Feature",
  "properties": {
    "iso:country":"US",
    "sg:address":"851 Westpoint Dr",
    "sg:city":"Wasilla",
    "sg:classifiers":[
        {
            "category":"Health Services",
            "subcategory":"Doctor",
            "type":"Services"
        }
    ],
    "sg:phone":"+1 907 357 2800",
    "sg:postcode":"99654",
    "sg:province":"AK",
    "sg:tags":[
        "physician",
        "surgeon"
    ],
    "wof:name":"Valley Dermatology Ctr Inc",
    "wof:placetype":"venue"
},
  "geometry": {"coordinates":[-149.429114,61.582332],"type":"Point"}
}