{
  "type": "Feature",
  "properties": {
    "addr:full":"158 S Binkley St Soldotna AK 99669",
    "addr:housenumber":"158",
    "addr:postcode":"99669",
    "addr:street":"S Binkley St",
    "iso:country":"US",
    "sg:address":"158 S Binkley St",
    "sg:city":"Soldotna",
    "sg:classifiers":[
        {
            "category":"Organizations",
            "subcategory":"Religious Organization",
            "type":"Services"
        }
    ],
    "sg:phone":"+1 907 262 4657",
    "sg:postcode":"99669",
    "sg:province":"AK",
    "sg:tags":[
        "church"
    ],
    "wof:name":"Soldotna United Methodist Chr",
    "wof:placetype":"venue"
},
  "geometry": {"coordinates":[-151.07219900000001,60.485382],"type":"Point"}
}