{
  "type": "Feature",
  "properties": {
    "iso:country":"US",
    "sg:address":"6161 A St",
    "sg:city":"Anchorage",
    "sg:classifiers":[
        {
            "category":"Building & Trades",
            "subcategory":"Construction",
            "type":"Services"
        }
    ],
    "sg:phone":"+1 907 258 4567",
    "sg:postcode":"99518",
    "sg:province":"AK",
    "sg:tags":[
        "general",
        "contractor"
    ],
    "wof:name":"First Alaska Contractors Inc",
    "wof:placetype":"venue"
},
  "geometry": {"coordinates":[-149.881588,61.166388],"type":"Point"}
}