{
  "type": "Feature",
  "properties": {
    "addr:full":"1302 Dolphin Way Fairbanks AK 99709",
    "addr:housenumber":"1302",
    "addr:postcode":"99709",
    "addr:street":"Dolphin Way",
    "iso:country":"US",
    "sg:address":"1302 Dolphin Way",
    "sg:city":"Fairbanks",
    "sg:classifiers":[
        {
            "category":"Professional",
            "subcategory":"Management & Consulting",
            "type":"Services"
        }
    ],
    "sg:phone":"+1 907 457 6457",
    "sg:postcode":"99709",
    "sg:province":"AK",
    "sg:tags":[
        "consultant",
        "mining"
    ],
    "wof:name":"Goldstream Explorations",
    "wof:placetype":"venue"
},
  "geometry": {"coordinates":[-147.92914400000001,64.809456],"type":"Point"}
}