{
  "type": "Feature",
  "properties": {
    "iso:country":"US",
    "sg:address":"46020 Spruce Pl",
    "sg:city":"Kenai",
    "sg:classifiers":[
        {
            "category":"Personal",
            "subcategory":"Beauty Salon",
            "type":"Services"
        }
    ],
    "sg:phone":"+1 907 776 5400",
    "sg:postcode":"99611",
    "sg:province":"AK",
    "wof:name":"Sunset Salon",
    "wof:placetype":"venue"
},
  "geometry": {"coordinates":[-151.347456,60.648018],"type":"Point"}
}