{
  "type": "Feature",
  "properties": {
    "iso:country":"US",
    "sg:address":"1712 Mill Bay Rd",
    "sg:city":"Kodiak",
    "sg:classifiers":[
        {
            "category":"Personal",
            "subcategory":"Beauty Salon",
            "type":"Services"
        }
    ],
    "sg:phone":"+1 907 481 3343",
    "sg:postcode":"99615",
    "sg:province":"AK",
    "wof:name":"Cutting Edge",
    "wof:placetype":"venue"
},
  "geometry": {"coordinates":[-152.38298,57.79943],"type":"Point"}
}