{
  "type": "Feature",
  "properties": {
    "iso:country":"US",
    "sg:address":"424 Marine Way W",
    "sg:city":"Kodiak",
    "sg:classifiers":[
        {
            "category":"Food & Beverages",
            "subcategory":"Liquor & Beverages",
            "type":"Retail Goods"
        }
    ],
    "sg:phone":"+1 907 486 5707",
    "sg:postcode":"99615",
    "sg:province":"AK",
    "wof:name":"Tony's",
    "wof:placetype":"venue"
},
  "geometry": {"coordinates":[-152.407352,57.787916],"type":"Point"}
}