{
  "type": "Feature",
  "properties": {
    "iso:country":"US",
    "sg:address":"2401 Spenard Rd",
    "sg:city":"Anchorage",
    "sg:classifiers":[
        {
            "category":"Food & Beverages",
            "subcategory":"Groceries & Convenience Stores",
            "type":"Retail Goods"
        }
    ],
    "sg:phone":"+1 907 274 3592",
    "sg:postcode":"99503",
    "sg:province":"AK",
    "wof:name":"2 Go Mart-Tesoro Northstore",
    "wof:placetype":"venue"
},
  "geometry": {"coordinates":[-149.908146,61.200547],"type":"Point"}
}