{
  "type": "Feature",
  "properties": {
    "iso:country":"US",
    "sg:address":"733 N Bliss St",
    "sg:city":"Anchorage",
    "sg:classifiers":[
        {
            "category":"Farming",
            "subcategory":"Fish & Marine Products",
            "type":"Manufacturing & Wholesale Goods"
        }
    ],
    "sg:phone":"+1 902 279 0248",
    "sg:postcode":"99508",
    "sg:province":"AK",
    "sg:tags":[
        "catching"
    ],
    "wof:name":"Goosebay Sports Fishing",
    "wof:placetype":"venue"
},
  "geometry": {"coordinates":[-149.795232,61.23106],"type":"Point"}
}