{
  "type": "Feature",
  "properties": {
    "iso:country":"US",
    "sg:address":"12812 Old Glenn Hwy",
    "sg:city":"Eagle River",
    "sg:classifiers":[
        {
            "category":"Shopping",
            "subcategory":"Computers & Home Electronics",
            "type":"Retail Goods"
        }
    ],
    "sg:phone":"+1 907 622 5600",
    "sg:postcode":"99577",
    "sg:province":"AK",
    "sg:tags":[
        "equipment",
        "dealer"
    ],
    "wof:name":"Alaska Computer Hardware",
    "wof:placetype":"venue"
},
  "geometry": {"coordinates":[-149.563516,61.335958],"type":"Point"}
}