{
  "type": "Feature",
  "properties": {
    "addr:full":"800 30th Ave Fairbanks AK 99701",
    "addr:housenumber":"800",
    "addr:postcode":"99701",
    "addr:street":"30Th Ave",
    "iso:country":"US",
    "sg:address":"800 30th Ave",
    "sg:city":"Fairbanks",
    "sg:classifiers":[
        {
            "category":"Building & Trades",
            "subcategory":"Plumbing",
            "type":"Services"
        }
    ],
    "sg:phone":"+1 907 456 7445",
    "sg:postcode":"99701",
    "sg:province":"AK",
    "sg:tags":[
        "contractor"
    ],
    "wof:name":"Pauls Heating Construction Co",
    "wof:placetype":"venue"
},
  "geometry": {"coordinates":[-147.71884299999999,64.820122],"type":"Point"}
}