{
  "type": "Feature",
  "properties": {
    "iso:country":"US",
    "sg:address":"399 Old Richardson Hwy",
    "sg:city":"Fairbanks",
    "sg:classifiers":[
        {
            "category":"Building & Trades",
            "subcategory":"Cleaning & Sanitation",
            "type":"Services"
        }
    ],
    "sg:phone":"+1 907 456 1774",
    "sg:postcode":"99701",
    "sg:province":"AK",
    "sg:tags":[
        "window",
        "janitorial"
    ],
    "wof:name":"Youngs Cleaning Service",
    "wof:placetype":"venue"
},
  "geometry": {"coordinates":[-147.698162,64.819307],"type":"Point"}
}