{
  "type": "Feature",
  "properties": {
    "iso:country":"US",
    "sg:address":"523 W 3rd Ave",
    "sg:city":"Anchorage",
    "sg:classifiers":[
        {
            "category":"Food & Beverages",
            "subcategory":"Bakery",
            "type":"Retail Goods"
        }
    ],
    "sg:phone":"+1 907 929 2253",
    "sg:postcode":"99501",
    "sg:province":"AK",
    "sg:tags":[
        "baker"
    ],
    "wof:name":"Cottage Boutique & Bakery",
    "wof:placetype":"venue"
},
  "geometry": {"coordinates":[-149.89305100000001,61.219613],"type":"Point"}
}