{
  "type": "Feature",
  "properties": {
    "iso:country":"US",
    "sg:address":"397 E Pioneer Ave",
    "sg:city":"Homer",
    "sg:classifiers":[
        {
            "category":"Shopping",
            "type":"Retail Goods"
        }
    ],
    "sg:phone":"+1 907 235 7788",
    "sg:postcode":"99603",
    "sg:province":"AK",
    "sg:tags":[
        "spa",
        "hot",
        "tub"
    ],
    "wof:name":"Big Dipper Spa & Sauna",
    "wof:placetype":"venue"
},
  "geometry": {"coordinates":[-151.53593000000001,59.646677],"type":"Point"}
}