{
  "type": "Feature",
  "properties": {
    "iso:country":"US",
    "sg:address":"3584 E 64th Ave",
    "sg:city":"Anchorage",
    "sg:classifiers":[
        {
            "category":"Manufacturing",
            "subcategory":"Metals",
            "type":"Manufacturing & Wholesale Goods"
        }
    ],
    "sg:phone":"+1 907 349 1659",
    "sg:postcode":"99507",
    "sg:province":"AK",
    "wof:name":"Nancy Gates",
    "wof:placetype":"venue"
},
  "geometry": {"coordinates":[-149.814255,61.162721],"type":"Point"}
}