{
  "type": "Feature",
  "properties": {
    "iso:country":"US",
    "sg:address":"491 E Pioneer Ave",
    "sg:city":"Homer",
    "sg:classifiers":[
        {
            "category":"Government",
            "subcategory":"Office",
            "type":"Public Place"
        }
    ],
    "sg:phone":"+1 907 235 8121",
    "sg:postcode":"99603",
    "sg:province":"AK",
    "sg:tags":[
        "city"
    ],
    "wof:name":"Homer City Hall",
    "wof:placetype":"venue"
},
  "geometry": {"coordinates":[-151.53358499999999,59.647206],"type":"Point"}
}