{
  "type": "Feature",
  "properties": {
    "iso:country":"US",
    "sg:address":"200 Jensen Cir",
    "sg:city":"Wasilla",
    "sg:classifiers":[
        {
            "category":"Building & Trades",
            "subcategory":"Construction",
            "type":"Services"
        }
    ],
    "sg:phone":"+1 907 373 3190",
    "sg:postcode":"99654",
    "sg:province":"AK",
    "sg:tags":[
        "general",
        "contractor"
    ],
    "wof:name":"Affordable Roofing Co",
    "wof:placetype":"venue"
},
  "geometry": {"coordinates":[-149.452474,61.601046],"type":"Point"}
}