{
  "type": "Feature",
  "properties": {
    "iso:country":"US",
    "sg:address":"17034 Eagle River Rd",
    "sg:city":"Eagle River",
    "sg:classifiers":[
        {
            "category":"Building & Trades",
            "subcategory":"Construction",
            "type":"Services"
        }
    ],
    "sg:phone":"+1 907 694 1373",
    "sg:postcode":"99577",
    "sg:province":"AK",
    "sg:tags":[
        "excavation",
        "house",
        "excavating",
        "contractor"
    ],
    "wof:name":"Tweed Excavating & Constr",
    "wof:placetype":"venue"
},
  "geometry": {"coordinates":[-149.568619,61.311792],"type":"Point"}
}