{
  "type": "Feature",
  "properties": {
    "addr:full":"10131 Chandalar St Eagle River AK 99577",
    "addr:housenumber":"10131",
    "addr:postcode":"99577",
    "addr:street":"Chandalar St",
    "iso:country":"US",
    "sg:address":"10131 Chandalar St",
    "sg:city":"Eagle River",
    "sg:classifiers":[
        {
            "category":"Travel",
            "subcategory":"Hotels & Motels",
            "type":"Entertainment"
        }
    ],
    "sg:phone":"+1 907 694 8260",
    "sg:postcode":"99577",
    "sg:province":"AK",
    "sg:tags":[
        "breakfast",
        "accommodation",
        "bed"
    ],
    "wof:name":"Randy's Valley View B & B",
    "wof:placetype":"venue"
},
  "geometry": {"coordinates":[-149.54457600000001,61.313139],"type":"Point"}
}