{
  "type": "Feature",
  "properties": {
    "addr:full":"202 Center St Kodiak AK 99615",
    "addr:housenumber":"202",
    "addr:postcode":"99615",
    "addr:street":"Center St",
    "iso:country":"US",
    "sg:address":"202 Center St",
    "sg:city":"Kodiak",
    "sg:classifiers":[
        {
            "category":"Shopping",
            "subcategory":"Clothing, Apparel, & Fashions",
            "type":"Retail Goods"
        }
    ],
    "sg:phone":"+1 907 486 5100",
    "sg:postcode":"99615",
    "sg:province":"AK",
    "sg:tags":[
        "sportswear"
    ],
    "wof:name":"Bases Loaded",
    "wof:placetype":"venue"
},
  "geometry": {"coordinates":[-152.40646799999999,57.789105],"type":"Point"}
}