{
  "type": "Feature",
  "properties": {
    "addr:full":"4321 Calhoun Ct Homer AK 99603",
    "addr:housenumber":"4321",
    "addr:postcode":"99603",
    "addr:street":"Calhoun Ct",
    "iso:country":"US",
    "sg:address":"4321 Calhoun Ct",
    "sg:city":"Homer",
    "sg:classifiers":[
        {
            "category":"Real Estate",
            "subcategory":"Surveying",
            "type":"Services"
        }
    ],
    "sg:phone":"+1 907 235 7388",
    "sg:postcode":"99603",
    "sg:province":"AK",
    "sg:tags":[
        "surveyor"
    ],
    "wof:name":"Patrick J Church",
    "wof:placetype":"venue"
},
  "geometry": {"coordinates":[-151.540663,59.653012],"type":"Point"}
}