{
  "type": "Feature",
  "properties": {
    "iso:country":"US",
    "sg:address":"35514 Kenai Spur Hwy",
    "sg:city":"Soldotna",
    "sg:classifiers":[
        {
            "category":"Manufacturing",
            "subcategory":"Food",
            "type":"Manufacturing & Wholesale Goods"
        }
    ],
    "sg:phone":"+1 907 262 7370",
    "sg:postcode":"99669",
    "sg:province":"AK",
    "sg:tags":[
        "drink",
        "soft",
        "mfg"
    ],
    "wof:name":"Bills Distributing Inc",
    "wof:placetype":"venue"
},
  "geometry": {"coordinates":[-151.069064,60.494958],"type":"Point"}
}