{
  "type": "Feature",
  "properties": {
    "iso:country":"US",
    "sg:address":"542 4th Ave",
    "sg:city":"Fairbanks",
    "sg:classifiers":[
        {
            "category":"Insurance",
            "subcategory":"Insurance Agent",
            "type":"Services"
        }
    ],
    "sg:phone":"+1 907 452 6633",
    "sg:postcode":"99701",
    "sg:province":"AK",
    "sg:website":"www.primerica.com/jeasaw",
    "wof:name":"Primerica Financial Svc",
    "wof:placetype":"venue"
},
  "geometry": {"coordinates":[-147.719585,64.842422],"type":"Point"}
}