{
  "type": "Feature",
  "properties": {
    "addr:full":"1110 W 8th Ave Anchorage AK 99501",
    "addr:housenumber":"1110",
    "addr:postcode":"99501",
    "addr:street":"W 8Th Ave",
    "iso:country":"US",
    "sg:address":"1110 W 8th Ave",
    "sg:city":"Anchorage",
    "sg:classifiers":[
        {
            "category":"Travel",
            "subcategory":"Hotels & Motels",
            "type":"Entertainment"
        }
    ],
    "sg:phone":"+1 907 222 5005",
    "sg:postcode":"99501",
    "sg:province":"AK",
    "wof:name":"Hawthorn Suites Hotel",
    "wof:placetype":"venue"
},
  "geometry": {"coordinates":[-149.90568999999999,61.214544],"type":"Point"}
}