{
  "type": "Feature",
  "properties": {
    "iso:country":"US",
    "sg:address":"13240 View Heights Way",
    "sg:city":"Anchorage",
    "sg:classifiers":[
        {
            "category":"Building & Trades",
            "subcategory":"Plumbing",
            "type":"Services"
        }
    ],
    "sg:phone":"+1 907 561 9997",
    "sg:postcode":"99516",
    "sg:province":"AK",
    "sg:tags":[
        "mechanical",
        "contractor"
    ],
    "wof:name":"Lewis Mechanical Inc",
    "wof:placetype":"venue"
},
  "geometry": {"coordinates":[-149.71093200000001,61.09983],"type":"Point"}
}