{
  "type": "Feature",
  "properties": {
    "addr:full":"3002 Industrial Ave Fairbanks AK 99701",
    "addr:housenumber":"3002",
    "addr:postcode":"99701",
    "addr:street":"Industrial Ave",
    "iso:country":"US",
    "sg:address":"3002 Industrial Ave",
    "sg:city":"Fairbanks",
    "sg:classifiers":[
        {
            "category":"Organizations",
            "subcategory":"Labor Organization",
            "type":"Services"
        }
    ],
    "sg:phone":"+1 907 452 4799",
    "sg:postcode":"99701",
    "sg:province":"AK",
    "wof:name":"Fairbanks Firefighters",
    "wof:placetype":"venue"
},
  "geometry": {"coordinates":[-147.75533100000001,64.819095],"type":"Point"}
}