{
  "type": "Feature",
  "properties": {
    "iso:country":"US",
    "sg:address":"838 S Colony Way",
    "sg:city":"Palmer",
    "sg:classifiers":[
        {
            "category":"Professional",
            "subcategory":"Accounting & Tax Preparation",
            "type":"Services"
        }
    ],
    "sg:phone":"+1 907 745 3239",
    "sg:postcode":"99645",
    "sg:province":"AK",
    "sg:tags":[
        "accountant"
    ],
    "wof:name":"Charles R Griffin CPA",
    "wof:placetype":"venue"
},
  "geometry": {"coordinates":[-149.114937,61.598792],"type":"Point"}
}