{
  "type": "Feature",
  "properties": {
    "iso:country":"US",
    "sg:address":"900 E 9th Ave",
    "sg:city":"Anchorage",
    "sg:classifiers":[
        {
            "category":"Food & Beverages",
            "subcategory":"Groceries & Convenience Stores",
            "type":"Retail Goods"
        }
    ],
    "sg:phone":"+1 907 753 4298",
    "sg:postcode":"99501",
    "sg:province":"AK",
    "sg:tags":[
        "grocer"
    ],
    "wof:name":"AAFES Cache Groceteria",
    "wof:placetype":"venue"
},
  "geometry": {"coordinates":[-149.864891,61.213618],"type":"Point"}
}