{
  "type": "Feature",
  "properties": {
    "iso:country":"US",
    "sg:address":"102 Gjoa St",
    "sg:city":"Petersburg",
    "sg:classifiers":[
        {
            "category":"Professional",
            "subcategory":"Accounting & Tax Preparation",
            "type":"Services"
        }
    ],
    "sg:phone":"+1 907 772 4632",
    "sg:postcode":"99833",
    "sg:province":"AK",
    "sg:tags":[
        "return",
        "filing"
    ],
    "wof:name":"Leilani Kito",
    "wof:placetype":"venue"
},
  "geometry": {"coordinates":[-132.954872,56.81168],"type":"Point"}
}