{
  "type": "Feature",
  "properties": {
    "iso:country":"US",
    "sg:address":"490 Shahafka Cir",
    "sg:city":"Kodiak",
    "sg:classifiers":[
        {
            "category":"Professional",
            "subcategory":"Secretarial Services",
            "type":"Services"
        }
    ],
    "sg:phone":"+1 907 486 6221",
    "sg:postcode":"99615",
    "sg:province":"AK",
    "sg:tags":[
        "convention",
        "court",
        "reporter"
    ],
    "sg:website":"www.alaskacourtreporter.com",
    "wof:name":"Kodiak Reporting & Transcriptn",
    "wof:placetype":"venue"
},
  "geometry": {"coordinates":[-152.367515,57.81381],"type":"Point"}
}