{
  "type": "Feature",
  "properties": {
    "iso:country":"US",
    "sg:address":"101 Alatna St",
    "sg:city":"Valdez",
    "sg:classifiers":[
        {
            "category":"Travel",
            "subcategory":"Hotels & Motels",
            "type":"Entertainment"
        }
    ],
    "sg:phone":"+1 907 835 2465",
    "sg:postcode":"99686",
    "sg:province":"AK",
    "sg:tags":[
        "breakfast",
        "accommodation",
        "bed"
    ],
    "wof:name":"Ivy Rose Bed & Breakfast",
    "wof:placetype":"venue"
},
  "geometry": {"coordinates":[-146.353849,61.131605],"type":"Point"}
}