{
  "type": "Feature",
  "properties": {
    "iso:country":"US",
    "sg:address":"4332 Spenard Rd",
    "sg:city":"Anchorage",
    "sg:classifiers":[
        {
            "category":"Travel",
            "subcategory":"Hotels & Motels",
            "type":"Entertainment"
        }
    ],
    "sg:phone":"+1 907 243 0533",
    "sg:postcode":"99517",
    "sg:province":"AK",
    "wof:name":"Polar Bear Motel",
    "wof:placetype":"venue"
},
  "geometry": {"coordinates":[-149.93274600000001,61.182159],"type":"Point"}
}