{
  "type": "Feature",
  "properties": {
    "iso:country":"US",
    "sg:address":"509 1st St",
    "sg:city":"Cordova",
    "sg:classifiers":[
        {
            "category":"Professional",
            "type":"Services"
        }
    ],
    "sg:phone":"+1 907 424 7738",
    "sg:postcode":"99574",
    "sg:province":"AK",
    "sg:tags":[
        "information",
        "bureau"
    ],
    "sg:website":"www.nativevillageofeyak.org",
    "wof:name":"Eyak Village",
    "wof:placetype":"venue"
},
  "geometry": {"coordinates":[-145.75851,60.544715],"type":"Point"}
}