{
  "type": "Feature",
  "properties": {
    "addr:full":"12319 Old Glenn Hwy Eagle River AK 99577",
    "addr:housenumber":"12319",
    "addr:postcode":"99577",
    "addr:street":"Old Glenn Hwy",
    "iso:country":"US",
    "sg:address":"12319 Old Glenn Hwy",
    "sg:city":"Eagle River",
    "sg:classifiers":[
        {
            "category":"Building & Trades",
            "subcategory":"Landscaping Services",
            "type":"Services"
        }
    ],
    "sg:phone":"+1 907 696 4769",
    "sg:postcode":"99577",
    "sg:province":"AK",
    "wof:name":"Avant Gardens",
    "wof:placetype":"venue"
},
  "geometry": {"coordinates":[-149.56599800000001,61.331605],"type":"Point"}
}