{
  "type": "Feature",
  "properties": {
    "addr:full":"634 K St Anchorage AK 99501",
    "addr:housenumber":"634",
    "addr:postcode":"99501",
    "addr:street":"K St",
    "iso:country":"US",
    "sg:address":"634 K St",
    "sg:city":"Anchorage",
    "sg:classifiers":[
        {
            "category":"Professional",
            "subcategory":"Lawyer & Legal Services",
            "type":"Services"
        }
    ],
    "sg:phone":"+1 907 276 4747",
    "sg:postcode":"99501",
    "sg:province":"AK",
    "sg:tags":[
        "attorney"
    ],
    "wof:name":"K F Huntington Law Offices",
    "wof:placetype":"venue"
},
  "geometry": {"coordinates":[-149.901726,61.215936],"type":"Point"}
}