{
  "type": "Feature",
  "properties": {
    "iso:country":"US",
    "sg:address":"6607 Mink Ave",
    "sg:city":"Anchorage",
    "sg:classifiers":[
        {
            "category":"Food & Beverages",
            "subcategory":"Meat & Fish",
            "type":"Retail Goods"
        }
    ],
    "sg:phone":"+1 907 770 2588",
    "sg:postcode":"99504",
    "sg:province":"AK",
    "sg:tags":[
        "seafood"
    ],
    "wof:name":"Alaskan Salsa Salmon LLC",
    "wof:placetype":"venue"
},
  "geometry": {"coordinates":[-149.755966,61.209215],"type":"Point"}
}