{
  "type": "Feature",
  "properties": {
    "iso:country":"US",
    "sg:address":"2612 Strawberry Rd",
    "sg:city":"Anchorage",
    "sg:classifiers":[
        {
            "category":"Travel",
            "subcategory":"Travel Agent",
            "type":"Entertainment"
        }
    ],
    "sg:phone":"+1 907 243 6003",
    "sg:postcode":"99502",
    "sg:province":"AK",
    "sg:tags":[
        "agency",
        "bureau"
    ],
    "wof:name":"Willies Travel",
    "wof:placetype":"venue"
},
  "geometry": {"coordinates":[-149.92946499999999,61.15186],"type":"Point"}
}