{
  "type": "Feature",
  "properties": {
    "iso:country":"US",
    "sg:address":"208 N Franklin St",
    "sg:city":"Juneau",
    "sg:classifiers":[
        {
            "category":"Building & Trades",
            "subcategory":"Landscaping Services",
            "type":"Services"
        }
    ],
    "sg:phone":"+1 907 586 4606",
    "sg:postcode":"99801",
    "sg:province":"AK",
    "sg:tags":[
        "landscape",
        "contractor"
    ],
    "wof:name":"J L Sherburne Landscape Dsgns",
    "wof:placetype":"venue"
},
  "geometry": {"coordinates":[-134.40708100000001,58.301448],"type":"Point"}
}