{
  "type": "Feature",
  "properties": {
    "iso:country":"US",
    "sg:address":"711 H St",
    "sg:city":"Anchorage",
    "sg:classifiers":[
        {
            "category":"Wholesale",
            "subcategory":"Electrical",
            "type":"Manufacturing & Wholesale Goods"
        }
    ],
    "sg:phone":"+1 907 279 7554",
    "sg:postcode":"99501",
    "sg:province":"AK",
    "sg:tags":[
        "communication",
        "radio",
        "system"
    ],
    "wof:name":"Information System Support",
    "wof:placetype":"venue"
},
  "geometry": {"coordinates":[-149.897492,61.214716],"type":"Point"}
}