{
  "type": "Feature",
  "properties": {
    "iso:country":"US",
    "sg:address":"301 Lucas Rd",
    "sg:city":"Wasilla",
    "sg:classifiers":[
        {
            "category":"Wholesale",
            "subcategory":"Hardware",
            "type":"Manufacturing & Wholesale Goods"
        }
    ],
    "sg:phone":"+1 907 357 6001",
    "sg:postcode":"99654",
    "sg:province":"AK",
    "sg:tags":[
        "plumbing",
        "fixture",
        "supply"
    ],
    "wof:name":"Pacific Plumbing Supply Co",
    "wof:placetype":"venue"
},
  "geometry": {"coordinates":[-149.48111,61.581357],"type":"Point"}
}