{
  "type": "Feature",
  "properties": {
    "iso:country":"US",
    "sg:address":"400 Gambell St",
    "sg:city":"Anchorage",
    "sg:classifiers":[
        {
            "category":"Professional",
            "subcategory":"Employment Agencies",
            "type":"Services"
        }
    ],
    "sg:phone":"+1 907 269 6414",
    "sg:postcode":"99501",
    "sg:province":"AK",
    "sg:tags":[
        "opportunity"
    ],
    "wof:name":"Alaska Job Ctr Network",
    "wof:placetype":"venue"
},
  "geometry": {"coordinates":[-149.871012,61.217563],"type":"Point"}
}