{
  "type": "Feature",
  "properties": {
    "iso:country":"US",
    "sg:address":"3202 Industrial Ave",
    "sg:city":"Fairbanks",
    "sg:classifiers":[
        {
            "category":"Building & Trades",
            "subcategory":"Electrical",
            "type":"Services"
        }
    ],
    "sg:phone":"+1 907 374 1605",
    "sg:postcode":"99701",
    "sg:province":"AK",
    "sg:tags":[
        "electric",
        "contractor"
    ],
    "wof:name":"Aurora Electric Data Tel",
    "wof:placetype":"venue"
},
  "geometry": {"coordinates":[-147.755371,64.820149],"type":"Point"}
}