{
  "type": "Feature",
  "properties": {
    "iso:country":"US",
    "sg:address":"260 S Willow St",
    "sg:city":"Kenai",
    "sg:classifiers":[
        {
            "category":"Travel",
            "subcategory":"Hotels & Motels",
            "type":"Entertainment"
        }
    ],
    "sg:phone":"+1 907 283 6131",
    "sg:postcode":"99611",
    "sg:province":"AK",
    "sg:website":"www.kenaimeritinn.com",
    "wof:name":"Kenai Merit Inn",
    "wof:placetype":"venue"
},
  "geometry": {"coordinates":[-151.25144,60.556546],"type":"Point"}
}