{
  "type": "Feature",
  "properties": {
    "addr:full":"5751 Mayflower Ct Wasilla AK 99654",
    "addr:housenumber":"5751",
    "addr:postcode":"99654",
    "addr:street":"Mayflower Ct",
    "iso:country":"US",
    "sg:address":"5751 Mayflower Ct",
    "sg:city":"Wasilla",
    "sg:classifiers":[
        {
            "category":"Manufacturing",
            "subcategory":"Printing",
            "type":"Manufacturing & Wholesale Goods"
        }
    ],
    "sg:phone":"+1 907 352 2250",
    "sg:postcode":"99654",
    "sg:province":"AK",
    "sg:tags":[
        "newspaper",
        "publishing"
    ],
    "sg:website":"www.frontiersman.com",
    "wof:name":"Frontiersman",
    "wof:placetype":"venue"
},
  "geometry": {"coordinates":[-149.30230700000001,61.587825],"type":"Point"}
}