{
  "type": "Feature",
  "properties": {
    "iso:country":"US",
    "sg:address":"9309 Glacier Hwy",
    "sg:city":"Juneau",
    "sg:classifiers":[
        {
            "category":"Banks & Credit Unions",
            "subcategory":"Investment Brokerage",
            "type":"Services"
        }
    ],
    "sg:phone":"+1 907 789 4688",
    "sg:postcode":"99801",
    "sg:province":"AK",
    "sg:tags":[
        "security"
    ],
    "wof:name":"Edward Jones Co",
    "wof:placetype":"venue"
},
  "geometry": {"coordinates":[-134.588089,58.364084],"type":"Point"}
}