{
  "type": "Feature",
  "properties": {
    "addr:full":"336 3rd Ave Seward AK 99664",
    "addr:housenumber":"336",
    "addr:postcode":"99664",
    "addr:street":"3Rd Ave",
    "iso:country":"US",
    "sg:address":"336 3rd Ave",
    "sg:city":"Seward",
    "sg:classifiers":[
        {
            "category":"Museum",
            "type":"Entertainment"
        }
    ],
    "sg:phone":"+1 907 224 3902",
    "sg:postcode":"99664",
    "sg:province":"AK",
    "wof:name":"Seward Museum",
    "wof:placetype":"venue"
},
  "geometry": {"coordinates":[-149.44201799999999,60.103915],"type":"Point"}
}