{
  "type": "Feature",
  "properties": {
    "iso:country":"US",
    "sg:address":"246 Illinois St",
    "sg:city":"Fairbanks",
    "sg:classifiers":[
        {
            "category":"Personal",
            "subcategory":"Barber",
            "type":"Services"
        }
    ],
    "sg:phone":"+1 907 458 8171",
    "sg:postcode":"99701",
    "sg:province":"AK",
    "wof:name":"J D Styles",
    "wof:placetype":"venue"
},
  "geometry": {"coordinates":[-147.720669,64.848232],"type":"Point"}
}