{
  "type": "Feature",
  "properties": {
    "iso:country":"US",
    "sg:address":"809 S Chugach St",
    "sg:city":"Palmer",
    "sg:classifiers":[
        {
            "category":"Government",
            "subcategory":"Office",
            "type":"Public Place"
        }
    ],
    "sg:phone":"+1 907 745 4272",
    "sg:postcode":"99645",
    "sg:province":"AK",
    "wof:name":"National Agricultural Sttstcs",
    "wof:placetype":"venue"
},
  "geometry": {"coordinates":[-149.110602,61.597033],"type":"Point"}
}