{
  "type": "Feature",
  "properties": {
    "iso:country":"US",
    "sg:address":"510 Water St",
    "sg:city":"Craig",
    "sg:classifiers":[
        {
            "category":"Restaurant",
            "type":"Food & Drink"
        }
    ],
    "sg:phone":"+1 907 826 2303",
    "sg:postcode":"99901",
    "sg:province":"AK",
    "wof:name":"Baitbox",
    "wof:placetype":"venue"
},
  "geometry": {"coordinates":[-131.650596,55.343584],"type":"Point"}
}