{
  "type": "Feature",
  "properties": {
    "iso:country":"US",
    "sg:address":"231 Lincoln St",
    "sg:city":"Sitka",
    "sg:classifiers":[
        {
            "category":"Shopping",
            "subcategory":"Crafts & Fabrics",
            "type":"Retail Goods"
        }
    ],
    "sg:phone":"+1 907 747 3510",
    "sg:postcode":"99835",
    "sg:province":"AK",
    "sg:tags":[
        "shop"
    ],
    "wof:name":"Abby's Reflection Apparel",
    "wof:placetype":"venue"
},
  "geometry": {"coordinates":[-135.33623,57.050806],"type":"Point"}
}