{
  "type": "Feature",
  "properties": {
    "iso:country":"US",
    "sg:address":"2611 Pago Pago Ave",
    "sg:city":"Anchorage",
    "sg:classifiers":[
        {
            "category":"Real Estate",
            "subcategory":"Real Estate Operator",
            "type":"Services"
        }
    ],
    "sg:phone":"+1 907 563 3382",
    "sg:postcode":"99507",
    "sg:province":"AK",
    "sg:tags":[
        "mobile",
        "home",
        "community"
    ],
    "wof:name":"Manoogs Isle Mobile Home Park",
    "wof:placetype":"venue"
},
  "geometry": {"coordinates":[-149.83139800000001,61.168768],"type":"Point"}
}