{
  "type": "Feature",
  "properties": {
    "addr:full":"329 E 5th Ave Anchorage AK 99501",
    "addr:housenumber":"329",
    "addr:postcode":"99501",
    "addr:street":"E 5Th Ave",
    "iso:country":"US",
    "sg:address":"329 E 5th Ave",
    "sg:city":"Anchorage",
    "sg:classifiers":[
        {
            "category":"Shopping",
            "subcategory":"Books",
            "type":"Retail Goods"
        }
    ],
    "sg:phone":"+1 907 274 5850",
    "sg:postcode":"99501",
    "sg:province":"AK",
    "sg:tags":[
        "dealer"
    ],
    "wof:name":"Source Metaphysical Book Store",
    "wof:placetype":"venue"
},
  "geometry": {"coordinates":[-149.877635,61.217641],"type":"Point"}
}