{
  "type": "Feature",
  "properties": {
    "iso:country":"US",
    "sg:address":"11910 Devonshire Cir",
    "sg:city":"Anchorage",
    "sg:classifiers":[
        {
            "category":"Personal",
            "type":"Services"
        }
    ],
    "sg:phone":"+1 907 929 2293",
    "sg:postcode":"99516",
    "sg:province":"AK",
    "sg:tags":[
        "therapist",
        "massage"
    ],
    "wof:name":"Hands For Health",
    "wof:placetype":"venue"
},
  "geometry": {"coordinates":[-149.83279999999999,61.11324],"type":"Point"}
}