{
  "type": "Feature",
  "properties": {
    "addr:full":"35618 Kenai Spur Hwy Soldotna AK 99669",
    "addr:postcode":"35618;99669",
    "addr:street":"Kenai Spur Hwy",
    "iso:country":"US",
    "sg:address":"35618 Kenai Spur Hwy",
    "sg:city":"Soldotna",
    "sg:classifiers":[
        {
            "category":"Manufacturing",
            "subcategory":"Retail Goods",
            "type":"Manufacturing & Wholesale Goods"
        },
        {
            "category":"Restaurant",
            "type":"Food & Drink"
        }
    ],
    "sg:phone":"+1 907 260 7674",
    "sg:postcode":"99669",
    "sg:province":"AK",
    "sg:tags":[
        "shop",
        "coffee",
        "eating",
        "product",
        "mfg"
    ],
    "wof:name":"Grind",
    "wof:placetype":"venue"
},
  "geometry": {"coordinates":[-151.070065,60.495939],"type":"Point"}
}