{
  "type": "Feature",
  "properties": {
    "addr:full":"6415 Arctic Blvd Anchorage AK 99518",
    "addr:housenumber":"6415",
    "addr:postcode":"99518",
    "addr:street":"Arctic Blvd",
    "iso:country":"US",
    "sg:address":"6415 Arctic Blvd",
    "sg:city":"Anchorage",
    "sg:phone":"+1 907 562 2080",
    "sg:postcode":"99518",
    "sg:province":"AK",
    "sg:tags":[
        "bulk",
        "gas"
    ],
    "sg:website":"www.airliquide.com",
    "wof:name":"Air Liquide America Corp",
    "wof:placetype":"venue"
},
  "geometry": {"coordinates":[-149.89204000000001,61.161198],"type":"Point"}
}