{
  "type": "Feature",
  "properties": {
    "addr:full":"3788 University Ave S Fairbanks AK 99709",
    "addr:housenumber":"3788",
    "addr:postcode":"99709",
    "addr:street":"University Ave S",
    "iso:country":"US",
    "sg:address":"3788 University Ave S",
    "sg:city":"Fairbanks",
    "sg:classifiers":[
        {
            "category":"Airline",
            "type":"Transportation"
        }
    ],
    "sg:phone":"+1 907 457 8359",
    "sg:postcode":"99709",
    "sg:province":"AK",
    "sg:tags":[
        "company"
    ],
    "wof:name":"Bellair Inc",
    "wof:placetype":"venue"
},
  "geometry": {"coordinates":[-147.84574499999999,64.812296],"type":"Point"}
}