{
  "type": "Feature",
  "properties": {
    "iso:country":"US",
    "sg:address":"4667 Homer Spit Rd",
    "sg:city":"Homer",
    "sg:classifiers":[
        {
            "category":"Ferry",
            "type":"Transportation"
        }
    ],
    "sg:phone":"+1 907 235 7099",
    "sg:postcode":"99603",
    "sg:province":"AK",
    "sg:website":"www.akmhs.com",
    "wof:name":"Alaska Ferry Adventures",
    "wof:placetype":"venue"
},
  "geometry": {"coordinates":[-151.41776999999999,59.600731],"type":"Point"}
}