{
  "type": "Feature",
  "properties": {
    "addr:full":"13506 Mainsail Dr Anchorage AK 99516",
    "addr:housenumber":"13506",
    "addr:postcode":"99516",
    "addr:street":"Mainsail Dr",
    "iso:country":"US",
    "sg:address":"13506 Mainsail Dr",
    "sg:city":"Anchorage",
    "sg:classifiers":[
        {
            "category":"Manufacturing",
            "subcategory":"Tools & Machinery",
            "type":"Manufacturing & Wholesale Goods"
        }
    ],
    "sg:phone":"+1 907 336 6334",
    "sg:postcode":"99516",
    "sg:province":"AK",
    "sg:tags":[
        "equipment",
        "calculating",
        "mfg"
    ],
    "wof:name":"R L Martin & Associates",
    "wof:placetype":"venue"
},
  "geometry": {"coordinates":[-149.81726699999999,61.099543],"type":"Point"}
}