{
  "type": "Feature",
  "properties": {
    "iso:country":"US",
    "sg:address":"784 Old Richardson Hwy",
    "sg:city":"Fairbanks",
    "sg:classifiers":[
        {
            "category":"Manufacturing",
            "subcategory":"Tools & Machinery",
            "type":"Manufacturing & Wholesale Goods"
        }
    ],
    "sg:phone":"+1 907 452 4538",
    "sg:postcode":"99701",
    "sg:province":"AK",
    "sg:tags":[
        "bit"
    ],
    "wof:name":"Skidmore Machine & Tool Co",
    "wof:placetype":"venue"
},
  "geometry": {"coordinates":[-147.67918,64.818213],"type":"Point"}
}