{
  "type": "Feature",
  "properties": {
    "iso:country":"US",
    "sg:address":"102 Center St",
    "sg:city":"Kodiak",
    "sg:classifiers":[
        {
            "category":"Arts & Performance",
            "subcategory":"Theater",
            "type":"Entertainment"
        }
    ],
    "sg:phone":"+1 907 486 5449",
    "sg:postcode":"99615",
    "sg:province":"AK",
    "wof:name":"Orpheum Theatre",
    "wof:placetype":"venue"
},
  "geometry": {"coordinates":[-152.40714700000001,57.78986],"type":"Point"}
}