{
  "type": "Feature",
  "properties": {
    "iso:country":"US",
    "sg:address":"3211 Coles Rd",
    "sg:city":"Wasilla",
    "sg:classifiers":[
        {
            "category":"Building & Trades",
            "subcategory":"Equipment Rental",
            "type":"Services"
        }
    ],
    "sg:phone":"+1 907 376 8981",
    "sg:postcode":"99654",
    "sg:province":"AK",
    "sg:tags":[
        "yard"
    ],
    "wof:name":"Baldy Mountain Rental",
    "wof:placetype":"venue"
},
  "geometry": {"coordinates":[-149.394867,61.664633],"type":"Point"}
}