{
  "type": "Feature",
  "properties": {
    "iso:country":"US",
    "sg:address":"139 Warehouse Dr",
    "sg:city":"Soldotna",
    "sg:classifiers":[
        {
            "category":"Recreation",
            "type":"Entertainment"
        }
    ],
    "sg:phone":"+1 907 260 6100",
    "sg:postcode":"99669",
    "sg:province":"AK",
    "sg:tags":[
        "punch",
        "boards"
    ],
    "wof:name":"River City Pull Tabs",
    "wof:placetype":"venue"
},
  "geometry": {"coordinates":[-151.07494800000001,60.481352],"type":"Point"}
}