{
  "type": "Feature",
  "properties": {
    "iso:country":"US",
    "sg:address":"6839 Jewel Lake Rd",
    "sg:city":"Anchorage",
    "sg:classifiers":[
        {
            "category":"Restaurant",
            "type":"Food & Drink"
        }
    ],
    "sg:phone":"+1 907 248 9404",
    "sg:postcode":"99502",
    "sg:province":"AK",
    "sg:website":"www.unclejoespizzeria.com",
    "wof:name":"Uncle Joe's Pizzeria",
    "wof:placetype":"venue"
},
  "geometry": {"coordinates":[-149.95183499999999,61.156507],"type":"Point"}
}