{
  "type": "Feature",
  "properties": {
    "iso:country":"US",
    "sg:address":"475 Agate Ln",
    "sg:city":"Wasilla",
    "sg:classifiers":[
        {
            "category":"Retail",
            "subcategory":"Repair Shop",
            "type":"Services"
        }
    ],
    "sg:phone":"+1 907 376 3193",
    "sg:postcode":"99654",
    "sg:province":"AK",
    "sg:tags":[
        "refinishing",
        "furniture"
    ],
    "wof:name":"Furniture Medic",
    "wof:placetype":"venue"
},
  "geometry": {"coordinates":[-149.439493,61.608626],"type":"Point"}
}