{
  "type": "Feature",
  "properties": {
    "iso:country":"US",
    "sg:address":"425 G St",
    "sg:city":"Anchorage",
    "sg:classifiers":[
        {
            "category":"Real Estate",
            "subcategory":"Real Estate Agent",
            "type":"Services"
        }
    ],
    "sg:phone":"+1 907 272 2121",
    "sg:postcode":"99501",
    "sg:province":"AK",
    "sg:website":"www.landinalaska.com",
    "wof:name":"Statewide Real Estate Svc",
    "wof:placetype":"venue"
},
  "geometry": {"coordinates":[-149.89546200000001,61.217809],"type":"Point"}
}