{
  "type": "Feature",
  "properties": {
    "iso:country":"US",
    "sg:address":"301 N Franklin St",
    "sg:city":"Juneau",
    "sg:classifiers":[
        {
            "category":"Banks & Credit Unions",
            "subcategory":"Bank",
            "type":"Services"
        }
    ],
    "sg:phone":"+1 907 586 1010",
    "sg:postcode":"99801",
    "sg:province":"AK",
    "wof:name":"Alaska Pacific Bank",
    "wof:placetype":"venue"
},
  "geometry": {"coordinates":[-134.407802,58.301939],"type":"Point"}
}