{
  "type": "Feature",
  "properties": {
    "iso:country":"US",
    "sg:address":"13700 E Jensen Ave",
    "sg:city":"Palmer",
    "sg:classifiers":[
        {
            "category":"Social Services",
            "type":"Services"
        }
    ],
    "sg:phone":"+1 907 746 2037",
    "sg:postcode":"99645",
    "sg:province":"AK",
    "sg:tags":[
        "organization",
        "welfare"
    ],
    "wof:name":"Care Connections",
    "wof:placetype":"venue"
},
  "geometry": {"coordinates":[-149.10569000000001,61.664382],"type":"Point"}
}