{
  "type": "Feature",
  "properties": {
    "iso:country":"US",
    "sg:address":"42295 Continental Way",
    "sg:city":"Soldotna",
    "sg:classifiers":[
        {
            "category":"Social Services",
            "subcategory":"Child Care",
            "type":"Services"
        }
    ],
    "sg:phone":"+1 907 260 3821",
    "sg:postcode":"99669",
    "sg:province":"AK",
    "wof:name":"Kiddy Campus",
    "wof:placetype":"venue"
},
  "geometry": {"coordinates":[-151.008232,60.511468],"type":"Point"}
}