{
  "type": "Feature",
  "properties": {
    "addr:full":"54955 Tachatna Ave Kenai AK 99611",
    "addr:postcode":"54955;99611",
    "addr:street":"Tachatna Ave",
    "iso:country":"US",
    "sg:address":"54955 Tachatna Ave",
    "sg:city":"Kenai",
    "sg:classifiers":[
        {
            "category":"Manufacturing",
            "subcategory":"Tools & Machinery",
            "type":"Manufacturing & Wholesale Goods"
        }
    ],
    "sg:phone":"+1 907 776 5166",
    "sg:postcode":"99611",
    "sg:province":"AK",
    "sg:tags":[
        "machine",
        "shop"
    ],
    "wof:name":"Cook Inlet Machine Works",
    "wof:placetype":"venue"
},
  "geometry": {"coordinates":[-151.379491,60.702548],"type":"Point"}
}