{
  "type": "Feature",
  "properties": {
    "addr:full":"4820 Klondike Ave Anchorage AK 99508",
    "addr:housenumber":"4820",
    "addr:postcode":"99508",
    "addr:street":"Klondike Ave",
    "iso:country":"US",
    "sg:address":"4820 Klondike Ave",
    "sg:city":"Anchorage",
    "sg:classifiers":[
        {
            "category":"Retail",
            "subcategory":"Repair Shop",
            "type":"Services"
        }
    ],
    "sg:phone":"+1 907 338 5153",
    "sg:postcode":"99508",
    "sg:province":"AK",
    "sg:tags":[
        "taxidermist"
    ],
    "sg:website":"www.talltalestaxidermy.com",
    "wof:name":"Tall Tales Taxidermy",
    "wof:placetype":"venue"
},
  "geometry": {"coordinates":[-149.79116300000001,61.219131],"type":"Point"}
}