{
  "type": "Feature",
  "properties": {
    "iso:country":"US",
    "sg:address":"3107 Willow St",
    "sg:city":"Anchorage",
    "sg:classifiers":[
        {
            "category":"Building & Trades",
            "subcategory":"Landscaping Services",
            "type":"Services"
        }
    ],
    "sg:phone":"+1 907 277 3135",
    "sg:postcode":"99517",
    "sg:province":"AK",
    "wof:name":"Pioneer Services",
    "wof:placetype":"venue"
},
  "geometry": {"coordinates":[-149.92422,61.191696],"type":"Point"}
}