{
  "type": "Feature",
  "properties": {
    "addr:full":"5600 Craig Dr Anchorage AK 99504",
    "addr:housenumber":"5600",
    "addr:postcode":"99504",
    "addr:street":"Craig Dr",
    "iso:country":"US",
    "sg:address":"5600 Craig Dr",
    "sg:city":"Anchorage",
    "sg:classifiers":[
        {
            "category":"Retail",
            "subcategory":"Repair Shop",
            "type":"Services"
        }
    ],
    "sg:phone":"+1 907 333 8012",
    "sg:postcode":"99504",
    "sg:province":"AK",
    "sg:tags":[
        "television",
        "radio"
    ],
    "wof:name":"G T Electronics",
    "wof:placetype":"venue"
},
  "geometry": {"coordinates":[-149.77623,61.202849],"type":"Point"}
}