{
  "type": "Feature",
  "properties": {
    "addr:full":"40220 Caroline Rd Homer AK 99603",
    "addr:housenumber":"40220",
    "addr:postcode":"99603",
    "addr:street":"Caroline Rd",
    "iso:country":"US",
    "sg:address":"40220 Caroline Rd",
    "sg:city":"Homer",
    "sg:classifiers":[
        {
            "category":"Recreation",
            "type":"Entertainment"
        }
    ],
    "sg:phone":"+1 907 235 2843",
    "sg:postcode":"99603",
    "sg:province":"AK",
    "sg:tags":[
        "amusement"
    ],
    "wof:name":"M & J Racing",
    "wof:placetype":"venue"
},
  "geometry": {"coordinates":[-151.374743,59.687614],"type":"Point"}
}