{
  "type": "Feature",
  "properties": {
    "addr:full":"418 Park St Juneau AK 99801",
    "addr:housenumber":"418",
    "addr:postcode":"99801",
    "addr:street":"Park St",
    "iso:country":"US",
    "sg:address":"418 Park St",
    "sg:city":"Juneau",
    "sg:classifiers":[
        {
            "category":"Shopping",
            "subcategory":"Gifts & Souvenirs",
            "type":"Retail Goods"
        }
    ],
    "sg:phone":"+1 907 463 2543",
    "sg:postcode":"99801",
    "sg:province":"AK",
    "sg:tags":[
        "shop"
    ],
    "wof:name":"Uncle Artie's Gifts",
    "wof:placetype":"venue"
},
  "geometry": {"coordinates":[-134.403526,58.30404],"type":"Point"}
}