{
  "type": "Feature",
  "properties": {
    "iso:country":"US",
    "sg:address":"2626 Abbott Rd",
    "sg:city":"Anchorage",
    "sg:classifiers":[
        {
            "category":"Organizations",
            "subcategory":"Religious Organization",
            "type":"Services"
        }
    ],
    "sg:phone":"+1 907 349 9641",
    "sg:postcode":"99507",
    "sg:province":"AK",
    "sg:tags":[
        "church"
    ],
    "sg:website":"www.abbottloop.org",
    "wof:name":"Abbott Loop Community Church",
    "wof:placetype":"venue"
},
  "geometry": {"coordinates":[-149.82697200000001,61.137447],"type":"Point"}
}