{
  "type": "Feature",
  "properties": {
    "iso:country":"US",
    "sg:address":"923 6th Ave",
    "sg:city":"Bethel",
    "sg:classifiers":[
        {
            "category":"Travel",
            "subcategory":"Hotels & Motels",
            "type":"Entertainment"
        }
    ],
    "sg:phone":"+1 907 543 4334",
    "sg:postcode":"99559",
    "sg:province":"AK",
    "sg:tags":[
        "breakfast",
        "accommodation",
        "bed"
    ],
    "wof:name":"Brown Slough Bed & Breakfast",
    "wof:placetype":"venue"
},
  "geometry": {"coordinates":[-161.75958600000001,60.798953],"type":"Point"}
}