{
  "type": "Feature",
  "properties": {
    "addr:full":"23450 Big Sky Dr Chugiak AK 99567",
    "addr:housenumber":"23450",
    "addr:postcode":"99567",
    "addr:street":"Big Sky Dr",
    "iso:country":"US",
    "sg:address":"23450 Big Sky Dr",
    "sg:city":"Chugiak",
    "sg:classifiers":[
        {
            "category":"Shopping",
            "subcategory":"Bicycles & Sporting Goods",
            "type":"Retail Goods"
        }
    ],
    "sg:phone":"+1 907 688 0366",
    "sg:postcode":"99567",
    "sg:province":"AK",
    "sg:tags":[
        "saddlery",
        "harness"
    ],
    "wof:name":"Diamond 'D' Custom Leather",
    "wof:placetype":"venue"
},
  "geometry": {"coordinates":[-149.44434000000001,61.401696],"type":"Point"}
}