{
  "type": "Feature",
  "properties": {
    "iso:country":"US",
    "sg:address":"6721 Round Tree Dr",
    "sg:city":"Anchorage",
    "sg:classifiers":[
        {
            "category":"Mining & Drilling",
            "type":"Manufacturing & Wholesale Goods"
        }
    ],
    "sg:phone":"+1 907 346 4090",
    "sg:postcode":"99507",
    "sg:province":"AK",
    "sg:tags":[
        "field"
    ],
    "wof:name":"Irf Group Inc",
    "wof:placetype":"venue"
},
  "geometry": {"coordinates":[-149.758393,61.1265],"type":"Point"}
}