{
  "type": "Feature",
  "properties": {
    "iso:country":"US",
    "sg:address":"3130 E Gislason Dr",
    "sg:city":"Wasilla",
    "sg:classifiers":[
        {
            "category":"Building & Trades",
            "subcategory":"Construction",
            "type":"Services"
        }
    ],
    "sg:phone":"+1 907 373 7442",
    "sg:postcode":"99654",
    "sg:province":"AK",
    "sg:tags":[
        "maker",
        "cabinet"
    ],
    "wof:name":"Alaska Good Time Charters",
    "wof:placetype":"venue"
},
  "geometry": {"coordinates":[-149.369837,61.5488],"type":"Point"}
}