{
  "type": "Feature",
  "properties": {
    "iso:country":"US",
    "sg:address":"8405 Nugget Dr",
    "sg:city":"Juneau",
    "sg:classifiers":[
        {
            "category":"Farming",
            "subcategory":"Fish & Marine Products",
            "type":"Manufacturing & Wholesale Goods"
        }
    ],
    "sg:phone":"+1 907 321 1857",
    "sg:postcode":"99801",
    "sg:province":"AK",
    "sg:tags":[
        "fishing"
    ],
    "wof:name":"Connie M F/V",
    "wof:placetype":"venue"
},
  "geometry": {"coordinates":[-134.563841,58.388749],"type":"Point"}
}