{
  "type": "Feature",
  "properties": {
    "iso:country":"US",
    "sg:address":"1015 W 7th Ave",
    "sg:city":"Anchorage",
    "sg:classifiers":[
        {
            "category":"Professional",
            "subcategory":"Lawyer & Legal Services",
            "type":"Services"
        }
    ],
    "sg:phone":"+1 907 272 6434",
    "sg:postcode":"99501",
    "sg:province":"AK",
    "sg:tags":[
        "attorney"
    ],
    "wof:name":"Randall W Patterson Law Office",
    "wof:placetype":"venue"
},
  "geometry": {"coordinates":[-149.903606,61.215675],"type":"Point"}
}