{
  "type": "Feature",
  "properties": {
    "iso:country":"US",
    "sg:address":"1254 Queens Way",
    "sg:city":"Fairbanks",
    "sg:classifiers":[
        {
            "category":"Retail",
            "subcategory":"Car Wash",
            "type":"Services"
        }
    ],
    "sg:phone":"+1 907 457 2930",
    "sg:postcode":"99701",
    "sg:province":"AK",
    "sg:tags":[
        "automobile",
        "detail",
        "clean"
    ],
    "wof:name":"Image Auto Detailing",
    "wof:placetype":"venue"
},
  "geometry": {"coordinates":[-147.731598,64.809474],"type":"Point"}
}