{
  "type": "Feature",
  "properties": {
    "addr:full":"1254 Queens Way Fairbanks AK 99701",
    "addr:housenumber":"1254",
    "addr:postcode":"99701",
    "addr:street":"Queens Way",
    "iso:country":"US",
    "sg:address":"1254 Queens Way",
    "sg:city":"Fairbanks",
    "sg:classifiers":[
        {
            "category":"Retail",
            "subcategory":"Car Wash",
            "type":"Services"
        }
    ],
    "sg:phone":"+1 907 457 2930",
    "sg:postcode":"99701",
    "sg:province":"AK",
    "sg:tags":[
        "automobile",
        "detail",
        "clean"
    ],
    "wof:name":"Image Auto Detailing",
    "wof:placetype":"venue"
},
  "geometry": {"coordinates":[-147.73159799999999,64.80947399999999],"type":"Point"}
}