{
  "type": "Feature",
  "properties": {
    "iso:country":"US",
    "sg:address":"3483 E 20th Ave",
    "sg:city":"Anchorage",
    "sg:classifiers":[
        {
            "category":"Professional",
            "subcategory":"Accounting & Tax Preparation",
            "type":"Services"
        }
    ],
    "sg:phone":"+1 907 277 4575",
    "sg:postcode":"99508",
    "sg:province":"AK",
    "sg:tags":[
        "bookkeeping",
        "general"
    ],
    "wof:name":"Kelly Bookkeeping Svc",
    "wof:placetype":"venue"
},
  "geometry": {"coordinates":[-149.815911,61.202572],"type":"Point"}
}