{
  "type": "Feature",
  "properties": {
    "iso:country":"US",
    "sg:address":"1142 E 71st Ave",
    "sg:city":"Anchorage",
    "sg:classifiers":[
        {
            "category":"Manufacturing",
            "subcategory":"Petroleum Products",
            "type":"Manufacturing & Wholesale Goods"
        }
    ],
    "sg:phone":"+1 907 344 2121",
    "sg:postcode":"99518",
    "sg:province":"AK",
    "sg:tags":[
        "roads"
    ],
    "wof:name":"Anderson Blading & Cnstr",
    "wof:placetype":"venue"
},
  "geometry": {"coordinates":[-149.861978,61.155916],"type":"Point"}
}