{
  "type": "Feature",
  "properties": {
    "iso:country":"US",
    "sg:address":"12836 Old Glenn Hwy",
    "sg:city":"Eagle River",
    "sg:classifiers":[
        {
            "category":"Organizations",
            "subcategory":"Religious Organization",
            "type":"Services"
        }
    ],
    "sg:phone":"+1 907 694 5753",
    "sg:postcode":"99577",
    "sg:province":"AK",
    "sg:tags":[
        "church"
    ],
    "sg:website":"www.er-pc.org",
    "wof:name":"Eagle River Presbyterian Chr",
    "wof:placetype":"venue"
},
  "geometry": {"coordinates":[-149.56328999999999,61.336493],"type":"Point"}
}