{
  "type": "Feature",
  "properties": {
    "addr:full":"1600 Craig-Klawock Hwy Craig AK 99921",
    "addr:housenumber":"1600",
    "addr:postcode":"99921",
    "addr:street":"Craig-Klawock Hwy",
    "iso:country":"US",
    "sg:address":"1600 Craig-Klawock Hwy",
    "sg:city":"Craig",
    "sg:classifiers":[
        {
            "category":"Manufacturing",
            "subcategory":"Watercraft",
            "type":"Manufacturing & Wholesale Goods"
        }
    ],
    "sg:phone":"+1 907 826 3419",
    "sg:postcode":"99921",
    "sg:province":"AK",
    "sg:tags":[
        "barge"
    ],
    "wof:name":"Alaska Marine Lines",
    "wof:placetype":"venue"
},
  "geometry": {"coordinates":[-133.140085,55.476845],"type":"Point"}
}