{
  "type": "Feature",
  "properties": {
    "iso:country":"US",
    "sg:address":"251 W Swanson Ave",
    "sg:city":"Wasilla",
    "sg:classifiers":[
        {
            "category":"Arts & Performance",
            "subcategory":"Theater",
            "type":"Entertainment"
        }
    ],
    "sg:phone":"+1 907 373 9500",
    "sg:postcode":"99654",
    "sg:province":"AK",
    "wof:name":"Valley Performing Arts",
    "wof:placetype":"venue"
},
  "geometry": {"coordinates":[-149.45912300000001,61.582829],"type":"Point"}
}