{
  "type": "Feature",
  "properties": {
    "iso:country":"US",
    "sg:address":"8840 Golovin St",
    "sg:city":"Anchorage",
    "sg:classifiers":[
        {
            "category":"Building & Trades",
            "subcategory":"Cleaning & Sanitation",
            "type":"Services"
        }
    ],
    "sg:phone":"+1 907 522 5221",
    "sg:postcode":"99507",
    "sg:province":"AK",
    "sg:tags":[
        "janitor"
    ],
    "wof:name":"Alaska's Heaven Scent",
    "wof:placetype":"venue"
},
  "geometry": {"coordinates":[-149.837932,61.137884],"type":"Point"}
}