{
  "type": "Feature",
  "properties": {
    "addr:full":"11417 Market St Eagle River AK 99577",
    "addr:housenumber":"11417",
    "addr:postcode":"99577",
    "addr:street":"Market St",
    "iso:country":"US",
    "sg:address":"11417 Market St",
    "sg:city":"Eagle River",
    "sg:classifiers":[
        {
            "category":"Retail",
            "subcategory":"Repair Shop",
            "type":"Services"
        }
    ],
    "sg:phone":"+1 907 694 7176",
    "sg:postcode":"99577",
    "sg:province":"AK",
    "sg:tags":[
        "jewelry"
    ],
    "wof:name":"St Pierre Master Jewelers",
    "wof:placetype":"venue"
},
  "geometry": {"coordinates":[-149.569884,61.325117],"type":"Point"}
}