{
  "type": "Feature",
  "properties": {
    "addr:full":"2272 Sunshine Ave Fairbanks AK 99709",
    "addr:housenumber":"2272",
    "addr:postcode":"99709",
    "addr:street":"Sunshine Ave",
    "iso:country":"US",
    "sg:address":"2272 Sunshine Ave",
    "sg:city":"Fairbanks",
    "sg:classifiers":[
        {
            "category":"Shopping",
            "subcategory":"Gifts & Souvenirs",
            "type":"Retail Goods"
        }
    ],
    "sg:phone":"+1 907 479 2201",
    "sg:postcode":"99709",
    "sg:province":"AK",
    "sg:tags":[
        "shop"
    ],
    "wof:name":"Alaska Wilderness Gourmet",
    "wof:placetype":"venue"
},
  "geometry": {"coordinates":[-147.87182999999999,64.91708199999999],"type":"Point"}
}