{
  "type": "Feature",
  "properties": {
    "iso:country":"US",
    "sg:address":"18743 Old Glenn Hwy",
    "sg:city":"Chugiak",
    "sg:classifiers":[
        {
            "category":"Wholesale",
            "subcategory":"Machinery & Supplies",
            "type":"Manufacturing & Wholesale Goods"
        }
    ],
    "sg:phone":"+1 907 770 5651",
    "sg:postcode":"99567",
    "sg:province":"AK",
    "sg:tags":[
        "concrete",
        "equipment"
    ],
    "wof:name":"Architectural Hardware Supply",
    "wof:placetype":"venue"
},
  "geometry": {"coordinates":[-149.46389199999999,61.394549],"type":"Point"}
}