{
  "type": "Feature",
  "properties": {
    "addr:full":"1363 Bay Ave Homer AK 99603",
    "addr:housenumber":"1363",
    "addr:postcode":"99603",
    "addr:street":"Bay Ave",
    "iso:country":"US",
    "sg:address":"1363 Bay Ave",
    "sg:city":"Homer",
    "sg:classifiers":[
        {
            "category":"Manufacturing",
            "subcategory":"Tools & Machinery",
            "type":"Manufacturing & Wholesale Goods"
        }
    ],
    "sg:phone":"+1 907 235 7458",
    "sg:postcode":"99603",
    "sg:province":"AK",
    "sg:tags":[
        "construction",
        "mfg"
    ],
    "wof:name":"Beluga Eqpt",
    "wof:placetype":"venue"
},
  "geometry": {"coordinates":[-151.50885700000001,59.63772],"type":"Point"}
}