{
  "type": "Feature",
  "properties": {
    "iso:country":"US",
    "sg:address":"500 Lake St",
    "sg:city":"Kenai",
    "sg:classifiers":[
        {
            "category":"Home & Garden",
            "subcategory":"Household Appliances",
            "type":"Retail Goods"
        }
    ],
    "sg:phone":"+1 907 283 4585",
    "sg:postcode":"99611",
    "sg:province":"AK",
    "wof:name":"Dan's TV & Appliance Inc",
    "wof:placetype":"venue"
},
  "geometry": {"coordinates":[-151.302912,60.659921],"type":"Point"}
}