{
  "type": "Feature",
  "properties": {
    "iso:country":"US",
    "sg:address":"4175 Tudor Centre Dr",
    "sg:city":"Anchorage",
    "sg:classifiers":[
        {
            "category":"Professional",
            "subcategory":"Accounting & Tax Preparation",
            "type":"Services"
        }
    ],
    "sg:phone":"+1 907 562 1369",
    "sg:postcode":"99508",
    "sg:province":"AK",
    "sg:tags":[
        "accountant"
    ],
    "wof:name":"Thonre & Assoc",
    "wof:placetype":"venue"
},
  "geometry": {"coordinates":[-149.797648,61.183585],"type":"Point"}
}