{
  "type": "Feature",
  "properties": {
    "iso:country":"US",
    "sg:address":"10665 Glacier Hwy",
    "sg:city":"Juneau",
    "sg:classifiers":[
        {
            "category":"Building & Trades",
            "subcategory":"Construction",
            "type":"Services"
        }
    ],
    "sg:phone":"+1 907 789 4267",
    "sg:postcode":"99801",
    "sg:province":"AK",
    "sg:tags":[
        "floor",
        "laying",
        "contractor"
    ],
    "wof:name":"Bryans Floor Service",
    "wof:placetype":"venue"
},
  "geometry": {"coordinates":[-134.625394,58.376682],"type":"Point"}
}