{
  "type": "Feature",
  "properties": {
    "iso:country":"US",
    "sg:address":"4235 Morphy Ct",
    "sg:city":"Anchorage",
    "sg:classifiers":[
        {
            "category":"Building & Trades",
            "subcategory":"Construction",
            "type":"Services"
        }
    ],
    "sg:phone":"+1 907 338 9762",
    "sg:postcode":"99508",
    "sg:province":"AK",
    "sg:tags":[
        "acoustical",
        "insulation",
        "access",
        "system",
        "flooring"
    ],
    "wof:name":"Sonrise Acoustics",
    "wof:placetype":"venue"
},
  "geometry": {"coordinates":[-149.78190599999999,61.182664],"type":"Point"}
}