{
  "type": "Feature",
  "properties": {
    "iso:country":"US",
    "sg:address":"543 2nd Ave",
    "sg:city":"Fairbanks",
    "sg:classifiers":[
        {
            "category":"Professional",
            "subcategory":"Lawyer & Legal Services",
            "type":"Services"
        }
    ],
    "sg:phone":"+1 907 456 6600",
    "sg:postcode":"99701",
    "sg:province":"AK",
    "sg:tags":[
        "attorney"
    ],
    "wof:name":"Stepovich Law Office",
    "wof:placetype":"venue"
},
  "geometry": {"coordinates":[-147.720016,64.843339],"type":"Point"}
}