{
  "type": "Feature",
  "properties": {
    "addr:full":"273 Main St Seldovia AK 99663",
    "addr:housenumber":"273",
    "addr:postcode":"99663",
    "addr:street":"Main St",
    "iso:country":"US",
    "sg:address":"273 Main St",
    "sg:city":"Seldovia",
    "sg:classifiers":[
        {
            "category":"Travel",
            "subcategory":"Hotels & Motels",
            "type":"Entertainment"
        }
    ],
    "sg:phone":"+1 907 234 1414",
    "sg:postcode":"99663",
    "sg:province":"AK",
    "sg:tags":[
        "breakfast",
        "accommodation",
        "bed"
    ],
    "wof:name":"Seldovia Harbor Inn",
    "wof:placetype":"venue"
},
  "geometry": {"coordinates":[-151.71221299999999,59.436792],"type":"Point"}
}