{
  "type": "Feature",
  "properties": {
    "addr:full":"3743 S Cushman St Fairbanks AK 99701",
    "addr:housenumber":"3743",
    "addr:postcode":"99701",
    "addr:street":"S Cushman St",
    "iso:country":"US",
    "sg:address":"3743 S Cushman St",
    "sg:city":"Fairbanks",
    "sg:classifiers":[
        {
            "category":"Autos & Motor Vehicles",
            "subcategory":"Auto Supplies",
            "type":"Retail Goods"
        }
    ],
    "sg:phone":"+1 907 479 3399",
    "sg:postcode":"99701",
    "sg:province":"AK",
    "sg:tags":[
        "tire"
    ],
    "wof:name":"Wingfoot Commercial Tire Systs",
    "wof:placetype":"venue"
},
  "geometry": {"coordinates":[-147.71064999999999,64.80959300000001],"type":"Point"}
}