{
  "type": "Feature",
  "properties": {
    "iso:country":"US",
    "sg:address":"5611 Silverado Way",
    "sg:city":"Anchorage",
    "sg:classifiers":[
        {
            "category":"Professional",
            "subcategory":"Advertising",
            "type":"Services"
        }
    ],
    "sg:phone":"+1 907 272 6100",
    "sg:postcode":"99518",
    "sg:province":"AK",
    "wof:name":"Ad Works",
    "wof:placetype":"venue"
},
  "geometry": {"coordinates":[-149.88854000000001,61.168298],"type":"Point"}
}