{
  "type": "Feature",
  "properties": {
    "iso:country":"US",
    "sg:address":"515 Craig Ave",
    "sg:city":"Fairbanks",
    "sg:classifiers":[
        {
            "category":"Real Estate",
            "subcategory":"Surveying",
            "type":"Services"
        }
    ],
    "sg:phone":"+1 907 456 1408",
    "sg:postcode":"99701",
    "sg:province":"AK",
    "sg:tags":[
        "surveyor"
    ],
    "wof:name":"Jenco Surveying",
    "wof:placetype":"venue"
},
  "geometry": {"coordinates":[-147.668753,64.847511],"type":"Point"}
}