{
  "type": "Feature",
  "properties": {
    "addr:full":"1670 Evergreen Ave Juneau AK 99801",
    "addr:housenumber":"1670",
    "addr:postcode":"99801",
    "addr:street":"Evergreen Ave",
    "iso:country":"US",
    "sg:address":"1670 Evergreen Ave",
    "sg:city":"Juneau",
    "sg:classifiers":[
        {
            "category":"Farming",
            "subcategory":"Fish & Marine Products",
            "type":"Manufacturing & Wholesale Goods"
        }
    ],
    "sg:phone":"+1 907 586 2242",
    "sg:postcode":"99801",
    "sg:province":"AK",
    "sg:tags":[
        "fishing"
    ],
    "wof:name":"Shelton Jev",
    "wof:placetype":"venue"
},
  "geometry": {"coordinates":[-134.423821,58.306549],"type":"Point"}
}