{
  "type": "Feature",
  "properties": {
    "addr:full":"39050 Sterling Hwy Soldotna AK 99669",
    "addr:housenumber":"39050",
    "addr:postcode":"99669",
    "addr:street":"Sterling Hwy",
    "iso:country":"US",
    "sg:address":"39050 Sterling Hwy",
    "sg:city":"Soldotna",
    "sg:classifiers":[
        {
            "category":"Food & Beverages",
            "subcategory":"Liquor & Beverages",
            "type":"Retail Goods"
        }
    ],
    "sg:phone":"+1 907 262 1068",
    "sg:postcode":"99669",
    "sg:province":"AK",
    "wof:name":"Longmere Grocery & Liquor",
    "wof:placetype":"venue"
},
  "geometry": {"coordinates":[-150.91329300000001,60.509972],"type":"Point"}
}