{
  "type": "Feature",
  "properties": {
    "iso:country":"US",
    "sg:address":"5700 Whispering Spruce Dr",
    "sg:city":"Anchorage",
    "sg:classifiers":[
        {
            "category":"Building & Trades",
            "subcategory":"Plumbing",
            "type":"Services"
        }
    ],
    "sg:phone":"+1 907 345 9126",
    "sg:postcode":"99516",
    "sg:province":"AK",
    "sg:tags":[
        "septic"
    ],
    "wof:name":"Around The Clock Pumping",
    "wof:placetype":"venue"
},
  "geometry": {"coordinates":[-149.77495300000001,61.11355],"type":"Point"}
}