{
  "type": "Feature",
  "properties": {
    "iso:country":"US",
    "sg:address":"107 S Willow St",
    "sg:city":"Kenai",
    "sg:classifiers":[
        {
            "category":"Government",
            "subcategory":"Police Station",
            "type":"Public Place"
        }
    ],
    "sg:phone":"+1 907 283 7879",
    "sg:postcode":"99611",
    "sg:province":"AK",
    "sg:tags":[
        "department"
    ],
    "sg:website":"www.ci.kenai.ak.us",
    "wof:name":"Kenai Police Dept",
    "wof:placetype":"venue"
},
  "geometry": {"coordinates":[-151.250608,60.559489],"type":"Point"}
}