{
  "type": "Feature",
  "properties": {
    "iso:country":"US",
    "sg:address":"731 I St",
    "sg:city":"Anchorage",
    "sg:classifiers":[
        {
            "category":"Professional",
            "subcategory":"Research",
            "type":"Services"
        }
    ],
    "sg:phone":"+1 907 258 8661",
    "sg:postcode":"99501",
    "sg:province":"AK",
    "sg:tags":[
        "environmental",
        "ecological"
    ],
    "wof:name":"White Environmental Consultant",
    "wof:placetype":"venue"
},
  "geometry": {"coordinates":[-149.89951400000001,61.214911],"type":"Point"}
}