{
  "type": "Feature",
  "properties": {
    "iso:country":"US",
    "sg:address":"491 S Willow St",
    "sg:city":"Wasilla",
    "sg:classifiers":[
        {
            "category":"Real Estate",
            "subcategory":"Real Estate Agent",
            "type":"Services"
        }
    ],
    "sg:phone":"+1 907 357 1750",
    "sg:postcode":"99654",
    "sg:province":"AK",
    "wof:name":"Advantage Realty Inc",
    "wof:placetype":"venue"
},
  "geometry": {"coordinates":[-149.447043,61.580354],"type":"Point"}
}