{
  "type": "Feature",
  "properties": {
    "iso:country":"US",
    "sg:address":"5761 Silverado Way",
    "sg:city":"Anchorage",
    "sg:classifiers":[
        {
            "category":"Professional",
            "subcategory":"Testing Lab",
            "type":"Services"
        }
    ],
    "sg:phone":"+1 907 349 1000",
    "sg:postcode":"99518",
    "sg:province":"AK",
    "sg:tags":[
        "laboratory"
    ],
    "sg:website":"www.ntlalaska.com",
    "wof:name":"Analytica Group",
    "wof:placetype":"venue"
},
  "geometry": {"coordinates":[-149.88853700000001,61.168586],"type":"Point"}
}