{
  "type": "Feature",
  "properties": {
    "iso:country":"US",
    "sg:address":"44539 Sterling Hwy",
    "sg:city":"Soldotna",
    "sg:classifiers":[
        {
            "category":"Building & Trades",
            "subcategory":"Construction",
            "type":"Services"
        }
    ],
    "sg:phone":"+1 907 262 3810",
    "sg:postcode":"99669",
    "sg:province":"AK",
    "sg:tags":[
        "general",
        "commercial",
        "family",
        "contractor"
    ],
    "wof:name":"Blazy Construction",
    "wof:placetype":"venue"
},
  "geometry": {"coordinates":[-151.074079,60.480869],"type":"Point"}
}