{
  "type": "Feature",
  "properties": {
    "iso:country":"US",
    "sg:address":"643 Wilcox Ave",
    "sg:city":"Fairbanks",
    "sg:classifiers":[
        {
            "category":"Personal",
            "subcategory":"Beauty Salon",
            "type":"Services"
        }
    ],
    "sg:phone":"+1 907 479 4164",
    "sg:postcode":"99709",
    "sg:province":"AK",
    "wof:name":"Belle-N-Beau Hairstyles",
    "wof:placetype":"venue"
},
  "geometry": {"coordinates":[-147.816807,64.847377],"type":"Point"}
}