{
  "type": "Feature",
  "properties": {
    "iso:country":"US",
    "sg:address":"2563 Meadow Ln",
    "sg:city":"Juneau",
    "sg:classifiers":[
        {
            "category":"Wholesale",
            "subcategory":"Durable Goods & Equipment",
            "type":"Manufacturing & Wholesale Goods"
        }
    ],
    "sg:phone":"+1 907 789 3744",
    "sg:postcode":"99801",
    "sg:province":"AK",
    "sg:tags":[
        "representative",
        "manufacturer"
    ],
    "wof:name":"Eight Stars Unlimited",
    "wof:placetype":"venue"
},
  "geometry": {"coordinates":[-134.597679,58.366228],"type":"Point"}
}