{
  "type": "Feature",
  "properties": {
    "iso:country":"US",
    "sg:address":"6151 Bogard Rd",
    "sg:city":"Wasilla",
    "sg:classifiers":[
        {
            "category":"Building & Trades",
            "subcategory":"Electrical",
            "type":"Services"
        }
    ],
    "sg:phone":"+1 907 376 9473",
    "sg:postcode":"99654",
    "sg:province":"AK",
    "sg:tags":[
        "electric",
        "contractor"
    ],
    "wof:name":"Bullseye Electric",
    "wof:placetype":"venue"
},
  "geometry": {"coordinates":[-149.292455,61.613927],"type":"Point"}
}