{
  "type": "Feature",
  "properties": {
    "iso:country":"US",
    "sg:address":"133 Steelhead Rd",
    "sg:city":"Fairbanks",
    "sg:classifiers":[
        {
            "category":"Building & Trades",
            "subcategory":"Construction",
            "type":"Services"
        }
    ],
    "sg:phone":"+1 907 456 4228",
    "sg:postcode":"99709",
    "sg:province":"AK",
    "sg:tags":[
        "general",
        "contractor"
    ],
    "wof:name":"C & G Construction",
    "wof:placetype":"venue"
},
  "geometry": {"coordinates":[-147.854299,64.842478],"type":"Point"}
}