{
  "type": "Feature",
  "properties": {
    "iso:country":"US",
    "sg:address":"2286 Waterford Rd",
    "sg:city":"Fairbanks",
    "sg:classifiers":[
        {
            "category":"Mining & Drilling",
            "type":"Manufacturing & Wholesale Goods"
        }
    ],
    "sg:phone":"+1 907 455 9023",
    "sg:postcode":"99709",
    "sg:province":"AK",
    "sg:tags":[
        "exploration",
        "mineral"
    ],
    "wof:name":"Interior Exploration Svc",
    "wof:placetype":"venue"
},
  "geometry": {"coordinates":[-147.74542700000001,64.96160399999999],"type":"Point"}
}