{
  "type": "Feature",
  "properties": {
    "iso:country":"US",
    "sg:address":"6250 Tuttle Pl",
    "sg:city":"Anchorage",
    "sg:classifiers":[
        {
            "category":"Home & Garden",
            "subcategory":"Building Materials",
            "type":"Retail Goods"
        }
    ],
    "sg:phone":"+1 907 561 1205",
    "sg:postcode":"99507",
    "sg:province":"AK",
    "sg:tags":[
        "equipment",
        "electric",
        "supply"
    ],
    "wof:name":"Westcoast Sales & Market",
    "wof:placetype":"venue"
},
  "geometry": {"coordinates":[-149.839559,61.165961],"type":"Point"}
}