{
  "type": "Feature",
  "properties": {
    "iso:country":"US",
    "sg:address":"903 W Northern Lights Blvd",
    "sg:city":"Anchorage",
    "sg:classifiers":[
        {
            "category":"Real Estate",
            "subcategory":"Real Estate Agent",
            "type":"Services"
        }
    ],
    "sg:phone":"+1 907 277 2580",
    "sg:postcode":"99503",
    "sg:province":"AK",
    "sg:tags":[
        "management"
    ],
    "wof:name":"Hilligas Co Inc",
    "wof:placetype":"venue"
},
  "geometry": {"coordinates":[-149.90255199999999,61.195373],"type":"Point"}
}