{
  "type": "Feature",
  "properties": {
    "addr:full":"13 Sing Lee Aly Petersburg AK 99833",
    "addr:housenumber":"13",
    "addr:postcode":"99833",
    "addr:street":"Sing Lee Aly",
    "iso:country":"US",
    "sg:address":"13 Sing Lee Aly",
    "sg:city":"Petersburg",
    "sg:classifiers":[
        {
            "category":"Food & Beverages",
            "subcategory":"Specialty",
            "type":"Retail Goods"
        }
    ],
    "sg:phone":"+1 907 772 3444",
    "sg:postcode":"99833",
    "sg:province":"AK",
    "sg:tags":[
        "health",
        "diet"
    ],
    "wof:name":"Helse",
    "wof:placetype":"venue"
},
  "geometry": {"coordinates":[-132.959079,56.810779],"type":"Point"}
}