{
  "type": "Feature",
  "properties": {
    "iso:country":"US",
    "sg:address":"2151 University Ave S",
    "sg:city":"Fairbanks",
    "sg:classifiers":[
        {
            "category":"Shopping",
            "type":"Retail Goods"
        }
    ],
    "sg:phone":"+1 907 479 5202",
    "sg:postcode":"99709",
    "sg:province":"AK",
    "sg:tags":[
        "trophy",
        "medal",
        "award"
    ],
    "wof:name":"Far North Trophy Cache Inc",
    "wof:placetype":"venue"
},
  "geometry": {"coordinates":[-147.81240199999999,64.82761499999999],"type":"Point"}
}