{
  "type": "Feature",
  "properties": {
    "iso:country":"US",
    "sg:address":"8001 Petersburg St",
    "sg:city":"Anchorage",
    "sg:classifiers":[
        {
            "category":"Wholesale",
            "subcategory":"Machinery & Supplies",
            "type":"Manufacturing & Wholesale Goods"
        }
    ],
    "sg:phone":"+1 907 522 3434",
    "sg:postcode":"99507",
    "sg:province":"AK",
    "sg:tags":[
        "engine"
    ],
    "sg:website":"www.pacificdda.com",
    "wof:name":"Pacific Detroit Diesel-Allison",
    "wof:placetype":"venue"
},
  "geometry": {"coordinates":[-149.84535600000001,61.146927],"type":"Point"}
}