{
  "type": "Feature",
  "properties": {
    "iso:country":"US",
    "sg:address":"1723 E Rezanof Dr",
    "sg:city":"Kodiak",
    "sg:classifiers":[
        {
            "category":"Recreation",
            "type":"Entertainment"
        }
    ],
    "sg:phone":"+1 907 486 3682",
    "sg:postcode":"99615",
    "sg:province":"AK",
    "sg:tags":[
        "guide"
    ],
    "wof:name":"Sea Otter Charters",
    "wof:placetype":"venue"
},
  "geometry": {"coordinates":[-152.377592,57.799245],"type":"Point"}
}