{
  "type": "Feature",
  "properties": {
    "iso:country":"US",
    "sg:address":"701 Pherson St",
    "sg:city":"Sitka",
    "sg:classifiers":[
        {
            "category":"Recreation",
            "type":"Entertainment"
        }
    ],
    "sg:phone":"+1 907 747 5161",
    "sg:postcode":"99835",
    "sg:province":"AK",
    "sg:tags":[
        "party",
        "fishing"
    ],
    "wof:name":"Big Blue Charters",
    "wof:placetype":"venue"
},
  "geometry": {"coordinates":[-135.33512400000001,57.059382],"type":"Point"}
}