{
  "type": "Feature",
  "properties": {
    "addr:full":"5875 Hideaway Cir Wasilla AK 99687",
    "addr:housenumber":"5875",
    "addr:postcode":"99687",
    "addr:street":"Hideaway Cir",
    "iso:country":"US",
    "sg:address":"5875 Hideaway Cir",
    "sg:city":"Wasilla",
    "sg:classifiers":[
        {
            "category":"Building & Trades",
            "subcategory":"Construction",
            "type":"Services"
        }
    ],
    "sg:phone":"+1 907 745 6014",
    "sg:postcode":"99687",
    "sg:province":"AK",
    "sg:tags":[
        "excavating",
        "contractor"
    ],
    "wof:name":"World Paving",
    "wof:placetype":"venue"
},
  "geometry": {"coordinates":[-149.30271200000001,61.579123],"type":"Point"}
}