{
  "type": "Feature",
  "properties": {
    "iso:country":"US",
    "sg:address":"4315 Lois Dr",
    "sg:city":"Anchorage",
    "sg:classifiers":[
        {
            "category":"Building & Trades",
            "subcategory":"Construction",
            "type":"Services"
        }
    ],
    "sg:phone":"+1 907 562 7748",
    "sg:postcode":"99517",
    "sg:province":"AK",
    "sg:tags":[
        "painter"
    ],
    "wof:name":"AMS",
    "wof:placetype":"venue"
},
  "geometry": {"coordinates":[-149.915434,61.18104],"type":"Point"}
}