{
  "type": "Feature",
  "properties": {
    "iso:country":"US",
    "sg:address":"412 Marine Way W",
    "sg:city":"Kodiak",
    "sg:classifiers":[
        {
            "category":"Shopping",
            "subcategory":"Gifts & Souvenirs",
            "type":"Retail Goods"
        }
    ],
    "sg:phone":"+1 907 486 3259",
    "sg:postcode":"99615",
    "sg:province":"AK",
    "sg:tags":[
        "shop"
    ],
    "wof:name":"Ardinger's Fine Furnishings",
    "wof:placetype":"venue"
},
  "geometry": {"coordinates":[-152.40731400000001,57.787866],"type":"Point"}
}