{
  "type": "Feature",
  "properties": {
    "iso:country":"US",
    "sg:address":"2119 Old Steese Hwy N",
    "sg:city":"Fairbanks",
    "sg:classifiers":[
        {
            "category":"Freight",
            "type":"Transportation"
        }
    ],
    "sg:phone":"+1 907 457 1967",
    "sg:postcode":"99712",
    "sg:province":"AK",
    "sg:tags":[
        "trucking"
    ],
    "wof:name":"Dineega Trucking",
    "wof:placetype":"venue"
},
  "geometry": {"coordinates":[-147.62887000000001,64.953535],"type":"Point"}
}