{
  "type": "Feature",
  "properties": {
    "iso:country":"US",
    "sg:address":"2408 Elm St",
    "sg:city":"Seward",
    "sg:classifiers":[
        {
            "category":"Professional",
            "subcategory":"Accounting & Tax Preparation",
            "type":"Services"
        }
    ],
    "sg:phone":"+1 907 224 8019",
    "sg:postcode":"99664",
    "sg:province":"AK",
    "sg:tags":[
        "bookkeeping",
        "general"
    ],
    "wof:name":"TLC Business Svc",
    "wof:placetype":"venue"
},
  "geometry": {"coordinates":[-149.436967,60.136273],"type":"Point"}
}