{
  "type": "Feature",
  "properties": {
    "iso:country":"US",
    "sg:address":"6111 Lockheed Ave",
    "sg:city":"Anchorage",
    "sg:classifiers":[
        {
            "category":"Manufacturing",
            "subcategory":"Tools & Machinery",
            "type":"Manufacturing & Wholesale Goods"
        }
    ],
    "sg:phone":"+1 907 243 6800",
    "sg:postcode":"99502",
    "sg:province":"AK",
    "sg:tags":[
        "devices",
        "mfg"
    ],
    "wof:name":"Instrument Services",
    "wof:placetype":"venue"
},
  "geometry": {"coordinates":[-149.99487300000001,61.195645],"type":"Point"}
}