{
  "type": "Feature",
  "properties": {
    "addr:full":"2201 E 84th Ct Anchorage AK 99507",
    "addr:housenumber":"2201",
    "addr:postcode":"99507",
    "addr:street":"E 84Th Ct",
    "iso:country":"US",
    "sg:address":"2201 E 84th Ct",
    "sg:city":"Anchorage",
    "sg:classifiers":[
        {
            "category":"Building & Trades",
            "subcategory":"Construction",
            "type":"Services"
        }
    ],
    "sg:phone":"+1 907 344 5545",
    "sg:postcode":"99507",
    "sg:province":"AK",
    "sg:tags":[
        "roofing",
        "contractor"
    ],
    "sg:website":"www.rainproofroofing.com",
    "wof:name":"Rain Proof Roofing LLC",
    "wof:placetype":"venue"
},
  "geometry": {"coordinates":[-149.841003,61.145454],"type":"Point"}
}