{
  "type": "Feature",
  "properties": {
    "iso:country":"US",
    "sg:address":"3900 C St",
    "sg:city":"Anchorage",
    "sg:classifiers":[
        {
            "category":"Airline",
            "type":"Transportation"
        }
    ],
    "sg:phone":"+1 907 339 6100",
    "sg:postcode":"99503",
    "sg:province":"AK",
    "sg:tags":[
        "air"
    ],
    "wof:name":"Arctic Slope World Svc",
    "wof:placetype":"venue"
},
  "geometry": {"coordinates":[-149.88657499999999,61.18447],"type":"Point"}
}