{
  "type": "Feature",
  "properties": {
    "addr:full":"4748 Old Seward Hwy Anchorage AK 99503",
    "addr:housenumber":"4748",
    "addr:postcode":"99503",
    "addr:street":"Old Seward Hwy",
    "iso:country":"US",
    "sg:address":"4748 Old Seward Hwy",
    "sg:city":"Anchorage",
    "sg:classifiers":[
        {
            "category":"Autos & Motor Vehicles",
            "subcategory":"Auto Supplies",
            "type":"Retail Goods"
        }
    ],
    "sg:phone":"+1 907 563 5490",
    "sg:postcode":"99503",
    "sg:province":"AK",
    "sg:tags":[
        "automobile",
        "parts"
    ],
    "wof:name":"Custom Truck Inc",
    "wof:placetype":"venue"
},
  "geometry": {"coordinates":[-149.86819,61.178346],"type":"Point"}
}