{
  "type": "Feature",
  "properties": {
    "iso:country":"US",
    "sg:address":"14441 Loc Loman Ln",
    "sg:city":"Anchorage",
    "sg:classifiers":[
        {
            "category":"Building & Trades",
            "subcategory":"Construction",
            "type":"Services"
        }
    ],
    "sg:phone":"+1 907 345 0615",
    "sg:postcode":"99516",
    "sg:province":"AK",
    "sg:tags":[
        "stonework",
        "masonry",
        "other"
    ],
    "wof:name":"Four Seasons Masonry",
    "wof:placetype":"venue"
},
  "geometry": {"coordinates":[-149.81150099999999,61.08879],"type":"Point"}
}