{
  "type": "Feature",
  "properties": {
    "addr:full":"4805 N Caprice Dr Palmer AK 99645",
    "addr:housenumber":"4805",
    "addr:postcode":"99645",
    "addr:street":"N Caprice Dr",
    "iso:country":"US",
    "sg:address":"4805 N Caprice Dr",
    "sg:city":"Palmer",
    "sg:classifiers":[
        {
            "category":"Organizations",
            "subcategory":"Non-profit Organization",
            "type":"Services"
        }
    ],
    "sg:phone":"+1 907 745 7290",
    "sg:postcode":"99645",
    "sg:province":"AK",
    "sg:tags":[
        "disability"
    ],
    "wof:name":"Elks-Help",
    "wof:placetype":"venue"
},
  "geometry": {"coordinates":[-149.13551100000001,61.640129],"type":"Point"}
}