{
  "type": "Feature",
  "properties": {
    "iso:country":"US",
    "sg:address":"2780 Cormorant St",
    "sg:city":"Fairbanks",
    "sg:classifiers":[
        {
            "category":"Wholesale",
            "subcategory":"Auto Parts",
            "type":"Manufacturing & Wholesale Goods"
        }
    ],
    "sg:phone":"+1 907 479 5128",
    "sg:postcode":"99709",
    "sg:province":"AK",
    "sg:tags":[
        "automobile",
        "rebuilt"
    ],
    "wof:name":"Ace Towing & Salvage",
    "wof:placetype":"venue"
},
  "geometry": {"coordinates":[-147.92381499999999,64.818814],"type":"Point"}
}