{
  "type": "Feature",
  "properties": {
    "iso:country":"US",
    "sg:address":"486 W Redoubt Ave",
    "sg:city":"Soldotna",
    "sg:classifiers":[
        {
            "category":"Education",
            "subcategory":"School",
            "type":"Public Place"
        }
    ],
    "sg:phone":"+1 907 262 9006",
    "sg:postcode":"99669",
    "sg:province":"AK",
    "wof:name":"Redoubt Elementary School",
    "wof:placetype":"venue"
},
  "geometry": {"coordinates":[-151.102863,60.48776],"type":"Point"}
}