{
  "type": "Feature",
  "properties": {
    "addr:full":"2971 Drake Dr Anchorage AK 99508",
    "addr:housenumber":"2971",
    "addr:postcode":"99508",
    "addr:street":"Drake Dr",
    "iso:country":"US",
    "sg:address":"2971 Drake Dr",
    "sg:city":"Anchorage",
    "sg:classifiers":[
        {
            "category":"Building & Trades",
            "subcategory":"Construction",
            "type":"Services"
        }
    ],
    "sg:phone":"+1 907 276 2396",
    "sg:postcode":"99508",
    "sg:province":"AK",
    "sg:tags":[
        "general",
        "contractor"
    ],
    "wof:name":"Reynolds General Contracting",
    "wof:placetype":"venue"
},
  "geometry": {"coordinates":[-149.84566100000001,61.194135],"type":"Point"}
}