{
  "type": "Feature",
  "properties": {
    "addr:full":"11555 Birch Hills Dr Eagle River AK 99577",
    "addr:housenumber":"11555",
    "addr:postcode":"99577",
    "addr:street":"Birch Hills Dr",
    "iso:country":"US",
    "sg:address":"11555 Birch Hills Dr",
    "sg:city":"Eagle River",
    "sg:classifiers":[
        {
            "category":"Organizations",
            "subcategory":"Religious Organization",
            "type":"Services"
        }
    ],
    "sg:phone":"+1 907 694 3456",
    "sg:postcode":"99577",
    "sg:province":"AK",
    "sg:tags":[
        "church"
    ],
    "wof:name":"Peace Lutheran Church-Wisc",
    "wof:placetype":"venue"
},
  "geometry": {"coordinates":[-149.54796200000001,61.326337],"type":"Point"}
}