{
  "type": "Feature",
  "properties": {
    "iso:country":"US",
    "sg:address":"261 E 56th Ave",
    "sg:city":"Anchorage",
    "sg:classifiers":[
        {
            "category":"Wholesale",
            "subcategory":"Machinery & Supplies",
            "type":"Manufacturing & Wholesale Goods"
        }
    ],
    "sg:phone":"+1 907 563 3424",
    "sg:postcode":"99518",
    "sg:province":"AK",
    "sg:tags":[
        "pump"
    ],
    "sg:website":"www.alaskapump.com",
    "wof:name":"Alaska Pump & Supply",
    "wof:placetype":"venue"
},
  "geometry": {"coordinates":[-149.87798,61.170099],"type":"Point"}
}