{
  "type": "Feature",
  "properties": {
    "iso:country":"US",
    "sg:address":"1432 University Ave S",
    "sg:city":"Fairbanks",
    "sg:classifiers":[
        {
            "category":"Retail",
            "subcategory":"Auto Repair",
            "type":"Services"
        }
    ],
    "sg:phone":"+1 907 479 7550",
    "sg:postcode":"99709",
    "sg:province":"AK",
    "sg:tags":[
        "repairing",
        "automobile"
    ],
    "wof:name":"Front End Shop Inc",
    "wof:placetype":"venue"
},
  "geometry": {"coordinates":[-147.812701,64.83643600000001],"type":"Point"}
}