{
  "type": "Feature",
  "properties": {
    "iso:country":"US",
    "sg:address":"4320 Checkmate Dr",
    "sg:city":"Anchorage",
    "sg:classifiers":[
        {
            "category":"Real Estate",
            "subcategory":"Real Estate Operator",
            "type":"Services"
        }
    ],
    "sg:phone":"+1 907 333 0031",
    "sg:postcode":"99508",
    "sg:province":"AK",
    "sg:tags":[
        "apartment"
    ],
    "wof:name":"Casablanca",
    "wof:placetype":"venue"
},
  "geometry": {"coordinates":[-149.785744,61.181015],"type":"Point"}
}