{
  "type": "Feature",
  "properties": {
    "addr:full":"4320 Checkmate Dr Anchorage AK 99508",
    "addr:postcode":"4320;99508",
    "addr:street":"Checkmate Dr",
    "iso:country":"US",
    "sg:address":"4320 Checkmate Dr",
    "sg:city":"Anchorage",
    "sg:classifiers":[
        {
            "category":"Real Estate",
            "subcategory":"Real Estate Operator",
            "type":"Services"
        }
    ],
    "sg:phone":"+1 907 333 0031",
    "sg:postcode":"99508",
    "sg:province":"AK",
    "sg:tags":[
        "apartment"
    ],
    "wof:name":"Casablanca",
    "wof:placetype":"venue"
},
  "geometry": {"coordinates":[-149.78574399999999,61.181015],"type":"Point"}
}