{
  "type": "Feature",
  "properties": {
    "iso:country":"US",
    "sg:address":"519 S Bragaw St",
    "sg:city":"Anchorage",
    "sg:classifiers":[
        {
            "category":"Retail",
            "subcategory":"Auto Repair",
            "type":"Services"
        }
    ],
    "sg:phone":"+1 907 569 5959",
    "sg:postcode":"99508",
    "sg:province":"AK",
    "sg:tags":[
        "wrecker"
    ],
    "wof:name":"Latino Towing",
    "wof:placetype":"venue"
},
  "geometry": {"coordinates":[-149.80829800000001,61.218024],"type":"Point"}
}