{
  "type": "Feature",
  "properties": {
    "iso:country":"US",
    "sg:address":"33095 Sterling Hwy",
    "sg:city":"Sterling",
    "sg:classifiers":[
        {
            "category":"Autos & Motor Vehicles",
            "subcategory":"Auto Supplies",
            "type":"Retail Goods"
        }
    ],
    "sg:phone":"+1 907 262 9626",
    "sg:postcode":"99672",
    "sg:province":"AK",
    "sg:tags":[
        "automobile",
        "parts"
    ],
    "wof:name":"Sterling Carquest Auto Parts",
    "wof:placetype":"venue"
},
  "geometry": {"coordinates":[-150.736392,60.532031],"type":"Point"}
}