{
  "type": "Feature",
  "properties": {
    "iso:country":"US",
    "sg:address":"251 Pisokak St",
    "sg:city":"Barrow",
    "sg:classifiers":[
        {
            "category":"Building & Trades",
            "subcategory":"Plumbing",
            "type":"Services"
        }
    ],
    "sg:phone":"+1 907 852 4000",
    "sg:postcode":"99723",
    "sg:province":"AK",
    "sg:tags":[
        "plumbing",
        "contractor"
    ],
    "wof:name":"Barrow Mechanical",
    "wof:placetype":"venue"
},
  "geometry": {"coordinates":[-156.782954,71.287613],"type":"Point"}
}