{
  "type": "Feature",
  "properties": {
    "iso:country":"US",
    "sg:address":"2217 E Tudor Rd",
    "sg:city":"Anchorage",
    "sg:classifiers":[
        {
            "category":"Education",
            "subcategory":"School",
            "type":"Public Place"
        }
    ],
    "sg:phone":"+1 907 562 7372",
    "sg:postcode":"99507",
    "sg:province":"AK",
    "sg:tags":[
        "academic",
        "special"
    ],
    "sg:website":"www.sesa.org",
    "wof:name":"Special Education Svc Agency",
    "wof:placetype":"venue"
},
  "geometry": {"coordinates":[-149.84459899999999,61.180917],"type":"Point"}
}