{
  "type": "Feature",
  "properties": {
    "addr:full":"374 Howling Wolf Ln Wasilla AK 99654",
    "addr:housenumber":"374",
    "addr:postcode":"99654",
    "addr:street":"Howling Wolf Ln",
    "iso:country":"US",
    "sg:address":"374 Howling Wolf Ln",
    "sg:city":"Wasilla",
    "sg:classifiers":[
        {
            "category":"Mining & Drilling",
            "type":"Manufacturing & Wholesale Goods"
        }
    ],
    "sg:phone":"+1 907 354 1298",
    "sg:postcode":"99654",
    "sg:province":"AK",
    "sg:tags":[
        "construction",
        "contractor"
    ],
    "wof:name":"Ace",
    "wof:placetype":"venue"
},
  "geometry": {"coordinates":[-149.440586,61.603857],"type":"Point"}
}