{
  "type": "Feature",
  "properties": {
    "iso:country":"US",
    "sg:address":"500 Muldoon Rd",
    "sg:city":"Anchorage",
    "sg:classifiers":[
        {
            "category":"Organizations",
            "subcategory":"Non-profit Organization",
            "type":"Services"
        }
    ],
    "sg:phone":"+1 907 332 7660",
    "sg:postcode":"99504",
    "sg:province":"AK",
    "sg:tags":[
        "info",
        "addiction",
        "abuse",
        "treatment",
        "drug"
    ],
    "wof:name":"Recovery Connection",
    "wof:placetype":"venue"
},
  "geometry": {"coordinates":[-149.733478,61.216953],"type":"Point"}
}