{
  "type": "Feature",
  "properties": {
    "iso:country":"US",
    "sg:address":"403 Klondike Ave",
    "sg:city":"Homer",
    "sg:classifiers":[
        {
            "category":"Professional",
            "subcategory":"Management & Consulting",
            "type":"Services"
        }
    ],
    "sg:phone":"+1 907 235 8050",
    "sg:postcode":"99603",
    "sg:province":"AK",
    "sg:tags":[
        "communications",
        "consultant"
    ],
    "wof:name":"O'Leary's Enterprises",
    "wof:placetype":"venue"
},
  "geometry": {"coordinates":[-151.535787,59.645853],"type":"Point"}
}