{
  "type": "Feature",
  "properties": {
    "addr:full":"1408 Hyder St Anchorage AK 99501",
    "addr:housenumber":"1408",
    "addr:postcode":"99501",
    "addr:street":"Hyder St",
    "iso:country":"US",
    "sg:address":"1408 Hyder St",
    "sg:city":"Anchorage",
    "sg:classifiers":[
        {
            "category":"Retail",
            "subcategory":"Repair Shop",
            "type":"Services"
        }
    ],
    "sg:phone":"+1 907 242 4294",
    "sg:postcode":"99501",
    "sg:province":"AK",
    "sg:tags":[
        "equipment",
        "photographic"
    ],
    "wof:name":"Camera Repair & Sales",
    "wof:placetype":"venue"
},
  "geometry": {"coordinates":[-149.86907400000001,61.207792],"type":"Point"}
}