{
  "type": "Feature",
  "properties": {
    "addr:full":"1504 Gillam Way Fairbanks AK 99701",
    "addr:housenumber":"1504",
    "addr:postcode":"99701",
    "addr:street":"Gillam Way",
    "iso:country":"US",
    "sg:address":"1504 Gillam Way",
    "sg:city":"Fairbanks",
    "sg:classifiers":[
        {
            "category":"Autos & Motor Vehicles",
            "subcategory":"Automobile Sales",
            "type":"Retail Goods"
        }
    ],
    "sg:phone":"+1 907 455 7233",
    "sg:postcode":"99701",
    "sg:province":"AK",
    "sg:tags":[
        "snowmobile"
    ],
    "wof:name":"Fairbanks Snowmobile Safety",
    "wof:placetype":"venue"
},
  "geometry": {"coordinates":[-147.72784300000001,64.83387],"type":"Point"}
}