{
  "type": "Feature",
  "properties": {
    "iso:country":"US",
    "sg:address":"1001 E Usa Cir",
    "sg:city":"Wasilla",
    "sg:classifiers":[
        {
            "category":"Health Services",
            "subcategory":"Doctor",
            "type":"Services"
        }
    ],
    "sg:phone":"+1 907 376 1510",
    "sg:postcode":"99654",
    "sg:province":"AK",
    "sg:tags":[
        "dentist"
    ],
    "wof:name":"Valley Orthodontics",
    "wof:placetype":"venue"
},
  "geometry": {"coordinates":[-149.427652,61.584127],"type":"Point"}
}