{
  "type": "Feature",
  "properties": {
    "addr:full":"371 Bolin St Anchorage AK 99504",
    "addr:housenumber":"371",
    "addr:postcode":"99504",
    "addr:street":"Bolin St",
    "iso:country":"US",
    "sg:address":"371 Bolin St",
    "sg:city":"Anchorage",
    "sg:classifiers":[
        {
            "category":"Organizations",
            "subcategory":"Non-profit Organization",
            "type":"Services"
        }
    ],
    "sg:phone":"+1 907 332 1345",
    "sg:postcode":"99504",
    "sg:province":"AK",
    "sg:tags":[
        "info",
        "addiction",
        "abuse",
        "treatment",
        "drug"
    ],
    "wof:name":"Teen Challenge Of Alaska",
    "wof:placetype":"venue"
},
  "geometry": {"coordinates":[-149.71934400000001,61.220382],"type":"Point"}
}