{
  "type": "Feature",
  "properties": {
    "iso:country":"US",
    "sg:address":"800 Ingra St",
    "sg:city":"Anchorage",
    "sg:classifiers":[
        {
            "category":"Government",
            "subcategory":"Post Office",
            "type":"Public Place"
        }
    ],
    "sg:phone":"+1 907 000 1111",
    "sg:postcode":"99501",
    "sg:province":"AK",
    "wof:name":"US Post Office",
    "wof:placetype":"venue"
},
  "geometry": {"coordinates":[-149.86693500000001,61.213618],"type":"Point"}
}