{
  "type": "Feature",
  "properties": {
    "iso:country":"US",
    "sg:address":"6211 Old Seward Hwy",
    "sg:city":"Anchorage",
    "sg:classifiers":[
        {
            "category":"Building & Trades",
            "subcategory":"Landscaping Services",
            "type":"Services"
        }
    ],
    "sg:phone":"+1 907 561 5885",
    "sg:postcode":"99518",
    "sg:province":"AK",
    "sg:tags":[
        "topsoil"
    ],
    "wof:name":"Turf Topsoil",
    "wof:placetype":"venue"
},
  "geometry": {"coordinates":[-149.86466100000001,61.162901],"type":"Point"}
}