{
  "type": "Feature",
  "properties": {
    "iso:country":"US",
    "sg:address":"1441 22nd Ave",
    "sg:city":"Fairbanks",
    "sg:classifiers":[
        {
            "category":"Real Estate",
            "subcategory":"Real Estate Operator",
            "type":"Services"
        }
    ],
    "sg:phone":"+1 907 456 3738",
    "sg:postcode":"99701",
    "sg:province":"AK",
    "sg:tags":[
        "apartment"
    ],
    "wof:name":"Alaska Housing Finance Corp",
    "wof:placetype":"venue"
},
  "geometry": {"coordinates":[-147.737033,64.827368],"type":"Point"}
}