{
  "type": "Feature",
  "properties": {
    "iso:country":"US",
    "sg:address":"110 American St",
    "sg:city":"Sitka",
    "sg:classifiers":[
        {
            "category":"Personal",
            "subcategory":"Beauty Salon",
            "type":"Services"
        }
    ],
    "sg:phone":"+1 907 747 7511",
    "sg:postcode":"99835",
    "sg:province":"AK",
    "wof:name":"Ahead Of Style",
    "wof:placetype":"venue"
},
  "geometry": {"coordinates":[-135.336253,57.050801],"type":"Point"}
}