{
  "type": "Feature",
  "properties": {
    "addr:full":"2005 E 5th Ave Anchorage AK 99501",
    "addr:housenumber":"2005",
    "addr:postcode":"99501",
    "addr:street":"E 5Th Ave",
    "iso:country":"US",
    "sg:address":"2005 E 5th Ave",
    "sg:city":"Anchorage",
    "sg:classifiers":[
        {
            "category":"Professional",
            "subcategory":"Computer Services",
            "type":"Services"
        }
    ],
    "sg:phone":"+1 907 222 3456",
    "sg:postcode":"99501",
    "sg:province":"AK",
    "sg:tags":[
        "programming"
    ],
    "wof:name":"Slamon Joes Enterprises",
    "wof:placetype":"venue"
},
  "geometry": {"coordinates":[-149.84173699999999,61.217619],"type":"Point"}
}