{
  "type": "Feature",
  "properties": {
    "addr:full":"1108 E Northern Lights Blvd Anchorage AK 99508",
    "addr:housenumber":"1108",
    "addr:postcode":"99508",
    "addr:street":"E Northern Lights Blvd",
    "iso:country":"US",
    "sg:address":"1108 E Northern Lights Blvd",
    "sg:city":"Anchorage",
    "sg:classifiers":[
        {
            "category":"Personal",
            "subcategory":"Beauty Salon",
            "type":"Services"
        }
    ],
    "sg:phone":"+1 907 222 5377",
    "sg:postcode":"99508",
    "sg:province":"AK",
    "wof:name":"Elite Hair Design",
    "wof:placetype":"venue"
},
  "geometry": {"coordinates":[-149.864103,61.195205],"type":"Point"}
}