{
  "type": "Feature",
  "properties": {
    "iso:country":"US",
    "sg:address":"44420 Cottonwood Dr",
    "sg:city":"Kenai",
    "sg:classifiers":[
        {
            "category":"Wholesale",
            "subcategory":"Non-durable Goods",
            "type":"Manufacturing & Wholesale Goods"
        }
    ],
    "sg:phone":"+1 907 283 3541",
    "sg:postcode":"99611",
    "sg:province":"AK",
    "sg:tags":[
        "advertising"
    ],
    "wof:name":"Alaskan Ad Specialty Co",
    "wof:placetype":"venue"
},
  "geometry": {"coordinates":[-151.33447699999999,60.624381],"type":"Point"}
}