{
  "type": "Feature",
  "properties": {
    "iso:country":"US",
    "sg:address":"338 Lincoln St",
    "sg:city":"Sitka",
    "sg:classifiers":[
        {
            "category":"Government",
            "subcategory":"Post Office",
            "type":"Public Place"
        }
    ],
    "sg:phone":"+1 907 747 8491",
    "sg:postcode":"99835",
    "sg:province":"AK",
    "wof:name":"US Post Office",
    "wof:placetype":"venue"
},
  "geometry": {"coordinates":[-135.335207,57.050834],"type":"Point"}
}