{
  "type": "Feature",
  "properties": {
    "iso:country":"US",
    "sg:address":"3530 Spence Ln",
    "sg:city":"Wasilla",
    "sg:classifiers":[
        {
            "category":"Building & Trades",
            "subcategory":"Construction",
            "type":"Services"
        }
    ],
    "sg:phone":"+1 907 373 1587",
    "sg:postcode":"99654",
    "sg:province":"AK",
    "sg:tags":[
        "well",
        "drilling"
    ],
    "wof:name":"E & D Water Wells & Pump Svc",
    "wof:placetype":"venue"
},
  "geometry": {"coordinates":[-149.54001,61.637678],"type":"Point"}
}