{
  "type": "Feature",
  "properties": {
    "iso:country":"US",
    "sg:address":"13140 Bainbridge Rd",
    "sg:city":"Anchorage",
    "sg:classifiers":[
        {
            "category":"Manufacturing",
            "subcategory":"Tools & Machinery",
            "type":"Manufacturing & Wholesale Goods"
        }
    ],
    "sg:phone":"+1 907 243 2980",
    "sg:postcode":"99516",
    "sg:province":"AK",
    "sg:tags":[
        "indicator",
        "component",
        "system",
        "aerospace",
        "mfg"
    ],
    "wof:name":"Honeywell",
    "wof:placetype":"venue"
},
  "geometry": {"coordinates":[-149.789309,61.102151],"type":"Point"}
}