{
  "type": "Feature",
  "properties": {
    "iso:country":"US",
    "sg:address":"3580 University Ave S",
    "sg:city":"Fairbanks",
    "sg:classifiers":[
        {
            "category":"Airport",
            "type":"Transportation"
        }
    ],
    "sg:phone":"+1 907 479 8100",
    "sg:postcode":"99709",
    "sg:province":"AK",
    "sg:tags":[
        "aircraft",
        "maintenance"
    ],
    "wof:name":"Arctic Aviation",
    "wof:placetype":"venue"
},
  "geometry": {"coordinates":[-147.835239,64.81752],"type":"Point"}
}