{
  "type": "Feature",
  "properties": {
    "iso:country":"US",
    "sg:address":"351 Carlanna Lake Rd",
    "sg:city":"Ketchikan",
    "sg:classifiers":[
        {
            "category":"Health Services",
            "subcategory":"Optometrist",
            "type":"Services"
        }
    ],
    "sg:phone":"+1 907 225 2020",
    "sg:postcode":"99901",
    "sg:province":"AK",
    "wof:name":"Ketchikan Eye Care Ctr",
    "wof:placetype":"venue"
},
  "geometry": {"coordinates":[-131.687226,55.355453],"type":"Point"}
}