{
  "type": "Feature",
  "properties": {
    "addr:full":"37405 Funny River Rd Soldotna AK 99669",
    "addr:postcode":"37405;99669",
    "addr:street":"Funny River Rd",
    "iso:country":"US",
    "sg:address":"37405 Funny River Rd",
    "sg:city":"Soldotna",
    "sg:classifiers":[
        {
            "category":"Home & Garden",
            "subcategory":"Building Materials",
            "type":"Retail Goods"
        }
    ],
    "sg:phone":"+1 907 262 9213",
    "sg:postcode":"99669",
    "sg:province":"AK",
    "sg:tags":[
        "truss"
    ],
    "wof:name":"Bailey Building Supply Truss",
    "wof:placetype":"venue"
},
  "geometry": {"coordinates":[-150.85659000000001,60.496617],"type":"Point"}
}