{
  "type": "Feature",
  "properties": {
    "addr:full":"2645 Mill Bay Rd Kodiak AK 99615",
    "addr:housenumber":"2645;bay",
    "addr:postcode":"99615",
    "addr:street":"Mill;Rd",
    "iso:country":"US",
    "sg:address":"2645 Mill Bay Rd",
    "sg:city":"Kodiak",
    "sg:classifiers":[
        {
            "category":"Banks & Credit Unions",
            "subcategory":"Bank",
            "type":"Services"
        }
    ],
    "sg:phone":"+1 907 486 6900",
    "sg:postcode":"99615",
    "sg:province":"AK",
    "wof:name":"Wells Fargo Bank",
    "wof:placetype":"venue"
},
  "geometry": {"coordinates":[-152.366524,57.808859],"type":"Point"}
}