{
  "type": "Feature",
  "properties": {
    "iso:country":"US",
    "sg:address":"13555 Sterling Hwy",
    "sg:city":"Ninilchik",
    "sg:classifiers":[
        {
            "category":"Recreation",
            "type":"Entertainment"
        }
    ],
    "sg:phone":"+1 907 567 7366",
    "sg:postcode":"99639",
    "sg:province":"AK",
    "sg:tags":[
        "guide"
    ],
    "wof:name":"Bottom Line Charters",
    "wof:placetype":"venue"
},
  "geometry": {"coordinates":[-151.63755499999999,60.070614],"type":"Point"}
}