{
  "type": "Feature",
  "properties": {
    "iso:country":"US",
    "sg:address":"617 Katlian St",
    "sg:city":"Sitka",
    "sg:classifiers":[
        {
            "category":"Government",
            "subcategory":"Office",
            "type":"Public Place"
        }
    ],
    "sg:phone":"+1 907 747 3439",
    "sg:postcode":"99835",
    "sg:province":"AK",
    "sg:tags":[
        "village"
    ],
    "wof:name":"Sitka Harbor Master",
    "wof:placetype":"venue"
},
  "geometry": {"coordinates":[-135.347577,57.054958],"type":"Point"}
}