{
  "type": "Feature",
  "properties": {
    "iso:country":"US",
    "sg:address":"1075 E 72nd Ave",
    "sg:city":"Anchorage",
    "sg:classifiers":[
        {
            "category":"Professional",
            "subcategory":"Management & Consulting",
            "type":"Services"
        }
    ],
    "sg:phone":"+1 907 277 8367",
    "sg:postcode":"99518",
    "sg:province":"AK",
    "sg:tags":[
        "engineer"
    ],
    "wof:name":"Temptel Inc",
    "wof:placetype":"venue"
},
  "geometry": {"coordinates":[-149.86379700000001,61.154975],"type":"Point"}
}