{
  "type": "Feature",
  "properties": {
    "iso:country":"US",
    "sg:address":"581 W Parks Hwy",
    "sg:city":"Wasilla",
    "sg:classifiers":[
        {
            "category":"Banks & Credit Unions",
            "subcategory":"Bank",
            "type":"Services"
        }
    ],
    "sg:phone":"+1 907 376 5355",
    "sg:postcode":"99654",
    "sg:province":"AK",
    "sg:website":"www.wellsfargo.com",
    "wof:name":"Wells Fargo Bank",
    "wof:placetype":"venue"
},
  "geometry": {"coordinates":[-149.460149,61.582268],"type":"Point"}
}