{
  "type": "Feature",
  "properties": {
    "iso:country":"US",
    "sg:address":"3807 Iowa Dr",
    "sg:city":"Anchorage",
    "sg:classifiers":[
        {
            "category":"Building & Trades",
            "subcategory":"Construction",
            "type":"Services"
        }
    ],
    "sg:phone":"+1 907 248 6005",
    "sg:postcode":"99517",
    "sg:province":"AK",
    "sg:tags":[
        "repairing",
        "house",
        "contractor",
        "remodeling",
        "nonresidential"
    ],
    "wof:name":"French's Construction",
    "wof:placetype":"venue"
},
  "geometry": {"coordinates":[-149.928792,61.183747],"type":"Point"}
}