{
  "type": "Feature",
  "properties": {
    "iso:country":"US",
    "sg:address":"4307 Arctic Blvd",
    "sg:city":"Anchorage",
    "sg:classifiers":[
        {
            "category":"Organizations",
            "subcategory":"Religious Organization",
            "type":"Services"
        }
    ],
    "sg:phone":"+1 907 561 4722",
    "sg:postcode":"99503",
    "sg:province":"AK",
    "sg:tags":[
        "church"
    ],
    "wof:name":"House Of Prayer",
    "wof:placetype":"venue"
},
  "geometry": {"coordinates":[-149.897954,61.180778],"type":"Point"}
}