{
  "type": "Feature",
  "properties": {
    "iso:country":"US",
    "sg:address":"280 W 34th Ave",
    "sg:city":"Anchorage",
    "sg:classifiers":[
        {
            "category":"Professional",
            "subcategory":"Lawyer & Legal Services",
            "type":"Services"
        }
    ],
    "sg:phone":"+1 907 563 5297",
    "sg:postcode":"99503",
    "sg:province":"AK",
    "sg:tags":[
        "attorney"
    ],
    "wof:name":"Wickersham & Assoc",
    "wof:placetype":"venue"
},
  "geometry": {"coordinates":[-149.88363200000001,61.189434],"type":"Point"}
}