{
  "type": "Feature",
  "properties": {
    "addr:full":"1440 E End Rd Homer AK 99603",
    "addr:housenumber":"1440",
    "addr:postcode":"99603",
    "addr:street":"E End Rd",
    "iso:country":"US",
    "sg:address":"1440 E End Rd",
    "sg:city":"Homer",
    "sg:classifiers":[
        {
            "category":"Retail",
            "subcategory":"Repair Shop",
            "type":"Services"
        }
    ],
    "sg:phone":"+1 907 235 6280",
    "sg:postcode":"99603",
    "sg:province":"AK",
    "sg:tags":[
        "pump"
    ],
    "wof:name":"D L Blackwell Pump Svc",
    "wof:placetype":"venue"
},
  "geometry": {"coordinates":[-151.50320500000001,59.654877],"type":"Point"}
}