{
  "type": "Feature",
  "properties": {
    "iso:country":"US",
    "sg:address":"701 E Parks Hwy",
    "sg:city":"Wasilla",
    "sg:classifiers":[
        {
            "category":"Shopping",
            "type":"Retail Goods"
        }
    ],
    "sg:phone":"+1 907 373 2355",
    "sg:postcode":"99654",
    "sg:province":"AK",
    "sg:tags":[
        "telephone",
        "cellular"
    ],
    "wof:name":"MTA Wireless",
    "wof:placetype":"venue"
},
  "geometry": {"coordinates":[-149.433051,61.581009],"type":"Point"}
}