{
  "type": "Feature",
  "properties": {
    "addr:full":"2530 Debarr Rd Anchorage AK 99508",
    "addr:housenumber":"2530",
    "addr:postcode":"99508",
    "addr:street":"Debarr Rd",
    "iso:country":"US",
    "sg:address":"2530 Debarr Rd",
    "sg:city":"Anchorage",
    "sg:classifiers":[
        {
            "category":"Health Services",
            "subcategory":"Health Practitioner",
            "type":"Services"
        }
    ],
    "sg:phone":"+1 907 563 8816",
    "sg:postcode":"99508",
    "sg:province":"AK",
    "sg:tags":[
        "psychologist"
    ],
    "wof:name":"David J Sperbeck PHD",
    "wof:placetype":"venue"
},
  "geometry": {"coordinates":[-149.83246800000001,61.209001],"type":"Point"}
}