{
  "type": "Feature",
  "properties": {
    "addr:full":"1921 W Dimond Blvd Anchorage AK 99515",
    "addr:housenumber":"1921",
    "addr:postcode":"99515",
    "addr:street":"W Dimond Blvd",
    "iso:country":"US",
    "sg:address":"1921 W Dimond Blvd",
    "sg:city":"Anchorage",
    "sg:classifiers":[
        {
            "category":"Personal",
            "subcategory":"Beauty Salon",
            "type":"Services"
        }
    ],
    "sg:phone":"+1 907 344 4922",
    "sg:postcode":"99515",
    "sg:province":"AK",
    "sg:tags":[
        "manicuring"
    ],
    "wof:name":"Extasy",
    "wof:placetype":"venue"
},
  "geometry": {"coordinates":[-149.91591399999999,61.138116],"type":"Point"}
}