{
  "type": "Feature",
  "properties": {
    "addr:full":"465 Ravenswood Loop Wasilla AK 99654",
    "addr:housenumber":"465",
    "addr:postcode":"99654",
    "addr:street":"Ravenswood Loop",
    "iso:country":"US",
    "sg:address":"465 Ravenswood Loop",
    "sg:city":"Wasilla",
    "sg:classifiers":[
        {
            "category":"Restaurant",
            "type":"Food & Drink"
        }
    ],
    "sg:phone":"+1 907 354 3647",
    "sg:postcode":"99654",
    "sg:province":"AK",
    "sg:tags":[
        "caterer"
    ],
    "wof:name":"Alaska Gourmet Catering",
    "wof:placetype":"venue"
},
  "geometry": {"coordinates":[-149.43641700000001,61.561217],"type":"Point"}
}