{
  "type": "Feature",
  "properties": {
    "iso:country":"US",
    "sg:address":"22837 Eagle River Rd",
    "sg:city":"Eagle River",
    "sg:classifiers":[
        {
            "category":"Professional",
            "subcategory":"Lawyer & Legal Services",
            "type":"Services"
        }
    ],
    "sg:phone":"+1 907 694 4345",
    "sg:postcode":"99577",
    "sg:province":"AK",
    "sg:tags":[
        "attorney"
    ],
    "wof:name":"Brad D De Noble",
    "wof:placetype":"venue"
},
  "geometry": {"coordinates":[-149.453172,61.302808],"type":"Point"}
}