{
  "type": "Feature",
  "properties": {
    "iso:country":"US",
    "sg:address":"423 Valley View Dr",
    "sg:city":"Fairbanks",
    "sg:classifiers":[
        {
            "category":"Insurance",
            "subcategory":"Insurance Agent",
            "type":"Services"
        }
    ],
    "sg:phone":"+1 907 452 2626",
    "sg:postcode":"99712",
    "sg:province":"AK",
    "wof:name":"New York Life Insurance Co",
    "wof:placetype":"venue"
},
  "geometry": {"coordinates":[-147.677358,64.898971],"type":"Point"}
}