{
  "type": "Feature",
  "properties": {
    "iso:country":"US",
    "sg:address":"331 E Pioneer Ave",
    "sg:city":"Homer",
    "sg:classifiers":[
        {
            "category":"Arts & Performance",
            "subcategory":"Theater",
            "type":"Entertainment"
        }
    ],
    "sg:phone":"+1 907 235 1212",
    "sg:postcode":"99603",
    "sg:province":"AK",
    "sg:tags":[
        "program",
        "radio",
        "producer"
    ],
    "wof:name":"Tempest Media Productions",
    "wof:placetype":"venue"
},
  "geometry": {"coordinates":[-151.53801899999999,59.646325],"type":"Point"}
}