{
  "type": "Feature",
  "properties": {
    "iso:country":"US",
    "sg:address":"1223 Mill Bay Rd",
    "sg:city":"Kodiak",
    "sg:classifiers":[
        {
            "category":"Bars & Pubs",
            "type":"Food & Drink"
        }
    ],
    "sg:phone":"+1 907 486 4428",
    "sg:postcode":"99615",
    "sg:province":"AK",
    "sg:tags":[
        "lounge",
        "cocktail"
    ],
    "wof:name":"Diamond Jim's Harvester Inn",
    "wof:placetype":"venue"
},
  "geometry": {"coordinates":[-152.390597,57.797031],"type":"Point"}
}