{
  "type": "Feature",
  "properties": {
    "iso:country":"US",
    "sg:address":"701 Oceanview Dr",
    "sg:city":"Craig",
    "sg:classifiers":[
        {
            "category":"Social Services",
            "type":"Services"
        }
    ],
    "sg:phone":"+1 907 826 3891",
    "sg:postcode":"99921",
    "sg:province":"AK",
    "sg:tags":[
        "organization",
        "welfare"
    ],
    "wof:name":"Community Connections",
    "wof:placetype":"venue"
},
  "geometry": {"coordinates":[-133.139288,55.472414],"type":"Point"}
}