{
  "type": "Feature",
  "properties": {
    "iso:country":"US",
    "sg:address":"907 Tasmania Ct",
    "sg:city":"Homer",
    "sg:classifiers":[
        {
            "category":"Marine",
            "type":"Transportation"
        }
    ],
    "sg:phone":"+1 907 235 8086",
    "sg:postcode":"99603",
    "sg:province":"AK",
    "sg:tags":[
        "towing"
    ],
    "wof:name":"Cook Inlet Marine",
    "wof:placetype":"venue"
},
  "geometry": {"coordinates":[-151.52156,59.655543],"type":"Point"}
}