{
  "type": "Feature",
  "properties": {
    "iso:country":"US",
    "sg:address":"400 Seward Meridian Rd",
    "sg:city":"Wasilla",
    "sg:classifiers":[
        {
            "category":"Building & Trades",
            "subcategory":"Construction",
            "type":"Services"
        }
    ],
    "sg:phone":"+1 907 376 3454",
    "sg:postcode":"99654",
    "sg:province":"AK",
    "sg:tags":[
        "resurfacing",
        "floor",
        "laying",
        "refinishing",
        "contractor"
    ],
    "wof:name":"Aarons Flooring & Cabinetry",
    "wof:placetype":"venue"
},
  "geometry": {"coordinates":[-149.35972699999999,61.579816],"type":"Point"}
}