{
  "type": "Feature",
  "properties": {
    "iso:country":"US",
    "sg:address":"4241 B St",
    "sg:city":"Anchorage",
    "sg:classifiers":[
        {
            "category":"Banks & Credit Unions",
            "subcategory":"Bank",
            "type":"Services"
        }
    ],
    "sg:phone":"+1 907 562 6444",
    "sg:postcode":"99503",
    "sg:province":"AK",
    "sg:tags":[
        "loan",
        "real estate"
    ],
    "wof:name":"Vista Mortgage Co",
    "wof:placetype":"venue"
},
  "geometry": {"coordinates":[-149.884366,61.183018],"type":"Point"}
}