{
  "type": "Feature",
  "properties": {
    "iso:country":"US",
    "sg:address":"3788 University Ave S",
    "sg:city":"Fairbanks",
    "sg:classifiers":[
        {
            "category":"Building & Trades",
            "subcategory":"Landscaping Services",
            "type":"Services"
        }
    ],
    "sg:phone":"+1 907 457 4190",
    "sg:postcode":"99709",
    "sg:province":"AK",
    "sg:tags":[
        "landscape",
        "contractor"
    ],
    "wof:name":"Exclusive Landscaping",
    "wof:placetype":"venue"
},
  "geometry": {"coordinates":[-147.845745,64.812296],"type":"Point"}
}