{
  "type": "Feature",
  "properties": {
    "iso:country":"US",
    "sg:address":"748 Gaffney Rd",
    "sg:city":"Fairbanks",
    "sg:classifiers":[
        {
            "category":"Social Services",
            "subcategory":"Job Training",
            "type":"Services"
        }
    ],
    "sg:phone":"+1 907 452 2275",
    "sg:postcode":"99701",
    "sg:province":"AK",
    "sg:tags":[
        "rehabilitation"
    ],
    "wof:name":"Compensation Risk Consultants",
    "wof:placetype":"venue"
},
  "geometry": {"coordinates":[-147.724574,64.837328],"type":"Point"}
}