{
  "type": "Feature",
  "properties": {
    "addr:full":"2333 E Tudor Rd Anchorage AK 99507",
    "addr:housenumber":"2333",
    "addr:postcode":"99507",
    "addr:street":"E Tudor Rd",
    "iso:country":"US",
    "sg:address":"2333 E Tudor Rd",
    "sg:city":"Anchorage",
    "sg:classifiers":[
        {
            "category":"Autos & Motor Vehicles",
            "subcategory":"Automobile Sales",
            "type":"Retail Goods"
        }
    ],
    "sg:phone":"+1 907 563 2277",
    "sg:postcode":"99507",
    "sg:province":"AK",
    "sg:tags":[
        "car",
        "dealer"
    ],
    "wof:name":"Park-N-Deal",
    "wof:placetype":"venue"
},
  "geometry": {"coordinates":[-149.838593,61.180914],"type":"Point"}
}