{
  "type": "Feature",
  "properties": {
    "iso:country":"US",
    "sg:address":"48665 Kalifornsky Beach Rd",
    "sg:city":"Kenai",
    "sg:classifiers":[
        {
            "category":"Freight",
            "type":"Transportation"
        }
    ],
    "sg:phone":"+1 907 262 5444",
    "sg:postcode":"99611",
    "sg:province":"AK",
    "sg:tags":[
        "trucking"
    ],
    "wof:name":"Midnight Sun Transportation",
    "wof:placetype":"venue"
},
  "geometry": {"coordinates":[-151.275602,60.502069],"type":"Point"}
}