{
  "type": "Feature",
  "properties": {
    "iso:country":"US",
    "sg:address":"2830 Airport Way",
    "sg:city":"Fairbanks",
    "sg:classifiers":[
        {
            "category":"Organizations",
            "subcategory":"Religious Organization",
            "type":"Services"
        }
    ],
    "sg:phone":"+1 907 474 9112",
    "sg:postcode":"99709",
    "sg:province":"AK",
    "sg:tags":[
        "church"
    ],
    "wof:name":"First Assembly Of God",
    "wof:placetype":"venue"
},
  "geometry": {"coordinates":[-147.78751700000001,64.836867],"type":"Point"}
}