{
  "type": "Feature",
  "properties": {
    "iso:country":"US",
    "sg:address":"619 E Ship Creek Ave",
    "sg:city":"Anchorage",
    "sg:classifiers":[
        {
            "category":"Government",
            "subcategory":"Office",
            "type":"Public Place"
        }
    ],
    "sg:phone":"+1 907 562 0460",
    "sg:postcode":"99501",
    "sg:province":"AK",
    "wof:name":"Disability Determination Svc",
    "wof:placetype":"venue"
},
  "geometry": {"coordinates":[-149.87096600000001,61.222862],"type":"Point"}
}