{
  "type": "Feature",
  "properties": {
    "addr:full":"3908 S Cushman St Fairbanks AK 99701",
    "addr:housenumber":"3908",
    "addr:postcode":"99701",
    "addr:street":"S Cushman St",
    "iso:country":"US",
    "sg:address":"3908 S Cushman St",
    "sg:city":"Fairbanks",
    "sg:classifiers":[
        {
            "category":"Building & Trades",
            "subcategory":"Construction",
            "type":"Services"
        }
    ],
    "sg:phone":"+1 907 457 4306",
    "sg:postcode":"99701",
    "sg:province":"AK",
    "sg:tags":[
        "general",
        "contractor"
    ],
    "sg:website":"www.landmarkalaska.com",
    "wof:name":"Landmark Inc",
    "wof:placetype":"venue"
},
  "geometry": {"coordinates":[-147.71080900000001,64.81178],"type":"Point"}
}