{
  "type": "Feature",
  "properties": {
    "iso:country":"US",
    "sg:address":"1325 Primrose St",
    "sg:city":"Anchorage",
    "sg:classifiers":[
        {
            "category":"Education",
            "subcategory":"Library",
            "type":"Public Place"
        }
    ],
    "sg:phone":"+1 907 279 8433",
    "sg:postcode":"99508",
    "sg:province":"AK",
    "wof:name":"Alaska Moving Images Prsrvtn",
    "wof:placetype":"venue"
},
  "geometry": {"coordinates":[-149.81010800000001,61.208123],"type":"Point"}
}