{
  "type": "Feature",
  "properties": {
    "addr:full":"2107 W 44th Ct Anchorage AK 99517",
    "addr:housenumber":"2107",
    "addr:postcode":"99517",
    "addr:street":"W 44Th Ct",
    "iso:country":"US",
    "sg:address":"2107 W 44th Ct",
    "sg:city":"Anchorage",
    "sg:classifiers":[
        {
            "category":"Real Estate",
            "subcategory":"Real Estate Agent",
            "type":"Services"
        }
    ],
    "sg:phone":"+1 907 243 2237",
    "sg:postcode":"99517",
    "sg:province":"AK",
    "wof:name":"Ace Realty",
    "wof:placetype":"venue"
},
  "geometry": {"coordinates":[-149.92227500000001,61.180425],"type":"Point"}
}