{
  "type": "Feature",
  "properties": {
    "iso:country":"US",
    "sg:address":"231 S Binkley St",
    "sg:city":"Soldotna",
    "sg:classifiers":[
        {
            "category":"Manufacturing",
            "subcategory":"Lumber",
            "type":"Manufacturing & Wholesale Goods"
        }
    ],
    "sg:phone":"+1 907 262 7361",
    "sg:postcode":"99669",
    "sg:province":"AK",
    "sg:tags":[
        "forestry"
    ],
    "wof:name":"Central Emergency Services",
    "wof:placetype":"venue"
},
  "geometry": {"coordinates":[-151.070935,60.482655],"type":"Point"}
}