{
  "type": "Feature",
  "properties": {
    "iso:country":"US",
    "sg:address":"323 Charles St",
    "sg:city":"Fairbanks",
    "sg:classifiers":[
        {
            "category":"Professional",
            "subcategory":"Business Services",
            "type":"Services"
        }
    ],
    "sg:phone":"+1 907 456 4646",
    "sg:postcode":"99701",
    "sg:province":"AK",
    "sg:tags":[
        "interior",
        "consultant",
        "design",
        "decorator"
    ],
    "wof:name":"Design Input",
    "wof:placetype":"venue"
},
  "geometry": {"coordinates":[-147.71618000000001,64.84980400000001],"type":"Point"}
}