{
  "type": "Feature",
  "properties": {
    "iso:country":"US",
    "sg:address":"922 W 73rd Ave",
    "sg:city":"Anchorage",
    "sg:classifiers":[
        {
            "category":"Social Services",
            "subcategory":"Child Care",
            "type":"Services"
        }
    ],
    "sg:phone":"+1 907 336 2650",
    "sg:postcode":"99518",
    "sg:province":"AK",
    "wof:name":"Glenda's Daycare",
    "wof:placetype":"venue"
},
  "geometry": {"coordinates":[-149.89788100000001,61.15469],"type":"Point"}
}