{
  "type": "Feature",
  "properties": {
    "addr:full":"1161 Shypoke Dr Fairbanks AK 99709",
    "addr:housenumber":"1161",
    "addr:postcode":"99709",
    "addr:street":"Shypoke Dr",
    "iso:country":"US",
    "sg:address":"1161 Shypoke Dr",
    "sg:city":"Fairbanks",
    "sg:classifiers":[
        {
            "category":"Travel",
            "subcategory":"Hotels & Motels",
            "type":"Entertainment"
        }
    ],
    "sg:phone":"+1 907 479 3710",
    "sg:postcode":"99709",
    "sg:province":"AK",
    "sg:tags":[
        "breakfast",
        "accommodation",
        "bed"
    ],
    "wof:name":"Plane Country Bed & Breakfast",
    "wof:placetype":"venue"
},
  "geometry": {"coordinates":[-147.914074,64.81498000000001],"type":"Point"}
}