{
  "type": "Feature",
  "properties": {
    "addr:full":"4164 Pennock St Homer AK 99603",
    "addr:housenumber":"4164",
    "addr:postcode":"99603",
    "addr:street":"Pennock St",
    "iso:country":"US",
    "sg:address":"4164 Pennock St",
    "sg:city":"Homer",
    "sg:classifiers":[
        {
            "category":"Professional",
            "subcategory":"Lawyer & Legal Services",
            "type":"Services"
        }
    ],
    "sg:phone":"+1 907 235 2009",
    "sg:postcode":"99603",
    "sg:province":"AK",
    "sg:tags":[
        "attorney"
    ],
    "wof:name":"Darin B Goff Law Office",
    "wof:placetype":"venue"
},
  "geometry": {"coordinates":[-151.517574,59.649854],"type":"Point"}
}