{
  "type": "Feature",
  "properties": {
    "iso:country":"US",
    "sg:address":"1649 Souhrada Rd",
    "sg:city":"Delta Junction",
    "sg:classifiers":[
        {
            "category":"Utilities",
            "subcategory":"Refuse",
            "type":"Services"
        }
    ],
    "sg:phone":"+1 907 895 4331",
    "sg:postcode":"99737",
    "sg:province":"AK",
    "sg:tags":[
        "consultant",
        "sanitation"
    ],
    "wof:name":"Delta Sanitation",
    "wof:placetype":"venue"
},
  "geometry": {"coordinates":[-145.547492,64.040905],"type":"Point"}
}