{
  "type": "Feature",
  "properties": {
    "iso:country":"US",
    "sg:address":"200 Marathon Dr",
    "sg:city":"Seward",
    "sg:classifiers":[
        {
            "category":"Travel",
            "subcategory":"Hotels & Motels",
            "type":"Entertainment"
        }
    ],
    "sg:phone":"+1 907 224 8766",
    "sg:postcode":"99664",
    "sg:province":"AK",
    "sg:tags":[
        "breakfast",
        "accommodation",
        "bed"
    ],
    "wof:name":"Chenai Bed & Breakfast",
    "wof:placetype":"venue"
},
  "geometry": {"coordinates":[-149.44062199999999,60.123436],"type":"Point"}
}