{
  "type": "Feature",
  "properties": {
    "iso:country":"US",
    "sg:address":"520 E 34th Ave",
    "sg:city":"Anchorage",
    "sg:classifiers":[
        {
            "category":"Insurance",
            "subcategory":"Insurance Agent",
            "type":"Services"
        }
    ],
    "sg:phone":"+1 907 561 9700",
    "sg:postcode":"99503",
    "sg:province":"AK",
    "sg:website":"www.davidfrazierinsurance.com",
    "wof:name":"David Frazier & Assoc Inc",
    "wof:placetype":"venue"
},
  "geometry": {"coordinates":[-149.875077,61.189444],"type":"Point"}
}