{
  "type": "Feature",
  "properties": {
    "iso:country":"US",
    "sg:address":"905 Cook Ave",
    "sg:city":"Kenai",
    "sg:classifiers":[
        {
            "category":"Social Services",
            "subcategory":"Adult Care",
            "type":"Services"
        }
    ],
    "sg:phone":"+1 907 283 7294",
    "sg:postcode":"99611",
    "sg:province":"AK",
    "sg:tags":[
        "organization",
        "senior",
        "citizen"
    ],
    "wof:name":"Forget-Me-Not Care Ctr",
    "wof:placetype":"venue"
},
  "geometry": {"coordinates":[-151.2636,60.551438],"type":"Point"}
}