{
  "type": "Feature",
  "properties": {
    "addr:full":"5614 Cobbler Dr Anchorage AK 99502",
    "addr:housenumber":"5614",
    "addr:postcode":"99502",
    "addr:street":"Cobbler Dr",
    "iso:country":"US",
    "sg:address":"5614 Cobbler Dr",
    "sg:city":"Anchorage",
    "sg:classifiers":[
        {
            "category":"Organizations",
            "subcategory":"Religious Organization",
            "type":"Services"
        }
    ],
    "sg:phone":"+1 907 243 6774",
    "sg:postcode":"99502",
    "sg:province":"AK",
    "sg:tags":[
        "church"
    ],
    "wof:name":"First Missionary Baptist Chr",
    "wof:placetype":"venue"
},
  "geometry": {"coordinates":[-149.98933299999999,61.152449],"type":"Point"}
}