{
  "type": "Feature",
  "properties": {
    "iso:country":"US",
    "sg:address":"1000 O'Malley Rd",
    "sg:city":"Anchorage",
    "sg:classifiers":[
        {
            "category":"Health Services",
            "subcategory":"Chiropractor",
            "type":"Services"
        }
    ],
    "sg:phone":"+1 907 349 5552",
    "sg:postcode":"99515",
    "sg:province":"AK",
    "wof:name":"Baker Chiropractic Clinic",
    "wof:placetype":"venue"
},
  "geometry": {"coordinates":[-149.77151,61.207457],"type":"Point"}
}