{
  "type": "Feature",
  "properties": {
    "addr:full":"35555 Spur Dr Kasilof AK 99610",
    "addr:housenumber":"35555",
    "addr:postcode":"99610",
    "addr:street":"Spur Dr",
    "iso:country":"US",
    "sg:address":"35555 Spur Dr",
    "sg:city":"Kasilof",
    "sg:classifiers":[
        {
            "category":"Manufacturing",
            "subcategory":"Printing",
            "type":"Manufacturing & Wholesale Goods"
        }
    ],
    "sg:phone":"+1 907 262 6189",
    "sg:postcode":"99610",
    "sg:province":"AK",
    "sg:tags":[
        "publisher"
    ],
    "wof:name":"Spruce Tree Publishing",
    "wof:placetype":"venue"
},
  "geometry": {"coordinates":[-151.26860099999999,60.337721],"type":"Point"}
}