{
  "type": "Feature",
  "properties": {
    "iso:country":"US",
    "sg:address":"16405 Marcus St",
    "sg:city":"Eagle River",
    "sg:classifiers":[
        {
            "category":"Shopping",
            "subcategory":"Computers & Home Electronics",
            "type":"Retail Goods"
        }
    ],
    "sg:phone":"+1 907 696 8273",
    "sg:postcode":"99577",
    "sg:province":"AK",
    "sg:tags":[
        "parts",
        "supply"
    ],
    "wof:name":"Alaska Audio/Visual & Data",
    "wof:placetype":"venue"
},
  "geometry": {"coordinates":[-149.576389,61.335642],"type":"Point"}
}