{
  "type": "Feature",
  "properties": {
    "addr:full":"433 Front St Nome AK 99762",
    "addr:housenumber":"433",
    "addr:postcode":"99762",
    "addr:street":"Front St",
    "iso:country":"US",
    "sg:address":"433 Front St",
    "sg:city":"Nome",
    "sg:classifiers":[
        {
            "category":"Government",
            "subcategory":"Office",
            "type":"Public Place"
        }
    ],
    "sg:phone":"+1 907 443 2023",
    "sg:postcode":"99762",
    "sg:province":"AK",
    "sg:tags":[
        "armed",
        "force",
        "recruiting"
    ],
    "wof:name":"State Of Alaska Recruiting",
    "wof:placetype":"venue"
},
  "geometry": {"coordinates":[-165.41140300000001,64.498178],"type":"Point"}
}