{
  "type": "Feature",
  "properties": {
    "iso:country":"US",
    "sg:address":"1845 Caribou Way",
    "sg:city":"Fairbanks",
    "sg:classifiers":[
        {
            "category":"Building & Trades",
            "subcategory":"Plumbing",
            "type":"Services"
        }
    ],
    "sg:phone":"+1 907 455 6506",
    "sg:postcode":"99709",
    "sg:province":"AK",
    "sg:tags":[
        "plumbing",
        "heating",
        "contractor"
    ],
    "sg:website":"www.akbestph.com",
    "wof:name":"Alaska Best Plumbing & Heating",
    "wof:placetype":"venue"
},
  "geometry": {"coordinates":[-147.780811,64.860275],"type":"Point"}
}