{
  "type": "Feature",
  "properties": {
    "iso:country":"US",
    "sg:address":"745 Westpoint Dr",
    "sg:city":"Wasilla",
    "sg:classifiers":[
        {
            "category":"Retail",
            "subcategory":"Laundry & Dry Cleaning",
            "type":"Services"
        }
    ],
    "sg:phone":"+1 907 376 4141",
    "sg:postcode":"99654",
    "sg:province":"AK",
    "wof:name":"Wasilla Wash Day Laundry & Dry",
    "wof:placetype":"venue"
},
  "geometry": {"coordinates":[-149.432269,61.582301],"type":"Point"}
}