{
  "type": "Feature",
  "properties": {
    "addr:full":"3730 Spenard Rd Anchorage AK 99517",
    "addr:housenumber":"3730",
    "addr:postcode":"99517",
    "addr:street":"Spenard Rd",
    "iso:country":"US",
    "sg:address":"3730 Spenard Rd",
    "sg:city":"Anchorage",
    "sg:classifiers":[
        {
            "category":"Retail",
            "subcategory":"Auto Rental",
            "type":"Services"
        }
    ],
    "sg:phone":"+1 907 276 2855",
    "sg:postcode":"99517",
    "sg:province":"AK",
    "sg:tags":[
        "renting",
        "automobile"
    ],
    "wof:name":"Thrifty Car Rental",
    "wof:placetype":"venue"
},
  "geometry": {"coordinates":[-149.91498799999999,61.186634],"type":"Point"}
}