{
  "type": "Feature",
  "properties": {
    "iso:country":"US",
    "sg:address":"1001 E Benson Blvd",
    "sg:city":"Anchorage",
    "sg:classifiers":[
        {
            "category":"Mining & Drilling",
            "type":"Manufacturing & Wholesale Goods"
        }
    ],
    "sg:phone":"+1 907 265 4100",
    "sg:postcode":"99508",
    "sg:province":"AK",
    "sg:tags":[
        "field",
        "oil"
    ],
    "wof:name":"Nana Regional Corporation Inc",
    "wof:placetype":"venue"
},
  "geometry": {"coordinates":[-149.86482699999999,61.193501],"type":"Point"}
}