{
  "type": "Feature",
  "properties": {
    "addr:full":"200 W 34th Ave Anchorage AK 99503",
    "addr:housenumber":"200",
    "addr:postcode":"99503",
    "addr:street":"W 34Th Ave",
    "iso:country":"US",
    "sg:address":"200 W 34th Ave",
    "sg:city":"Anchorage",
    "sg:classifiers":[
        {
            "category":"Education",
            "subcategory":"Special Training",
            "type":"Public Place"
        }
    ],
    "sg:phone":"+1 907 562 7006",
    "sg:postcode":"99503",
    "sg:province":"AK",
    "sg:tags":[
        "instruction",
        "music"
    ],
    "wof:name":"Alaska Children's Choir",
    "wof:placetype":"venue"
},
  "geometry": {"coordinates":[-149.88539299999999,61.189432],"type":"Point"}
}