{
  "type": "Feature",
  "properties": {
    "iso:country":"US",
    "sg:address":"4011 W Dimond Blvd",
    "sg:city":"Anchorage",
    "sg:classifiers":[
        {
            "category":"Personal",
            "subcategory":"Beauty Salon",
            "type":"Services"
        }
    ],
    "sg:phone":"+1 907 336 2547",
    "sg:postcode":"99502",
    "sg:province":"AK",
    "wof:name":"Great Clips",
    "wof:placetype":"venue"
},
  "geometry": {"coordinates":[-149.954735,61.137551],"type":"Point"}
}