{
  "type": "Feature",
  "properties": {
    "iso:country":"US",
    "sg:address":"3637 Old Seward Hwy",
    "sg:city":"Anchorage",
    "sg:classifiers":[
        {
            "category":"Restaurant",
            "type":"Food & Drink"
        }
    ],
    "sg:phone":"+1 907 563 8616",
    "sg:postcode":"99503",
    "sg:province":"AK",
    "wof:name":"Thai House Restaurant",
    "wof:placetype":"venue"
},
  "geometry": {"coordinates":[-149.868086,61.18775],"type":"Point"}
}