{
  "type": "Feature",
  "properties": {
    "iso:country":"US",
    "sg:address":"315 Tundra Way",
    "sg:city":"Bethel",
    "sg:classifiers":[
        {
            "category":"Manufacturing",
            "subcategory":"Printing",
            "type":"Manufacturing & Wholesale Goods"
        }
    ],
    "sg:phone":"+1 907 442 2716",
    "sg:postcode":"99559",
    "sg:province":"AK",
    "sg:tags":[
        "newspaper"
    ],
    "wof:name":"Artic Sounder",
    "wof:placetype":"venue"
},
  "geometry": {"coordinates":[-161.75154599999999,60.794336],"type":"Point"}
}