{
  "type": "Feature",
  "properties": {
    "addr:full":"3330 Industrial Ave Fairbanks AK 99701",
    "addr:housenumber":"3330",
    "addr:postcode":"99701",
    "addr:street":"Industrial Ave",
    "iso:country":"US",
    "sg:address":"3330 Industrial Ave",
    "sg:city":"Fairbanks",
    "sg:classifiers":[
        {
            "category":"Professional",
            "type":"Services"
        }
    ],
    "sg:phone":"+1 907 456 3116",
    "sg:postcode":"99701",
    "sg:province":"AK",
    "sg:tags":[
        "water",
        "analysis"
    ],
    "sg:website":"www.analyticagroup.com",
    "wof:name":"Analytical International",
    "wof:placetype":"venue"
},
  "geometry": {"coordinates":[-147.75531799999999,64.815275],"type":"Point"}
}