{
  "type": "Feature",
  "properties": {
    "iso:country":"US",
    "sg:address":"3330 Industrial Ave",
    "sg:city":"Fairbanks",
    "sg:classifiers":[
        {
            "category":"Professional",
            "type":"Services"
        }
    ],
    "sg:phone":"+1 907 456 3116",
    "sg:postcode":"99701",
    "sg:province":"AK",
    "sg:tags":[
        "water",
        "analysis"
    ],
    "sg:website":"www.analyticagroup.com",
    "wof:name":"Analytical International",
    "wof:placetype":"venue"
},
  "geometry": {"coordinates":[-147.755318,64.815275],"type":"Point"}
}