{
  "type": "Feature",
  "properties": {
    "iso:country":"US",
    "sg:address":"202 Center St",
    "sg:city":"Kodiak",
    "sg:classifiers":[
        {
            "category":"Personal",
            "subcategory":"Beauty Salon",
            "type":"Services"
        }
    ],
    "sg:phone":"+1 907 486 4928",
    "sg:postcode":"99615",
    "sg:province":"AK",
    "wof:name":"Hair Masters",
    "wof:placetype":"venue"
},
  "geometry": {"coordinates":[-152.40646799999999,57.789105],"type":"Point"}
}