{
  "type": "Feature",
  "properties": {
    "iso:country":"US",
    "sg:address":"40520 Waterman Rd",
    "sg:city":"Homer",
    "sg:classifiers":[
        {
            "category":"Farming",
            "subcategory":"Livestock Farm",
            "type":"Manufacturing & Wholesale Goods"
        }
    ],
    "sg:phone":"+1 907 235 8830",
    "sg:postcode":"99603",
    "sg:province":"AK",
    "sg:tags":[
        "animal",
        "crop",
        "general"
    ],
    "wof:name":"Willard Farms",
    "wof:placetype":"venue"
},
  "geometry": {"coordinates":[-151.406211,59.68923],"type":"Point"}
}