{
  "type": "Feature",
  "properties": {
    "iso:country":"US",
    "sg:address":"15 Sing Lee Aly",
    "sg:city":"Petersburg",
    "sg:classifiers":[
        {
            "category":"Wholesale",
            "subcategory":"Seafood",
            "type":"Manufacturing & Wholesale Goods"
        }
    ],
    "sg:phone":"+1 907 772 4000",
    "sg:postcode":"99833",
    "sg:province":"AK",
    "sg:tags":[
        "fish"
    ],
    "sg:website":"www.alaskabroker.com",
    "wof:name":"Petersburg Fishermen's Svc",
    "wof:placetype":"venue"
},
  "geometry": {"coordinates":[-132.957734,56.811795],"type":"Point"}
}