{
  "type": "Feature",
  "properties": {
    "iso:country":"US",
    "sg:address":"47 Spr View Dr",
    "sg:city":"Kenai",
    "sg:classifiers":[
        {
            "category":"Travel",
            "subcategory":"Hotels & Motels",
            "type":"Entertainment"
        }
    ],
    "sg:phone":"+1 907 283 3660",
    "sg:postcode":"99611",
    "sg:province":"AK",
    "sg:website":"www.uptownmotel.com",
    "wof:name":"Uptown Motel",
    "wof:placetype":"venue"
},
  "geometry": {"coordinates":[-151.24454800000001,60.555578],"type":"Point"}
}