{
  "type": "Feature",
  "properties": {
    "addr:full":"225 E Fireweed Ln Anchorage AK 99503",
    "addr:housenumber":"225",
    "addr:postcode":"99503",
    "addr:street":"E Fireweed Ln",
    "iso:country":"US",
    "sg:address":"225 E Fireweed Ln",
    "sg:city":"Anchorage",
    "sg:classifiers":[
        {
            "category":"Professional",
            "subcategory":"Lawyer & Legal Services",
            "type":"Services"
        }
    ],
    "sg:phone":"+1 907 274 9555",
    "sg:postcode":"99503",
    "sg:province":"AK",
    "sg:tags":[
        "attorney"
    ],
    "wof:name":"Johnson & Kim",
    "wof:placetype":"venue"
},
  "geometry": {"coordinates":[-149.879142,61.198176],"type":"Point"}
}