{
  "type": "Feature",
  "properties": {
    "iso:country":"US",
    "sg:address":"9108 Mendenhall Mall Rd",
    "sg:city":"Juneau",
    "sg:classifiers":[
        {
            "category":"Restaurant",
            "type":"Food & Drink"
        }
    ],
    "sg:menulink":"http://www.allmenus.com/ak/juneau/78134-papa-murphys/menu/",
    "sg:phone":"+1 907 789 7567",
    "sg:postcode":"99801",
    "sg:province":"AK",
    "sg:tags":[
        "american",
        "pizza"
    ],
    "wof:name":"Papa Murphy's",
    "wof:placetype":"venue"
},
  "geometry": {"coordinates":[-134.58258000000001,58.371231],"type":"Point"}
}