{
  "type": "Feature",
  "properties": {
    "addr:full":"475 Katlian St Sitka AK 99835",
    "addr:housenumber":"475",
    "addr:postcode":"99835",
    "addr:street":"Katlian St",
    "iso:country":"US",
    "sg:address":"475 Katlian St",
    "sg:city":"Sitka",
    "sg:classifiers":[
        {
            "category":"Shopping",
            "subcategory":"Bicycles & Sporting Goods",
            "type":"Retail Goods"
        }
    ],
    "sg:phone":"+1 907 747 3171",
    "sg:postcode":"99835",
    "sg:province":"AK",
    "sg:tags":[
        "tackle",
        "fishing"
    ],
    "wof:name":"Murray Pacific Supply Corp",
    "wof:placetype":"venue"
},
  "geometry": {"coordinates":[-135.34465,57.053104],"type":"Point"}
}