{
  "type": "Feature",
  "properties": {
    "iso:country":"US",
    "sg:address":"1200 W 33rd Ave",
    "sg:city":"Anchorage",
    "sg:classifiers":[
        {
            "category":"Organizations",
            "subcategory":"Community Association",
            "type":"Services"
        }
    ],
    "sg:phone":"+1 907 562 1685",
    "sg:postcode":"99503",
    "sg:province":"AK",
    "sg:tags":[
        "military"
    ],
    "wof:name":"VFW Post",
    "wof:placetype":"venue"
},
  "geometry": {"coordinates":[-149.90633,61.190681],"type":"Point"}
}