{
  "type": "Feature",
  "properties": {
    "addr:full":"3619 Image Dr Anchorage AK 99504",
    "addr:housenumber":"3619",
    "addr:postcode":"99504",
    "addr:street":"Image Dr",
    "iso:country":"US",
    "sg:address":"3619 Image Dr",
    "sg:city":"Anchorage",
    "sg:classifiers":[
        {
            "category":"Home & Garden",
            "subcategory":"Furniture",
            "type":"Retail Goods"
        }
    ],
    "sg:phone":"+1 907 337 8485",
    "sg:postcode":"99504",
    "sg:province":"AK",
    "sg:tags":[
        "cabinet"
    ],
    "wof:name":"Bishop's Image",
    "wof:placetype":"venue"
},
  "geometry": {"coordinates":[-149.77401800000001,61.187745],"type":"Point"}
}