{
  "type": "Feature",
  "properties": {
    "addr:full":"2808 E Tudor Rd Anchorage AK 99507",
    "addr:housenumber":"2808",
    "addr:postcode":"99507",
    "addr:street":"E Tudor Rd",
    "iso:country":"US",
    "sg:address":"2808 E Tudor Rd",
    "sg:city":"Anchorage",
    "sg:classifiers":[
        {
            "category":"Shopping",
            "subcategory":"Music",
            "type":"Retail Goods"
        }
    ],
    "sg:phone":"+1 907 743 0509",
    "sg:postcode":"99507",
    "sg:province":"AK",
    "sg:tags":[
        "video",
        "disc",
        "tape",
        "cassette"
    ],
    "wof:name":"Video Liquidators",
    "wof:placetype":"venue"
},
  "geometry": {"coordinates":[-149.82834800000001,61.180762],"type":"Point"}
}