{
  "type": "Feature",
  "properties": {
    "iso:country":"US",
    "sg:address":"650 W Northern Lights Blvd",
    "sg:city":"Anchorage",
    "sg:classifiers":[
        {
            "category":"Restaurant",
            "type":"Food & Drink"
        }
    ],
    "sg:menulink":"http://www.allmenus.com/ak/anchorage/160968-carls-jr/menu/",
    "sg:phone":"+1 907 276 2275",
    "sg:postcode":"99503",
    "sg:province":"AK",
    "sg:tags":[
        "burger",
        "american"
    ],
    "wof:name":"Carl's Jr.",
    "wof:placetype":"venue"
},
  "geometry": {"coordinates":[-149.89567099999999,61.195297],"type":"Point"}
}