{
  "type": "Feature",
  "properties": {
    "addr:full":"3321 Orbit Dr Anchorage AK 99517",
    "addr:housenumber":"3321",
    "addr:postcode":"99517",
    "addr:street":"Orbit Dr",
    "iso:country":"US",
    "sg:address":"3321 Orbit Dr",
    "sg:city":"Anchorage",
    "sg:classifiers":[
        {
            "category":"Building & Trades",
            "subcategory":"Landscaping Services",
            "type":"Services"
        }
    ],
    "sg:phone":"+1 907 245 9888",
    "sg:postcode":"99517",
    "sg:province":"AK",
    "sg:tags":[
        "lawn",
        "maintenance",
        "grounds"
    ],
    "wof:name":"C C't Lawn Care & Snow Plowing",
    "wof:placetype":"venue"
},
  "geometry": {"coordinates":[-149.963864,61.190938],"type":"Point"}
}