{
  "type": "Feature",
  "properties": {
    "iso:country":"US",
    "sg:address":"3935 Apollo Dr",
    "sg:city":"Anchorage",
    "sg:classifiers":[
        {
            "category":"Health Services",
            "subcategory":"Health Practitioner",
            "type":"Services"
        }
    ],
    "sg:phone":"+1 907 333 0262",
    "sg:postcode":"99504",
    "sg:province":"AK",
    "sg:tags":[
        "nutritionist"
    ],
    "wof:name":"EDN Nutrition Consulting",
    "wof:placetype":"venue"
},
  "geometry": {"coordinates":[-149.751375,61.185038],"type":"Point"}
}