{
  "type": "Feature",
  "properties": {
    "iso:country":"US",
    "sg:address":"6401 E Northern Lights Blvd",
    "sg:city":"Anchorage",
    "sg:classifiers":[
        {
            "category":"Education",
            "subcategory":"School",
            "type":"Public Place"
        }
    ],
    "sg:phone":"+1 907 337 9575",
    "sg:postcode":"99504",
    "sg:province":"AK",
    "sg:website":"www.acsedu.org",
    "wof:name":"Anchorage Christian Schools",
    "wof:placetype":"venue"
},
  "geometry": {"coordinates":[-149.759789,61.195348],"type":"Point"}
}