{
  "type": "Feature",
  "properties": {
    "iso:country":"US",
    "sg:address":"7216 Lake Otis Pkwy",
    "sg:city":"Anchorage",
    "sg:classifiers":[
        {
            "category":"Recreation",
            "type":"Entertainment"
        }
    ],
    "sg:phone":"+1 907 563 3025",
    "sg:postcode":"99507",
    "sg:province":"AK",
    "sg:tags":[
        "martial",
        "arts",
        "instruction"
    ],
    "wof:name":"Tae KWON Do USA",
    "wof:placetype":"venue"
},
  "geometry": {"coordinates":[-149.834255,61.153917],"type":"Point"}
}