{
  "type": "Feature",
  "properties": {
    "iso:country":"US",
    "sg:address":"2081 Van Horn Rd",
    "sg:city":"Fairbanks",
    "sg:classifiers":[
        {
            "category":"Building & Trades",
            "subcategory":"Construction",
            "type":"Services"
        }
    ],
    "sg:phone":"+1 907 455 7712",
    "sg:postcode":"99701",
    "sg:province":"AK",
    "sg:tags":[
        "industrial",
        "general",
        "solution",
        "contractor"
    ],
    "wof:name":"Alaska Dreams Inc",
    "wof:placetype":"venue"
},
  "geometry": {"coordinates":[-147.757612,64.812898],"type":"Point"}
}