{
  "type": "Feature",
  "properties": {
    "iso:country":"US",
    "sg:address":"197 W Park Ave",
    "sg:city":"Soldotna",
    "sg:classifiers":[
        {
            "category":"Social Services",
            "subcategory":"Adult Care",
            "type":"Services"
        }
    ],
    "sg:phone":"+1 907 262 2322",
    "sg:postcode":"99669",
    "sg:province":"AK",
    "sg:tags":[
        "organization",
        "senior",
        "citizen"
    ],
    "wof:name":"Soldotna Senior Citizens Ctr",
    "wof:placetype":"venue"
},
  "geometry": {"coordinates":[-151.07938100000001,60.490058],"type":"Point"}
}