{
  "type": "Feature",
  "properties": {
    "iso:country":"US",
    "sg:address":"10639 Kenai Spur Hwy",
    "sg:city":"Kenai",
    "sg:classifiers":[
        {
            "category":"Sports & Exercise",
            "subcategory":"Bowling",
            "type":"Entertainment"
        }
    ],
    "sg:phone":"+1 907 283 3314",
    "sg:postcode":"99611",
    "sg:province":"AK",
    "sg:tags":[
        "center"
    ],
    "wof:name":"Alaskalanes Family Bowling Ctr",
    "wof:placetype":"venue"
},
  "geometry": {"coordinates":[-151.23753099999999,60.558982],"type":"Point"}
}