{
  "type": "Feature",
  "properties": {
    "addr:full":"1205 W 29th Ave Anchorage AK 99503",
    "addr:housenumber":"1205",
    "addr:postcode":"99503",
    "addr:street":"W 29Th Ave",
    "iso:country":"US",
    "sg:address":"1205 W 29th Ave",
    "sg:city":"Anchorage",
    "sg:classifiers":[
        {
            "category":"Wholesale",
            "subcategory":"Seafood",
            "type":"Manufacturing & Wholesale Goods"
        }
    ],
    "sg:phone":"+1 907 278 1525",
    "sg:postcode":"99503",
    "sg:province":"AK",
    "wof:name":"Favco Inc",
    "wof:placetype":"venue"
},
  "geometry": {"coordinates":[-149.90686700000001,61.194019],"type":"Point"}
}