{
  "type": "Feature",
  "properties": {
    "iso:country":"US",
    "sg:address":"1317 W Northern Lights Blvd",
    "sg:city":"Anchorage",
    "sg:classifiers":[
        {
            "category":"Professional",
            "subcategory":"Business Services",
            "type":"Services"
        }
    ],
    "sg:phone":"+1 907 258 2050",
    "sg:postcode":"99503",
    "sg:province":"AK",
    "sg:tags":[
        "translator",
        "interpreter"
    ],
    "wof:name":"Russian From A To Z",
    "wof:placetype":"venue"
},
  "geometry": {"coordinates":[-149.91086100000001,61.195372],"type":"Point"}
}