{
  "type": "Feature",
  "properties": {
    "iso:country":"US",
    "sg:address":"2000 E 88th Ave",
    "sg:city":"Anchorage",
    "sg:classifiers":[
        {
            "category":"Mining & Drilling",
            "type":"Manufacturing & Wholesale Goods"
        }
    ],
    "sg:phone":"+1 907 276 6037",
    "sg:postcode":"99507",
    "sg:province":"AK",
    "sg:tags":[
        "development",
        "gas",
        "oil",
        "exploration"
    ],
    "wof:name":"Veritas Dgc Land",
    "wof:placetype":"venue"
},
  "geometry": {"coordinates":[-149.843171,61.141053],"type":"Point"}
}