{
  "type": "Feature",
  "properties": {
    "addr:full":"12034 N Tongass Hwy Ketchikan AK 99901",
    "addr:housenumber":"12034",
    "addr:postcode":"99901",
    "addr:street":"N Tongass Hwy",
    "iso:country":"US",
    "sg:address":"12034 N Tongass Hwy",
    "sg:city":"Ketchikan",
    "sg:classifiers":[
        {
            "category":"Shopping",
            "type":"Retail Goods"
        }
    ],
    "sg:phone":"+1 907 225 1321",
    "sg:postcode":"99901",
    "sg:province":"AK",
    "sg:tags":[
        "merchandise",
        "animal"
    ],
    "wof:name":"Groomingdales",
    "wof:placetype":"venue"
},
  "geometry": {"coordinates":[-131.80934300000001,55.445264],"type":"Point"}
}