{
  "type": "Feature",
  "properties": {
    "addr:full":"8195 Erin St Juneau AK 99801",
    "addr:housenumber":"8195",
    "addr:postcode":"99801",
    "addr:street":"Erin St",
    "iso:country":"US",
    "sg:address":"8195 Erin St",
    "sg:city":"Juneau",
    "sg:classifiers":[
        {
            "category":"Shopping",
            "subcategory":"Clothing, Apparel, & Fashions",
            "type":"Retail Goods"
        }
    ],
    "sg:phone":"+1 907 789 2309",
    "sg:postcode":"99801",
    "sg:province":"AK",
    "sg:tags":[
        "alteration"
    ],
    "wof:name":"Linda's Sewing",
    "wof:placetype":"venue"
},
  "geometry": {"coordinates":[-134.55862200000001,58.397761],"type":"Point"}
}