{
  "type": "Feature",
  "properties": {
    "iso:country":"US",
    "sg:address":"2100 S Cushman St",
    "sg:city":"Fairbanks",
    "sg:classifiers":[
        {
            "category":"Home & Garden",
            "subcategory":"Building Materials",
            "type":"Retail Goods"
        }
    ],
    "sg:phone":"+1 907 452 1981",
    "sg:postcode":"99701",
    "sg:province":"AK",
    "sg:tags":[
        "equipment",
        "electric",
        "supply"
    ],
    "wof:name":"Tesco Lighting & Design Ctr",
    "wof:placetype":"venue"
},
  "geometry": {"coordinates":[-147.714416,64.828414],"type":"Point"}
}